Workbook

Sheet Summary
A1: CRM × ERP Matched Contacts Summary
A2: Contacts present in both the CRM contact list and the active ERP customer list, matched by account/customer name.
A4: Metric | B4: Count | C4: % of matched
A5: Matched contacts (this sheet) | B5: =COUNTA('Matched Contacts'!A2:A996) -> 995 | C5: =B5/$B$5 -> 1
A6: Unique accounts represented | B6: =SUMPRODUCT(1/COUNTIF('Matched Contacts'!B2:B996,'Matched Contacts'!B2:B996)) -> 664 | C6: =B6/$B$5 -> 0.66733668
A7: Match (owner & email align) | B7: =COUNTIF('Matched Contacts'!L2:L996,"Match") -> 53 | C7: =B7/$B$5 -> 0.053266332
A8: Different owner only | B8: =COUNTIF('Matched Contacts'!L2:L996,"Different owner") -> 221 | C8: =B8/$B$5 -> 0.22211055
A9: Different contact only | B9: =COUNTIF('Matched Contacts'!L2:L996,"Different contact") -> 206 | C9: =B9/$B$5 -> 0.20703518
A10: Different owner & contact | B10: =COUNTIF('Matched Contacts'!L2:L996,"Different owner & contact") -> 515 | C10: =B10/$B$5 -> 0.51758794

Sheet Matched Contacts
A1: Contact Name | B1: Account Name | C1: Contact Email | D1: Contact Phone | E1: CRM Contact Owner | F1: Customer ID | G1: Customer Class | H1: Customer Region | I1: Route Name | J1: ERP Sales Rep | K1: ERP Account Email | L1: Owner Match
A2: Faith Aganda | B2: 254 Brewing Company | C2: procurement@global-slacker.com | D2: 0726150112 | E2: Susan Ngina | F2: CUST102400 | G2: KPSERVICE | H2: Nairobi Central | I2: Kikuyu Town | J2: Diana Wendy | K2: procurement@global-slacker.com | L2: =IF(AND(TRIM(LOWER(E2))=TRIM(LOWER(J2)),TRIM(LOWER(C2))=TRIM(LOWER(K2))),"Match",IF(AND(NOT(TRIM(LOWER(E2))=TRIM(LOWER(J2))),TRIM(LOWER(C2))=TRIM(LOWER(K2))),"Different owner",IF(AND(TRIM(LOWER(E2))=TRIM(LOWER(J2)),NOT(TRIM(LOWER(C2))=TRIM(LOWER(K2)))),"Different contact","Different owner & contact"))) -> Different owner
A3: Lilian | B3: 254 Brewing Company | E3: Berna Piwang | F3: CUST102400 | G3: KPSERVICE | H3: Nairobi Central | I3: Kikuyu Town | J3: Diana Wendy | K3: procurement@global-slacker.com | L3: =IF(AND(TRIM(LOWER(E3))=TRIM(LOWER(J3)),TRIM(LOWER(C3))=TRIM(LOWER(K3))),"Match",IF(AND(NOT(TRIM(LOWER(E3))=TRIM(LOWER(J3))),TRIM(LOWER(C3))=TRIM(LOWER(K3))),"Different owner",IF(AND(TRIM(LOWER(E3))=TRIM(LOWER(J3)),NOT(TRIM(LOWER(C3))=TRIM(LOWER(K3)))),"Different contact","Different owner & contact"))) -> Different owner & contact
A4: Samantha | B4: 254 Brewing Company | E4: Berna Piwang | F4: CUST102400 | G4: KPSERVICE | H4: Nairobi Central | I4: Kikuyu Town | J4: Diana Wendy | K4: procurement@global-slacker.com | L4: =IF(AND(TRIM(LOWER(E4))=TRIM(LOWER(J4)),TRIM(LOWER(C4))=TRIM(LOWER(K4))),"Match",IF(AND(NOT(TRIM(LOWER(E4))=TRIM(LOWER(J4))),TRIM(LOWER(C4))=TRIM(LOWER(K4))),"Different owner",IF(AND(TRIM(LOWER(E4))=TRIM(LOWER(J4)),NOT(TRIM(LOWER(C4))=TRIM(LOWER(K4)))),"Different contact","Different owner & contact"))) -> Different owner & contact
A5: Mercy Wamboi | B5: 5Th Avenue Management Office | D5: 0708017933 | E5: Berna Piwang | F5: CUST100003 | G5: KPPMGR | H5: Nairobi West | I5: Ngong Road | J5: Berna Piwang | K5: 5thavenuemgmt@gmail.com | L5: =IF(AND(TRIM(LOWER(E5))=TRIM(LOWER(J5)),TRIM(LOWER(C5))=TRIM(LOWER(K5))),"Match",IF(AND(NOT(TRIM(LOWER(E5))=TRIM(LOWER(J5))),TRIM(LOWER(C5))=TRIM(LOWER(K5))),"Different owner",IF(AND(TRIM(LOWER(E5))=TRIM(LOWER(J5)),NOT(TRIM(LOWER(C5))=TRIM(LOWER(K5)))),"Different contact","Different owner & contact"))) -> Different contact
A6: Mirriam Waithera | B6: A.I.C Cure International Hospital | C6: mirriam.waithera@cureinternational.org | E6: Maureen | F6: CUST101927 | G6: KPHEALTH | H6: South Rift | I6: Kijabe | J6: June Chesire | K6: mirriam.waithera@cureinternational.org | L6: =IF(AND(TRIM(LOWER(E6))=TRIM(LOWER(J6)),TRIM(LOWER(C6))=TRIM(LOWER(K6))),"Match",IF(AND(NOT(TRIM(LOWER(E6))=TRIM(LOWER(J6))),TRIM(LOWER(C6))=TRIM(LOWER(K6))),"Different owner",IF(AND(TRIM(LOWER(E6))=TRIM(LOWER(J6)),NOT(TRIM(LOWER(C6))=TRIM(LOWER(K6)))),"Different contact","Different owner & contact"))) -> Different owner
A7: Kevin Wasike | B7: AACC Guest House | C7: kevin@aacc-ceta.org | E7: Mercy Irungu | F7: CUST100007 | G7: KPHOTEL | H7: Nairobi West | I7: Waiyaki Way | J7: Mercyline Kemunto | K7: stores@aacc-ceta.org | L7: =IF(AND(TRIM(LOWER(E7))=TRIM(LOWER(J7)),TRIM(LOWER(C7))=TRIM(LOWER(K7))),"Match",IF(AND(NOT(TRIM(LOWER(E7))=TRIM(LOWER(J7))),TRIM(LOWER(C7))=TRIM(LOWER(K7))),"Different owner",IF(AND(TRIM(LOWER(E7))=TRIM(LOWER(J7)),NOT(TRIM(LOWER(C7))=TRIM(LOWER(K7)))),"Different contact","Different owner & contact"))) -> Different owner & contact
A8: Allan Were | B8: AAR Hospital Limited | C8: allan.were@aarhospital.com | D8: 0725880147 | E8: Doreen Mugwika | F8: CUST101857 | G8: KPHEALTH | H8: Nairobi East | I8: Kiambu | J8: Doreen Mugwika | K8: james.mwaura@aarhospital.com | L8: =IF(AND(TRIM(LOWER(E8))=TRIM(LOWER(J8)),TRIM(LOWER(C8))=TRIM(LOWER(K8))),"Match",IF(AND(NOT(TRIM(LOWER(E8))=TRIM(LOWER(J8))),TRIM(LOWER(C8))=TRIM(LOWER(K8))),"Different owner",IF(AND(TRIM(LOWER(E8))=TRIM(LOWER(J8)),NOT(TRIM(LOWER(C8))=TRIM(LOWER(K8)))),"Different contact","Different owner & contact"))) -> Different contact
A9: Chris Otieno | B9: AAR Hospital Limited | C9: chris.otieno@aarhospital.com | E9: Doreen Mugwika | F9: CUST101857 | G9: KPHEALTH | H9: Nairobi East | I9: Kiambu | J9: Doreen Mugwika | K9: james.mwaura@aarhospital.com | L9: =IF(AND(TRIM(LOWER(E9))=TRIM(LOWER(J9)),TRIM(LOWER(C9))=TRIM(LOWER(K9))),"Match",IF(AND(NOT(TRIM(LOWER(E9))=TRIM(LOWER(J9))),TRIM(LOWER(C9))=TRIM(LOWER(K9))),"Different owner",IF(AND(TRIM(LOWER(E9))=TRIM(LOWER(J9)),NOT(TRIM(LOWER(C9))=TRIM(LOWER(K9)))),"Different contact","Different owner & contact"))) -> Different contact
A10: Christine muema | B10: AAR Hospital Limited | C10: Christine.muema@aarhospital.com | D10: 0793 410 850 | E10: Doreen Mugwika | F10: CUST101857 | G10: KPHEALTH | H10: Nairobi East | I10: Kiambu | J10: Doreen Mugwika | K10: james.mwaura@aarhospital.com | L10: =IF(AND(TRIM(LOWER(E10))=TRIM(LOWER(J10)),TRIM(LOWER(C10))=TRIM(LOWER(K10))),"Match",IF(AND(NOT(TRIM(LOWER(E10))=TRIM(LOWER(J10))),TRIM(LOWER(C10))=TRIM(LOWER(K10))),"Different owner",IF(AND(TRIM(LOWER(E10))=TRIM(LOWER(J10)),NOT(TRIM(LOWER(C10))=TRIM(LOWER(K10)))),"Different contact","Different owner & contact"))) -> Different contact
A11: Sylvia Njeru | B11: AAR Hospital Limited | C11: sylvia.njeru@aarhospital.com | D11: 0723346023 | E11: Doreen Mugwika | F11: CUST101857 | G11: KPHEALTH | H11: Nairobi East | I11: Kiambu | J11: Doreen Mugwika | K11: james.mwaura@aarhospital.com | L11: =IF(AND(TRIM(LOWER(E11))=TRIM(LOWER(J11)),TRIM(LOWER(C11))=TRIM(LOWER(K11))),"Match",IF(AND(NOT(TRIM(LOWER(E11))=TRIM(LOWER(J11))),TRIM(LOWER(C11))=TRIM(LOWER(K11))),"Different owner",IF(AND(TRIM(LOWER(E11))=TRIM(LOWER(J11)),NOT(TRIM(LOWER(C11))=TRIM(LOWER(K11)))),"Different contact","Different owner & contact"))) -> Different contact
A12: Teresa Maina | B12: AAR Insurance Kenya Limited | C12: teresa.maina@aar.co.ke | D12: 0736691196 | E12: Doreen Mugwika | F12: CUST100008 | G12: KPINDUSTRY | H12: Nairobi West | I12: Upper Hill | J12: Doreen Mugwika | K12: rkisese@aar.co.ke | L12: =IF(AND(TRIM(LOWER(E12))=TRIM(LOWER(J12)),TRIM(LOWER(C12))=TRIM(LOWER(K12))),"Match",IF(AND(NOT(TRIM(LOWER(E12))=TRIM(LOWER(J12))),TRIM(LOWER(C12))=TRIM(LOWER(K12))),"Different owner",IF(AND(TRIM(LOWER(E12))=TRIM(LOWER(J12)),NOT(TRIM(LOWER(C12))=TRIM(LOWER(K12)))),"Different contact","Different owner & contact"))) -> Different contact
A13: Benard Kambutu | B13: AHN Kenya Limited | C13: benard@africahealthcarenetwork.com | D13: 0796258271 | E13: Yvonne Otieno | F13: CUST100043 | G13: KPHEALTH | H13: Nairobi West | I13: Mombasa Road | J13: Yvonne Achieng | K13: donie@africahealthcarenetwork.com | L13: =IF(AND(TRIM(LOWER(E13))=TRIM(LOWER(J13)),TRIM(LOWER(C13))=TRIM(LOWER(K13))),"Match",IF(AND(NOT(TRIM(LOWER(E13))=TRIM(LOWER(J13))),TRIM(LOWER(C13))=TRIM(LOWER(K13))),"Different owner",IF(AND(TRIM(LOWER(E13))=TRIM(LOWER(J13)),NOT(TRIM(LOWER(C13))=TRIM(LOWER(K13)))),"Different contact","Different owner & contact"))) -> Different owner & contact
A14: Gillian Kibugi | B14: AIG Kenya Insurance Company Ltd | C14: gillian.kibugi@aig.com | E14: Doreen Mugwika | F14: CUST100045 | G14: KPBANK | H14: Nairobi West | I14: Westlands | J14: Shirleen Chebet | K14: gillian.kibugi@aig.com | L14: =IF(AND(TRIM(LOWER(E14))=TRIM(LOWER(J14)),TRIM(LOWER(C14))=TRIM(LOWER(K14))),"Match",IF(AND(NOT(TRIM(LOWER(E14))=TRIM(LOWER(J14))),TRIM(LOWER(C14))=TRIM(LOWER(K14))),"Different owner",IF(AND(TRIM(LOWER(E14))=TRIM(LOWER(J14)),NOT(TRIM(LOWER(C14))=TRIM(LOWER(K14)))),"Different contact","Different owner & contact"))) -> Different owner
A15: Patrick Angoiya | B15: AMREF Health Africa | C15: patrick.angoiya@amref.org | E15: Irene Luketelo | F15: CUST100067 | G15: KPHEALTH | H15: Nairobi West | I15: Langata Road | J15: Irene Luketelo | K15: samuel.amwata@amref.org | L15: =IF(AND(TRIM(LOWER(E15))=TRIM(LOWER(J15)),TRIM(LOWER(C15))=TRIM(LOWER(K15))),"Match",IF(AND(NOT(TRIM(LOWER(E15))=TRIM(LOWER(J15))),TRIM(LOWER(C15))=TRIM(LOWER(K15))),"Different owner",IF(AND(TRIM(LOWER(E15))=TRIM(LOWER(J15)),NOT(TRIM(LOWER(C15))=TRIM(LOWER(K15)))),"Different contact","Different owner & contact"))) -> Different contact
A16: Kennedy . | B16: Abai Lodges Limited | C16: info@abailodges.com | D16: 0707222555 | E16: John Kaguai | F16: CUST102706 | G16: KPHOTEL | H16: Lower Mountain | I16: Kerugoya | J16: John Kaguai | K16: accounts@abailodges.com | L16: =IF(AND(TRIM(LOWER(E16))=TRIM(LOWER(J16)),TRIM(LOWER(C16))=TRIM(LOWER(K16))),"Match",IF(AND(NOT(TRIM(LOWER(E16))=TRIM(LOWER(J16))),TRIM(LOWER(C16))=TRIM(LOWER(K16))),"Different owner",IF(AND(TRIM(LOWER(E16))=TRIM(LOWER(J16)),NOT(TRIM(LOWER(C16))=TRIM(LOWER(K16)))),"Different contact","Different owner & contact"))) -> Different contact
A17: Winnie Mwangi | B17: Abgai Hygiene Ltd | C17: waynmuhia@gmail.com | D17: 0712636287 | E17: Irene Luketelo | F17: CUST103185 | G17: KPCCLNRS | H17: Nairobi Central | I17: CBD | J17: Irene Luketelo | K17: waynmuhia@gmail.com | L17: =IF(AND(TRIM(LOWER(E17))=TRIM(LOWER(J17)),TRIM(LOWER(C17))=TRIM(LOWER(K17))),"Match",IF(AND(NOT(TRIM(LOWER(E17))=TRIM(LOWER(J17))),TRIM(LOWER(C17))=TRIM(LOWER(K17))),"Different owner",IF(AND(TRIM(LOWER(E17))=TRIM(LOWER(J17)),NOT(TRIM(LOWER(C17))=TRIM(LOWER(K17)))),"Different contact","Different owner & contact"))) -> Match
A18: Tabitha Tabitha | B18: Academy Of Dance And Arts Ltd | C18: origins@academyonline.me | E18: Yvonne Otieno | F18: CUST100010 | G18: KPEDU | H18: Nairobi West | I18: Karen | J18: Diana Wendy | K18: dance@academyonline.me | L18: =IF(AND(TRIM(LOWER(E18))=TRIM(LOWER(J18)),TRIM(LOWER(C18))=TRIM(LOWER(K18))),"Match",IF(AND(NOT(TRIM(LOWER(E18))=TRIM(LOWER(J18))),TRIM(LOWER(C18))=TRIM(LOWER(K18))),"Different owner",IF(AND(TRIM(LOWER(E18))=TRIM(LOWER(J18)),NOT(TRIM(LOWER(C18))=TRIM(LOWER(K18)))),"Different contact","Different owner & contact"))) -> Different owner & contact
A19: Jane Awuor | B19: Adamji Multi Supplies Limited | C19: finance@adamji.co.ke | D19: 0732673200 | E19: June Chesire | F19: CUST100012 | G19: KPDIST | H19: Nairobi East | I19: Mombasa Road | J19: June Chesire | K19: finance@adamji.co.ke | L19: =IF(AND(TRIM(LOWER(E19))=TRIM(LOWER(J19)),TRIM(LOWER(C19))=TRIM(LOWER(K19))),"Match",IF(AND(NOT(TRIM(LOWER(E19))=TRIM(LOWER(J19))),TRIM(LOWER(C19))=TRIM(LOWER(K19))),"Different owner",IF(AND(TRIM(LOWER(E19))=TRIM(LOWER(J19)),NOT(TRIM(LOWER(C19))=TRIM(LOWER(K19)))),"Different contact","Different owner & contact"))) -> Match
A20: Jane Jane | B20: Adamji Multi Supplies Limited | C20: stockcontrol@adamji.co.ke | E20: June Chesire | F20: CUST100012 | G20: KPDIST | H20: Nairobi East | I20: Mombasa Road | J20: June Chesire | K20: finance@adamji.co.ke | L20: =IF(AND(TRIM(LOWER(E20))=TRIM(LOWER(J20)),TRIM(LOWER(C20))=TRIM(LOWER(K20))),"Match",IF(AND(NOT(TRIM(LOWER(E20))=TRIM(LOWER(J20))),TRIM(LOWER(C20))=TRIM(LOWER(K20))),"Different owner",IF(AND(TRIM(LOWER(E20))=TRIM(LOWER(J20)),NOT(TRIM(LOWER(C20))=TRIM(LOWER(K20)))),"Different contact","Different owner & contact"))) -> Different contact
A21: Winnie | B21: Adams Brown & Company Ltd | C21: info@abc-place.com | D21: 0721619018 | E21: Doreen Mugwika | F21: CUST100013 | G21: KPPMGR | H21: Nairobi West | I21: Waiyaki Way | J21: Doreen Mugwika | K21: info@abc-place.com | L21: =IF(AND(TRIM(LOWER(E21))=TRIM(LOWER(J21)),TRIM(LOWER(C21))=TRIM(LOWER(K21))),"Match",IF(AND(NOT(TRIM(LOWER(E21))=TRIM(LOWER(J21))),TRIM(LOWER(C21))=TRIM(LOWER(K21))),"Different owner",IF(AND(TRIM(LOWER(E21))=TRIM(LOWER(J21)),NOT(TRIM(LOWER(C21))=TRIM(LOWER(K21)))),"Different contact","Different owner & contact"))) -> Match
A22: Emma and Tyrus | B22: Adlife Management Company Ltd | E22: Berna Piwang | F22: CUST100014 | G22: KPPMGR | H22: Nairobi West | I22: Hurlingham | J22: Berna Piwang | K22: wenceslaus@adlifeplaza.com | L22: =IF(AND(TRIM(LOWER(E22))=TRIM(LOWER(J22)),TRIM(LOWER(C22))=TRIM(LOWER(K22))),"Match",IF(AND(NOT(TRIM(LOWER(E22))=TRIM(LOWER(J22))),TRIM(LOWER(C22))=TRIM(LOWER(K22))),"Different owner",IF(AND(TRIM(LOWER(E22))=TRIM(LOWER(J22)),NOT(TRIM(LOWER(C22))=TRIM(LOWER(K22)))),"Different contact","Different owner & contact"))) -> Different contact
A23: Ann Wanjira | B23: Adrian Kenya Ltd | C23: ann.wanjira@adriankenya.com | D23: 0726339919 | E23: Yvonne Otieno | F23: CUST100015 | G23: KPINDUSTRY | H23: Nairobi West | I23: Waiyaki Way | J23: Yvonne Achieng | K23: adrianpayables@adriankenya.com | L23: =IF(AND(TRIM(LOWER(E23))=TRIM(LOWER(J23)),TRIM(LOWER(C23))=TRIM(LOWER(K23))),"Match",IF(AND(NOT(TRIM(LOWER(E23))=TRIM(LOWER(J23))),TRIM(LOWER(C23))=TRIM(LOWER(K23))),"Different owner",IF(AND(TRIM(LOWER(E23))=TRIM(LOWER(J23)),NOT(TRIM(LOWER(C23))=TRIM(LOWER(K23)))),"Different contact","Different owner & contact"))) -> Different owner & contact
A24: Veronica Wanjema | B24: Adrian Kenya Ltd | C24: v.wanjema@adriankenya.com | D24: 0726339919 | E24: Yvonne Otieno | F24: CUST100015 | G24: KPINDUSTRY | H24: Nairobi West | I24: Waiyaki Way | J24: Yvonne Achieng | K24: adrianpayables@adriankenya.com | L24: =IF(AND(TRIM(LOWER(E24))=TRIM(LOWER(J24)),TRIM(LOWER(C24))=TRIM(LOWER(K24))),"Match",IF(AND(NOT(TRIM(LOWER(E24))=TRIM(LOWER(J24))),TRIM(LOWER(C24))=TRIM(LOWER(K24))),"Different owner",IF(AND(TRIM(LOWER(E24))=TRIM(LOWER(J24)),NOT(TRIM(LOWER(C24))=TRIM(LOWER(K24)))),"Different contact","Different owner & contact"))) -> Different owner & contact
A25: Mercy Njane | B25: Aero Club East Africa Ltd | C25: admin@aeroclubea.com | E25: Mercy Irungu | F25: CUST100017 | G25: KPAIRLINE | H25: Nairobi East | I25: Wilson Airport | J25: Berna Piwang | K25: purchasing@aeroclubea.com | L25: =IF(AND(TRIM(LOWER(E25))=TRIM(LOWER(J25)),TRIM(LOWER(C25))=TRIM(LOWER(K25))),"Match",IF(AND(NOT(TRIM(LOWER(E25))=TRIM(LOWER(J25))),TRIM(LOWER(C25))=TRIM(LOWER(K25))),"Different owner",IF(AND(TRIM(LOWER(E25))=TRIM(LOWER(J25)),NOT(TRIM(LOWER(C25))=TRIM(LOWER(K25)))),"Different contact","Different owner & contact"))) -> Different owner & contact
A26: Ruth Ndege | B26: Afex Kenya Ltd | C26: ruth.ndege@afexgroup.com | E26: June Chesire | F26: CUST100018 | G26: KPHOTEL | H26: Nairobi West | I26: Waiyaki Way | J26: June Chesire | K26: ruth.ndege@afexgroup.com | L26: =IF(AND(TRIM(LOWER(E26))=TRIM(LOWER(J26)),TRIM(LOWER(C26))=TRIM(LOWER(K26))),"Match",IF(AND(NOT(TRIM(LOWER(E26))=TRIM(LOWER(J26))),TRIM(LOWER(C26))=TRIM(LOWER(K26))),"Different owner",IF(AND(TRIM(LOWER(E26))=TRIM(LOWER(J26)),NOT(TRIM(LOWER(C26))=TRIM(LOWER(K26)))),"Different contact","Different owner & contact"))) -> Match
A27: Joseph Leorso | B27: Afri-Sine Limited T/A Nyali Golf View Residence | E27: Lucy Gakii | F27: CUST101487 | G27: KPHOTEL | H27: Coast | I27: Mombasa | J27: Lucy Rimberia | K27: afrisineltd@gmail.com | L27: =IF(AND(TRIM(LOWER(E27))=TRIM(LOWER(J27)),TRIM(LOWER(C27))=TRIM(LOWER(K27))),"Match",IF(AND(NOT(TRIM(LOWER(E27))=TRIM(LOWER(J27))),TRIM(LOWER(C27))=TRIM(LOWER(K27))),"Different owner",IF(AND(TRIM(LOWER(E27))=TRIM(LOWER(J27)),NOT(TRIM(LOWER(C27))=TRIM(LOWER(K27)))),"Different contact","Different owner & contact"))) -> Different owner & contact
A28: Laban Zewe | B28: Afri-Sine Limited T/A Nyali Golf View Residence | C28: laban@afrisine.co.ke | D28: 0714423826 | E28: Lucy Gakii | F28: CUST101487 | G28: KPHOTEL | H28: Coast | I28: Mombasa | J28: Lucy Rimberia | K28: afrisineltd@gmail.com | L28: =IF(AND(TRIM(LOWER(E28))=TRIM(LOWER(J28)),TRIM(LOWER(C28))=TRIM(LOWER(K28))),"Match",IF(AND(NOT(TRIM(LOWER(E28))=TRIM(LOWER(J28))),TRIM(LOWER(C28))=TRIM(LOWER(K28))),"Different owner",IF(AND(TRIM(LOWER(E28))=TRIM(LOWER(J28)),NOT(TRIM(LOWER(C28))=TRIM(LOWER(K28)))),"Different contact","Different owner & contact"))) -> Different owner & contact
A29: Grace A | B29: Afri-Trail Ventures Ltd | C29: gracem@gmail.com | D29: 0722773443 | E29: June Chesire | F29: CUST100030 | G29: KPDIST | H29: Nairobi Central | I29: CBD | J29: Berna Piwang | K29: afritrail@gmail.com | L29: =IF(AND(TRIM(LOWER(E29))=TRIM(LOWER(J29)),TRIM(LOWER(C29))=TRIM(LOWER(K29))),"Match",IF(AND(NOT(TRIM(LOWER(E29))=TRIM(LOWER(J29))),TRIM(LOWER(C29))=TRIM(LOWER(K29))),"Different owner",IF(AND(TRIM(LOWER(E29))=TRIM(LOWER(J29)),NOT(TRIM(LOWER(C29))=TRIM(LOWER(K29)))),"Different contact","Different owner & contact"))) -> Different owner & contact
A30: Davina Ngina | B30: Africa Reit | C30: info@africareit.com | E30: Mercy Irungu | F30: CUST100019 | G30: KPSERVICE | H30: Nairobi West | I30: Karen | J30: Shirleen Chebet | K30: accounts@africareit.com | L30: =IF(AND(TRIM(LOWER(E30))=TRIM(LOWER(J30)),TRIM(LOWER(C30))=TRIM(LOWER(K30))),"Match",IF(AND(NOT(TRIM(LOWER(E30))=TRIM(LOWER(J30))),TRIM(LOWER(C30))=TRIM(LOWER(K30))),"Different owner",IF(AND(TRIM(LOWER(E30))=TRIM(LOWER(J30)),NOT(TRIM(LOWER(C30))=TRIM(LOWER(K30)))),"Different contact","Different owner & contact"))) -> Different owner & contact
A31: Eric Njenga | B31: African Forest Lodges Ltd | C31: procurement@theforest.co.ke | E31: Mercy Irungu | F31: CUST100023 | G31: KPHOTEL | H31: Nairobi West | I31: Naivasha | J31: Diana Wendy | K31: njengaeric1@gmail.com | L31: =IF(AND(TRIM(LOWER(E31))=TRIM(LOWER(J31)),TRIM(LOWER(C31))=TRIM(LOWER(K31))),"Match",IF(AND(NOT(TRIM(LOWER(E31))=TRIM(LOWER(J31))),TRIM(LOWER(C31))=TRIM(LOWER(K31))),"Different owner",IF(AND(TRIM(LOWER(E31))=TRIM(LOWER(J31)),NOT(TRIM(LOWER(C31))=TRIM(LOWER(K31)))),"Different contact","Different owner & contact"))) -> Different owner & contact
A32: Christine | B32: African Fund For Endagered Wildlife Afew | C32: admin@giraffecentre.org | D32: 0723934980 | E32: Doreen Mugwika | F32: CUST100024 | G32: KPPMGR | H32: Nairobi West | I32: Karen | J32: Doreen Mugwika | K32: solomon@giraffecentre.org | L32: =IF(AND(TRIM(LOWER(E32))=TRIM(LOWER(J32)),TRIM(LOWER(C32))=TRIM(LOWER(K32))),"Match",IF(AND(NOT(TRIM(LOWER(E32))=TRIM(LOWER(J32))),TRIM(LOWER(C32))=TRIM(LOWER(K32))),"Different owner",IF(AND(TRIM(LOWER(E32))=TRIM(LOWER(J32)),NOT(TRIM(LOWER(C32))=TRIM(LOWER(K32)))),"Different contact","Different owner & contact"))) -> Different contact
A33: Bethsheba Getanda | B33: African Population & Health Research Centre | C33: bgetanda@aphrc.org | D33: 0720359978 | E33: Doreen Mugwika | F33: CUST100026 | G33: KPNGO | H33: Nairobi West | I33: Lower Kabete | J33: Doreen Mugwika | K33: guest234@aphrc.org | L33: =IF(AND(TRIM(LOWER(E33))=TRIM(LOWER(J33)),TRIM(LOWER(C33))=TRIM(LOWER(K33))),"Match",IF(AND(NOT(TRIM(LOWER(E33))=TRIM(LOWER(J33))),TRIM(LOWER(C33))=TRIM(LOWER(K33))),"Different owner",IF(AND(TRIM(LOWER(E33))=TRIM(LOWER(J33)),NOT(TRIM(LOWER(C33))=TRIM(LOWER(K33)))),"Different contact","Different owner & contact"))) -> Different contact
A34: Sophie Muoni | B34: African Tulip Ltd C/O Knight Frank | C34: Sophie.Muoni@ke.knightfrank.com | E34: Irene Luketelo | F34: CUST100028 | G34: KPPMGR | H34: Nairobi West | I34: Waiyaki Way | J34: Irene Luketelo | K34: Sophie.Muoni@ke.knightfrank.com | L34: =IF(AND(TRIM(LOWER(E34))=TRIM(LOWER(J34)),TRIM(LOWER(C34))=TRIM(LOWER(K34))),"Match",IF(AND(NOT(TRIM(LOWER(E34))=TRIM(LOWER(J34))),TRIM(LOWER(C34))=TRIM(LOWER(K34))),"Different owner",IF(AND(TRIM(LOWER(E34))=TRIM(LOWER(J34)),NOT(TRIM(LOWER(C34))=TRIM(LOWER(K34)))),"Different contact","Different owner & contact"))) -> Match
A35: Peter Belo | B35: Aga Khan Academy Mombasa | C35: belo@agakhanacademies.org | D35: 0780505044 | E35: Lucy Gakii | F35: CUST100032 | G35: KPEDU | H35: Coast | I35: Mombasa | J35: Lucy Rimberia | K35: sameer.hanif@agakhanacademies.org; vincent.kwendo@oshwalacademy.sc.ke | L35: =IF(AND(TRIM(LOWER(E35))=TRIM(LOWER(J35)),TRIM(LOWER(C35))=TRIM(LOWER(K35))),"Match",IF(AND(NOT(TRIM(LOWER(E35))=TRIM(LOWER(J35))),TRIM(LOWER(C35))=TRIM(LOWER(K35))),"Different owner",IF(AND(TRIM(LOWER(E35))=TRIM(LOWER(J35)),NOT(TRIM(LOWER(C35))=TRIM(LOWER(K35)))),"Different contact","Different owner & contact"))) -> Different owner & contact
A36: Sameer Hanif | B36: Aga Khan Academy Mombasa | C36: sameer.hanif@agakhanacademies.org | E36: Lucy Gakii | F36: CUST100032 | G36: KPEDU | H36: Coast | I36: Mombasa | J36: Lucy Rimberia | K36: sameer.hanif@agakhanacademies.org; vincent.kwendo@oshwalacademy.sc.ke | L36: =IF(AND(TRIM(LOWER(E36))=TRIM(LOWER(J36)),TRIM(LOWER(C36))=TRIM(LOWER(K36))),"Match",IF(AND(NOT(TRIM(LOWER(E36))=TRIM(LOWER(J36))),TRIM(LOWER(C36))=TRIM(LOWER(K36))),"Different owner",IF(AND(TRIM(LOWER(E36))=TRIM(LOWER(J36)),NOT(TRIM(LOWER(C36))=TRIM(LOWER(K36)))),"Different contact","Different owner & contact"))) -> Different owner & contact
A37: shamim damji | B37: Aga Khan Academy Senior School Nairobi | C37: shamim.damji@akesk.org | E37: Yvonne Otieno | F37: CUST100033 | G37: KPEDU | H37: Nairobi West | I37: Parklands | J37: Diana Wendy | K37: sismail@akesk.org | L37: =IF(AND(TRIM(LOWER(E37))=TRIM(LOWER(J37)),TRIM(LOWER(C37))=TRIM(LOWER(K37))),"Match",IF(AND(NOT(TRIM(LOWER(E37))=TRIM(LOWER(J37))),TRIM(LOWER(C37))=TRIM(LOWER(K37))),"Different owner",IF(AND(TRIM(LOWER(E37))=TRIM(LOWER(J37)),NOT(TRIM(LOWER(C37))=TRIM(LOWER(K37)))),"Different contact","Different owner & contact"))) -> Different owner & contact
A38: Gulzar Suleiman | B38: Aga Khan Development Network - Kenya | C38: gulzar.suleman@akdn.org | E38: June Chesire | F38: CUST100034 | G38: KPHEALTH | H38: Nairobi Central | I38: CBD | J38: June Chesire | K38: gulzar.suleman@akdnkenya.org | L38: =IF(AND(TRIM(LOWER(E38))=TRIM(LOWER(J38)),TRIM(LOWER(C38))=TRIM(LOWER(K38))),"Match",IF(AND(NOT(TRIM(LOWER(E38))=TRIM(LOWER(J38))),TRIM(LOWER(C38))=TRIM(LOWER(K38))),"Different owner",IF(AND(TRIM(LOWER(E38))=TRIM(LOWER(J38)),NOT(TRIM(LOWER(C38))=TRIM(LOWER(K38)))),"Different contact","Different owner & contact"))) -> Different contact
A39: Gulzar Suleman | B39: Aga Khan Development Network - Kenya | C39: gulzar.suleman@akdnkenya.org | E39: June Chesire | F39: CUST100034 | G39: KPHEALTH | H39: Nairobi Central | I39: CBD | J39: June Chesire | K39: gulzar.suleman@akdnkenya.org | L39: =IF(AND(TRIM(LOWER(E39))=TRIM(LOWER(J39)),TRIM(LOWER(C39))=TRIM(LOWER(K39))),"Match",IF(AND(NOT(TRIM(LOWER(E39))=TRIM(LOWER(J39))),TRIM(LOWER(C39))=TRIM(LOWER(K39))),"Different owner",IF(AND(TRIM(LOWER(E39))=TRIM(LOWER(J39)),NOT(TRIM(LOWER(C39))=TRIM(LOWER(K39)))),"Different contact","Different owner & contact"))) -> Match
A40: Alice Kariuki | B40: Aga Khan Health Service Kenya | C40: alice.kariuki@aku.edu | E40: June Chesire | F40: CUST100035 | G40: KPHEALTH | H40: Nairobi West | I40: Parklands | J40: June Chesire | K40: anne.nyambura@aku.edu | L40: =IF(AND(TRIM(LOWER(E40))=TRIM(LOWER(J40)),TRIM(LOWER(C40))=TRIM(LOWER(K40))),"Match",IF(AND(NOT(TRIM(LOWER(E40))=TRIM(LOWER(J40))),TRIM(LOWER(C40))=TRIM(LOWER(K40))),"Different owner",IF(AND(TRIM(LOWER(E40))=TRIM(LOWER(J40)),NOT(TRIM(LOWER(C40))=TRIM(LOWER(K40)))),"Different contact","Different owner & contact"))) -> Different contact
A41: Anne Nyambura | B41: Aga Khan Health Service Kenya | C41: anne.nyambura@aku.edu | E41: June Chesire | F41: CUST100035 | G41: KPHEALTH | H41: Nairobi West | I41: Parklands | J41: June Chesire | K41: anne.nyambura@aku.edu | L41: =IF(AND(TRIM(LOWER(E41))=TRIM(LOWER(J41)),TRIM(LOWER(C41))=TRIM(LOWER(K41))),"Match",IF(AND(NOT(TRIM(LOWER(E41))=TRIM(LOWER(J41))),TRIM(LOWER(C41))=TRIM(LOWER(K41))),"Different owner",IF(AND(TRIM(LOWER(E41))=TRIM(LOWER(J41)),NOT(TRIM(LOWER(C41))=TRIM(LOWER(K41)))),"Different contact","Different owner & contact"))) -> Match
A42: Gady Onyango | B42: Aga Khan Health Service Kenya | C42: gady.onyango@aku.edu | D42: 0711092611 | E42: June Chesire | F42: CUST100035 | G42: KPHEALTH | H42: Nairobi West | I42: Parklands | J42: June Chesire | K42: anne.nyambura@aku.edu | L42: =IF(AND(TRIM(LOWER(E42))=TRIM(LOWER(J42)),TRIM(LOWER(C42))=TRIM(LOWER(K42))),"Match",IF(AND(NOT(TRIM(LOWER(E42))=TRIM(LOWER(J42))),TRIM(LOWER(C42))=TRIM(LOWER(K42))),"Different owner",IF(AND(TRIM(LOWER(E42))=TRIM(LOWER(J42)),NOT(TRIM(LOWER(C42))=TRIM(LOWER(K42)))),"Different contact","Different owner & contact"))) -> Different contact
A43: Mr Keval | B43: Aga Khan Sports Centre | C43: kp@aksc.co.ke | D43: 0724710486 | E43: Yvonne Otieno | F43: CUST100038 | G43: KPEDU | H43: Nairobi West | I43: Parklands | J43: Diana Wendy | K43: info@aksc.co.ke | L43: =IF(AND(TRIM(LOWER(E43))=TRIM(LOWER(J43)),TRIM(LOWER(C43))=TRIM(LOWER(K43))),"Match",IF(AND(NOT(TRIM(LOWER(E43))=TRIM(LOWER(J43))),TRIM(LOWER(C43))=TRIM(LOWER(K43))),"Different owner",IF(AND(TRIM(LOWER(E43))=TRIM(LOWER(J43)),NOT(TRIM(LOWER(C43))=TRIM(LOWER(K43)))),"Different contact","Different owner & contact"))) -> Different owner & contact
A44: salome mirenja | B44: Agra | C44: smirenja@agra.org | E44: Mercy Irungu | F44: CUST100040 | G44: KPNGO | H44: Nairobi West | I44: Westlands | J44: Mercyline Kemunto | K44: sgaitho@agra.org | L44: =IF(AND(TRIM(LOWER(E44))=TRIM(LOWER(J44)),TRIM(LOWER(C44))=TRIM(LOWER(K44))),"Match",IF(AND(NOT(TRIM(LOWER(E44))=TRIM(LOWER(J44))),TRIM(LOWER(C44))=TRIM(LOWER(K44))),"Different owner",IF(AND(TRIM(LOWER(E44))=TRIM(LOWER(J44)),NOT(TRIM(LOWER(C44))=TRIM(LOWER(K44)))),"Different contact","Different owner & contact"))) -> Different owner & contact
A45: Estherke Kimonyi | B45: Airkenya Express Ltd | C45: catering@airkenya.com | E45: Mercy Irungu | F45: CUST100046 | G45: KPAIRLINE | H45: Nairobi East | I45: Wilson Airport | J45: Mercyline Kemunto | K45: judith.mwaka@airkenya.com | L45: =IF(AND(TRIM(LOWER(E45))=TRIM(LOWER(J45)),TRIM(LOWER(C45))=TRIM(LOWER(K45))),"Match",IF(AND(NOT(TRIM(LOWER(E45))=TRIM(LOWER(J45))),TRIM(LOWER(C45))=TRIM(LOWER(K45))),"Different owner",IF(AND(TRIM(LOWER(E45))=TRIM(LOWER(J45)),NOT(TRIM(LOWER(C45))=TRIM(LOWER(K45)))),"Different contact","Different owner & contact"))) -> Different owner & contact
A46: Boston | B46: Airmarc Ltd T/A Fourpoints By Sheraton | E46: Berna Piwang | F46: CUST100047 | G46: KPHOTEL | H46: Nairobi East | I46: JKIA | J46: Berna Piwang | K46: finance@fourpointsnairobiairport.co.ke | L46: =IF(AND(TRIM(LOWER(E46))=TRIM(LOWER(J46)),TRIM(LOWER(C46))=TRIM(LOWER(K46))),"Match",IF(AND(NOT(TRIM(LOWER(E46))=TRIM(LOWER(J46))),TRIM(LOWER(C46))=TRIM(LOWER(K46))),"Different owner",IF(AND(TRIM(LOWER(E46))=TRIM(LOWER(J46)),NOT(TRIM(LOWER(C46))=TRIM(LOWER(K46)))),"Different contact","Different owner & contact"))) -> Different contact
A47: Boston | B47: Airmarc Ltd T/A Fourpoints By Sheraton | E47: Berna Piwang | F47: CUST100047 | G47: KPHOTEL | H47: Nairobi East | I47: JKIA | J47: Berna Piwang | K47: finance@fourpointsnairobiairport.co.ke | L47: =IF(AND(TRIM(LOWER(E47))=TRIM(LOWER(J47)),TRIM(LOWER(C47))=TRIM(LOWER(K47))),"Match",IF(AND(NOT(TRIM(LOWER(E47))=TRIM(LOWER(J47))),TRIM(LOWER(C47))=TRIM(LOWER(K47))),"Different owner",IF(AND(TRIM(LOWER(E47))=TRIM(LOWER(J47)),NOT(TRIM(LOWER(C47))=TRIM(LOWER(K47)))),"Different contact","Different owner & contact"))) -> Different contact
A48: Boston | B48: Airmarc Ltd T/A Fourpoints By Sheraton | E48: Berna Piwang | F48: CUST100047 | G48: KPHOTEL | H48: Nairobi East | I48: JKIA | J48: Berna Piwang | K48: finance@fourpointsnairobiairport.co.ke | L48: =IF(AND(TRIM(LOWER(E48))=TRIM(LOWER(J48)),TRIM(LOWER(C48))=TRIM(LOWER(K48))),"Match",IF(AND(NOT(TRIM(LOWER(E48))=TRIM(LOWER(J48))),TRIM(LOWER(C48))=TRIM(LOWER(K48))),"Different owner",IF(AND(TRIM(LOWER(E48))=TRIM(LOWER(J48)),NOT(TRIM(LOWER(C48))=TRIM(LOWER(K48)))),"Different contact","Different owner & contact"))) -> Different contact
A49: Boston Ouna | B49: Airmarc Ltd T/A Fourpoints By Sheraton | C49: accounts@fourpointsnairobiairport.co.ke | D49: 0715897067 | E49: Susan Ngina | F49: CUST100047 | G49: KPHOTEL | H49: Nairobi East | I49: JKIA | J49: Berna Piwang | K49: finance@fourpointsnairobiairport.co.ke | L49: =IF(AND(TRIM(LOWER(E49))=TRIM(LOWER(J49)),TRIM(LOWER(C49))=TRIM(LOWER(K49))),"Match",IF(AND(NOT(TRIM(LOWER(E49))=TRIM(LOWER(J49))),TRIM(LOWER(C49))=TRIM(LOWER(K49))),"Different owner",IF(AND(TRIM(LOWER(E49))=TRIM(LOWER(J49)),NOT(TRIM(LOWER(C49))=TRIM(LOWER(K49)))),"Different contact","Different owner & contact"))) -> Different owner & contact
A50: Boston Ouna | B50: Airmarc Ltd T/A Fourpoints By Sheraton | E50: Berna Piwang | F50: CUST100047 | G50: KPHOTEL | H50: Nairobi East | I50: JKIA | J50: Berna Piwang | K50: finance@fourpointsnairobiairport.co.ke | L50: =IF(AND(TRIM(LOWER(E50))=TRIM(LOWER(J50)),TRIM(LOWER(C50))=TRIM(LOWER(K50))),"Match",IF(AND(NOT(TRIM(LOWER(E50))=TRIM(LOWER(J50))),TRIM(LOWER(C50))=TRIM(LOWER(K50))),"Different owner",IF(AND(TRIM(LOWER(E50))=TRIM(LOWER(J50)),NOT(TRIM(LOWER(C50))=TRIM(LOWER(K50)))),"Different contact","Different owner & contact"))) -> Different contact
A51: David Opar | B51: Airmarc Ltd T/A Fourpoints By Sheraton | C51: stores@fourpointsnairobiairport.co.ke | D51: 0709760000 | E51: Berna Piwang | F51: CUST100047 | G51: KPHOTEL | H51: Nairobi East | I51: JKIA | J51: Berna Piwang | K51: finance@fourpointsnairobiairport.co.ke | L51: =IF(AND(TRIM(LOWER(E51))=TRIM(LOWER(J51)),TRIM(LOWER(C51))=TRIM(LOWER(K51))),"Match",IF(AND(NOT(TRIM(LOWER(E51))=TRIM(LOWER(J51))),TRIM(LOWER(C51))=TRIM(LOWER(K51))),"Different owner",IF(AND(TRIM(LOWER(E51))=TRIM(LOWER(J51)),NOT(TRIM(LOWER(C51))=TRIM(LOWER(K51)))),"Different contact","Different owner & contact"))) -> Different contact
A52: Kevin Omondi | B52: Airmarc Ltd T/A Fourpoints By Sheraton | C52: purchase@fourpointsnairobiairport.co.ke | D52: 0740031202 | E52: Susan Ngina | F52: CUST100047 | G52: KPHOTEL | H52: Nairobi East | I52: JKIA | J52: Berna Piwang | K52: finance@fourpointsnairobiairport.co.ke | L52: =IF(AND(TRIM(LOWER(E52))=TRIM(LOWER(J52)),TRIM(LOWER(C52))=TRIM(LOWER(K52))),"Match",IF(AND(NOT(TRIM(LOWER(E52))=TRIM(LOWER(J52))),TRIM(LOWER(C52))=TRIM(LOWER(K52))),"Different owner",IF(AND(TRIM(LOWER(E52))=TRIM(LOWER(J52)),NOT(TRIM(LOWER(C52))=TRIM(LOWER(K52)))),"Different contact","Different owner & contact"))) -> Different owner & contact
A53: Mr. Joseph | B53: Airport Landing Hotel | C53: accounts@airportlandinghotel.com | D53: 0703887777 | E53: Doreen Mugwika | F53: CUST100048 | G53: KPHOTEL | H53: Nairobi East | I53: Embakasi | J53: Doreen Mugwika | K53: accounts@airportlandinghotel.com | L53: =IF(AND(TRIM(LOWER(E53))=TRIM(LOWER(J53)),TRIM(LOWER(C53))=TRIM(LOWER(K53))),"Match",IF(AND(NOT(TRIM(LOWER(E53))=TRIM(LOWER(J53))),TRIM(LOWER(C53))=TRIM(LOWER(K53))),"Different owner",IF(AND(TRIM(LOWER(E53))=TRIM(LOWER(J53)),NOT(TRIM(LOWER(C53))=TRIM(LOWER(K53)))),"Different contact","Different owner & contact"))) -> Match
A54: Ms. Wambui | B54: Airport Landing Hotel | C54: airportlanding254@gmail.com | D54: 0722960407 | E54: Doreen Mugwika | F54: CUST100048 | G54: KPHOTEL | H54: Nairobi East | I54: Embakasi | J54: Doreen Mugwika | K54: accounts@airportlandinghotel.com | L54: =IF(AND(TRIM(LOWER(E54))=TRIM(LOWER(J54)),TRIM(LOWER(C54))=TRIM(LOWER(K54))),"Match",IF(AND(NOT(TRIM(LOWER(E54))=TRIM(LOWER(J54))),TRIM(LOWER(C54))=TRIM(LOWER(K54))),"Different owner",IF(AND(TRIM(LOWER(E54))=TRIM(LOWER(J54)),NOT(TRIM(LOWER(C54))=TRIM(LOWER(K54)))),"Different contact","Different owner & contact"))) -> Different contact
A55: Bessy Muthuri | B55: Al Jazeera Kiswahili Limited | C55: bessy.muthuri@aljazeera.net | E55: Susan Ngina | F55: CUST100052 | G55: KPSERVICE | H55: Nairobi West | I55: Upper Hill | J55: Diana Wendy | K55: bessy.muthuri@aljazeera.net | L55: =IF(AND(TRIM(LOWER(E55))=TRIM(LOWER(J55)),TRIM(LOWER(C55))=TRIM(LOWER(K55))),"Match",IF(AND(NOT(TRIM(LOWER(E55))=TRIM(LOWER(J55))),TRIM(LOWER(C55))=TRIM(LOWER(K55))),"Different owner",IF(AND(TRIM(LOWER(E55))=TRIM(LOWER(J55)),NOT(TRIM(LOWER(C55))=TRIM(LOWER(K55)))),"Different contact","Different owner & contact"))) -> Different owner
A56: Raphael Kigo | B56: All Africa Conference Of Churches | C56: raphael@aacc-ceta.org | D56: 0724253354 | E56: Irene Luketelo | F56: CUST100056 | G56: KPRELGS | H56: Nairobi West | I56: Waiyaki Way | J56: Irene Luketelo | K56: raphael@aacc-ceta.org | L56: =IF(AND(TRIM(LOWER(E56))=TRIM(LOWER(J56)),TRIM(LOWER(C56))=TRIM(LOWER(K56))),"Match",IF(AND(NOT(TRIM(LOWER(E56))=TRIM(LOWER(J56))),TRIM(LOWER(C56))=TRIM(LOWER(K56))),"Different owner",IF(AND(TRIM(LOWER(E56))=TRIM(LOWER(J56)),NOT(TRIM(LOWER(C56))=TRIM(LOWER(K56)))),"Different contact","Different owner & contact"))) -> Match
A57: Naomi Wangare | B57: All And Sundry Services | C57: allandsundriesservices@gmail.com | D57: 0721534305 | E57: Irene Luketelo | F57: CUST100057 | G57: KPCCLNRS | H57: Nairobi East | I57: Thika Road | J57: Irene Luketelo | K57: allandsundryservices@gmail.com | L57: =IF(AND(TRIM(LOWER(E57))=TRIM(LOWER(J57)),TRIM(LOWER(C57))=TRIM(LOWER(K57))),"Match",IF(AND(NOT(TRIM(LOWER(E57))=TRIM(LOWER(J57))),TRIM(LOWER(C57))=TRIM(LOWER(K57))),"Different owner",IF(AND(TRIM(LOWER(E57))=TRIM(LOWER(J57)),NOT(TRIM(LOWER(C57))=TRIM(LOWER(K57)))),"Different contact","Different owner & contact"))) -> Different contact
A58: Wilfred Thiong'o | B58: All Saints Cathedral Church. | C58: wthiongo@allsaintsnairobi.org | D58: 0702645062 | E58: Susan Ngina | F58: CUST100058 | G58: KPRELGS | H58: Nairobi Central | I58: CBD | J58: Berna Piwang | K58: wthiongo@allsaintsnairobi.org | L58: =IF(AND(TRIM(LOWER(E58))=TRIM(LOWER(J58)),TRIM(LOWER(C58))=TRIM(LOWER(K58))),"Match",IF(AND(NOT(TRIM(LOWER(E58))=TRIM(LOWER(J58))),TRIM(LOWER(C58))=TRIM(LOWER(K58))),"Different owner",IF(AND(TRIM(LOWER(E58))=TRIM(LOWER(J58)),NOT(TRIM(LOWER(C58))=TRIM(LOWER(K58)))),"Different contact","Different owner & contact"))) -> Different owner
A59: Jeremiah Katonde | B59: Allterrain Services Kenya Ltd | C59: jkatonde@tsebo.com | D59: 0723557914 | E59: Irene Luketelo | F59: CUST100059 | G59: KPCCLNRS | H59: Nairobi West | I59: Ruiru | J59: Irene Luketelo | K59: akungu@tsebo.com; bogaga@tsebo.com | L59: =IF(AND(TRIM(LOWER(E59))=TRIM(LOWER(J59)),TRIM(LOWER(C59))=TRIM(LOWER(K59))),"Match",IF(AND(NOT(TRIM(LOWER(E59))=TRIM(LOWER(J59))),TRIM(LOWER(C59))=TRIM(LOWER(K59))),"Different owner",IF(AND(TRIM(LOWER(E59))=TRIM(LOWER(J59)),NOT(TRIM(LOWER(C59))=TRIM(LOWER(K59)))),"Different contact","Different owner & contact"))) -> Different contact
A60: James Macharia | B60: Althaus Services Ltd | C60: james@althaus.co.ke | D60: 0724437445 | E60: Irene Luketelo | F60: CUST100061 | G60: KPPMGR | H60: Nairobi West | I60: Westlands | J60: Irene Luketelo | K60: stephen@althaus.co.ke; mike.kimathi@althaus.co.ke; margaret@althaus.co.ke | L60: =IF(AND(TRIM(LOWER(E60))=TRIM(LOWER(J60)),TRIM(LOWER(C60))=TRIM(LOWER(K60))),"Match",IF(AND(NOT(TRIM(LOWER(E60))=TRIM(LOWER(J60))),TRIM(LOWER(C60))=TRIM(LOWER(K60))),"Different owner",IF(AND(TRIM(LOWER(E60))=TRIM(LOWER(J60)),NOT(TRIM(LOWER(C60))=TRIM(LOWER(K60)))),"Different contact","Different owner & contact"))) -> Different contact
A61: Peris Mureithi | B61: Amadeus GTD Ltd | C61: pmureithi@amadeus.co.ke | D61: 0717704826 | E61: Yvonne Otieno | F61: CUST100063 | G61: KPSERVICE | H61: Nairobi West | I61: Upper Hill | J61: Berna Piwang | K61: peris.mureithi@amadeus.com | L61: =IF(AND(TRIM(LOWER(E61))=TRIM(LOWER(J61)),TRIM(LOWER(C61))=TRIM(LOWER(K61))),"Match",IF(AND(NOT(TRIM(LOWER(E61))=TRIM(LOWER(J61))),TRIM(LOWER(C61))=TRIM(LOWER(K61))),"Different owner",IF(AND(TRIM(LOWER(E61))=TRIM(LOWER(J61)),NOT(TRIM(LOWER(C61))=TRIM(LOWER(K61)))),"Different contact","Different owner & contact"))) -> Different owner & contact
A62: Rueben Gitonga | B62: Amani Ya Juu Foundation | C62: cafe.assistant@amaniafrica.org | D62: 0710572892 | E62: Doreen Mugwika | F62: CUST101436 | G62: KPNGO | H62: Nairobi West | I62: Westlands | J62: Doreen Mugwika | K62: gardencafe@amaniafrica.org | L62: =IF(AND(TRIM(LOWER(E62))=TRIM(LOWER(J62)),TRIM(LOWER(C62))=TRIM(LOWER(K62))),"Match",IF(AND(NOT(TRIM(LOWER(E62))=TRIM(LOWER(J62))),TRIM(LOWER(C62))=TRIM(LOWER(K62))),"Different owner",IF(AND(TRIM(LOWER(E62))=TRIM(LOWER(J62)),NOT(TRIM(LOWER(C62))=TRIM(LOWER(K62)))),"Different contact","Different owner & contact"))) -> Different contact
A63: Chris Rwamwejo | B63: Amtoll Rwanda | C63: chris@byudagroup.com | D63: +250 783 202 777 | E63: Florence Karaya | F63: CUST100069 | G63: KPEXP | H63: Rwanda | I63: Rwanda | J63: Florence Karaya | K63: jacky.amtoll.rw@gmail.com | L63: =IF(AND(TRIM(LOWER(E63))=TRIM(LOWER(J63)),TRIM(LOWER(C63))=TRIM(LOWER(K63))),"Match",IF(AND(NOT(TRIM(LOWER(E63))=TRIM(LOWER(J63))),TRIM(LOWER(C63))=TRIM(LOWER(K63))),"Different owner",IF(AND(TRIM(LOWER(E63))=TRIM(LOWER(J63)),NOT(TRIM(LOWER(C63))=TRIM(LOWER(K63)))),"Different contact","Different owner & contact"))) -> Different contact
A64: Alvin Mutama | B64: And Beyond Kenya Limited | C64: alvin.mutama@andbeyond.com | E64: VQL | F64: CUST100071 | G64: KPHOTEL | H64: Nairobi West | I64: Westlands | J64: Irene Luketelo | K64: triza.njeri@andBeyond.com | L64: =IF(AND(TRIM(LOWER(E64))=TRIM(LOWER(J64)),TRIM(LOWER(C64))=TRIM(LOWER(K64))),"Match",IF(AND(NOT(TRIM(LOWER(E64))=TRIM(LOWER(J64))),TRIM(LOWER(C64))=TRIM(LOWER(K64))),"Different owner",IF(AND(TRIM(LOWER(E64))=TRIM(LOWER(J64)),NOT(TRIM(LOWER(C64))=TRIM(LOWER(K64)))),"Different contact","Different owner & contact"))) -> Different owner & contact
A65: Peterson Muraya | B65: And Beyond Kenya Limited | C65: peterson.muraya@andbeyond.com | E65: Irene Luketelo | F65: CUST100071 | G65: KPHOTEL | H65: Nairobi West | I65: Westlands | J65: Irene Luketelo | K65: triza.njeri@andBeyond.com | L65: =IF(AND(TRIM(LOWER(E65))=TRIM(LOWER(J65)),TRIM(LOWER(C65))=TRIM(LOWER(K65))),"Match",IF(AND(NOT(TRIM(LOWER(E65))=TRIM(LOWER(J65))),TRIM(LOWER(C65))=TRIM(LOWER(K65))),"Different owner",IF(AND(TRIM(LOWER(E65))=TRIM(LOWER(J65)),NOT(TRIM(LOWER(C65))=TRIM(LOWER(K65)))),"Different contact","Different owner & contact"))) -> Different contact
A66: Hellen Kaberere | B66: Andela Kenya Ltd | C66: hellen.kaberere@andela.com | E66: June Chesire | F66: CUST100072 | G66: KPEDU | H66: Nairobi East | I66: Thika Road | J66: Shirleen Chebet | K66: hellen.kaberere@andela.com | L66: =IF(AND(TRIM(LOWER(E66))=TRIM(LOWER(J66)),TRIM(LOWER(C66))=TRIM(LOWER(K66))),"Match",IF(AND(NOT(TRIM(LOWER(E66))=TRIM(LOWER(J66))),TRIM(LOWER(C66))=TRIM(LOWER(K66))),"Different owner",IF(AND(TRIM(LOWER(E66))=TRIM(LOWER(J66)),NOT(TRIM(LOWER(C66))=TRIM(LOWER(K66)))),"Different contact","Different owner & contact"))) -> Different owner
A67: Israel wachira | B67: Androse Enterprises Ltd | C67: israel.wachira05@gmail.com | D67: 0727903059 | E67: June Chesire | F67: CUST100073 | G67: KPPMGR | H67: Nairobi Central | I67: CBD | J67: Berna Piwang | K67: androsenterprisesltd@gmail.com | L67: =IF(AND(TRIM(LOWER(E67))=TRIM(LOWER(J67)),TRIM(LOWER(C67))=TRIM(LOWER(K67))),"Match",IF(AND(NOT(TRIM(LOWER(E67))=TRIM(LOWER(J67))),TRIM(LOWER(C67))=TRIM(LOWER(K67))),"Different owner",IF(AND(TRIM(LOWER(E67))=TRIM(LOWER(J67)),NOT(TRIM(LOWER(C67))=TRIM(LOWER(K67)))),"Different contact","Different owner & contact"))) -> Different owner & contact
A68: Angela procurement | B68: Ankole Grill Limited | E68: Berna Piwang | F68: CUST100077 | G68: KPREST | H68: Nairobi West | I68: Ngong Road | J68: Berna Piwang | K68: accounts@ankole.co.ke | L68: =IF(AND(TRIM(LOWER(E68))=TRIM(LOWER(J68)),TRIM(LOWER(C68))=TRIM(LOWER(K68))),"Match",IF(AND(NOT(TRIM(LOWER(E68))=TRIM(LOWER(J68))),TRIM(LOWER(C68))=TRIM(LOWER(K68))),"Different owner",IF(AND(TRIM(LOWER(E68))=TRIM(LOWER(J68)),NOT(TRIM(LOWER(C68))=TRIM(LOWER(K68)))),"Different contact","Different owner & contact"))) -> Different contact
A69: Mercy Birech | B69: Ankole Grill Limited | C69: procurement@ankole.co.ke | D69: 0748465776 | E69: Susan Ngina | F69: CUST100077 | G69: KPREST | H69: Nairobi West | I69: Ngong Road | J69: Berna Piwang | K69: accounts@ankole.co.ke | L69: =IF(AND(TRIM(LOWER(E69))=TRIM(LOWER(J69)),TRIM(LOWER(C69))=TRIM(LOWER(K69))),"Match",IF(AND(NOT(TRIM(LOWER(E69))=TRIM(LOWER(J69))),TRIM(LOWER(C69))=TRIM(LOWER(K69))),"Different owner",IF(AND(TRIM(LOWER(E69))=TRIM(LOWER(J69)),NOT(TRIM(LOWER(C69))=TRIM(LOWER(K69)))),"Different contact","Different owner & contact"))) -> Different owner & contact
A70: Vincent Odhiambo Oyugi | B70: Ankole Grill Limited | C70: stores.kitisuru@ankole.co.ke | D70: 0723335043 | E70: Susan Ngina | F70: CUST100077 | G70: KPREST | H70: Nairobi West | I70: Ngong Road | J70: Berna Piwang | K70: accounts@ankole.co.ke | L70: =IF(AND(TRIM(LOWER(E70))=TRIM(LOWER(J70)),TRIM(LOWER(C70))=TRIM(LOWER(K70))),"Match",IF(AND(NOT(TRIM(LOWER(E70))=TRIM(LOWER(J70))),TRIM(LOWER(C70))=TRIM(LOWER(K70))),"Different owner",IF(AND(TRIM(LOWER(E70))=TRIM(LOWER(J70)),NOT(TRIM(LOWER(C70))=TRIM(LOWER(K70)))),"Different contact","Different owner & contact"))) -> Different owner & contact
A71: Careena Careena | B71: Aquadrom Restaurant | D71: 0702436500 | E71: Lucy Gakii | F71: CUST100079 | G71: KPREST | H71: Coast | I71: Mombasa | J71: Lucy Rimberia | K71: aquadromlimited@gmail.com | L71: =IF(AND(TRIM(LOWER(E71))=TRIM(LOWER(J71)),TRIM(LOWER(C71))=TRIM(LOWER(K71))),"Match",IF(AND(NOT(TRIM(LOWER(E71))=TRIM(LOWER(J71))),TRIM(LOWER(C71))=TRIM(LOWER(K71))),"Different owner",IF(AND(TRIM(LOWER(E71))=TRIM(LOWER(J71)),NOT(TRIM(LOWER(C71))=TRIM(LOWER(K71)))),"Different contact","Different owner & contact"))) -> Different owner & contact
A72: Vivian Vivian | B72: Aquadrom Restaurant | C72: yulspurchasing@gmail.com | D72: 0702436500 | E72: Lucy Gakii | F72: CUST100079 | G72: KPREST | H72: Coast | I72: Mombasa | J72: Lucy Rimberia | K72: aquadromlimited@gmail.com | L72: =IF(AND(TRIM(LOWER(E72))=TRIM(LOWER(J72)),TRIM(LOWER(C72))=TRIM(LOWER(K72))),"Match",IF(AND(NOT(TRIM(LOWER(E72))=TRIM(LOWER(J72))),TRIM(LOWER(C72))=TRIM(LOWER(K72))),"Different owner",IF(AND(TRIM(LOWER(E72))=TRIM(LOWER(J72)),NOT(TRIM(LOWER(C72))=TRIM(LOWER(K72)))),"Different contact","Different owner & contact"))) -> Different owner & contact
A73: mufaddal mufaddal | B73: Aquadrom Restaurant | D73: 0722566336 | E73: Lucy Gakii | F73: CUST100079 | G73: KPREST | H73: Coast | I73: Mombasa | J73: Lucy Rimberia | K73: aquadromlimited@gmail.com | L73: =IF(AND(TRIM(LOWER(E73))=TRIM(LOWER(J73)),TRIM(LOWER(C73))=TRIM(LOWER(K73))),"Match",IF(AND(NOT(TRIM(LOWER(E73))=TRIM(LOWER(J73))),TRIM(LOWER(C73))=TRIM(LOWER(K73))),"Different owner",IF(AND(TRIM(LOWER(E73))=TRIM(LOWER(J73)),NOT(TRIM(LOWER(C73))=TRIM(LOWER(K73)))),"Different contact","Different owner & contact"))) -> Different owner & contact
A74: Elizabeth Kamene | B74: Arichem Ltd | C74: elizabeth@arichem.co.ke | E74: Mercy Irungu | F74: CUST100081 | G74: KPINDUSTRY | H74: Nairobi East | I74: Embakasi | J74: Mercyline Kemunto | K74: fkirimi@arichem.co.ke | L74: =IF(AND(TRIM(LOWER(E74))=TRIM(LOWER(J74)),TRIM(LOWER(C74))=TRIM(LOWER(K74))),"Match",IF(AND(NOT(TRIM(LOWER(E74))=TRIM(LOWER(J74))),TRIM(LOWER(C74))=TRIM(LOWER(K74))),"Different owner",IF(AND(TRIM(LOWER(E74))=TRIM(LOWER(J74)),NOT(TRIM(LOWER(C74))=TRIM(LOWER(K74)))),"Different contact","Different owner & contact"))) -> Different owner & contact
A75: Lydia | B75: Art Investments Ltd C/O Knight Frank Kenya Ltd | E75: Collins Kazee | F75: CUST100083 | G75: KPPMGR | H75: Nairobi West | I75: Westlands | J75: Irene Luketelo | K75: lydia-ndichu@ke.knightfrank.com | L75: =IF(AND(TRIM(LOWER(E75))=TRIM(LOWER(J75)),TRIM(LOWER(C75))=TRIM(LOWER(K75))),"Match",IF(AND(NOT(TRIM(LOWER(E75))=TRIM(LOWER(J75))),TRIM(LOWER(C75))=TRIM(LOWER(K75))),"Different owner",IF(AND(TRIM(LOWER(E75))=TRIM(LOWER(J75)),NOT(TRIM(LOWER(C75))=TRIM(LOWER(K75)))),"Different contact","Different owner & contact"))) -> Different owner & contact
A76: Lydia Ndichu | B76: Art Investments Ltd C/O Knight Frank Kenya Ltd | C76: lydia-ndichu@ke.knightfrank.com | E76: Irene Luketelo | F76: CUST100083 | G76: KPPMGR | H76: Nairobi West | I76: Westlands | J76: Irene Luketelo | K76: lydia-ndichu@ke.knightfrank.com | L76: =IF(AND(TRIM(LOWER(E76))=TRIM(LOWER(J76)),TRIM(LOWER(C76))=TRIM(LOWER(K76))),"Match",IF(AND(NOT(TRIM(LOWER(E76))=TRIM(LOWER(J76))),TRIM(LOWER(C76))=TRIM(LOWER(K76))),"Different owner",IF(AND(TRIM(LOWER(E76))=TRIM(LOWER(J76)),NOT(TRIM(LOWER(C76))=TRIM(LOWER(K76)))),"Different contact","Different owner & contact"))) -> Match
A77: Cosmas Munene | B77: Artcafe Coffee & Bakery Ltd | C77: cosmas.munene@artcaffe.co.ke | D77: 0727735356 | E77: Susan Ngina | F77: CUST100084 | G77: KPREST | H77: Nairobi East | I77: Thika Road | J77: Susan Mwathi | K77: grace@artcaffe.co.ke | L77: =IF(AND(TRIM(LOWER(E77))=TRIM(LOWER(J77)),TRIM(LOWER(C77))=TRIM(LOWER(K77))),"Match",IF(AND(NOT(TRIM(LOWER(E77))=TRIM(LOWER(J77))),TRIM(LOWER(C77))=TRIM(LOWER(K77))),"Different owner",IF(AND(TRIM(LOWER(E77))=TRIM(LOWER(J77)),NOT(TRIM(LOWER(C77))=TRIM(LOWER(K77)))),"Different contact","Different owner & contact"))) -> Different owner & contact
A78: Francis Mutuku | B78: Artcafe Coffee & Bakery Ltd | C78: francis.mutuku@artcaffe.co.ke | E78: Susan Ngina | F78: CUST100084 | G78: KPREST | H78: Nairobi East | I78: Thika Road | J78: Susan Mwathi | K78: grace@artcaffe.co.ke | L78: =IF(AND(TRIM(LOWER(E78))=TRIM(LOWER(J78)),TRIM(LOWER(C78))=TRIM(LOWER(K78))),"Match",IF(AND(NOT(TRIM(LOWER(E78))=TRIM(LOWER(J78))),TRIM(LOWER(C78))=TRIM(LOWER(K78))),"Different owner",IF(AND(TRIM(LOWER(E78))=TRIM(LOWER(J78)),NOT(TRIM(LOWER(C78))=TRIM(LOWER(K78)))),"Different contact","Different owner & contact"))) -> Different owner & contact
A79: Grace Njeru | B79: Artcafe Coffee & Bakery Ltd | C79: grace@artcaffe.co.ke | D79: 0727545962 | E79: Susan Ngina | F79: CUST100084 | G79: KPREST | H79: Nairobi East | I79: Thika Road | J79: Susan Mwathi | K79: grace@artcaffe.co.ke | L79: =IF(AND(TRIM(LOWER(E79))=TRIM(LOWER(J79)),TRIM(LOWER(C79))=TRIM(LOWER(K79))),"Match",IF(AND(NOT(TRIM(LOWER(E79))=TRIM(LOWER(J79))),TRIM(LOWER(C79))=TRIM(LOWER(K79))),"Different owner",IF(AND(TRIM(LOWER(E79))=TRIM(LOWER(J79)),NOT(TRIM(LOWER(C79))=TRIM(LOWER(K79)))),"Different contact","Different owner & contact"))) -> Different owner
A80: Anne | B80: Asefah Ltd | D80: 0722-727390 | E80: Collins Kazee | F80: CUST100085 | G80: KPSERVICE | H80: Nairobi East | I80: South C | J80: Shirleen Chebet | K80: stores@ngonghillshotel.com | L80: =IF(AND(TRIM(LOWER(E80))=TRIM(LOWER(J80)),TRIM(LOWER(C80))=TRIM(LOWER(K80))),"Match",IF(AND(NOT(TRIM(LOWER(E80))=TRIM(LOWER(J80))),TRIM(LOWER(C80))=TRIM(LOWER(K80))),"Different owner",IF(AND(TRIM(LOWER(E80))=TRIM(LOWER(J80)),NOT(TRIM(LOWER(C80))=TRIM(LOWER(K80)))),"Different contact","Different owner & contact"))) -> Different owner & contact
A81: Anne Kiragu | B81: Asefah Ltd | C81: annek@asefah.com | E81: Mercy Irungu | F81: CUST100085 | G81: KPSERVICE | H81: Nairobi East | I81: South C | J81: Shirleen Chebet | K81: stores@ngonghillshotel.com | L81: =IF(AND(TRIM(LOWER(E81))=TRIM(LOWER(J81)),TRIM(LOWER(C81))=TRIM(LOWER(K81))),"Match",IF(AND(NOT(TRIM(LOWER(E81))=TRIM(LOWER(J81))),TRIM(LOWER(C81))=TRIM(LOWER(K81))),"Different owner",IF(AND(TRIM(LOWER(E81))=TRIM(LOWER(J81)),NOT(TRIM(LOWER(C81))=TRIM(LOWER(K81)))),"Different contact","Different owner & contact"))) -> Different owner & contact
A82: Mike Mike | B82: Ashnil Hotels Ltd | C82: mike@ashnilhotels.com | D82: 0733713713 | E82: Irene Luketelo | F82: CUST100086 | G82: KPHOTEL | H82: Nairobi East | I82: Mombasa Road | J82: Irene Luketelo | K82: accounts@ashnilhotels.com | L82: =IF(AND(TRIM(LOWER(E82))=TRIM(LOWER(J82)),TRIM(LOWER(C82))=TRIM(LOWER(K82))),"Match",IF(AND(NOT(TRIM(LOWER(E82))=TRIM(LOWER(J82))),TRIM(LOWER(C82))=TRIM(LOWER(K82))),"Different owner",IF(AND(TRIM(LOWER(E82))=TRIM(LOWER(J82)),NOT(TRIM(LOWER(C82))=TRIM(LOWER(K82)))),"Different contact","Different owner & contact"))) -> Different contact
A83: Mike Mutuku | B83: Ashnil Hotels Ltd | C83: accounts@ashnilhotels.com | E83: VQL | F83: CUST100086 | G83: KPHOTEL | H83: Nairobi East | I83: Mombasa Road | J83: Irene Luketelo | K83: accounts@ashnilhotels.com | L83: =IF(AND(TRIM(LOWER(E83))=TRIM(LOWER(J83)),TRIM(LOWER(C83))=TRIM(LOWER(K83))),"Match",IF(AND(NOT(TRIM(LOWER(E83))=TRIM(LOWER(J83))),TRIM(LOWER(C83))=TRIM(LOWER(K83))),"Different owner",IF(AND(TRIM(LOWER(E83))=TRIM(LOWER(J83)),NOT(TRIM(LOWER(C83))=TRIM(LOWER(K83)))),"Different contact","Different owner & contact"))) -> Different owner
A84: Nixon | B84: Ashnil Hotels Ltd | E84: Berna Piwang | F84: CUST100086 | G84: KPHOTEL | H84: Nairobi East | I84: Mombasa Road | J84: Irene Luketelo | K84: accounts@ashnilhotels.com | L84: =IF(AND(TRIM(LOWER(E84))=TRIM(LOWER(J84)),TRIM(LOWER(C84))=TRIM(LOWER(K84))),"Match",IF(AND(NOT(TRIM(LOWER(E84))=TRIM(LOWER(J84))),TRIM(LOWER(C84))=TRIM(LOWER(K84))),"Different owner",IF(AND(TRIM(LOWER(E84))=TRIM(LOWER(J84)),NOT(TRIM(LOWER(C84))=TRIM(LOWER(K84)))),"Different contact","Different owner & contact"))) -> Different owner & contact
A85: Julie | B85: August 7Th Memorial Trust | C85: admin@memorialparkkenya.org | D85: 0722323302 | E85: Yvonne Otieno | F85: CUST100088 | G85: KPSERVICE | H85: Nairobi Central | I85: CBD | J85: Shirleen Chebet | L85: =IF(AND(TRIM(LOWER(E85))=TRIM(LOWER(J85)),TRIM(LOWER(C85))=TRIM(LOWER(K85))),"Match",IF(AND(NOT(TRIM(LOWER(E85))=TRIM(LOWER(J85))),TRIM(LOWER(C85))=TRIM(LOWER(K85))),"Different owner",IF(AND(TRIM(LOWER(E85))=TRIM(LOWER(J85)),NOT(TRIM(LOWER(C85))=TRIM(LOWER(K85)))),"Different contact","Different owner & contact"))) -> Different owner & contact
A86: Nick Nyoike | B86: Australian High Commission - Nairobi | C86: nick.nyoike@dfat.gov.au | D86: 020 4277100 | E86: Doreen Mugwika | F86: CUST100089 | G86: KPNGO | H86: Nairobi West | I86: Westlands | J86: Shirleen Chebet | K86: nairobi.property@dfat.gov.au | L86: =IF(AND(TRIM(LOWER(E86))=TRIM(LOWER(J86)),TRIM(LOWER(C86))=TRIM(LOWER(K86))),"Match",IF(AND(NOT(TRIM(LOWER(E86))=TRIM(LOWER(J86))),TRIM(LOWER(C86))=TRIM(LOWER(K86))),"Different owner",IF(AND(TRIM(LOWER(E86))=TRIM(LOWER(J86)),NOT(TRIM(LOWER(C86))=TRIM(LOWER(K86)))),"Different contact","Different owner & contact"))) -> Different owner & contact
A87: Caroline Manyinsa | B87: Avenue Healthcare Ltd | C87: foodservice@avenuehealthcare.com | D87: 0723932855 | E87: Susan Ngina | F87: CUST100091 | G87: KPHEALTH | H87: Nairobi West | I87: Kisumu | J87: June Chesire | K87: okeyo@avenuehealthcare.com | L87: =IF(AND(TRIM(LOWER(E87))=TRIM(LOWER(J87)),TRIM(LOWER(C87))=TRIM(LOWER(K87))),"Match",IF(AND(NOT(TRIM(LOWER(E87))=TRIM(LOWER(J87))),TRIM(LOWER(C87))=TRIM(LOWER(K87))),"Different owner",IF(AND(TRIM(LOWER(E87))=TRIM(LOWER(J87)),NOT(TRIM(LOWER(C87))=TRIM(LOWER(K87)))),"Different contact","Different owner & contact"))) -> Different owner & contact
A88: Catherine Mbugua | B88: Avenue Healthcare Ltd | C88: kmbugua@avenueahealthcare.com | D88: 0110088083 | E88: Susan Ngina | F88: CUST100091 | G88: KPHEALTH | H88: Nairobi West | I88: Kisumu | J88: June Chesire | K88: okeyo@avenuehealthcare.com | L88: =IF(AND(TRIM(LOWER(E88))=TRIM(LOWER(J88)),TRIM(LOWER(C88))=TRIM(LOWER(K88))),"Match",IF(AND(NOT(TRIM(LOWER(E88))=TRIM(LOWER(J88))),TRIM(LOWER(C88))=TRIM(LOWER(K88))),"Different owner",IF(AND(TRIM(LOWER(E88))=TRIM(LOWER(J88)),NOT(TRIM(LOWER(C88))=TRIM(LOWER(K88)))),"Different contact","Different owner & contact"))) -> Different owner & contact
A89: Catherine Mbugua | B89: Avenue Healthcare Ltd | C89: kmbugua@avenuehealthcare.com | D89: 110088083 | E89: Susan Ngina | F89: CUST100091 | G89: KPHEALTH | H89: Nairobi West | I89: Kisumu | J89: June Chesire | K89: okeyo@avenuehealthcare.com | L89: =IF(AND(TRIM(LOWER(E89))=TRIM(LOWER(J89)),TRIM(LOWER(C89))=TRIM(LOWER(K89))),"Match",IF(AND(NOT(TRIM(LOWER(E89))=TRIM(LOWER(J89))),TRIM(LOWER(C89))=TRIM(LOWER(K89))),"Different owner",IF(AND(TRIM(LOWER(E89))=TRIM(LOWER(J89)),NOT(TRIM(LOWER(C89))=TRIM(LOWER(K89)))),"Different contact","Different owner & contact"))) -> Different owner & contact
A90: Catherine Olande | B90: Avenue Healthcare Ltd | C90: admin.kisumu@avenuehealthcare.com | D90: 0718860200 | E90: Susan Ngina | F90: CUST100091 | G90: KPHEALTH | H90: Nairobi West | I90: Kisumu | J90: June Chesire | K90: okeyo@avenuehealthcare.com | L90: =IF(AND(TRIM(LOWER(E90))=TRIM(LOWER(J90)),TRIM(LOWER(C90))=TRIM(LOWER(K90))),"Match",IF(AND(NOT(TRIM(LOWER(E90))=TRIM(LOWER(J90))),TRIM(LOWER(C90))=TRIM(LOWER(K90))),"Different owner",IF(AND(TRIM(LOWER(E90))=TRIM(LOWER(J90)),NOT(TRIM(LOWER(C90))=TRIM(LOWER(K90)))),"Different contact","Different owner & contact"))) -> Different owner & contact
A91: Collins Omondi | B91: Avenue Healthcare Ltd | C91: collins.omondi@avenuehealthcare.com | E91: Lucy Gakii | F91: CUST100091 | G91: KPHEALTH | H91: Nairobi West | I91: Kisumu | J91: June Chesire | K91: okeyo@avenuehealthcare.com | L91: =IF(AND(TRIM(LOWER(E91))=TRIM(LOWER(J91)),TRIM(LOWER(C91))=TRIM(LOWER(K91))),"Match",IF(AND(NOT(TRIM(LOWER(E91))=TRIM(LOWER(J91))),TRIM(LOWER(C91))=TRIM(LOWER(K91))),"Different owner",IF(AND(TRIM(LOWER(E91))=TRIM(LOWER(J91)),NOT(TRIM(LOWER(C91))=TRIM(LOWER(K91)))),"Different contact","Different owner & contact"))) -> Different owner & contact
A92: Felx Osano | B92: Avenue Healthcare Ltd | C92: felix.osano@evercaregroup.com | D92: 0722727560 | E92: Susan Ngina | F92: CUST100091 | G92: KPHEALTH | H92: Nairobi West | I92: Kisumu | J92: June Chesire | K92: okeyo@avenuehealthcare.com | L92: =IF(AND(TRIM(LOWER(E92))=TRIM(LOWER(J92)),TRIM(LOWER(C92))=TRIM(LOWER(K92))),"Match",IF(AND(NOT(TRIM(LOWER(E92))=TRIM(LOWER(J92))),TRIM(LOWER(C92))=TRIM(LOWER(K92))),"Different owner",IF(AND(TRIM(LOWER(E92))=TRIM(LOWER(J92)),NOT(TRIM(LOWER(C92))=TRIM(LOWER(K92)))),"Different contact","Different owner & contact"))) -> Different owner & contact
A93: Fred Mutisya | B93: Avenue Healthcare Ltd | C93: fredrick@avenuehealthcare.com | D93: 0724642222 | E93: Susan Ngina | F93: CUST100091 | G93: KPHEALTH | H93: Nairobi West | I93: Kisumu | J93: June Chesire | K93: okeyo@avenuehealthcare.com | L93: =IF(AND(TRIM(LOWER(E93))=TRIM(LOWER(J93)),TRIM(LOWER(C93))=TRIM(LOWER(K93))),"Match",IF(AND(NOT(TRIM(LOWER(E93))=TRIM(LOWER(J93))),TRIM(LOWER(C93))=TRIM(LOWER(K93))),"Different owner",IF(AND(TRIM(LOWER(E93))=TRIM(LOWER(J93)),NOT(TRIM(LOWER(C93))=TRIM(LOWER(K93)))),"Different contact","Different owner & contact"))) -> Different owner & contact
A94: Hezron Okeyo | B94: Avenue Healthcare Ltd | C94: okeyo@avenuehealthcare.com | D94: 0732175000 | E94: Susan Ngina | F94: CUST100091 | G94: KPHEALTH | H94: Nairobi West | I94: Kisumu | J94: June Chesire | K94: okeyo@avenuehealthcare.com | L94: =IF(AND(TRIM(LOWER(E94))=TRIM(LOWER(J94)),TRIM(LOWER(C94))=TRIM(LOWER(K94))),"Match",IF(AND(NOT(TRIM(LOWER(E94))=TRIM(LOWER(J94))),TRIM(LOWER(C94))=TRIM(LOWER(K94))),"Different owner",IF(AND(TRIM(LOWER(E94))=TRIM(LOWER(J94)),NOT(TRIM(LOWER(C94))=TRIM(LOWER(K94)))),"Different contact","Different owner & contact"))) -> Different owner
A95: Judy Omondi | B95: Avenue Healthcare Ltd | D95: 0711060720 | E95: Lucy Gakii | F95: CUST100091 | G95: KPHEALTH | H95: Nairobi West | I95: Kisumu | J95: June Chesire | K95: okeyo@avenuehealthcare.com | L95: =IF(AND(TRIM(LOWER(E95))=TRIM(LOWER(J95)),TRIM(LOWER(C95))=TRIM(LOWER(K95))),"Match",IF(AND(NOT(TRIM(LOWER(E95))=TRIM(LOWER(J95))),TRIM(LOWER(C95))=TRIM(LOWER(K95))),"Different owner",IF(AND(TRIM(LOWER(E95))=TRIM(LOWER(J95)),NOT(TRIM(LOWER(C95))=TRIM(LOWER(K95)))),"Different contact","Different owner & contact"))) -> Different owner & contact
A96: Lucy Macharia | B96: Avenue Healthcare Ltd | D96: 0707569328 | E96: Collins Kazee | F96: CUST100091 | G96: KPHEALTH | H96: Nairobi West | I96: Kisumu | J96: June Chesire | K96: okeyo@avenuehealthcare.com | L96: =IF(AND(TRIM(LOWER(E96))=TRIM(LOWER(J96)),TRIM(LOWER(C96))=TRIM(LOWER(K96))),"Match",IF(AND(NOT(TRIM(LOWER(E96))=TRIM(LOWER(J96))),TRIM(LOWER(C96))=TRIM(LOWER(K96))),"Different owner",IF(AND(TRIM(LOWER(E96))=TRIM(LOWER(J96)),NOT(TRIM(LOWER(C96))=TRIM(LOWER(K96)))),"Different contact","Different owner & contact"))) -> Different owner & contact
A97: CAROL CAROL | B97: Avenue Healthcare Ltd - Mombasa | C97: reception@avenuehealthcare.com | D97: 0714831195 | E97: Lucy Gakii | F97: CUST101132 | G97: KPHEALTH | H97: Coast | I97: Mombasa | J97: Lucy Rimberia | L97: =IF(AND(TRIM(LOWER(E97))=TRIM(LOWER(J97)),TRIM(LOWER(C97))=TRIM(LOWER(K97))),"Match",IF(AND(NOT(TRIM(LOWER(E97))=TRIM(LOWER(J97))),TRIM(LOWER(C97))=TRIM(LOWER(K97))),"Different owner",IF(AND(TRIM(LOWER(E97))=TRIM(LOWER(J97)),NOT(TRIM(LOWER(C97))=TRIM(LOWER(K97)))),"Different contact","Different owner & contact"))) -> Different owner & contact
A98: Carol Carol | B98: Avenue Healthcare Ltd - Mombasa | C98: reception.mombasa@avenuehealthcare.com | E98: Lucy Gakii | F98: CUST101132 | G98: KPHEALTH | H98: Coast | I98: Mombasa | J98: Lucy Rimberia | L98: =IF(AND(TRIM(LOWER(E98))=TRIM(LOWER(J98)),TRIM(LOWER(C98))=TRIM(LOWER(K98))),"Match",IF(AND(NOT(TRIM(LOWER(E98))=TRIM(LOWER(J98))),TRIM(LOWER(C98))=TRIM(LOWER(K98))),"Different owner",IF(AND(TRIM(LOWER(E98))=TRIM(LOWER(J98)),NOT(TRIM(LOWER(C98))=TRIM(LOWER(K98)))),"Different contact","Different owner & contact"))) -> Different owner & contact
A99: Dr. Esther Ajowi | B99: Avenue Healthcare Ltd - Mombasa | C99: esther.ajowi@avenuehealthcare.com | D99: +254 732 175 230 | E99: Susan Ngina | F99: CUST101132 | G99: KPHEALTH | H99: Coast | I99: Mombasa | J99: Lucy Rimberia | L99: =IF(AND(TRIM(LOWER(E99))=TRIM(LOWER(J99)),TRIM(LOWER(C99))=TRIM(LOWER(K99))),"Match",IF(AND(NOT(TRIM(LOWER(E99))=TRIM(LOWER(J99))),TRIM(LOWER(C99))=TRIM(LOWER(K99))),"Different owner",IF(AND(TRIM(LOWER(E99))=TRIM(LOWER(J99)),NOT(TRIM(LOWER(C99))=TRIM(LOWER(K99)))),"Different contact","Different owner & contact"))) -> Different owner & contact
A100: Jackline Mumbi | B100: Avenue Healthcare Ltd - Mombasa | C100: jackline.mumbi@avenuehealthcare.com | D100: 0726681314 | E100: Susan Ngina | F100: CUST101132 | G100: KPHEALTH | H100: Coast | I100: Mombasa | J100: Lucy Rimberia | L100: =IF(AND(TRIM(LOWER(E100))=TRIM(LOWER(J100)),TRIM(LOWER(C100))=TRIM(LOWER(K100))),"Match",IF(AND(NOT(TRIM(LOWER(E100))=TRIM(LOWER(J100))),TRIM(LOWER(C100))=TRIM(LOWER(K100))),"Different owner",IF(AND(TRIM(LOWER(E100))=TRIM(LOWER(J100)),NOT(TRIM(LOWER(C100))=TRIM(LOWER(K100)))),"Different contact","Different owner & contact"))) -> Different owner & contact
...
