Workbook

Sheet Filters & Definitions
A1: Backorder Audit Trail — Export
A2: TEMPLATE / STRUCTURE DEMO. Sample rows use real order numbers, customers and SKUs from the 23 Jul 2026 extract; quantities and dates are illustrative. Replace with output of BackorderQueryBuilder.
A4: REPORT PROVENANCE
A5: Generated at | B5: 2026-07-26 09:15 EAT
A6: Generated by | B6: ipay.user@kim-fay.com
A7: Source | B7: Acumatica REST API via backorder_episodes / backorder_line_events
A8: Sync run id | B8: 48213
A9: Snapshot basis | B9: Live (episodes as at generation time)
A11: FILTERS APPLIED (echoed verbatim from the API payload — do not edit)
A12: Filter | B12: Value
A13: Period basis | B13: Backorders that STARTED in the period (opened_at)
A14: Period | B14: 20 – 25 Jul 2026
A15: State | B15: Open + Resolved (All)
A16: Duration basis | B16: Working days (Mon–Sat, Sundays & Kenyan gazetted holidays excluded)
A17: Order type | B17: SO only
A18: Reason family | B18: All
A19: Channel | B19: All
A20: Warehouse | B20: All (FGS, TPFGS)
A21: Include excluded-from-KPI episodes | B21: Yes — shown, but not in KPI totals
A22: Include backfilled start dates in durations | B22: No
A23: Include zero-value / free lines | B23: No
A24: Include internal / cash-sale accounts | B24: No
A26: DATA QUALITY — read before quoting any figure
A27: Measure | B27: Value | C27: Meaning
A28: Reason coverage | B28: 64.2% | C28: Share of episodes carrying a reason_code. Every family split is a sample of this size.
A29: Backfilled start dates | B29: 16.2% | C29: Episodes open before the ledger went live. Their durations are MINIMUMS, labelled "(min.)".
A30: Episodes excluded from KPIs | B30: 19 | C30: Free lines, zero-value lines, rejected/on-hold headers, internal accounts.
A31: Reconciled to Acumatica | B31: Yes — variance 0.31% | C31: Gate is 0.5%. See the Acumatica Bridge sheet.
A33: CANONICAL FORMULAS — these are the agreed definitions
A34: Measure | B34: Formula | C34: Note
A35: net_order_qty | B35: order_qty - cancelled_qty | C35: Cancelled qty never counts against fill rate.
A36: open_qty | B36: net_order_qty - shipped_qty | C36: Owed to the customer, including goods already picked.
A37: backorder_qty | B37: GREATEST(0, open_qty - qty_on_shipments) | C37: THE shortage. Excludes goods already on a shipment.
A38: line_fill_rate_pct | B38: shipped_qty / net_order_qty | C38: Denominator excludes cancelled qty.
A39: revenue_at_risk | B39: backorder_qty x net_unit_price | C39: Still recoverable. NOT a loss.
A40: days_to_resolve | B40: resolved_at - opened_at (calendar days) | C40: Blank while open; ageing uses NOW().
A41: working_days_to_resolve | B41: As above, excluding Sundays + gazetted holidays | C41: Default basis for service KPIs.
A42: days_late | B42: GREATEST(0, working_days - promised_lead_time_days) | C42: Promised lead time is per channel.
A43: delayed_revenue | B43: shipped_late_qty x net_unit_price | C43: Sale HAPPENED, just late. Not a loss.
A44: revenue_days_delayed | B44: delayed_revenue x days_late (KES-days) | C44: Ranks causes by weighted impact.
A45: lost_revenue | B45: cancelled_qty x price (where cancelled) + backorder_qty x price (where open beyond channel write-off threshold) | C45: THIS is loss of sales.
A47: Never add Revenue at Risk + Delayed Revenue + Lost Revenue together — they measure different things and overlap.

Sheet Summary
A1: Summary — 20 – 25 Jul 2026
A2: All values are formulas referencing Episode Detail. Nothing on this sheet is hardcoded.
A4: KPI | B4: Value | C4: Basis / caveat
A5: Open episodes | B5: =COUNTIFS('Episode Detail'!$AP$5:$AP$22,"Open",'Episode Detail'!$AL$5:$AL$22,"No") -> 12 | C5: Excludes free / zero-value lines
A6: Open orders (distinct) | B6: =SUM('Episode Detail'!$AQ$5:$AQ$22) -> 12 | C6: DISTINCT order_nbr via helper column AQ — never a row count
A7: Open items (distinct SKUs) | B7: =SUM('Episode Detail'!$AR$5:$AR$22) -> 8 | C7: DISTINCT inventory_id via helper column AR
A8: Revenue at Risk (KES) | B8: =SUMIFS('Episode Detail'!$AB$5:$AB$22,'Episode Detail'!$AP$5:$AP$22,"Open",'Episode Detail'!$AL$5:$AL$22,"No") -> 2274582.8 | C8: Open only. Recoverable — NOT a loss
A9: Resolved episodes | B9: =COUNTIFS('Episode Detail'!$AP$5:$AP$22,"Resolved",'Episode Detail'!$AL$5:$AL$22,"No") -> 5 | C9: In-period resolutions
A10: Avg Time to Resolve (working days) | B10: =IFERROR(AVERAGEIFS('Episode Detail'!$Q$5:$Q$22,'Episode Detail'!$AP$5:$AP$22,"Resolved",'Episode Detail'!$S$5:$S$22,"Yes",'Episode Detail'!$AL$5:$AL$22,"No"),"") -> 5.6 | C10: Verified start dates only — backfilled excluded
A11: Longest open (working days) | B11: =_xlfn.MAXIFS('Episode Detail'!$Q$5:$Q$22,'Episode Detail'!$AP$5:$AP$22,"Open",'Episode Detail'!$AL$5:$AL$22,"No") -> 15 | C11: Ageing against as-at date
A12: Delayed Revenue (KES) | B12: =SUMIFS('Episode Detail'!$AC$5:$AC$22,'Episode Detail'!$AL$5:$AL$22,"No") -> 320488.84 | C12: Shipped late. Sale happened
A13: Revenue-Days Delayed (KES-days) | B13: =SUMIFS('Episode Detail'!$AD$5:$AD$22,'Episode Detail'!$AL$5:$AL$22,"No") -> 534994.6 | C13: Weighted service cost — use to rank causes
A14: Lost Revenue (KES) | B14: =SUMIFS('Episode Detail'!$AE$5:$AE$22,'Episode Detail'!$AL$5:$AL$22,"No") -> 256648.56 | C14: THIS is loss of sales
A15: Reason coverage | B15: =IFERROR(COUNTIFS('Episode Detail'!$AG$5:$AG$22,"<>(unreasoned)",'Episode Detail'!$AL$5:$AL$22,"No")/COUNTIFS('Episode Detail'!$AL$5:$AL$22,"No"),"") -> 0.94117647 | C15: Every family split is a sample of this size
A16: Verified start dates | B16: =IFERROR(COUNTIFS('Episode Detail'!$S$5:$S$22,"Yes",'Episode Detail'!$AL$5:$AL$22,"No")/COUNTIFS('Episode Detail'!$AL$5:$AL$22,"No"),"") -> 0.88235294 | C16: Backfilled durations are minimums
A19: Loss of sales due to delayed production — the headline the business asked for
A20: Measure (PRODUCTION family only) | B20: Value | C20: Read as
A21: Lost Revenue — PRODUCTION (KES) | B21: =SUMIFS('Episode Detail'!$AE$5:$AE$22,'Episode Detail'!$AH$5:$AH$22,"PRODUCTION",'Episode Detail'!$AL$5:$AL$22,"No") -> 226138.2 | C21: Revenue we will never invoice
A22: Revenue at Risk — PRODUCTION (KES) | B22: =SUMIFS('Episode Detail'!$AB$5:$AB$22,'Episode Detail'!$AH$5:$AH$22,"PRODUCTION",'Episode Detail'!$AP$5:$AP$22,"Open",'Episode Detail'!$AL$5:$AL$22,"No") -> 220640.7 | C22: Still recoverable if stock lands
A23: Revenue-Days Delayed — PRODUCTION | B23: =SUMIFS('Episode Detail'!$AD$5:$AD$22,'Episode Detail'!$AH$5:$AH$22,"PRODUCTION",'Episode Detail'!$AL$5:$AL$22,"No") -> 475654 | C23: How long we made customers wait
A24: Episodes — PRODUCTION | B24: =COUNTIFS('Episode Detail'!$AH$5:$AH$22,"PRODUCTION",'Episode Detail'!$AL$5:$AL$22,"No") -> 8 | C24: Count of order-item shortages
A25: Avg delay — PRODUCTION (working days) | B25: =IFERROR(AVERAGEIFS('Episode Detail'!$Q$5:$Q$22,'Episode Detail'!$AH$5:$AH$22,"PRODUCTION",'Episode Detail'!$S$5:$S$22,"Yes",'Episode Detail'!$AL$5:$AL$22,"No"),"") -> 10.714286 | C25: Verified starts only

Sheet Loss by Reason
A1: Loss by reason family and code
A2: Family totals are SUMIFS over Episode Detail. All 33 Acumatica reason codes map to exactly one family.
A4: Family | B4: Reason code | C4: True supply shortage? | D4: Episodes | E4: Peak Qty | F4: Revenue at Risk | G4: Delayed Revenue | H4: Revenue-Days Delayed | I4: Lost Revenue | J4: Avg Days Delay
A5: PRODUCTION | B5: — family total — | C5: Yes | D5: =COUNTIFS('Episode Detail'!$AH$5:$AH$22,$A5,'Episode Detail'!$AL$5:$AL$22,"No") -> 8 | E5: =SUMIFS('Episode Detail'!$U$5:$U$22,'Episode Detail'!$AH$5:$AH$22,$A5,'Episode Detail'!$AL$5:$AL$22,"No") -> 3080 | F5: =SUMIFS('Episode Detail'!$AB$5:$AB$22,'Episode Detail'!$AH$5:$AH$22,$A5,'Episode Detail'!$AP$5:$AP$22,"Open",'Episode Detail'!$AL$5:$AL$22,"No") -> 220640.7 | G5: =SUMIFS('Episode Detail'!$AC$5:$AC$22,'Episode Detail'!$AH$5:$AH$22,$A5,'Episode Detail'!$AL$5:$AL$22,"No") -> 68216.1 | H5: =SUMIFS('Episode Detail'!$AD$5:$AD$22,'Episode Detail'!$AH$5:$AH$22,$A5,'Episode Detail'!$AL$5:$AL$22,"No") -> 475654 | I5: =SUMIFS('Episode Detail'!$AE$5:$AE$22,'Episode Detail'!$AH$5:$AH$22,$A5,'Episode Detail'!$AL$5:$AL$22,"No") -> 226138.2 | J5: =IFERROR(AVERAGEIFS('Episode Detail'!$Q$5:$Q$22,'Episode Detail'!$AH$5:$AH$22,$A5,'Episode Detail'!$S$5:$S$22,"Yes",'Episode Detail'!$AL$5:$AL$22,"No"),"") -> 10.714286
B6: out_of_stock_production | D6: =COUNTIFS('Episode Detail'!$AG$5:$AG$22,$B6,'Episode Detail'!$AL$5:$AL$22,"No") -> 4 | E6: =SUMIFS('Episode Detail'!$U$5:$U$22,'Episode Detail'!$AG$5:$AG$22,$B6,'Episode Detail'!$AL$5:$AL$22,"No") -> 2266 | F6: =SUMIFS('Episode Detail'!$AB$5:$AB$22,'Episode Detail'!$AG$5:$AG$22,$B6,'Episode Detail'!$AP$5:$AP$22,"Open",'Episode Detail'!$AL$5:$AL$22,"No") -> 135137.4 | G6: =SUMIFS('Episode Detail'!$AC$5:$AC$22,'Episode Detail'!$AG$5:$AG$22,$B6,'Episode Detail'!$AL$5:$AL$22,"No") -> 68216.1 | H6: =SUMIFS('Episode Detail'!$AD$5:$AD$22,'Episode Detail'!$AG$5:$AG$22,$B6,'Episode Detail'!$AL$5:$AL$22,"No") -> 475654 | I6: =SUMIFS('Episode Detail'!$AE$5:$AE$22,'Episode Detail'!$AG$5:$AG$22,$B6,'Episode Detail'!$AL$5:$AL$22,"No") -> 140634.9 | J6: =IFERROR(AVERAGEIFS('Episode Detail'!$Q$5:$Q$22,'Episode Detail'!$AG$5:$AG$22,$B6,'Episode Detail'!$S$5:$S$22,"Yes",'Episode Detail'!$AL$5:$AL$22,"No"),"") -> 11
B7: production_stockout | D7: =COUNTIFS('Episode Detail'!$AG$5:$AG$22,$B7,'Episode Detail'!$AL$5:$AL$22,"No") -> 0 | E7: =SUMIFS('Episode Detail'!$U$5:$U$22,'Episode Detail'!$AG$5:$AG$22,$B7,'Episode Detail'!$AL$5:$AL$22,"No") -> 0 | F7: =SUMIFS('Episode Detail'!$AB$5:$AB$22,'Episode Detail'!$AG$5:$AG$22,$B7,'Episode Detail'!$AP$5:$AP$22,"Open",'Episode Detail'!$AL$5:$AL$22,"No") -> 0 | G7: =SUMIFS('Episode Detail'!$AC$5:$AC$22,'Episode Detail'!$AG$5:$AG$22,$B7,'Episode Detail'!$AL$5:$AL$22,"No") -> 0 | H7: =SUMIFS('Episode Detail'!$AD$5:$AD$22,'Episode Detail'!$AG$5:$AG$22,$B7,'Episode Detail'!$AL$5:$AL$22,"No") -> 0 | I7: =SUMIFS('Episode Detail'!$AE$5:$AE$22,'Episode Detail'!$AG$5:$AG$22,$B7,'Episode Detail'!$AL$5:$AL$22,"No") -> 0 | J7: =IFERROR(AVERAGEIFS('Episode Detail'!$Q$5:$Q$22,'Episode Detail'!$AG$5:$AG$22,$B7,'Episode Detail'!$S$5:$S$22,"Yes",'Episode Detail'!$AL$5:$AL$22,"No"),"")
B8: raw_material_stockout | D8: =COUNTIFS('Episode Detail'!$AG$5:$AG$22,$B8,'Episode Detail'!$AL$5:$AL$22,"No") -> 1 | E8: =SUMIFS('Episode Detail'!$U$5:$U$22,'Episode Detail'!$AG$5:$AG$22,$B8,'Episode Detail'!$AL$5:$AL$22,"No") -> 542 | F8: =SUMIFS('Episode Detail'!$AB$5:$AB$22,'Episode Detail'!$AG$5:$AG$22,$B8,'Episode Detail'!$AP$5:$AP$22,"Open",'Episode Detail'!$AL$5:$AL$22,"No") -> 32920.5 | G8: =SUMIFS('Episode Detail'!$AC$5:$AC$22,'Episode Detail'!$AG$5:$AG$22,$B8,'Episode Detail'!$AL$5:$AL$22,"No") -> 0 | H8: =SUMIFS('Episode Detail'!$AD$5:$AD$22,'Episode Detail'!$AG$5:$AG$22,$B8,'Episode Detail'!$AL$5:$AL$22,"No") -> 0 | I8: =SUMIFS('Episode Detail'!$AE$5:$AE$22,'Episode Detail'!$AG$5:$AG$22,$B8,'Episode Detail'!$AL$5:$AL$22,"No") -> 32920.5 | J8: =IFERROR(AVERAGEIFS('Episode Detail'!$Q$5:$Q$22,'Episode Detail'!$AG$5:$AG$22,$B8,'Episode Detail'!$S$5:$S$22,"Yes",'Episode Detail'!$AL$5:$AL$22,"No"),"") -> 13
B9: order_to_make | D9: =COUNTIFS('Episode Detail'!$AG$5:$AG$22,$B9,'Episode Detail'!$AL$5:$AL$22,"No") -> 1 | E9: =SUMIFS('Episode Detail'!$U$5:$U$22,'Episode Detail'!$AG$5:$AG$22,$B9,'Episode Detail'!$AL$5:$AL$22,"No") -> 260 | F9: =SUMIFS('Episode Detail'!$AB$5:$AB$22,'Episode Detail'!$AG$5:$AG$22,$B9,'Episode Detail'!$AP$5:$AP$22,"Open",'Episode Detail'!$AL$5:$AL$22,"No") -> 19500 | G9: =SUMIFS('Episode Detail'!$AC$5:$AC$22,'Episode Detail'!$AG$5:$AG$22,$B9,'Episode Detail'!$AL$5:$AL$22,"No") -> 0 | H9: =SUMIFS('Episode Detail'!$AD$5:$AD$22,'Episode Detail'!$AG$5:$AG$22,$B9,'Episode Detail'!$AL$5:$AL$22,"No") -> 0 | I9: =SUMIFS('Episode Detail'!$AE$5:$AE$22,'Episode Detail'!$AG$5:$AG$22,$B9,'Episode Detail'!$AL$5:$AL$22,"No") -> 19500 | J9: =IFERROR(AVERAGEIFS('Episode Detail'!$Q$5:$Q$22,'Episode Detail'!$AG$5:$AG$22,$B9,'Episode Detail'!$S$5:$S$22,"Yes",'Episode Detail'!$AL$5:$AL$22,"No"),"")
B10: conversion_delays | D10: =COUNTIFS('Episode Detail'!$AG$5:$AG$22,$B10,'Episode Detail'!$AL$5:$AL$22,"No") -> 2 | E10: =SUMIFS('Episode Detail'!$U$5:$U$22,'Episode Detail'!$AG$5:$AG$22,$B10,'Episode Detail'!$AL$5:$AL$22,"No") -> 12 | F10: =SUMIFS('Episode Detail'!$AB$5:$AB$22,'Episode Detail'!$AG$5:$AG$22,$B10,'Episode Detail'!$AP$5:$AP$22,"Open",'Episode Detail'!$AL$5:$AL$22,"No") -> 33082.8 | G10: =SUMIFS('Episode Detail'!$AC$5:$AC$22,'Episode Detail'!$AG$5:$AG$22,$B10,'Episode Detail'!$AL$5:$AL$22,"No") -> 0 | H10: =SUMIFS('Episode Detail'!$AD$5:$AD$22,'Episode Detail'!$AG$5:$AG$22,$B10,'Episode Detail'!$AL$5:$AL$22,"No") -> 0 | I10: =SUMIFS('Episode Detail'!$AE$5:$AE$22,'Episode Detail'!$AG$5:$AG$22,$B10,'Episode Detail'!$AL$5:$AL$22,"No") -> 33082.8 | J10: =IFERROR(AVERAGEIFS('Episode Detail'!$Q$5:$Q$22,'Episode Detail'!$AG$5:$AG$22,$B10,'Episode Detail'!$S$5:$S$22,"Yes",'Episode Detail'!$AL$5:$AL$22,"No"),"") -> 9
B11: conversion_issues | D11: =COUNTIFS('Episode Detail'!$AG$5:$AG$22,$B11,'Episode Detail'!$AL$5:$AL$22,"No") -> 0 | E11: =SUMIFS('Episode Detail'!$U$5:$U$22,'Episode Detail'!$AG$5:$AG$22,$B11,'Episode Detail'!$AL$5:$AL$22,"No") -> 0 | F11: =SUMIFS('Episode Detail'!$AB$5:$AB$22,'Episode Detail'!$AG$5:$AG$22,$B11,'Episode Detail'!$AP$5:$AP$22,"Open",'Episode Detail'!$AL$5:$AL$22,"No") -> 0 | G11: =SUMIFS('Episode Detail'!$AC$5:$AC$22,'Episode Detail'!$AG$5:$AG$22,$B11,'Episode Detail'!$AL$5:$AL$22,"No") -> 0 | H11: =SUMIFS('Episode Detail'!$AD$5:$AD$22,'Episode Detail'!$AG$5:$AG$22,$B11,'Episode Detail'!$AL$5:$AL$22,"No") -> 0 | I11: =SUMIFS('Episode Detail'!$AE$5:$AE$22,'Episode Detail'!$AG$5:$AG$22,$B11,'Episode Detail'!$AL$5:$AL$22,"No") -> 0 | J11: =IFERROR(AVERAGEIFS('Episode Detail'!$Q$5:$Q$22,'Episode Detail'!$AG$5:$AG$22,$B11,'Episode Detail'!$S$5:$S$22,"Yes",'Episode Detail'!$AL$5:$AL$22,"No"),"")
B12: batch_sequence | D12: =COUNTIFS('Episode Detail'!$AG$5:$AG$22,$B12,'Episode Detail'!$AL$5:$AL$22,"No") -> 0 | E12: =SUMIFS('Episode Detail'!$U$5:$U$22,'Episode Detail'!$AG$5:$AG$22,$B12,'Episode Detail'!$AL$5:$AL$22,"No") -> 0 | F12: =SUMIFS('Episode Detail'!$AB$5:$AB$22,'Episode Detail'!$AG$5:$AG$22,$B12,'Episode Detail'!$AP$5:$AP$22,"Open",'Episode Detail'!$AL$5:$AL$22,"No") -> 0 | G12: =SUMIFS('Episode Detail'!$AC$5:$AC$22,'Episode Detail'!$AG$5:$AG$22,$B12,'Episode Detail'!$AL$5:$AL$22,"No") -> 0 | H12: =SUMIFS('Episode Detail'!$AD$5:$AD$22,'Episode Detail'!$AG$5:$AG$22,$B12,'Episode Detail'!$AL$5:$AL$22,"No") -> 0 | I12: =SUMIFS('Episode Detail'!$AE$5:$AE$22,'Episode Detail'!$AG$5:$AG$22,$B12,'Episode Detail'!$AL$5:$AL$22,"No") -> 0 | J12: =IFERROR(AVERAGEIFS('Episode Detail'!$Q$5:$Q$22,'Episode Detail'!$AG$5:$AG$22,$B12,'Episode Detail'!$S$5:$S$22,"Yes",'Episode Detail'!$AL$5:$AL$22,"No"),"")
B13: wrong_moq | D13: =COUNTIFS('Episode Detail'!$AG$5:$AG$22,$B13,'Episode Detail'!$AL$5:$AL$22,"No") -> 0 | E13: =SUMIFS('Episode Detail'!$U$5:$U$22,'Episode Detail'!$AG$5:$AG$22,$B13,'Episode Detail'!$AL$5:$AL$22,"No") -> 0 | F13: =SUMIFS('Episode Detail'!$AB$5:$AB$22,'Episode Detail'!$AG$5:$AG$22,$B13,'Episode Detail'!$AP$5:$AP$22,"Open",'Episode Detail'!$AL$5:$AL$22,"No") -> 0 | G13: =SUMIFS('Episode Detail'!$AC$5:$AC$22,'Episode Detail'!$AG$5:$AG$22,$B13,'Episode Detail'!$AL$5:$AL$22,"No") -> 0 | H13: =SUMIFS('Episode Detail'!$AD$5:$AD$22,'Episode Detail'!$AG$5:$AG$22,$B13,'Episode Detail'!$AL$5:$AL$22,"No") -> 0 | I13: =SUMIFS('Episode Detail'!$AE$5:$AE$22,'Episode Detail'!$AG$5:$AG$22,$B13,'Episode Detail'!$AL$5:$AL$22,"No") -> 0 | J13: =IFERROR(AVERAGEIFS('Episode Detail'!$Q$5:$Q$22,'Episode Detail'!$AG$5:$AG$22,$B13,'Episode Detail'!$S$5:$S$22,"Yes",'Episode Detail'!$AL$5:$AL$22,"No"),"")
A14: PROCUREMENT | B14: — family total — | C14: Yes | D14: =COUNTIFS('Episode Detail'!$AH$5:$AH$22,$A14,'Episode Detail'!$AL$5:$AL$22,"No") -> 4 | E14: =SUMIFS('Episode Detail'!$U$5:$U$22,'Episode Detail'!$AH$5:$AH$22,$A14,'Episode Detail'!$AL$5:$AL$22,"No") -> 90 | F14: =SUMIFS('Episode Detail'!$AB$5:$AB$22,'Episode Detail'!$AH$5:$AH$22,$A14,'Episode Detail'!$AP$5:$AP$22,"Open",'Episode Detail'!$AL$5:$AL$22,"No") -> 158475.6 | G14: =SUMIFS('Episode Detail'!$AC$5:$AC$22,'Episode Detail'!$AH$5:$AH$22,$A14,'Episode Detail'!$AL$5:$AL$22,"No") -> 0 | H14: =SUMIFS('Episode Detail'!$AD$5:$AD$22,'Episode Detail'!$AH$5:$AH$22,$A14,'Episode Detail'!$AL$5:$AL$22,"No") -> 0 | I14: =SUMIFS('Episode Detail'!$AE$5:$AE$22,'Episode Detail'!$AH$5:$AH$22,$A14,'Episode Detail'!$AL$5:$AL$22,"No") -> 30510.36 | J14: =IFERROR(AVERAGEIFS('Episode Detail'!$Q$5:$Q$22,'Episode Detail'!$AH$5:$AH$22,$A14,'Episode Detail'!$S$5:$S$22,"Yes",'Episode Detail'!$AL$5:$AL$22,"No"),"") -> 4
B15: out_of_stock_procurement | D15: =COUNTIFS('Episode Detail'!$AG$5:$AG$22,$B15,'Episode Detail'!$AL$5:$AL$22,"No") -> 3 | E15: =SUMIFS('Episode Detail'!$U$5:$U$22,'Episode Detail'!$AG$5:$AG$22,$B15,'Episode Detail'!$AL$5:$AL$22,"No") -> 54 | F15: =SUMIFS('Episode Detail'!$AB$5:$AB$22,'Episode Detail'!$AG$5:$AG$22,$B15,'Episode Detail'!$AP$5:$AP$22,"Open",'Episode Detail'!$AL$5:$AL$22,"No") -> 121215.6 | G15: =SUMIFS('Episode Detail'!$AC$5:$AC$22,'Episode Detail'!$AG$5:$AG$22,$B15,'Episode Detail'!$AL$5:$AL$22,"No") -> 0 | H15: =SUMIFS('Episode Detail'!$AD$5:$AD$22,'Episode Detail'!$AG$5:$AG$22,$B15,'Episode Detail'!$AL$5:$AL$22,"No") -> 0 | I15: =SUMIFS('Episode Detail'!$AE$5:$AE$22,'Episode Detail'!$AG$5:$AG$22,$B15,'Episode Detail'!$AL$5:$AL$22,"No") -> 30510.36 | J15: =IFERROR(AVERAGEIFS('Episode Detail'!$Q$5:$Q$22,'Episode Detail'!$AG$5:$AG$22,$B15,'Episode Detail'!$S$5:$S$22,"Yes",'Episode Detail'!$AL$5:$AL$22,"No"),"") -> 4
B16: out_of_stock_msa | D16: =COUNTIFS('Episode Detail'!$AG$5:$AG$22,$B16,'Episode Detail'!$AL$5:$AL$22,"No") -> 1 | E16: =SUMIFS('Episode Detail'!$U$5:$U$22,'Episode Detail'!$AG$5:$AG$22,$B16,'Episode Detail'!$AL$5:$AL$22,"No") -> 36 | F16: =SUMIFS('Episode Detail'!$AB$5:$AB$22,'Episode Detail'!$AG$5:$AG$22,$B16,'Episode Detail'!$AP$5:$AP$22,"Open",'Episode Detail'!$AL$5:$AL$22,"No") -> 37260 | G16: =SUMIFS('Episode Detail'!$AC$5:$AC$22,'Episode Detail'!$AG$5:$AG$22,$B16,'Episode Detail'!$AL$5:$AL$22,"No") -> 0 | H16: =SUMIFS('Episode Detail'!$AD$5:$AD$22,'Episode Detail'!$AG$5:$AG$22,$B16,'Episode Detail'!$AL$5:$AL$22,"No") -> 0 | I16: =SUMIFS('Episode Detail'!$AE$5:$AE$22,'Episode Detail'!$AG$5:$AG$22,$B16,'Episode Detail'!$AL$5:$AL$22,"No") -> 0 | J16: =IFERROR(AVERAGEIFS('Episode Detail'!$Q$5:$Q$22,'Episode Detail'!$AG$5:$AG$22,$B16,'Episode Detail'!$S$5:$S$22,"Yes",'Episode Detail'!$AL$5:$AL$22,"No"),"")
B17: delayed_supplier_payment | D17: =COUNTIFS('Episode Detail'!$AG$5:$AG$22,$B17,'Episode Detail'!$AL$5:$AL$22,"No") -> 0 | E17: =SUMIFS('Episode Detail'!$U$5:$U$22,'Episode Detail'!$AG$5:$AG$22,$B17,'Episode Detail'!$AL$5:$AL$22,"No") -> 0 | F17: =SUMIFS('Episode Detail'!$AB$5:$AB$22,'Episode Detail'!$AG$5:$AG$22,$B17,'Episode Detail'!$AP$5:$AP$22,"Open",'Episode Detail'!$AL$5:$AL$22,"No") -> 0 | G17: =SUMIFS('Episode Detail'!$AC$5:$AC$22,'Episode Detail'!$AG$5:$AG$22,$B17,'Episode Detail'!$AL$5:$AL$22,"No") -> 0 | H17: =SUMIFS('Episode Detail'!$AD$5:$AD$22,'Episode Detail'!$AG$5:$AG$22,$B17,'Episode Detail'!$AL$5:$AL$22,"No") -> 0 | I17: =SUMIFS('Episode Detail'!$AE$5:$AE$22,'Episode Detail'!$AG$5:$AG$22,$B17,'Episode Detail'!$AL$5:$AL$22,"No") -> 0 | J17: =IFERROR(AVERAGEIFS('Episode Detail'!$Q$5:$Q$22,'Episode Detail'!$AG$5:$AG$22,$B17,'Episode Detail'!$S$5:$S$22,"Yes",'Episode Detail'!$AL$5:$AL$22,"No"),"")
B18: kebs_stickers | D18: =COUNTIFS('Episode Detail'!$AG$5:$AG$22,$B18,'Episode Detail'!$AL$5:$AL$22,"No") -> 0 | E18: =SUMIFS('Episode Detail'!$U$5:$U$22,'Episode Detail'!$AG$5:$AG$22,$B18,'Episode Detail'!$AL$5:$AL$22,"No") -> 0 | F18: =SUMIFS('Episode Detail'!$AB$5:$AB$22,'Episode Detail'!$AG$5:$AG$22,$B18,'Episode Detail'!$AP$5:$AP$22,"Open",'Episode Detail'!$AL$5:$AL$22,"No") -> 0 | G18: =SUMIFS('Episode Detail'!$AC$5:$AC$22,'Episode Detail'!$AG$5:$AG$22,$B18,'Episode Detail'!$AL$5:$AL$22,"No") -> 0 | H18: =SUMIFS('Episode Detail'!$AD$5:$AD$22,'Episode Detail'!$AG$5:$AG$22,$B18,'Episode Detail'!$AL$5:$AL$22,"No") -> 0 | I18: =SUMIFS('Episode Detail'!$AE$5:$AE$22,'Episode Detail'!$AG$5:$AG$22,$B18,'Episode Detail'!$AL$5:$AL$22,"No") -> 0 | J18: =IFERROR(AVERAGEIFS('Episode Detail'!$Q$5:$Q$22,'Episode Detail'!$AG$5:$AG$22,$B18,'Episode Detail'!$S$5:$S$22,"Yes",'Episode Detail'!$AL$5:$AL$22,"No"),"")
A19: LOGISTICS | B19: — family total — | C19: No | D19: =COUNTIFS('Episode Detail'!$AH$5:$AH$22,$A19,'Episode Detail'!$AL$5:$AL$22,"No") -> 3 | E19: =SUMIFS('Episode Detail'!$U$5:$U$22,'Episode Detail'!$AH$5:$AH$22,$A19,'Episode Detail'!$AL$5:$AL$22,"No") -> 564 | F19: =SUMIFS('Episode Detail'!$AB$5:$AB$22,'Episode Detail'!$AH$5:$AH$22,$A19,'Episode Detail'!$AP$5:$AP$22,"Open",'Episode Detail'!$AL$5:$AL$22,"No") -> 0 | G19: =SUMIFS('Episode Detail'!$AC$5:$AC$22,'Episode Detail'!$AH$5:$AH$22,$A19,'Episode Detail'!$AL$5:$AL$22,"No") -> 252272.74 | H19: =SUMIFS('Episode Detail'!$AD$5:$AD$22,'Episode Detail'!$AH$5:$AH$22,$A19,'Episode Detail'!$AL$5:$AL$22,"No") -> 59340.6 | I19: =SUMIFS('Episode Detail'!$AE$5:$AE$22,'Episode Detail'!$AH$5:$AH$22,$A19,'Episode Detail'!$AL$5:$AL$22,"No") -> 0 | J19: =IFERROR(AVERAGEIFS('Episode Detail'!$Q$5:$Q$22,'Episode Detail'!$AH$5:$AH$22,$A19,'Episode Detail'!$S$5:$S$22,"Yes",'Episode Detail'!$AL$5:$AL$22,"No"),"") -> 3.3333333
B20: delay_in_delivery | D20: =COUNTIFS('Episode Detail'!$AG$5:$AG$22,$B20,'Episode Detail'!$AL$5:$AL$22,"No") -> 0 | E20: =SUMIFS('Episode Detail'!$U$5:$U$22,'Episode Detail'!$AG$5:$AG$22,$B20,'Episode Detail'!$AL$5:$AL$22,"No") -> 0 | F20: =SUMIFS('Episode Detail'!$AB$5:$AB$22,'Episode Detail'!$AG$5:$AG$22,$B20,'Episode Detail'!$AP$5:$AP$22,"Open",'Episode Detail'!$AL$5:$AL$22,"No") -> 0 | G20: =SUMIFS('Episode Detail'!$AC$5:$AC$22,'Episode Detail'!$AG$5:$AG$22,$B20,'Episode Detail'!$AL$5:$AL$22,"No") -> 0 | H20: =SUMIFS('Episode Detail'!$AD$5:$AD$22,'Episode Detail'!$AG$5:$AG$22,$B20,'Episode Detail'!$AL$5:$AL$22,"No") -> 0 | I20: =SUMIFS('Episode Detail'!$AE$5:$AE$22,'Episode Detail'!$AG$5:$AG$22,$B20,'Episode Detail'!$AL$5:$AL$22,"No") -> 0 | J20: =IFERROR(AVERAGEIFS('Episode Detail'!$Q$5:$Q$22,'Episode Detail'!$AG$5:$AG$22,$B20,'Episode Detail'!$S$5:$S$22,"Yes",'Episode Detail'!$AL$5:$AL$22,"No"),"")
B21: transfer_delays | D21: =COUNTIFS('Episode Detail'!$AG$5:$AG$22,$B21,'Episode Detail'!$AL$5:$AL$22,"No") -> 1 | E21: =SUMIFS('Episode Detail'!$U$5:$U$22,'Episode Detail'!$AG$5:$AG$22,$B21,'Episode Detail'!$AL$5:$AL$22,"No") -> 262 | F21: =SUMIFS('Episode Detail'!$AB$5:$AB$22,'Episode Detail'!$AG$5:$AG$22,$B21,'Episode Detail'!$AP$5:$AP$22,"Open",'Episode Detail'!$AL$5:$AL$22,"No") -> 0 | G21: =SUMIFS('Episode Detail'!$AC$5:$AC$22,'Episode Detail'!$AG$5:$AG$22,$B21,'Episode Detail'!$AL$5:$AL$22,"No") -> 225364.54 | H21: =SUMIFS('Episode Detail'!$AD$5:$AD$22,'Episode Detail'!$AG$5:$AG$22,$B21,'Episode Detail'!$AL$5:$AL$22,"No") -> 0 | I21: =SUMIFS('Episode Detail'!$AE$5:$AE$22,'Episode Detail'!$AG$5:$AG$22,$B21,'Episode Detail'!$AL$5:$AL$22,"No") -> 0 | J21: =IFERROR(AVERAGEIFS('Episode Detail'!$Q$5:$Q$22,'Episode Detail'!$AG$5:$AG$22,$B21,'Episode Detail'!$S$5:$S$22,"Yes",'Episode Detail'!$AL$5:$AL$22,"No"),"") -> 2
B22: truck_full | D22: =COUNTIFS('Episode Detail'!$AG$5:$AG$22,$B22,'Episode Detail'!$AL$5:$AL$22,"No") -> 0 | E22: =SUMIFS('Episode Detail'!$U$5:$U$22,'Episode Detail'!$AG$5:$AG$22,$B22,'Episode Detail'!$AL$5:$AL$22,"No") -> 0 | F22: =SUMIFS('Episode Detail'!$AB$5:$AB$22,'Episode Detail'!$AG$5:$AG$22,$B22,'Episode Detail'!$AP$5:$AP$22,"Open",'Episode Detail'!$AL$5:$AL$22,"No") -> 0 | G22: =SUMIFS('Episode Detail'!$AC$5:$AC$22,'Episode Detail'!$AG$5:$AG$22,$B22,'Episode Detail'!$AL$5:$AL$22,"No") -> 0 | H22: =SUMIFS('Episode Detail'!$AD$5:$AD$22,'Episode Detail'!$AG$5:$AG$22,$B22,'Episode Detail'!$AL$5:$AL$22,"No") -> 0 | I22: =SUMIFS('Episode Detail'!$AE$5:$AE$22,'Episode Detail'!$AG$5:$AG$22,$B22,'Episode Detail'!$AL$5:$AL$22,"No") -> 0 | J22: =IFERROR(AVERAGEIFS('Episode Detail'!$Q$5:$Q$22,'Episode Detail'!$AG$5:$AG$22,$B22,'Episode Detail'!$S$5:$S$22,"Yes",'Episode Detail'!$AL$5:$AL$22,"No"),"")
B23: did_not_pick_on_shipment | D23: =COUNTIFS('Episode Detail'!$AG$5:$AG$22,$B23,'Episode Detail'!$AL$5:$AL$22,"No") -> 2 | E23: =SUMIFS('Episode Detail'!$U$5:$U$22,'Episode Detail'!$AG$5:$AG$22,$B23,'Episode Detail'!$AL$5:$AL$22,"No") -> 302 | F23: =SUMIFS('Episode Detail'!$AB$5:$AB$22,'Episode Detail'!$AG$5:$AG$22,$B23,'Episode Detail'!$AP$5:$AP$22,"Open",'Episode Detail'!$AL$5:$AL$22,"No") -> 0 | G23: =SUMIFS('Episode Detail'!$AC$5:$AC$22,'Episode Detail'!$AG$5:$AG$22,$B23,'Episode Detail'!$AL$5:$AL$22,"No") -> 26908.2 | H23: =SUMIFS('Episode Detail'!$AD$5:$AD$22,'Episode Detail'!$AG$5:$AG$22,$B23,'Episode Detail'!$AL$5:$AL$22,"No") -> 59340.6 | I23: =SUMIFS('Episode Detail'!$AE$5:$AE$22,'Episode Detail'!$AG$5:$AG$22,$B23,'Episode Detail'!$AL$5:$AL$22,"No") -> 0 | J23: =IFERROR(AVERAGEIFS('Episode Detail'!$Q$5:$Q$22,'Episode Detail'!$AG$5:$AG$22,$B23,'Episode Detail'!$S$5:$S$22,"Yes",'Episode Detail'!$AL$5:$AL$22,"No"),"") -> 4
A24: COMMERCIAL | B24: — family total — | C24: No | D24: =COUNTIFS('Episode Detail'!$AH$5:$AH$22,$A24,'Episode Detail'!$AL$5:$AL$22,"No") -> 0 | E24: =SUMIFS('Episode Detail'!$U$5:$U$22,'Episode Detail'!$AH$5:$AH$22,$A24,'Episode Detail'!$AL$5:$AL$22,"No") -> 0 | F24: =SUMIFS('Episode Detail'!$AB$5:$AB$22,'Episode Detail'!$AH$5:$AH$22,$A24,'Episode Detail'!$AP$5:$AP$22,"Open",'Episode Detail'!$AL$5:$AL$22,"No") -> 0 | G24: =SUMIFS('Episode Detail'!$AC$5:$AC$22,'Episode Detail'!$AH$5:$AH$22,$A24,'Episode Detail'!$AL$5:$AL$22,"No") -> 0 | H24: =SUMIFS('Episode Detail'!$AD$5:$AD$22,'Episode Detail'!$AH$5:$AH$22,$A24,'Episode Detail'!$AL$5:$AL$22,"No") -> 0 | I24: =SUMIFS('Episode Detail'!$AE$5:$AE$22,'Episode Detail'!$AH$5:$AH$22,$A24,'Episode Detail'!$AL$5:$AL$22,"No") -> 0 | J24: =IFERROR(AVERAGEIFS('Episode Detail'!$Q$5:$Q$22,'Episode Detail'!$AH$5:$AH$22,$A24,'Episode Detail'!$S$5:$S$22,"Yes",'Episode Detail'!$AL$5:$AL$22,"No"),"")
B25: discontinued | D25: =COUNTIFS('Episode Detail'!$AG$5:$AG$22,$B25,'Episode Detail'!$AL$5:$AL$22,"No") -> 0 | E25: =SUMIFS('Episode Detail'!$U$5:$U$22,'Episode Detail'!$AG$5:$AG$22,$B25,'Episode Detail'!$AL$5:$AL$22,"No") -> 0 | F25: =SUMIFS('Episode Detail'!$AB$5:$AB$22,'Episode Detail'!$AG$5:$AG$22,$B25,'Episode Detail'!$AP$5:$AP$22,"Open",'Episode Detail'!$AL$5:$AL$22,"No") -> 0 | G25: =SUMIFS('Episode Detail'!$AC$5:$AC$22,'Episode Detail'!$AG$5:$AG$22,$B25,'Episode Detail'!$AL$5:$AL$22,"No") -> 0 | H25: =SUMIFS('Episode Detail'!$AD$5:$AD$22,'Episode Detail'!$AG$5:$AG$22,$B25,'Episode Detail'!$AL$5:$AL$22,"No") -> 0 | I25: =SUMIFS('Episode Detail'!$AE$5:$AE$22,'Episode Detail'!$AG$5:$AG$22,$B25,'Episode Detail'!$AL$5:$AL$22,"No") -> 0 | J25: =IFERROR(AVERAGEIFS('Episode Detail'!$Q$5:$Q$22,'Episode Detail'!$AG$5:$AG$22,$B25,'Episode Detail'!$S$5:$S$22,"Yes",'Episode Detail'!$AL$5:$AL$22,"No"),"")
B26: pb_discontinued | D26: =COUNTIFS('Episode Detail'!$AG$5:$AG$22,$B26,'Episode Detail'!$AL$5:$AL$22,"No") -> 0 | E26: =SUMIFS('Episode Detail'!$U$5:$U$22,'Episode Detail'!$AG$5:$AG$22,$B26,'Episode Detail'!$AL$5:$AL$22,"No") -> 0 | F26: =SUMIFS('Episode Detail'!$AB$5:$AB$22,'Episode Detail'!$AG$5:$AG$22,$B26,'Episode Detail'!$AP$5:$AP$22,"Open",'Episode Detail'!$AL$5:$AL$22,"No") -> 0 | G26: =SUMIFS('Episode Detail'!$AC$5:$AC$22,'Episode Detail'!$AG$5:$AG$22,$B26,'Episode Detail'!$AL$5:$AL$22,"No") -> 0 | H26: =SUMIFS('Episode Detail'!$AD$5:$AD$22,'Episode Detail'!$AG$5:$AG$22,$B26,'Episode Detail'!$AL$5:$AL$22,"No") -> 0 | I26: =SUMIFS('Episode Detail'!$AE$5:$AE$22,'Episode Detail'!$AG$5:$AG$22,$B26,'Episode Detail'!$AL$5:$AL$22,"No") -> 0 | J26: =IFERROR(AVERAGEIFS('Episode Detail'!$Q$5:$Q$22,'Episode Detail'!$AG$5:$AG$22,$B26,'Episode Detail'!$S$5:$S$22,"Yes",'Episode Detail'!$AL$5:$AL$22,"No"),"")
B27: non_focus | D27: =COUNTIFS('Episode Detail'!$AG$5:$AG$22,$B27,'Episode Detail'!$AL$5:$AL$22,"No") -> 0 | E27: =SUMIFS('Episode Detail'!$U$5:$U$22,'Episode Detail'!$AG$5:$AG$22,$B27,'Episode Detail'!$AL$5:$AL$22,"No") -> 0 | F27: =SUMIFS('Episode Detail'!$AB$5:$AB$22,'Episode Detail'!$AG$5:$AG$22,$B27,'Episode Detail'!$AP$5:$AP$22,"Open",'Episode Detail'!$AL$5:$AL$22,"No") -> 0 | G27: =SUMIFS('Episode Detail'!$AC$5:$AC$22,'Episode Detail'!$AG$5:$AG$22,$B27,'Episode Detail'!$AL$5:$AL$22,"No") -> 0 | H27: =SUMIFS('Episode Detail'!$AD$5:$AD$22,'Episode Detail'!$AG$5:$AG$22,$B27,'Episode Detail'!$AL$5:$AL$22,"No") -> 0 | I27: =SUMIFS('Episode Detail'!$AE$5:$AE$22,'Episode Detail'!$AG$5:$AG$22,$B27,'Episode Detail'!$AL$5:$AL$22,"No") -> 0 | J27: =IFERROR(AVERAGEIFS('Episode Detail'!$Q$5:$Q$22,'Episode Detail'!$AG$5:$AG$22,$B27,'Episode Detail'!$S$5:$S$22,"Yes",'Episode Detail'!$AL$5:$AL$22,"No"),"")
B28: promo_product | D28: =COUNTIFS('Episode Detail'!$AG$5:$AG$22,$B28,'Episode Detail'!$AL$5:$AL$22,"No") -> 0 | E28: =SUMIFS('Episode Detail'!$U$5:$U$22,'Episode Detail'!$AG$5:$AG$22,$B28,'Episode Detail'!$AL$5:$AL$22,"No") -> 0 | F28: =SUMIFS('Episode Detail'!$AB$5:$AB$22,'Episode Detail'!$AG$5:$AG$22,$B28,'Episode Detail'!$AP$5:$AP$22,"Open",'Episode Detail'!$AL$5:$AL$22,"No") -> 0 | G28: =SUMIFS('Episode Detail'!$AC$5:$AC$22,'Episode Detail'!$AG$5:$AG$22,$B28,'Episode Detail'!$AL$5:$AL$22,"No") -> 0 | H28: =SUMIFS('Episode Detail'!$AD$5:$AD$22,'Episode Detail'!$AG$5:$AG$22,$B28,'Episode Detail'!$AL$5:$AL$22,"No") -> 0 | I28: =SUMIFS('Episode Detail'!$AE$5:$AE$22,'Episode Detail'!$AG$5:$AG$22,$B28,'Episode Detail'!$AL$5:$AL$22,"No") -> 0 | J28: =IFERROR(AVERAGEIFS('Episode Detail'!$Q$5:$Q$22,'Episode Detail'!$AG$5:$AG$22,$B28,'Episode Detail'!$S$5:$S$22,"Yes",'Episode Detail'!$AL$5:$AL$22,"No"),"")
B29: short_expiry | D29: =COUNTIFS('Episode Detail'!$AG$5:$AG$22,$B29,'Episode Detail'!$AL$5:$AL$22,"No") -> 0 | E29: =SUMIFS('Episode Detail'!$U$5:$U$22,'Episode Detail'!$AG$5:$AG$22,$B29,'Episode Detail'!$AL$5:$AL$22,"No") -> 0 | F29: =SUMIFS('Episode Detail'!$AB$5:$AB$22,'Episode Detail'!$AG$5:$AG$22,$B29,'Episode Detail'!$AP$5:$AP$22,"Open",'Episode Detail'!$AL$5:$AL$22,"No") -> 0 | G29: =SUMIFS('Episode Detail'!$AC$5:$AC$22,'Episode Detail'!$AG$5:$AG$22,$B29,'Episode Detail'!$AL$5:$AL$22,"No") -> 0 | H29: =SUMIFS('Episode Detail'!$AD$5:$AD$22,'Episode Detail'!$AG$5:$AG$22,$B29,'Episode Detail'!$AL$5:$AL$22,"No") -> 0 | I29: =SUMIFS('Episode Detail'!$AE$5:$AE$22,'Episode Detail'!$AG$5:$AG$22,$B29,'Episode Detail'!$AL$5:$AL$22,"No") -> 0 | J29: =IFERROR(AVERAGEIFS('Episode Detail'!$Q$5:$Q$22,'Episode Detail'!$AG$5:$AG$22,$B29,'Episode Detail'!$S$5:$S$22,"Yes",'Episode Detail'!$AL$5:$AL$22,"No"),"")
B30: npd | D30: =COUNTIFS('Episode Detail'!$AG$5:$AG$22,$B30,'Episode Detail'!$AL$5:$AL$22,"No") -> 0 | E30: =SUMIFS('Episode Detail'!$U$5:$U$22,'Episode Detail'!$AG$5:$AG$22,$B30,'Episode Detail'!$AL$5:$AL$22,"No") -> 0 | F30: =SUMIFS('Episode Detail'!$AB$5:$AB$22,'Episode Detail'!$AG$5:$AG$22,$B30,'Episode Detail'!$AP$5:$AP$22,"Open",'Episode Detail'!$AL$5:$AL$22,"No") -> 0 | G30: =SUMIFS('Episode Detail'!$AC$5:$AC$22,'Episode Detail'!$AG$5:$AG$22,$B30,'Episode Detail'!$AL$5:$AL$22,"No") -> 0 | H30: =SUMIFS('Episode Detail'!$AD$5:$AD$22,'Episode Detail'!$AG$5:$AG$22,$B30,'Episode Detail'!$AL$5:$AL$22,"No") -> 0 | I30: =SUMIFS('Episode Detail'!$AE$5:$AE$22,'Episode Detail'!$AG$5:$AG$22,$B30,'Episode Detail'!$AL$5:$AL$22,"No") -> 0 | J30: =IFERROR(AVERAGEIFS('Episode Detail'!$Q$5:$Q$22,'Episode Detail'!$AG$5:$AG$22,$B30,'Episode Detail'!$S$5:$S$22,"Yes",'Episode Detail'!$AL$5:$AL$22,"No"),"")
A31: DATA_PROCESS | B31: — family total — | C31: No | D31: =COUNTIFS('Episode Detail'!$AH$5:$AH$22,$A31,'Episode Detail'!$AL$5:$AL$22,"No") -> 1 | E31: =SUMIFS('Episode Detail'!$U$5:$U$22,'Episode Detail'!$AH$5:$AH$22,$A31,'Episode Detail'!$AL$5:$AL$22,"No") -> 1 | F31: =SUMIFS('Episode Detail'!$AB$5:$AB$22,'Episode Detail'!$AH$5:$AH$22,$A31,'Episode Detail'!$AP$5:$AP$22,"Open",'Episode Detail'!$AL$5:$AL$22,"No") -> 2935 | G31: =SUMIFS('Episode Detail'!$AC$5:$AC$22,'Episode Detail'!$AH$5:$AH$22,$A31,'Episode Detail'!$AL$5:$AL$22,"No") -> 0 | H31: =SUMIFS('Episode Detail'!$AD$5:$AD$22,'Episode Detail'!$AH$5:$AH$22,$A31,'Episode Detail'!$AL$5:$AL$22,"No") -> 0 | I31: =SUMIFS('Episode Detail'!$AE$5:$AE$22,'Episode Detail'!$AH$5:$AH$22,$A31,'Episode Detail'!$AL$5:$AL$22,"No") -> 0 | J31: =IFERROR(AVERAGEIFS('Episode Detail'!$Q$5:$Q$22,'Episode Detail'!$AH$5:$AH$22,$A31,'Episode Detail'!$S$5:$S$22,"Yes",'Episode Detail'!$AL$5:$AL$22,"No"),"") -> 4
B32: delayed_communication | D32: =COUNTIFS('Episode Detail'!$AG$5:$AG$22,$B32,'Episode Detail'!$AL$5:$AL$22,"No") -> 0 | E32: =SUMIFS('Episode Detail'!$U$5:$U$22,'Episode Detail'!$AG$5:$AG$22,$B32,'Episode Detail'!$AL$5:$AL$22,"No") -> 0 | F32: =SUMIFS('Episode Detail'!$AB$5:$AB$22,'Episode Detail'!$AG$5:$AG$22,$B32,'Episode Detail'!$AP$5:$AP$22,"Open",'Episode Detail'!$AL$5:$AL$22,"No") -> 0 | G32: =SUMIFS('Episode Detail'!$AC$5:$AC$22,'Episode Detail'!$AG$5:$AG$22,$B32,'Episode Detail'!$AL$5:$AL$22,"No") -> 0 | H32: =SUMIFS('Episode Detail'!$AD$5:$AD$22,'Episode Detail'!$AG$5:$AG$22,$B32,'Episode Detail'!$AL$5:$AL$22,"No") -> 0 | I32: =SUMIFS('Episode Detail'!$AE$5:$AE$22,'Episode Detail'!$AG$5:$AG$22,$B32,'Episode Detail'!$AL$5:$AL$22,"No") -> 0 | J32: =IFERROR(AVERAGEIFS('Episode Detail'!$Q$5:$Q$22,'Episode Detail'!$AG$5:$AG$22,$B32,'Episode Detail'!$S$5:$S$22,"Yes",'Episode Detail'!$AL$5:$AL$22,"No"),"")
B33: price_difference | D33: =COUNTIFS('Episode Detail'!$AG$5:$AG$22,$B33,'Episode Detail'!$AL$5:$AL$22,"No") -> 0 | E33: =SUMIFS('Episode Detail'!$U$5:$U$22,'Episode Detail'!$AG$5:$AG$22,$B33,'Episode Detail'!$AL$5:$AL$22,"No") -> 0 | F33: =SUMIFS('Episode Detail'!$AB$5:$AB$22,'Episode Detail'!$AG$5:$AG$22,$B33,'Episode Detail'!$AP$5:$AP$22,"Open",'Episode Detail'!$AL$5:$AL$22,"No") -> 0 | G33: =SUMIFS('Episode Detail'!$AC$5:$AC$22,'Episode Detail'!$AG$5:$AG$22,$B33,'Episode Detail'!$AL$5:$AL$22,"No") -> 0 | H33: =SUMIFS('Episode Detail'!$AD$5:$AD$22,'Episode Detail'!$AG$5:$AG$22,$B33,'Episode Detail'!$AL$5:$AL$22,"No") -> 0 | I33: =SUMIFS('Episode Detail'!$AE$5:$AE$22,'Episode Detail'!$AG$5:$AG$22,$B33,'Episode Detail'!$AL$5:$AL$22,"No") -> 0 | J33: =IFERROR(AVERAGEIFS('Episode Detail'!$Q$5:$Q$22,'Episode Detail'!$AG$5:$AG$22,$B33,'Episode Detail'!$S$5:$S$22,"Yes",'Episode Detail'!$AL$5:$AL$22,"No"),"")
B34: price_variance | D34: =COUNTIFS('Episode Detail'!$AG$5:$AG$22,$B34,'Episode Detail'!$AL$5:$AL$22,"No") -> 0 | E34: =SUMIFS('Episode Detail'!$U$5:$U$22,'Episode Detail'!$AG$5:$AG$22,$B34,'Episode Detail'!$AL$5:$AL$22,"No") -> 0 | F34: =SUMIFS('Episode Detail'!$AB$5:$AB$22,'Episode Detail'!$AG$5:$AG$22,$B34,'Episode Detail'!$AP$5:$AP$22,"Open",'Episode Detail'!$AL$5:$AL$22,"No") -> 0 | G34: =SUMIFS('Episode Detail'!$AC$5:$AC$22,'Episode Detail'!$AG$5:$AG$22,$B34,'Episode Detail'!$AL$5:$AL$22,"No") -> 0 | H34: =SUMIFS('Episode Detail'!$AD$5:$AD$22,'Episode Detail'!$AG$5:$AG$22,$B34,'Episode Detail'!$AL$5:$AL$22,"No") -> 0 | I34: =SUMIFS('Episode Detail'!$AE$5:$AE$22,'Episode Detail'!$AG$5:$AG$22,$B34,'Episode Detail'!$AL$5:$AL$22,"No") -> 0 | J34: =IFERROR(AVERAGEIFS('Episode Detail'!$Q$5:$Q$22,'Episode Detail'!$AG$5:$AG$22,$B34,'Episode Detail'!$S$5:$S$22,"Yes",'Episode Detail'!$AL$5:$AL$22,"No"),"")
B35: price_overcharge | D35: =COUNTIFS('Episode Detail'!$AG$5:$AG$22,$B35,'Episode Detail'!$AL$5:$AL$22,"No") -> 0 | E35: =SUMIFS('Episode Detail'!$U$5:$U$22,'Episode Detail'!$AG$5:$AG$22,$B35,'Episode Detail'!$AL$5:$AL$22,"No") -> 0 | F35: =SUMIFS('Episode Detail'!$AB$5:$AB$22,'Episode Detail'!$AG$5:$AG$22,$B35,'Episode Detail'!$AP$5:$AP$22,"Open",'Episode Detail'!$AL$5:$AL$22,"No") -> 0 | G35: =SUMIFS('Episode Detail'!$AC$5:$AC$22,'Episode Detail'!$AG$5:$AG$22,$B35,'Episode Detail'!$AL$5:$AL$22,"No") -> 0 | H35: =SUMIFS('Episode Detail'!$AD$5:$AD$22,'Episode Detail'!$AG$5:$AG$22,$B35,'Episode Detail'!$AL$5:$AL$22,"No") -> 0 | I35: =SUMIFS('Episode Detail'!$AE$5:$AE$22,'Episode Detail'!$AG$5:$AG$22,$B35,'Episode Detail'!$AL$5:$AL$22,"No") -> 0 | J35: =IFERROR(AVERAGEIFS('Episode Detail'!$Q$5:$Q$22,'Episode Detail'!$AG$5:$AG$22,$B35,'Episode Detail'!$S$5:$S$22,"Yes",'Episode Detail'!$AL$5:$AL$22,"No"),"")
B36: invoicing_error | D36: =COUNTIFS('Episode Detail'!$AG$5:$AG$22,$B36,'Episode Detail'!$AL$5:$AL$22,"No") -> 0 | E36: =SUMIFS('Episode Detail'!$U$5:$U$22,'Episode Detail'!$AG$5:$AG$22,$B36,'Episode Detail'!$AL$5:$AL$22,"No") -> 0 | F36: =SUMIFS('Episode Detail'!$AB$5:$AB$22,'Episode Detail'!$AG$5:$AG$22,$B36,'Episode Detail'!$AP$5:$AP$22,"Open",'Episode Detail'!$AL$5:$AL$22,"No") -> 0 | G36: =SUMIFS('Episode Detail'!$AC$5:$AC$22,'Episode Detail'!$AG$5:$AG$22,$B36,'Episode Detail'!$AL$5:$AL$22,"No") -> 0 | H36: =SUMIFS('Episode Detail'!$AD$5:$AD$22,'Episode Detail'!$AG$5:$AG$22,$B36,'Episode Detail'!$AL$5:$AL$22,"No") -> 0 | I36: =SUMIFS('Episode Detail'!$AE$5:$AE$22,'Episode Detail'!$AG$5:$AG$22,$B36,'Episode Detail'!$AL$5:$AL$22,"No") -> 0 | J36: =IFERROR(AVERAGEIFS('Episode Detail'!$Q$5:$Q$22,'Episode Detail'!$AG$5:$AG$22,$B36,'Episode Detail'!$S$5:$S$22,"Yes",'Episode Detail'!$AL$5:$AL$22,"No"),"")
B37: stock_variance | D37: =COUNTIFS('Episode Detail'!$AG$5:$AG$22,$B37,'Episode Detail'!$AL$5:$AL$22,"No") -> 0 | E37: =SUMIFS('Episode Detail'!$U$5:$U$22,'Episode Detail'!$AG$5:$AG$22,$B37,'Episode Detail'!$AL$5:$AL$22,"No") -> 0 | F37: =SUMIFS('Episode Detail'!$AB$5:$AB$22,'Episode Detail'!$AG$5:$AG$22,$B37,'Episode Detail'!$AP$5:$AP$22,"Open",'Episode Detail'!$AL$5:$AL$22,"No") -> 0 | G37: =SUMIFS('Episode Detail'!$AC$5:$AC$22,'Episode Detail'!$AG$5:$AG$22,$B37,'Episode Detail'!$AL$5:$AL$22,"No") -> 0 | H37: =SUMIFS('Episode Detail'!$AD$5:$AD$22,'Episode Detail'!$AG$5:$AG$22,$B37,'Episode Detail'!$AL$5:$AL$22,"No") -> 0 | I37: =SUMIFS('Episode Detail'!$AE$5:$AE$22,'Episode Detail'!$AG$5:$AG$22,$B37,'Episode Detail'!$AL$5:$AL$22,"No") -> 0 | J37: =IFERROR(AVERAGEIFS('Episode Detail'!$Q$5:$Q$22,'Episode Detail'!$AG$5:$AG$22,$B37,'Episode Detail'!$S$5:$S$22,"Yes",'Episode Detail'!$AL$5:$AL$22,"No"),"")
B38: isolation_error | D38: =COUNTIFS('Episode Detail'!$AG$5:$AG$22,$B38,'Episode Detail'!$AL$5:$AL$22,"No") -> 0 | E38: =SUMIFS('Episode Detail'!$U$5:$U$22,'Episode Detail'!$AG$5:$AG$22,$B38,'Episode Detail'!$AL$5:$AL$22,"No") -> 0 | F38: =SUMIFS('Episode Detail'!$AB$5:$AB$22,'Episode Detail'!$AG$5:$AG$22,$B38,'Episode Detail'!$AP$5:$AP$22,"Open",'Episode Detail'!$AL$5:$AL$22,"No") -> 0 | G38: =SUMIFS('Episode Detail'!$AC$5:$AC$22,'Episode Detail'!$AG$5:$AG$22,$B38,'Episode Detail'!$AL$5:$AL$22,"No") -> 0 | H38: =SUMIFS('Episode Detail'!$AD$5:$AD$22,'Episode Detail'!$AG$5:$AG$22,$B38,'Episode Detail'!$AL$5:$AL$22,"No") -> 0 | I38: =SUMIFS('Episode Detail'!$AE$5:$AE$22,'Episode Detail'!$AG$5:$AG$22,$B38,'Episode Detail'!$AL$5:$AL$22,"No") -> 0 | J38: =IFERROR(AVERAGEIFS('Episode Detail'!$Q$5:$Q$22,'Episode Detail'!$AG$5:$AG$22,$B38,'Episode Detail'!$S$5:$S$22,"Yes",'Episode Detail'!$AL$5:$AL$22,"No"),"")
B39: wrong_product_description | D39: =COUNTIFS('Episode Detail'!$AG$5:$AG$22,$B39,'Episode Detail'!$AL$5:$AL$22,"No") -> 0 | E39: =SUMIFS('Episode Detail'!$U$5:$U$22,'Episode Detail'!$AG$5:$AG$22,$B39,'Episode Detail'!$AL$5:$AL$22,"No") -> 0 | F39: =SUMIFS('Episode Detail'!$AB$5:$AB$22,'Episode Detail'!$AG$5:$AG$22,$B39,'Episode Detail'!$AP$5:$AP$22,"Open",'Episode Detail'!$AL$5:$AL$22,"No") -> 0 | G39: =SUMIFS('Episode Detail'!$AC$5:$AC$22,'Episode Detail'!$AG$5:$AG$22,$B39,'Episode Detail'!$AL$5:$AL$22,"No") -> 0 | H39: =SUMIFS('Episode Detail'!$AD$5:$AD$22,'Episode Detail'!$AG$5:$AG$22,$B39,'Episode Detail'!$AL$5:$AL$22,"No") -> 0 | I39: =SUMIFS('Episode Detail'!$AE$5:$AE$22,'Episode Detail'!$AG$5:$AG$22,$B39,'Episode Detail'!$AL$5:$AL$22,"No") -> 0 | J39: =IFERROR(AVERAGEIFS('Episode Detail'!$Q$5:$Q$22,'Episode Detail'!$AG$5:$AG$22,$B39,'Episode Detail'!$S$5:$S$22,"Yes",'Episode Detail'!$AL$5:$AL$22,"No"),"")
B40: wrong_code | D40: =COUNTIFS('Episode Detail'!$AG$5:$AG$22,$B40,'Episode Detail'!$AL$5:$AL$22,"No") -> 1 | E40: =SUMIFS('Episode Detail'!$U$5:$U$22,'Episode Detail'!$AG$5:$AG$22,$B40,'Episode Detail'!$AL$5:$AL$22,"No") -> 1 | F40: =SUMIFS('Episode Detail'!$AB$5:$AB$22,'Episode Detail'!$AG$5:$AG$22,$B40,'Episode Detail'!$AP$5:$AP$22,"Open",'Episode Detail'!$AL$5:$AL$22,"No") -> 2935 | G40: =SUMIFS('Episode Detail'!$AC$5:$AC$22,'Episode Detail'!$AG$5:$AG$22,$B40,'Episode Detail'!$AL$5:$AL$22,"No") -> 0 | H40: =SUMIFS('Episode Detail'!$AD$5:$AD$22,'Episode Detail'!$AG$5:$AG$22,$B40,'Episode Detail'!$AL$5:$AL$22,"No") -> 0 | I40: =SUMIFS('Episode Detail'!$AE$5:$AE$22,'Episode Detail'!$AG$5:$AG$22,$B40,'Episode Detail'!$AL$5:$AL$22,"No") -> 0 | J40: =IFERROR(AVERAGEIFS('Episode Detail'!$Q$5:$Q$22,'Episode Detail'!$AG$5:$AG$22,$B40,'Episode Detail'!$S$5:$S$22,"Yes",'Episode Detail'!$AL$5:$AL$22,"No"),"") -> 4
B41: system_error | D41: =COUNTIFS('Episode Detail'!$AG$5:$AG$22,$B41,'Episode Detail'!$AL$5:$AL$22,"No") -> 0 | E41: =SUMIFS('Episode Detail'!$U$5:$U$22,'Episode Detail'!$AG$5:$AG$22,$B41,'Episode Detail'!$AL$5:$AL$22,"No") -> 0 | F41: =SUMIFS('Episode Detail'!$AB$5:$AB$22,'Episode Detail'!$AG$5:$AG$22,$B41,'Episode Detail'!$AP$5:$AP$22,"Open",'Episode Detail'!$AL$5:$AL$22,"No") -> 0 | G41: =SUMIFS('Episode Detail'!$AC$5:$AC$22,'Episode Detail'!$AG$5:$AG$22,$B41,'Episode Detail'!$AL$5:$AL$22,"No") -> 0 | H41: =SUMIFS('Episode Detail'!$AD$5:$AD$22,'Episode Detail'!$AG$5:$AG$22,$B41,'Episode Detail'!$AL$5:$AL$22,"No") -> 0 | I41: =SUMIFS('Episode Detail'!$AE$5:$AE$22,'Episode Detail'!$AG$5:$AG$22,$B41,'Episode Detail'!$AL$5:$AL$22,"No") -> 0 | J41: =IFERROR(AVERAGEIFS('Episode Detail'!$Q$5:$Q$22,'Episode Detail'!$AG$5:$AG$22,$B41,'Episode Detail'!$S$5:$S$22,"Yes",'Episode Detail'!$AL$5:$AL$22,"No"),"")
B42: lpo_error | D42: =COUNTIFS('Episode Detail'!$AG$5:$AG$22,$B42,'Episode Detail'!$AL$5:$AL$22,"No") -> 0 | E42: =SUMIFS('Episode Detail'!$U$5:$U$22,'Episode Detail'!$AG$5:$AG$22,$B42,'Episode Detail'!$AL$5:$AL$22,"No") -> 0 | F42: =SUMIFS('Episode Detail'!$AB$5:$AB$22,'Episode Detail'!$AG$5:$AG$22,$B42,'Episode Detail'!$AP$5:$AP$22,"Open",'Episode Detail'!$AL$5:$AL$22,"No") -> 0 | G42: =SUMIFS('Episode Detail'!$AC$5:$AC$22,'Episode Detail'!$AG$5:$AG$22,$B42,'Episode Detail'!$AL$5:$AL$22,"No") -> 0 | H42: =SUMIFS('Episode Detail'!$AD$5:$AD$22,'Episode Detail'!$AG$5:$AG$22,$B42,'Episode Detail'!$AL$5:$AL$22,"No") -> 0 | I42: =SUMIFS('Episode Detail'!$AE$5:$AE$22,'Episode Detail'!$AG$5:$AG$22,$B42,'Episode Detail'!$AL$5:$AL$22,"No") -> 0 | J42: =IFERROR(AVERAGEIFS('Episode Detail'!$Q$5:$Q$22,'Episode Detail'!$AG$5:$AG$22,$B42,'Episode Detail'!$S$5:$S$22,"Yes",'Episode Detail'!$AL$5:$AL$22,"No"),"")
A43: UNCLASSIFIED | B43: — family total — | C43: No | D43: =COUNTIFS('Episode Detail'!$AH$5:$AH$22,$A43,'Episode Detail'!$AL$5:$AL$22,"No") -> 1 | E43: =SUMIFS('Episode Detail'!$U$5:$U$22,'Episode Detail'!$AH$5:$AH$22,$A43,'Episode Detail'!$AL$5:$AL$22,"No") -> 1188 | F43: =SUMIFS('Episode Detail'!$AB$5:$AB$22,'Episode Detail'!$AH$5:$AH$22,$A43,'Episode Detail'!$AP$5:$AP$22,"Open",'Episode Detail'!$AL$5:$AL$22,"No") -> 1892531.5 | G43: =SUMIFS('Episode Detail'!$AC$5:$AC$22,'Episode Detail'!$AH$5:$AH$22,$A43,'Episode Detail'!$AL$5:$AL$22,"No") -> 0 | H43: =SUMIFS('Episode Detail'!$AD$5:$AD$22,'Episode Detail'!$AH$5:$AH$22,$A43,'Episode Detail'!$AL$5:$AL$22,"No") -> 0 | I43: =SUMIFS('Episode Detail'!$AE$5:$AE$22,'Episode Detail'!$AH$5:$AH$22,$A43,'Episode Detail'!$AL$5:$AL$22,"No") -> 0 | J43: =IFERROR(AVERAGEIFS('Episode Detail'!$Q$5:$Q$22,'Episode Detail'!$AH$5:$AH$22,$A43,'Episode Detail'!$S$5:$S$22,"Yes",'Episode Detail'!$AL$5:$AL$22,"No"),"") -> 2
B44: (unreasoned) | D44: =COUNTIFS('Episode Detail'!$AG$5:$AG$22,$B44,'Episode Detail'!$AL$5:$AL$22,"No") -> 1 | E44: =SUMIFS('Episode Detail'!$U$5:$U$22,'Episode Detail'!$AG$5:$AG$22,$B44,'Episode Detail'!$AL$5:$AL$22,"No") -> 1188 | F44: =SUMIFS('Episode Detail'!$AB$5:$AB$22,'Episode Detail'!$AG$5:$AG$22,$B44,'Episode Detail'!$AP$5:$AP$22,"Open",'Episode Detail'!$AL$5:$AL$22,"No") -> 1892531.5 | G44: =SUMIFS('Episode Detail'!$AC$5:$AC$22,'Episode Detail'!$AG$5:$AG$22,$B44,'Episode Detail'!$AL$5:$AL$22,"No") -> 0 | H44: =SUMIFS('Episode Detail'!$AD$5:$AD$22,'Episode Detail'!$AG$5:$AG$22,$B44,'Episode Detail'!$AL$5:$AL$22,"No") -> 0 | I44: =SUMIFS('Episode Detail'!$AE$5:$AE$22,'Episode Detail'!$AG$5:$AG$22,$B44,'Episode Detail'!$AL$5:$AL$22,"No") -> 0 | J44: =IFERROR(AVERAGEIFS('Episode Detail'!$Q$5:$Q$22,'Episode Detail'!$AG$5:$AG$22,$B44,'Episode Detail'!$S$5:$S$22,"Yes",'Episode Detail'!$AL$5:$AL$22,"No"),"") -> 2

Sheet Episode Detail
A1: Episode Detail — one row per (order, item, occurrence)
A2: As-at date: | B2: 46229 | C2: Promised lead time (days): | D2: Blue cells are parameters — edit these, not the formula columns.
A3: Lead time (days): | B3: 2
A4: Write-off threshold (working days): | B4: 7 | C4: Order Date | D4: Customer | E4: Main Account | F4: Channel | G4: Warehouse | H4: Inventory ID | I4: Item Description | J4: UOM | K4: Order Qty | L4: Unit Price (net) | M4: Backordered On | N4: Resolved On | O4: Window | P4: Days (calendar) | Q4: Days (working) | R4: Delay Label | S4: Start Date Verified? | T4: Episode No. | U4: Peak Backorder Qty | V4: Current Backorder Qty | W4: Shipped Qty | X4: Shipped Late Qty | Y4: Cancelled Qty | Z4: Partial Fills | AA4: Fill Rate % | AB4: Revenue at Risk | AC4: Delayed Revenue | AD4: Revenue-Days Delayed | AE4: Lost Revenue | AF4: Resolution Type | AG4: Reason Code | AH4: Reason Family | AI4: Reason Notes | AJ4: Reason Set By | AK4: Reason Set At | AL4: Excluded from KPI? | AM4: Exclusion Reason | AN4: Sync Run (opened) | AO4: Sync Run (resolved) | AP4: State | AQ4: Order 1st open row | AR4: Item 1st open row
A5: SO363506 | B5: SO | C5: 46213 | D5: Khetia Drapers Ltd - Plus | E5: Khetia Drapers Ltd | F5: Modern Trade T2 | G5: FGS | H5: SIFTP0015 | I5: Sifa TP Emb. Unwrap. Twinpack 20x2s White | J5: CASE | K5: 1356 | L5: 142.55 | M5: 46213 | O5: =IF(N5="",TEXT(M5,"d mmm yyyy")&" – ongoing",IF(TEXT(M5,"mmmyyyy")=TEXT(N5,"mmmyyyy"),TEXT(M5,"d")&" – "&TEXT(N5,"d mmm yyyy"),IF(TEXT(M5,"yyyy")=TEXT(N5,"yyyy"),TEXT(M5,"d mmm")&" – "&TEXT(N5,"d mmm yyyy"),TEXT(M5,"d mmm yyyy")&" – "&TEXT(N5,"d mmm yyyy")))) -> 10 Jul 2026 – ongoing | P5: =IF(N5="",$B$2-M5,N5-M5) -> 16 | Q5: =IF(N5="",NETWORKDAYS.INTL(M5,$B$2,"0000001")-1,NETWORKDAYS.INTL(M5,N5,"0000001")-1) -> 13 | R5: =IF(Q5=0,"Same Day",Q5&IF(Q5=1," Day Delay"," Days Delay")&IF(S5="Yes",""," (min.)")) -> 13 Days Delay | S5: Yes | T5: 1 | U5: 680 | V5: 420 | W5: 936 | X5: 0 | Y5: 0 | Z5: 2 | AA5: =IFERROR(W5/(K5-Y5),"") -> 0.69026549 | AB5: =V5*L5 -> 59871 | AC5: =X5*L5 -> 0 | AD5: =AC5*MAX(0,Q5-$B$3) -> 0 | AE5: =IF(AF5="cancelled",Y5*L5,IF(AND(N5="",Q5>$B$4),V5*L5,Y5*L5)) -> 59871 | AG5: out_of_stock_production | AH5: PRODUCTION | AI5: Mill line 2 down 11-14 Jul | AJ5: j.mwangi | AK5: 46214 | AL5: No | AN5: 48100 | AP5: =IF(ISBLANK(N5),"Open","Resolved") -> Open | AQ5: =IF(AND($AP5="Open",$AL5="No",COUNTIFS($A$5:$A5,$A5,$AP$5:$AP5,"Open",$AL$5:$AL5,"No")=1),1,0) -> 1 | AR5: =IF(AND($AP5="Open",$AL5="No",COUNTIFS($H$5:$H5,$H5,$AP$5:$AP5,"Open",$AL$5:$AL5,"No")=1),1,0) -> 1
A6: SO363491 | B6: SO | C6: 46213 | D6: Khetia Drapers Ltd - Gigamart | E6: Khetia Drapers Ltd | F6: Modern Trade T2 | G6: FGS | H6: SIFTP0015 | I6: Sifa TP Emb. Unwrap. Twinpack 20x2s White | J6: CASE | K6: 1086 | L6: 142.55 | M6: 46213 | O6: =IF(N6="",TEXT(M6,"d mmm yyyy")&" – ongoing",IF(TEXT(M6,"mmmyyyy")=TEXT(N6,"mmmyyyy"),TEXT(M6,"d")&" – "&TEXT(N6,"d mmm yyyy"),IF(TEXT(M6,"yyyy")=TEXT(N6,"yyyy"),TEXT(M6,"d mmm")&" – "&TEXT(N6,"d mmm yyyy"),TEXT(M6,"d mmm yyyy")&" – "&TEXT(N6,"d mmm yyyy")))) -> 10 Jul 2026 – ongoing | P6: =IF(N6="",$B$2-M6,N6-M6) -> 16 | Q6: =IF(N6="",NETWORKDAYS.INTL(M6,$B$2,"0000001")-1,NETWORKDAYS.INTL(M6,N6,"0000001")-1) -> 13 | R6: =IF(Q6=0,"Same Day",Q6&IF(Q6=1," Day Delay"," Days Delay")&IF(S6="Yes",""," (min.)")) -> 13 Days Delay | S6: Yes | T6: 1 | U6: 594 | V6: 528 | W6: 558 | X6: 0 | Y6: 0 | Z6: 1 | AA6: =IFERROR(W6/(K6-Y6),"") -> 0.51381215 | AB6: =V6*L6 -> 75266.4 | AC6: =X6*L6 -> 0 | AD6: =AC6*MAX(0,Q6-$B$3) -> 0 | AE6: =IF(AF6="cancelled",Y6*L6,IF(AND(N6="",Q6>$B$4),V6*L6,Y6*L6)) -> 75266.4 | AG6: out_of_stock_production | AH6: PRODUCTION | AI6: Same mill event | AJ6: j.mwangi | AK6: 46214 | AL6: No | AN6: 48103 | AP6: =IF(ISBLANK(N6),"Open","Resolved") -> Open | AQ6: =IF(AND($AP6="Open",$AL6="No",COUNTIFS($A$5:$A6,$A6,$AP$5:$AP6,"Open",$AL$5:$AL6,"No")=1),1,0) -> 1 | AR6: =IF(AND($AP6="Open",$AL6="No",COUNTIFS($H$5:$H6,$H6,$AP$5:$AP6,"Open",$AL$5:$AL6,"No")=1),1,0) -> 0
A7: SO363495 | B7: SO | C7: 46213 | D7: Khetia Drapers Ltd - Eldoret CBD | E7: Khetia Drapers Ltd | F7: Modern Trade T2 | G7: FGS | H7: COSTP0004 | I7: Cosy TP Emb. Wrap. 40s Singles White | J7: CASE | K7: 1128 | L7: 64.55 | M7: 46213 | O7: =IF(N7="",TEXT(M7,"d mmm yyyy")&" – ongoing",IF(TEXT(M7,"mmmyyyy")=TEXT(N7,"mmmyyyy"),TEXT(M7,"d")&" – "&TEXT(N7,"d mmm yyyy"),IF(TEXT(M7,"yyyy")=TEXT(N7,"yyyy"),TEXT(M7,"d mmm")&" – "&TEXT(N7,"d mmm yyyy"),TEXT(M7,"d mmm yyyy")&" – "&TEXT(N7,"d mmm yyyy")))) -> 10 Jul 2026 – ongoing | P7: =IF(N7="",$B$2-M7,N7-M7) -> 16 | Q7: =IF(N7="",NETWORKDAYS.INTL(M7,$B$2,"0000001")-1,NETWORKDAYS.INTL(M7,N7,"0000001")-1) -> 13 | R7: =IF(Q7=0,"Same Day",Q7&IF(Q7=1," Day Delay"," Days Delay")&IF(S7="Yes",""," (min.)")) -> 13 Days Delay | S7: Yes | T7: 1 | U7: 542 | V7: 510 | W7: 618 | X7: 0 | Y7: 0 | Z7: 1 | AA7: =IFERROR(W7/(K7-Y7),"") -> 0.54787234 | AB7: =V7*L7 -> 32920.5 | AC7: =X7*L7 -> 0 | AD7: =AC7*MAX(0,Q7-$B$3) -> 0 | AE7: =IF(AF7="cancelled",Y7*L7,IF(AND(N7="",Q7>$B$4),V7*L7,Y7*L7)) -> 32920.5 | AG7: raw_material_stockout | AH7: PRODUCTION | AI7: Parent reel short shipped | AJ7: j.mwangi | AK7: 46215 | AL7: No | AN7: 48106 | AP7: =IF(ISBLANK(N7),"Open","Resolved") -> Open | AQ7: =IF(AND($AP7="Open",$AL7="No",COUNTIFS($A$5:$A7,$A7,$AP$5:$AP7,"Open",$AL$5:$AL7,"No")=1),1,0) -> 1 | AR7: =IF(AND($AP7="Open",$AL7="No",COUNTIFS($H$5:$H7,$H7,$AP$5:$AP7,"Open",$AL$5:$AL7,"No")=1),1,0) -> 1
A8: SO363507 | B8: SO | C8: 46213 | D8: Khetia Drapers Ltd - Kakamega Poa | E8: Khetia Drapers Ltd | F8: Modern Trade T2 | G8: FGS | H8: COSTP0006 | I8: Cosy TP Emb. Unwrap. 4x10s White | J8: CASE | K8: 876 | L8: 64.55 | M8: 46213 | N8: 46225 | O8: =IF(N8="",TEXT(M8,"d mmm yyyy")&" – ongoing",IF(TEXT(M8,"mmmyyyy")=TEXT(N8,"mmmyyyy"),TEXT(M8,"d")&" – "&TEXT(N8,"d mmm yyyy"),IF(TEXT(M8,"yyyy")=TEXT(N8,"yyyy"),TEXT(M8,"d mmm")&" – "&TEXT(N8,"d mmm yyyy"),TEXT(M8,"d mmm yyyy")&" – "&TEXT(N8,"d mmm yyyy")))) -> 10 – 22 Jul 2026 | P8: =IF(N8="",$B$2-M8,N8-M8) -> 12 | Q8: =IF(N8="",NETWORKDAYS.INTL(M8,$B$2,"0000001")-1,NETWORKDAYS.INTL(M8,N8,"0000001")-1) -> 10 | R8: =IF(Q8=0,"Same Day",Q8&IF(Q8=1," Day Delay"," Days Delay")&IF(S8="Yes",""," (min.)")) -> 10 Days Delay | S8: Yes | T8: 1 | U8: 514 | V8: 0 | W8: 876 | X8: 514 | Y8: 0 | Z8: 3 | AA8: =IFERROR(W8/(K8-Y8),"") -> 1 | AB8: =V8*L8 -> 0 | AC8: =X8*L8 -> 33178.7 | AD8: =AC8*MAX(0,Q8-$B$3) -> 265429.6 | AE8: =IF(AF8="cancelled",Y8*L8,IF(AND(N8="",Q8>$B$4),V8*L8,Y8*L8)) -> 0 | AF8: shipped_full | AG8: out_of_stock_production | AH8: PRODUCTION | AI8: Cleared on 22 Jul run | AJ8: j.mwangi | AK8: 46215 | AL8: No | AN8: 48109 | AO8: 48189 | AP8: =IF(ISBLANK(N8),"Open","Resolved") -> Resolved | AQ8: =IF(AND($AP8="Open",$AL8="No",COUNTIFS($A$5:$A8,$A8,$AP$5:$AP8,"Open",$AL$5:$AL8,"No")=1),1,0) -> 0 | AR8: =IF(AND($AP8="Open",$AL8="No",COUNTIFS($H$5:$H8,$H8,$AP$5:$AP8,"Open",$AL$5:$AL8,"No")=1),1,0) -> 0
A9: SO363603 | B9: SO | C9: 46213 | D9: Khetia Drapers Ltd - Thika | E9: Khetia Drapers Ltd | F9: Modern Trade T2 | G9: FGS | H9: FAYTP0013 | I9: Fay TP Emb. Wrap. 40s Singles White | J9: CASE | K9: 965 | L9: 73.3 | M9: 46213 | N9: 46223 | O9: =IF(N9="",TEXT(M9,"d mmm yyyy")&" – ongoing",IF(TEXT(M9,"mmmyyyy")=TEXT(N9,"mmmyyyy"),TEXT(M9,"d")&" – "&TEXT(N9,"d mmm yyyy"),IF(TEXT(M9,"yyyy")=TEXT(N9,"yyyy"),TEXT(M9,"d mmm")&" – "&TEXT(N9,"d mmm yyyy"),TEXT(M9,"d mmm yyyy")&" – "&TEXT(N9,"d mmm yyyy")))) -> 10 – 20 Jul 2026 | P9: =IF(N9="",$B$2-M9,N9-M9) -> 10 | Q9: =IF(N9="",NETWORKDAYS.INTL(M9,$B$2,"0000001")-1,NETWORKDAYS.INTL(M9,N9,"0000001")-1) -> 8 | R9: =IF(Q9=0,"Same Day",Q9&IF(Q9=1," Day Delay"," Days Delay")&IF(S9="Yes",""," (min.)")) -> 8 Days Delay | S9: Yes | T9: 1 | U9: 478 | V9: 0 | W9: 890 | X9: 478 | Y9: 75 | Z9: 2 | AA9: =IFERROR(W9/(K9-Y9),"") -> 1 | AB9: =V9*L9 -> 0 | AC9: =X9*L9 -> 35037.4 | AD9: =AC9*MAX(0,Q9-$B$3) -> 210224.4 | AE9: =IF(AF9="cancelled",Y9*L9,IF(AND(N9="",Q9>$B$4),V9*L9,Y9*L9)) -> 5497.5 | AF9: shipped_partial | AG9: out_of_stock_production | AH9: PRODUCTION | AI9: 75 CASE cancelled by buyer | AJ9: j.mwangi | AK9: 46215 | AL9: No | AN9: 48112 | AO9: 48192 | AP9: =IF(ISBLANK(N9),"Open","Resolved") -> Resolved | AQ9: =IF(AND($AP9="Open",$AL9="No",COUNTIFS($A$5:$A9,$A9,$AP$5:$AP9,"Open",$AL$5:$AL9,"No")=1),1,0) -> 0 | AR9: =IF(AND($AP9="Open",$AL9="No",COUNTIFS($H$5:$H9,$H9,$AP$5:$AP9,"Open",$AL$5:$AL9,"No")=1),1,0) -> 0
A10: SO367035 | B10: SO | C10: 46226 | D10: Majid Al Futtaim Hypermarkets Ltd - Business Bay Square | E10: Majid Al Futtaim Hypermarkets Ltd | F10: Modern Trade T1 | G10: FGS | H10: FAYFL0010 | I10: Fay Aluminium Foil Catering (45x50m) | J10: ROLL | K10: 24 | L10: 2542.53 | M10: 46226 | O10: =IF(N10="",TEXT(M10,"d mmm yyyy")&" – ongoing",IF(TEXT(M10,"mmmyyyy")=TEXT(N10,"mmmyyyy"),TEXT(M10,"d")&" – "&TEXT(N10,"d mmm yyyy"),IF(TEXT(M10,"yyyy")=TEXT(N10,"yyyy"),TEXT(M10,"d mmm")&" – "&TEXT(N10,"d mmm yyyy"),TEXT(M10,"d mmm yyyy")&" – "&TEXT(N10,"d mmm yyyy")))) -> 23 Jul 2026 – ongoing | P10: =IF(N10="",$B$2-M10,N10-M10) -> 3 | Q10: =IF(N10="",NETWORKDAYS.INTL(M10,$B$2,"0000001")-1,NETWORKDAYS.INTL(M10,N10,"0000001")-1) -> 2 | R10: =IF(Q10=0,"Same Day",Q10&IF(Q10=1," Day Delay"," Days Delay")&IF(S10="Yes",""," (min.)")) -> 2 Days Delay | S10: Yes | T10: 1 | U10: 24 | V10: 24 | W10: 0 | X10: 0 | Y10: 0 | Z10: 0 | AA10: =IFERROR(W10/(K10-Y10),"") -> 0 | AB10: =V10*L10 -> 61020.72 | AC10: =X10*L10 -> 0 | AD10: =AC10*MAX(0,Q10-$B$3) -> 0 | AE10: =IF(AF10="cancelled",Y10*L10,IF(AND(N10="",Q10>$B$4),V10*L10,Y10*L10)) -> 0 | AG10: out_of_stock_procurement | AH10: PROCUREMENT | AI10: Import ETA 29 Jul | AJ10: a.otieno | AK10: 46226 | AL10: No | AN10: 48115 | AP10: =IF(ISBLANK(N10),"Open","Resolved") -> Open | AQ10: =IF(AND($AP10="Open",$AL10="No",COUNTIFS($A$5:$A10,$A10,$AP$5:$AP10,"Open",$AL$5:$AL10,"No")=1),1,0) -> 1 | AR10: =IF(AND($AP10="Open",$AL10="No",COUNTIFS($H$5:$H10,$H10,$AP$5:$AP10,"Open",$AL$5:$AL10,"No")=1),1,0) -> 1
A11: SO367021 | B11: SO | C11: 46226 | D11: Majid Al Futtaim Hypermarkets Ltd - The Hub | E11: Majid Al Futtaim Hypermarkets Ltd | F11: Modern Trade T1 | G11: FGS | H11: FAYFL0010 | I11: Fay Aluminium Foil Catering (45x50m) | J11: ROLL | K11: 18 | L11: 1649.14 | M11: 46226 | O11: =IF(N11="",TEXT(M11,"d mmm yyyy")&" – ongoing",IF(TEXT(M11,"mmmyyyy")=TEXT(N11,"mmmyyyy"),TEXT(M11,"d")&" – "&TEXT(N11,"d mmm yyyy"),IF(TEXT(M11,"yyyy")=TEXT(N11,"yyyy"),TEXT(M11,"d mmm")&" – "&TEXT(N11,"d mmm yyyy"),TEXT(M11,"d mmm yyyy")&" – "&TEXT(N11,"d mmm yyyy")))) -> 23 Jul 2026 – ongoing | P11: =IF(N11="",$B$2-M11,N11-M11) -> 3 | Q11: =IF(N11="",NETWORKDAYS.INTL(M11,$B$2,"0000001")-1,NETWORKDAYS.INTL(M11,N11,"0000001")-1) -> 2 | R11: =IF(Q11=0,"Same Day",Q11&IF(Q11=1," Day Delay"," Days Delay")&IF(S11="Yes",""," (min.)")) -> 2 Days Delay | S11: Yes | T11: 1 | U11: 18 | V11: 18 | W11: 0 | X11: 0 | Y11: 0 | Z11: 0 | AA11: =IFERROR(W11/(K11-Y11),"") -> 0 | AB11: =V11*L11 -> 29684.52 | AC11: =X11*L11 -> 0 | AD11: =AC11*MAX(0,Q11-$B$3) -> 0 | AE11: =IF(AF11="cancelled",Y11*L11,IF(AND(N11="",Q11>$B$4),V11*L11,Y11*L11)) -> 0 | AG11: out_of_stock_procurement | AH11: PROCUREMENT | AI11: Same import | AJ11: a.otieno | AK11: 46226 | AL11: No | AN11: 48118 | AP11: =IF(ISBLANK(N11),"Open","Resolved") -> Open | AQ11: =IF(AND($AP11="Open",$AL11="No",COUNTIFS($A$5:$A11,$A11,$AP$5:$AP11,"Open",$AL$5:$AL11,"No")=1),1,0) -> 1 | AR11: =IF(AND($AP11="Open",$AL11="No",COUNTIFS($H$5:$H11,$H11,$AP$5:$AP11,"Open",$AL$5:$AL11,"No")=1),1,0) -> 0
A12: SO364962 | B12: SO | C12: 46219 | D12: Quick Mart Ltd- Nakuru Statehouse | E12: Quick Mart Ltd | F12: Modern Trade T1 | G12: FGS | H12: FAYFL0010 | I12: Fay Aluminium Foil Catering (45x50m) | J12: ROLL | K12: 12 | L12: 2542.53 | M12: 46219 | O12: =IF(N12="",TEXT(M12,"d mmm yyyy")&" – ongoing",IF(TEXT(M12,"mmmyyyy")=TEXT(N12,"mmmyyyy"),TEXT(M12,"d")&" – "&TEXT(N12,"d mmm yyyy"),IF(TEXT(M12,"yyyy")=TEXT(N12,"yyyy"),TEXT(M12,"d mmm")&" – "&TEXT(N12,"d mmm yyyy"),TEXT(M12,"d mmm yyyy")&" – "&TEXT(N12,"d mmm yyyy")))) -> 16 Jul 2026 – ongoing | P12: =IF(N12="",$B$2-M12,N12-M12) -> 10 | Q12: =IF(N12="",NETWORKDAYS.INTL(M12,$B$2,"0000001")-1,NETWORKDAYS.INTL(M12,N12,"0000001")-1) -> 8 | R12: =IF(Q12=0,"Same Day",Q12&IF(Q12=1," Day Delay"," Days Delay")&IF(S12="Yes",""," (min.)")) -> 8 Days Delay | S12: Yes | T12: 1 | U12: 12 | V12: 12 | W12: 0 | X12: 0 | Y12: 0 | Z12: 0 | AA12: =IFERROR(W12/(K12-Y12),"") -> 0 | AB12: =V12*L12 -> 30510.36 | AC12: =X12*L12 -> 0 | AD12: =AC12*MAX(0,Q12-$B$3) -> 0 | AE12: =IF(AF12="cancelled",Y12*L12,IF(AND(N12="",Q12>$B$4),V12*L12,Y12*L12)) -> 30510.36 | AG12: out_of_stock_procurement | AH12: PROCUREMENT | AI12: Same import | AJ12: a.otieno | AK12: 46220 | AL12: No | AN12: 48121 | AP12: =IF(ISBLANK(N12),"Open","Resolved") -> Open | AQ12: =IF(AND($AP12="Open",$AL12="No",COUNTIFS($A$5:$A12,$A12,$AP$5:$AP12,"Open",$AL$5:$AL12,"No")=1),1,0) -> 1 | AR12: =IF(AND($AP12="Open",$AL12="No",COUNTIFS($H$5:$H12,$H12,$AP$5:$AP12,"Open",$AL$5:$AL12,"No")=1),1,0) -> 0
A13: SO364948 | B13: SO | C13: 46218 | D13: Quick Mart Ltd - Rongai | E13: Quick Mart Ltd | F13: Modern Trade T1 | G13: FGS | H13: FAYCL0009 | I13: Fay Cling Film Catering 30cmx300m GP | J13: PIECE | K13: 6 | L13: 2756.9 | M13: 46218 | O13: =IF(N13="",TEXT(M13,"d mmm yyyy")&" – ongoing",IF(TEXT(M13,"mmmyyyy")=TEXT(N13,"mmmyyyy"),TEXT(M13,"d")&" – "&TEXT(N13,"d mmm yyyy"),IF(TEXT(M13,"yyyy")=TEXT(N13,"yyyy"),TEXT(M13,"d mmm")&" – "&TEXT(N13,"d mmm yyyy"),TEXT(M13,"d mmm yyyy")&" – "&TEXT(N13,"d mmm yyyy")))) -> 15 Jul 2026 – ongoing | P13: =IF(N13="",$B$2-M13,N13-M13) -> 11 | Q13: =IF(N13="",NETWORKDAYS.INTL(M13,$B$2,"0000001")-1,NETWORKDAYS.INTL(M13,N13,"0000001")-1) -> 9 | R13: =IF(Q13=0,"Same Day",Q13&IF(Q13=1," Day Delay"," Days Delay")&IF(S13="Yes",""," (min.)")) -> 9 Days Delay | S13: Yes | T13: 1 | U13: 6 | V13: 6 | W13: 0 | X13: 0 | Y13: 0 | Z13: 0 | AA13: =IFERROR(W13/(K13-Y13),"") -> 0 | AB13: =V13*L13 -> 16541.4 | AC13: =X13*L13 -> 0 | AD13: =AC13*MAX(0,Q13-$B$3) -> 0 | AE13: =IF(AF13="cancelled",Y13*L13,IF(AND(N13="",Q13>$B$4),V13*L13,Y13*L13)) -> 16541.4 | AG13: conversion_delays | AH13: PRODUCTION | AI13: Awaiting converting slot | AJ13: a.otieno | AK13: 46220 | AL13: No | AN13: 48124 | AP13: =IF(ISBLANK(N13),"Open","Resolved") -> Open | AQ13: =IF(AND($AP13="Open",$AL13="No",COUNTIFS($A$5:$A13,$A13,$AP$5:$AP13,"Open",$AL$5:$AL13,"No")=1),1,0) -> 1 | AR13: =IF(AND($AP13="Open",$AL13="No",COUNTIFS($H$5:$H13,$H13,$AP$5:$AP13,"Open",$AL$5:$AL13,"No")=1),1,0) -> 1
A14: SO364955 | B14: SO | C14: 46218 | D14: Quick Mart Ltd - Nakuru | E14: Quick Mart Ltd | F14: Modern Trade T1 | G14: FGS | H14: FAYCL0009 | I14: Fay Cling Film Catering 30cmx300m GP | J14: PIECE | K14: 6 | L14: 2756.9 | M14: 46218 | O14: =IF(N14="",TEXT(M14,"d mmm yyyy")&" – ongoing",IF(TEXT(M14,"mmmyyyy")=TEXT(N14,"mmmyyyy"),TEXT(M14,"d")&" – "&TEXT(N14,"d mmm yyyy"),IF(TEXT(M14,"yyyy")=TEXT(N14,"yyyy"),TEXT(M14,"d mmm")&" – "&TEXT(N14,"d mmm yyyy"),TEXT(M14,"d mmm yyyy")&" – "&TEXT(N14,"d mmm yyyy")))) -> 15 Jul 2026 – ongoing | P14: =IF(N14="",$B$2-M14,N14-M14) -> 11 | Q14: =IF(N14="",NETWORKDAYS.INTL(M14,$B$2,"0000001")-1,NETWORKDAYS.INTL(M14,N14,"0000001")-1) -> 9 | R14: =IF(Q14=0,"Same Day",Q14&IF(Q14=1," Day Delay"," Days Delay")&IF(S14="Yes",""," (min.)")) -> 9 Days Delay | S14: Yes | T14: 1 | U14: 6 | V14: 6 | W14: 0 | X14: 0 | Y14: 0 | Z14: 0 | AA14: =IFERROR(W14/(K14-Y14),"") -> 0 | AB14: =V14*L14 -> 16541.4 | AC14: =X14*L14 -> 0 | AD14: =AC14*MAX(0,Q14-$B$3) -> 0 | AE14: =IF(AF14="cancelled",Y14*L14,IF(AND(N14="",Q14>$B$4),V14*L14,Y14*L14)) -> 16541.4 | AG14: conversion_delays | AH14: PRODUCTION | AI14: Awaiting converting slot | AJ14: a.otieno | AK14: 46220 | AL14: No | AN14: 48127 | AP14: =IF(ISBLANK(N14),"Open","Resolved") -> Open | AQ14: =IF(AND($AP14="Open",$AL14="No",COUNTIFS($A$5:$A14,$A14,$AP$5:$AP14,"Open",$AL$5:$AL14,"No")=1),1,0) -> 1 | AR14: =IF(AND($AP14="Open",$AL14="No",COUNTIFS($H$5:$H14,$H14,$AP$5:$AP14,"Open",$AL$5:$AL14,"No")=1),1,0) -> 0
A15: SO365985 | B15: SO | C15: 46223 | D15: Sam West Distributors LTD | E15: Sam West Distributors LTD | F15: General Trade | G15: FGS | H15: TISTP0008 | I15: Tishu Poa TP Emb. Wrap. 4x10s White 100s | J15: CASE | K15: 980 | L15: 860.17 | M15: 46223 | N15: 46225 | O15: =IF(N15="",TEXT(M15,"d mmm yyyy")&" – ongoing",IF(TEXT(M15,"mmmyyyy")=TEXT(N15,"mmmyyyy"),TEXT(M15,"d")&" – "&TEXT(N15,"d mmm yyyy"),IF(TEXT(M15,"yyyy")=TEXT(N15,"yyyy"),TEXT(M15,"d mmm")&" – "&TEXT(N15,"d mmm yyyy"),TEXT(M15,"d mmm yyyy")&" – "&TEXT(N15,"d mmm yyyy")))) -> 20 – 22 Jul 2026 | P15: =IF(N15="",$B$2-M15,N15-M15) -> 2 | Q15: =IF(N15="",NETWORKDAYS.INTL(M15,$B$2,"0000001")-1,NETWORKDAYS.INTL(M15,N15,"0000001")-1) -> 2 | R15: =IF(Q15=0,"Same Day",Q15&IF(Q15=1," Day Delay"," Days Delay")&IF(S15="Yes",""," (min.)")) -> 2 Days Delay | S15: Yes | T15: 1 | U15: 262 | V15: 0 | W15: 980 | X15: 262 | Y15: 0 | Z15: 3 | AA15: =IFERROR(W15/(K15-Y15),"") -> 1 | AB15: =V15*L15 -> 0 | AC15: =X15*L15 -> 225364.54 | AD15: =AC15*MAX(0,Q15-$B$3) -> 0 | AE15: =IF(AF15="cancelled",Y15*L15,IF(AND(N15="",Q15>$B$4),V15*L15,Y15*L15)) -> 0 | AF15: shipped_full | AG15: transfer_delays | AH15: LOGISTICS | AI15: Inter-warehouse transfer 2 days late | AJ15: p.kamau | AK15: 46224 | AL15: No | AN15: 48130 | AO15: 48210 | AP15: =IF(ISBLANK(N15),"Open","Resolved") -> Resolved | AQ15: =IF(AND($AP15="Open",$AL15="No",COUNTIFS($A$5:$A15,$A15,$AP$5:$AP15,"Open",$AL$5:$AL15,"No")=1),1,0) -> 0 | AR15: =IF(AND($AP15="Open",$AL15="No",COUNTIFS($H$5:$H15,$H15,$AP$5:$AP15,"Open",$AL$5:$AL15,"No")=1),1,0) -> 0
A16: SO367051 | B16: SO | C16: 46226 | D16: Stage Mattresses Ltd | E16: Stage Mattresses Ltd | F16: General Trade | G16: FGS | H16: COWGT0001 | I16: Cow & Gate First 400g | J16: CAN | K16: 36 | L16: 1035 | M16: 46226 | O16: =IF(N16="",TEXT(M16,"d mmm yyyy")&" – ongoing",IF(TEXT(M16,"mmmyyyy")=TEXT(N16,"mmmyyyy"),TEXT(M16,"d")&" – "&TEXT(N16,"d mmm yyyy"),IF(TEXT(M16,"yyyy")=TEXT(N16,"yyyy"),TEXT(M16,"d mmm")&" – "&TEXT(N16,"d mmm yyyy"),TEXT(M16,"d mmm yyyy")&" – "&TEXT(N16,"d mmm yyyy")))) -> 23 Jul 2026 – ongoing | P16: =IF(N16="",$B$2-M16,N16-M16) -> 3 | Q16: =IF(N16="",NETWORKDAYS.INTL(M16,$B$2,"0000001")-1,NETWORKDAYS.INTL(M16,N16,"0000001")-1) -> 2 | R16: =IF(Q16=0,"Same Day",Q16&IF(Q16=1," Day Delay"," Days Delay")&IF(S16="Yes",""," (min.)")) -> 2 Days Delay (min.) | S16: No (estimated) | T16: 1 | U16: 36 | V16: 36 | W16: 0 | X16: 0 | Y16: 0 | Z16: 0 | AA16: =IFERROR(W16/(K16-Y16),"") -> 0 | AB16: =V16*L16 -> 37260 | AC16: =X16*L16 -> 0 | AD16: =AC16*MAX(0,Q16-$B$3) -> 0 | AE16: =IF(AF16="cancelled",Y16*L16,IF(AND(N16="",Q16>$B$4),V16*L16,Y16*L16)) -> 0 | AG16: out_of_stock_msa | AH16: PROCUREMENT | AI16: MSA allocation pending | AL16: No | AN16: 48133 | AP16: =IF(ISBLANK(N16),"Open","Resolved") -> Open | AQ16: =IF(AND($AP16="Open",$AL16="No",COUNTIFS($A$5:$A16,$A16,$AP$5:$AP16,"Open",$AL$5:$AL16,"No")=1),1,0) -> 1 | AR16: =IF(AND($AP16="Open",$AL16="No",COUNTIFS($H$5:$H16,$H16,$AP$5:$AP16,"Open",$AL$5:$AL16,"No")=1),1,0) -> 1
A17: SO367174 | B17: SO | C17: 46226 | D17: Goodlife Pharmacy Ltd | E17: Goodlife Pharmacy Ltd | F17: Pharmacy | G17: FGS | H17: COWGT0002 | I17: Cow & Gate Follow Up 400g | J17: CAN | K17: 1188 | L17: 1593.04 | M17: 46226 | O17: =IF(N17="",TEXT(M17,"d mmm yyyy")&" – ongoing",IF(TEXT(M17,"mmmyyyy")=TEXT(N17,"mmmyyyy"),TEXT(M17,"d")&" – "&TEXT(N17,"d mmm yyyy"),IF(TEXT(M17,"yyyy")=TEXT(N17,"yyyy"),TEXT(M17,"d mmm")&" – "&TEXT(N17,"d mmm yyyy"),TEXT(M17,"d mmm yyyy")&" – "&TEXT(N17,"d mmm yyyy")))) -> 23 Jul 2026 – ongoing | P17: =IF(N17="",$B$2-M17,N17-M17) -> 3 | Q17: =IF(N17="",NETWORKDAYS.INTL(M17,$B$2,"0000001")-1,NETWORKDAYS.INTL(M17,N17,"0000001")-1) -> 2 | R17: =IF(Q17=0,"Same Day",Q17&IF(Q17=1," Day Delay"," Days Delay")&IF(S17="Yes",""," (min.)")) -> 2 Days Delay | S17: Yes | T17: 1 | U17: 1188 | V17: 1188 | W17: 0 | X17: 0 | Y17: 0 | Z17: 0 | AA17: =IFERROR(W17/(K17-Y17),"") -> 0 | AB17: =V17*L17 -> 1892531.5 | AC17: =X17*L17 -> 0 | AD17: =AC17*MAX(0,Q17-$B$3) -> 0 | AE17: =IF(AF17="cancelled",Y17*L17,IF(AND(N17="",Q17>$B$4),V17*L17,Y17*L17)) -> 0 | AG17: (unreasoned) | AH17: UNCLASSIFIED | AL17: No | AN17: 48136 | AP17: =IF(ISBLANK(N17),"Open","Resolved") -> Open | AQ17: =IF(AND($AP17="Open",$AL17="No",COUNTIFS($A$5:$A17,$A17,$AP$5:$AP17,"Open",$AL$5:$AL17,"No")=1),1,0) -> 1 | AR17: =IF(AND($AP17="Open",$AL17="No",COUNTIFS($H$5:$H17,$H17,$AP$5:$AP17,"Open",$AL$5:$AL17,"No")=1),1,0) -> 1
A18: SO361051 | B18: SO | C18: 46204 | D18: Nairobi Java House Ltd | E18: Nairobi Java House Ltd | F18: Modern Trade T2 | G18: FGS | H18: SIFTP0009 | I18: Sifa TP Emb. Unwrap. 4x10s White | J18: CASE | K18: 150 | L18: 0.1 | M18: 46204 | O18: =IF(N18="",TEXT(M18,"d mmm yyyy")&" – ongoing",IF(TEXT(M18,"mmmyyyy")=TEXT(N18,"mmmyyyy"),TEXT(M18,"d")&" – "&TEXT(N18,"d mmm yyyy"),IF(TEXT(M18,"yyyy")=TEXT(N18,"yyyy"),TEXT(M18,"d mmm")&" – "&TEXT(N18,"d mmm yyyy"),TEXT(M18,"d mmm yyyy")&" – "&TEXT(N18,"d mmm yyyy")))) -> 1 Jul 2026 – ongoing | P18: =IF(N18="",$B$2-M18,N18-M18) -> 25 | Q18: =IF(N18="",NETWORKDAYS.INTL(M18,$B$2,"0000001")-1,NETWORKDAYS.INTL(M18,N18,"0000001")-1) -> 21 | R18: =IF(Q18=0,"Same Day",Q18&IF(Q18=1," Day Delay"," Days Delay")&IF(S18="Yes",""," (min.)")) -> 21 Days Delay (min.) | S18: No (estimated) | T18: 1 | U18: 150 | V18: 36 | W18: 114 | X18: 0 | Y18: 0 | Z18: 4 | AA18: =IFERROR(W18/(K18-Y18),"") -> 0.76 | AB18: =V18*L18 -> 3.6 | AC18: =X18*L18 -> 0 | AD18: =AC18*MAX(0,Q18-$B$3) -> 0 | AE18: =IF(AF18="cancelled",Y18*L18,IF(AND(N18="",Q18>$B$4),V18*L18,Y18*L18)) -> 3.6 | AG18: promo_product | AH18: COMMERCIAL | AI18: Free-goods line — excluded | AJ18: p.kamau | AK18: 46208 | AL18: Yes | AM18: Free / zero-value line | AN18: 48139 | AP18: =IF(ISBLANK(N18),"Open","Resolved") -> Open | AQ18: =IF(AND($AP18="Open",$AL18="No",COUNTIFS($A$5:$A18,$A18,$AP$5:$AP18,"Open",$AL$5:$AL18,"No")=1),1,0) -> 0 | AR18: =IF(AND($AP18="Open",$AL18="No",COUNTIFS($H$5:$H18,$H18,$AP$5:$AP18,"Open",$AL$5:$AL18,"No")=1),1,0) -> 0
A19: SO363484 | B19: SO | C19: 46213 | D19: Maguna's Superstore (K) Ltd - EMBU | E19: Maguna's Super Stores (K) Ltd | F19: Modern Trade T2 | G19: FGS | H19: FAYTP0008 | I19: Fay TP Emb. Unwrap. 4x10s White | J19: CASE | K19: 612 | L19: 89.1 | M19: 46213 | N19: 46219 | O19: =IF(N19="",TEXT(M19,"d mmm yyyy")&" – ongoing",IF(TEXT(M19,"mmmyyyy")=TEXT(N19,"mmmyyyy"),TEXT(M19,"d")&" – "&TEXT(N19,"d mmm yyyy"),IF(TEXT(M19,"yyyy")=TEXT(N19,"yyyy"),TEXT(M19,"d mmm")&" – "&TEXT(N19,"d mmm yyyy"),TEXT(M19,"d mmm yyyy")&" – "&TEXT(N19,"d mmm yyyy")))) -> 10 – 16 Jul 2026 | P19: =IF(N19="",$B$2-M19,N19-M19) -> 6 | Q19: =IF(N19="",NETWORKDAYS.INTL(M19,$B$2,"0000001")-1,NETWORKDAYS.INTL(M19,N19,"0000001")-1) -> 5 | R19: =IF(Q19=0,"Same Day",Q19&IF(Q19=1," Day Delay"," Days Delay")&IF(S19="Yes",""," (min.)")) -> 5 Days Delay | S19: Yes | T19: 1 | U19: 182 | V19: 0 | W19: 612 | X19: 182 | Y19: 0 | Z19: 2 | AA19: =IFERROR(W19/(K19-Y19),"") -> 1 | AB19: =V19*L19 -> 0 | AC19: =X19*L19 -> 16216.2 | AD19: =AC19*MAX(0,Q19-$B$3) -> 48648.6 | AE19: =IF(AF19="cancelled",Y19*L19,IF(AND(N19="",Q19>$B$4),V19*L19,Y19*L19)) -> 0 | AF19: shipped_full | AG19: did_not_pick_on_shipment | AH19: LOGISTICS | AI19: Picked short on first shipment | AJ19: p.kamau | AK19: 46216 | AL19: No | AN19: 48142 | AO19: 48222 | AP19: =IF(ISBLANK(N19),"Open","Resolved") -> Resolved | AQ19: =IF(AND($AP19="Open",$AL19="No",COUNTIFS($A$5:$A19,$A19,$AP$5:$AP19,"Open",$AL$5:$AL19,"No")=1),1,0) -> 0 | AR19: =IF(AND($AP19="Open",$AL19="No",COUNTIFS($H$5:$H19,$H19,$AP$5:$AP19,"Open",$AL$5:$AL19,"No")=1),1,0) -> 0
A20: SO363482 | B20: SO | C20: 46213 | D20: Maguna's Superstore (K) Ltd - EMBU | E20: Maguna's Super Stores (K) Ltd | F20: Modern Trade T2 | G20: FGS | H20: FAYTP0008 | I20: Fay TP Emb. Unwrap. 4x10s White | J20: CASE | K20: 480 | L20: 89.1 | M20: 46213 | N20: 46217 | O20: =IF(N20="",TEXT(M20,"d mmm yyyy")&" – ongoing",IF(TEXT(M20,"mmmyyyy")=TEXT(N20,"mmmyyyy"),TEXT(M20,"d")&" – "&TEXT(N20,"d mmm yyyy"),IF(TEXT(M20,"yyyy")=TEXT(N20,"yyyy"),TEXT(M20,"d mmm")&" – "&TEXT(N20,"d mmm yyyy"),TEXT(M20,"d mmm yyyy")&" – "&TEXT(N20,"d mmm yyyy")))) -> 10 – 14 Jul 2026 | P20: =IF(N20="",$B$2-M20,N20-M20) -> 4 | Q20: =IF(N20="",NETWORKDAYS.INTL(M20,$B$2,"0000001")-1,NETWORKDAYS.INTL(M20,N20,"0000001")-1) -> 3 | R20: =IF(Q20=0,"Same Day",Q20&IF(Q20=1," Day Delay"," Days Delay")&IF(S20="Yes",""," (min.)")) -> 3 Days Delay | S20: Yes | T20: 2 | U20: 120 | V20: 0 | W20: 480 | X20: 120 | Y20: 0 | Z20: 1 | AA20: =IFERROR(W20/(K20-Y20),"") -> 1 | AB20: =V20*L20 -> 0 | AC20: =X20*L20 -> 10692 | AD20: =AC20*MAX(0,Q20-$B$3) -> 10692 | AE20: =IF(AF20="cancelled",Y20*L20,IF(AND(N20="",Q20>$B$4),V20*L20,Y20*L20)) -> 0 | AF20: shipped_full | AG20: did_not_pick_on_shipment | AH20: LOGISTICS | AI20: Re-opened after shipment cancel | AJ20: p.kamau | AK20: 46216 | AL20: No | AN20: 48145 | AO20: 48225 | AP20: =IF(ISBLANK(N20),"Open","Resolved") -> Resolved | AQ20: =IF(AND($AP20="Open",$AL20="No",COUNTIFS($A$5:$A20,$A20,$AP$5:$AP20,"Open",$AL$5:$AL20,"No")=1),1,0) -> 0 | AR20: =IF(AND($AP20="Open",$AL20="No",COUNTIFS($H$5:$H20,$H20,$AP$5:$AP20,"Open",$AL$5:$AL20,"No")=1),1,0) -> 0
A21: SO366429 | B21: SO | C21: 46224 | D21: Sheal Limited | E21: Sheal Limited | F21: (not classified) | G21: TPFGS | H21: TISTP0008 | I21: Tishu Poa TP Emb. Wrap. 4x10s White 100s | J21: CASE | K21: 1 | L21: 2935 | M21: 46224 | O21: =IF(N21="",TEXT(M21,"d mmm yyyy")&" – ongoing",IF(TEXT(M21,"mmmyyyy")=TEXT(N21,"mmmyyyy"),TEXT(M21,"d")&" – "&TEXT(N21,"d mmm yyyy"),IF(TEXT(M21,"yyyy")=TEXT(N21,"yyyy"),TEXT(M21,"d mmm")&" – "&TEXT(N21,"d mmm yyyy"),TEXT(M21,"d mmm yyyy")&" – "&TEXT(N21,"d mmm yyyy")))) -> 21 Jul 2026 – ongoing | P21: =IF(N21="",$B$2-M21,N21-M21) -> 5 | Q21: =IF(N21="",NETWORKDAYS.INTL(M21,$B$2,"0000001")-1,NETWORKDAYS.INTL(M21,N21,"0000001")-1) -> 4 | R21: =IF(Q21=0,"Same Day",Q21&IF(Q21=1," Day Delay"," Days Delay")&IF(S21="Yes",""," (min.)")) -> 4 Days Delay | S21: Yes | T21: 1 | U21: 1 | V21: 1 | W21: 0 | X21: 0 | Y21: 0 | Z21: 0 | AA21: =IFERROR(W21/(K21-Y21),"") -> 0 | AB21: =V21*L21 -> 2935 | AC21: =X21*L21 -> 0 | AD21: =AC21*MAX(0,Q21-$B$3) -> 0 | AE21: =IF(AF21="cancelled",Y21*L21,IF(AND(N21="",Q21>$B$4),V21*L21,Y21*L21)) -> 0 | AG21: wrong_code | AH21: DATA_PROCESS | AI21: Item code corrected 24 Jul | AJ21: c.wanjiru | AK21: 46227 | AL21: No | AN21: 48148 | AP21: =IF(ISBLANK(N21),"Open","Resolved") -> Open | AQ21: =IF(AND($AP21="Open",$AL21="No",COUNTIFS($A$5:$A21,$A21,$AP$5:$AP21,"Open",$AL$5:$AL21,"No")=1),1,0) -> 1 | AR21: =IF(AND($AP21="Open",$AL21="No",COUNTIFS($H$5:$H21,$H21,$AP$5:$AP21,"Open",$AL$5:$AL21,"No")=1),1,0) -> 1
A22: SO362943 | B22: SO | C22: 46211 | D22: Bluewave Multisupplies Ltd | E22: Bluewave Multisupplies Ltd | F22: (not classified) | G22: FGS | H22: COSTP0023 | I22: Cosy Poa TP Emb. Wrap. 4x10s White 150s | J22: CASE | K22: 260 | L22: 75 | M22: 46211 | O22: =IF(N22="",TEXT(M22,"d mmm yyyy")&" – ongoing",IF(TEXT(M22,"mmmyyyy")=TEXT(N22,"mmmyyyy"),TEXT(M22,"d")&" – "&TEXT(N22,"d mmm yyyy"),IF(TEXT(M22,"yyyy")=TEXT(N22,"yyyy"),TEXT(M22,"d mmm")&" – "&TEXT(N22,"d mmm yyyy"),TEXT(M22,"d mmm yyyy")&" – "&TEXT(N22,"d mmm yyyy")))) -> 8 Jul 2026 – ongoing | P22: =IF(N22="",$B$2-M22,N22-M22) -> 18 | Q22: =IF(N22="",NETWORKDAYS.INTL(M22,$B$2,"0000001")-1,NETWORKDAYS.INTL(M22,N22,"0000001")-1) -> 15 | R22: =IF(Q22=0,"Same Day",Q22&IF(Q22=1," Day Delay"," Days Delay")&IF(S22="Yes",""," (min.)")) -> 15 Days Delay (min.) | S22: No (estimated) | T22: 1 | U22: 260 | V22: 260 | W22: 0 | X22: 0 | Y22: 0 | Z22: 0 | AA22: =IFERROR(W22/(K22-Y22),"") -> 0 | AB22: =V22*L22 -> 19500 | AC22: =X22*L22 -> 0 | AD22: =AC22*MAX(0,Q22-$B$3) -> 0 | AE22: =IF(AF22="cancelled",Y22*L22,IF(AND(N22="",Q22>$B$4),V22*L22,Y22*L22)) -> 19500 | AG22: order_to_make | AH22: PRODUCTION | AI22: Made-to-order, batch not scheduled | AJ22: j.mwangi | AK22: 46213 | AL22: No | AN22: 48151 | AP22: =IF(ISBLANK(N22),"Open","Resolved") -> Open | AQ22: =IF(AND($AP22="Open",$AL22="No",COUNTIFS($A$5:$A22,$A22,$AP$5:$AP22,"Open",$AL$5:$AL22,"No")=1),1,0) -> 1 | AR22: =IF(AND($AP22="Open",$AL22="No",COUNTIFS($H$5:$H22,$H22,$AP$5:$AP22,"Open",$AL$5:$AL22,"No")=1),1,0) -> 1
A23: TOTAL | U23: =SUM(U5:U22) -> 5073 | V23: =SUM(V5:V22) -> 3045 | W23: =SUM(W5:W22) -> 6064 | X23: =SUM(X5:X22) -> 1556 | Y23: =SUM(Y5:Y22) -> 75 | AB23: =SUM(AB5:AB22) -> 2274586.4 | AC23: =SUM(AC5:AC22) -> 320488.84 | AD23: =SUM(AD5:AD22) -> 534994.6 | AE23: =SUM(AE5:AE22) -> 256652.16 | AQ23: =SUM(AQ5:AQ22) -> 12 | AR23: =SUM(AR5:AR22) -> 8

Sheet Event Log
A1: Event Log — append-only audit trail
A2: One row per state transition, straight from backorder_line_events. No formulas: this sheet is evidence and must stay immutable.
A4: Episode ID | B4: Order Nbr. | C4: Inventory ID | D4: Occurred At | E4: Event Type | F4: Event Label | G4: BO Qty Before | H4: BO Qty After | I4: Delta Qty | J4: Delta Value (KES) | K4: Order Status at Event | L4: Reason Code at Event | M4: Actor | N4: Sync Run ID
A5: 8821 | B5: SO363506 | C5: SIFTP0015 | D5: 46213.385 | E5: opened | F5: Entered backorder — 680 CASE short | H5: 680 | I5: 680 | J5: 96934 | K5: Back Order | M5: system | N5: 48100
A6: 8821 | B6: SO363506 | C6: SIFTP0015 | D6: 46214.46 | E6: reason_set | F6: Reason set: Out of stock — production | G6: 680 | H6: 680 | I6: 0 | J6: 0 | K6: Back Order | L6: out_of_stock_production | M6: j.mwangi | N6: 48112
A7: 8821 | B7: SO363506 | C7: SIFTP0015 | D7: 46218.604 | E7: partial_fill | F7: Partial fill — 180 CASE shipped | G7: 680 | H7: 500 | I7: -180 | J7: -25659 | K7: Back Order | L7: out_of_stock_production | M7: system | N7: 48131
A8: 8821 | B8: SO363506 | C8: SIFTP0015 | D8: 46221.337 | E8: partial_fill | F8: Partial fill — 80 CASE shipped | G8: 500 | H8: 420 | I8: -80 | J8: -11404 | K8: Back Order | L8: out_of_stock_production | M8: system | N8: 48148
A9: 8834 | B9: SO363507 | C9: COSTP0006 | D9: 46213.385 | E9: opened | F9: Entered backorder — 514 CASE short | H9: 514 | I9: 514 | J9: 33179 | K9: Back Order | M9: system | N9: 48100
A10: 8834 | B10: SO363507 | C10: COSTP0006 | D10: 46215.431 | E10: reason_set | F10: Reason set: Out of stock — production | G10: 514 | H10: 514 | I10: 0 | J10: 0 | K10: Back Order | L10: out_of_stock_production | M10: j.mwangi | N10: 48119
A11: 8834 | B11: SO363507 | C11: COSTP0006 | D11: 46220.697 | E11: partial_fill | F11: Partial fill — 214 CASE shipped | G11: 514 | H11: 300 | I11: -214 | J11: -13813 | K11: Back Order | L11: out_of_stock_production | M11: system | N11: 48141
A12: 8834 | B12: SO363507 | C12: COSTP0006 | D12: 46223.376 | E12: partial_fill | F12: Partial fill — 160 CASE shipped | G12: 300 | H12: 140 | I12: -160 | J12: -10328 | K12: Back Order | L12: out_of_stock_production | M12: system | N12: 48155
A13: 8834 | B13: SO363507 | C13: COSTP0006 | D13: 46225.484 | E13: resolved | F13: Resolved — shipped in full (12 working days) | G13: 140 | H13: 0 | I13: -140 | J13: -9037 | K13: Shipping | L13: out_of_stock_production | M13: system | N13: 48168
A14: 8902 | B14: SO363484 | C14: FAYTP0008 | D14: 46213.385 | E14: opened | F14: Entered backorder — 182 CASE short | H14: 182 | I14: 182 | J14: 16216 | K14: Back Order | M14: system | N14: 48100
A15: 8902 | B15: SO363484 | C15: FAYTP0008 | D15: 46219.549 | E15: resolved | F15: Resolved — shipped in full (5 working days) | G15: 182 | H15: 0 | I15: -182 | J15: -16216 | K15: Shipping | L15: did_not_pick_on_shipment | M15: system | N15: 48137
A16: 8903 | B16: SO363482 | C16: FAYTP0008 | D16: 46214.385 | E16: opened | F16: Entered backorder — 120 CASE short (episode 1) | H16: 120 | I16: 120 | J16: 10692 | K16: Back Order | M16: system | N16: 48104
A17: 8903 | B17: SO363482 | C17: FAYTP0008 | D17: 46215.66 | E17: resolved | F17: Resolved — picked and shipped | G17: 120 | H17: 0 | I17: -120 | J17: -10692 | K17: Shipping | L17: did_not_pick_on_shipment | M17: system | N17: 48121
A18: 8904 | B18: SO363482 | C18: FAYTP0008 | D18: 46216.354 | E18: reopened | F18: Re-opened — shipment cancelled, 120 CASE short again (episode 2) | G18: 0 | H18: 120 | I18: 120 | J18: 10692 | K18: Back Order | L18: did_not_pick_on_shipment | M18: system | N18: 48125
A19: 8904 | B19: SO363482 | C19: FAYTP0008 | D19: 46217.503 | E19: resolved | F19: Resolved — shipped in full (1 working day) | G19: 120 | H19: 0 | I19: -120 | J19: -10692 | K19: Shipping | L19: did_not_pick_on_shipment | M19: system | N19: 48129
A20: 9011 | B20: SO367035 | C20: FAYFL0010 | D20: 46226.347 | E20: opened | F20: Entered backorder — 24 ROLL short | H20: 24 | I20: 24 | J20: 61021 | K20: Back Order | M20: system | N20: 48201
A21: 9011 | B21: SO367035 | C21: FAYFL0010 | D21: 46226.406 | E21: reason_set | F21: Reason set: Out of stock — procurement (import ETA 29 Jul) | G21: 24 | H21: 24 | I21: 0 | J21: 0 | K21: Back Order | L21: out_of_stock_procurement | M21: a.otieno | N21: 48203
A22: 9044 | B22: SO361051 | C22: SIFTP0009 | D22: 46204.33 | E22: excluded | F22: Excluded from KPIs — free / zero-value promotional line | G22: 150 | H22: 150 | I22: 0 | J22: 0 | K22: Back Order | L22: promo_product | M22: system | N22: 48012

Sheet By Item
A1: By item — ranked by Revenue-Days Delayed
A2: Revenue-Days Delayed is the correct ranking measure: it weights a large order held briefly against a small one held for weeks.
A4: Inventory ID | B4: Description | C4: UOM | D4: Episodes | E4: Distinct orders | F4: Peak Qty short | G4: Revenue at Risk | H4: Revenue-Days Delayed | I4: Lost Revenue | J4: Avg Days Delay | K4: Repeat episodes
A5: SIFTP0015 | B5: Sifa TP Emb. Unwrap. Twinpack 20x2s White | C5: CASE | D5: =COUNTIFS('Episode Detail'!$H$5:$H$22,$A5,'Episode Detail'!$AL$5:$AL$22,"No") -> 2 | E5: =SUMPRODUCT(('Episode Detail'!$H$5:$H$22=$A5)*('Episode Detail'!$AL$5:$AL$22="No")*'Episode Detail'!$AQ$5:$AQ$22) -> 2 | F5: =SUMIFS('Episode Detail'!$U$5:$U$22,'Episode Detail'!$H$5:$H$22,$A5,'Episode Detail'!$AL$5:$AL$22,"No") -> 1274 | G5: =SUMIFS('Episode Detail'!$AB$5:$AB$22,'Episode Detail'!$H$5:$H$22,$A5,'Episode Detail'!$AP$5:$AP$22,"Open",'Episode Detail'!$AL$5:$AL$22,"No") -> 135137.4 | H5: =SUMIFS('Episode Detail'!$AD$5:$AD$22,'Episode Detail'!$H$5:$H$22,$A5,'Episode Detail'!$AL$5:$AL$22,"No") -> 0 | I5: =SUMIFS('Episode Detail'!$AE$5:$AE$22,'Episode Detail'!$H$5:$H$22,$A5,'Episode Detail'!$AL$5:$AL$22,"No") -> 135137.4 | J5: =IFERROR(AVERAGEIFS('Episode Detail'!$Q$5:$Q$22,'Episode Detail'!$H$5:$H$22,$A5,'Episode Detail'!$S$5:$S$22,"Yes",'Episode Detail'!$AL$5:$AL$22,"No"),"") -> 13 | K5: =COUNTIFS('Episode Detail'!$H$5:$H$22,$A5,'Episode Detail'!$T$5:$T$22,">1") -> 0
A6: COSTP0004 | B6: Cosy TP Emb. Wrap. 40s Singles White | C6: CASE | D6: =COUNTIFS('Episode Detail'!$H$5:$H$22,$A6,'Episode Detail'!$AL$5:$AL$22,"No") -> 1 | E6: =SUMPRODUCT(('Episode Detail'!$H$5:$H$22=$A6)*('Episode Detail'!$AL$5:$AL$22="No")*'Episode Detail'!$AQ$5:$AQ$22) -> 1 | F6: =SUMIFS('Episode Detail'!$U$5:$U$22,'Episode Detail'!$H$5:$H$22,$A6,'Episode Detail'!$AL$5:$AL$22,"No") -> 542 | G6: =SUMIFS('Episode Detail'!$AB$5:$AB$22,'Episode Detail'!$H$5:$H$22,$A6,'Episode Detail'!$AP$5:$AP$22,"Open",'Episode Detail'!$AL$5:$AL$22,"No") -> 32920.5 | H6: =SUMIFS('Episode Detail'!$AD$5:$AD$22,'Episode Detail'!$H$5:$H$22,$A6,'Episode Detail'!$AL$5:$AL$22,"No") -> 0 | I6: =SUMIFS('Episode Detail'!$AE$5:$AE$22,'Episode Detail'!$H$5:$H$22,$A6,'Episode Detail'!$AL$5:$AL$22,"No") -> 32920.5 | J6: =IFERROR(AVERAGEIFS('Episode Detail'!$Q$5:$Q$22,'Episode Detail'!$H$5:$H$22,$A6,'Episode Detail'!$S$5:$S$22,"Yes",'Episode Detail'!$AL$5:$AL$22,"No"),"") -> 13 | K6: =COUNTIFS('Episode Detail'!$H$5:$H$22,$A6,'Episode Detail'!$T$5:$T$22,">1") -> 0
A7: COSTP0006 | B7: Cosy TP Emb. Unwrap. 4x10s White | C7: CASE | D7: =COUNTIFS('Episode Detail'!$H$5:$H$22,$A7,'Episode Detail'!$AL$5:$AL$22,"No") -> 1 | E7: =SUMPRODUCT(('Episode Detail'!$H$5:$H$22=$A7)*('Episode Detail'!$AL$5:$AL$22="No")*'Episode Detail'!$AQ$5:$AQ$22) -> 0 | F7: =SUMIFS('Episode Detail'!$U$5:$U$22,'Episode Detail'!$H$5:$H$22,$A7,'Episode Detail'!$AL$5:$AL$22,"No") -> 514 | G7: =SUMIFS('Episode Detail'!$AB$5:$AB$22,'Episode Detail'!$H$5:$H$22,$A7,'Episode Detail'!$AP$5:$AP$22,"Open",'Episode Detail'!$AL$5:$AL$22,"No") -> 0 | H7: =SUMIFS('Episode Detail'!$AD$5:$AD$22,'Episode Detail'!$H$5:$H$22,$A7,'Episode Detail'!$AL$5:$AL$22,"No") -> 265429.6 | I7: =SUMIFS('Episode Detail'!$AE$5:$AE$22,'Episode Detail'!$H$5:$H$22,$A7,'Episode Detail'!$AL$5:$AL$22,"No") -> 0 | J7: =IFERROR(AVERAGEIFS('Episode Detail'!$Q$5:$Q$22,'Episode Detail'!$H$5:$H$22,$A7,'Episode Detail'!$S$5:$S$22,"Yes",'Episode Detail'!$AL$5:$AL$22,"No"),"") -> 10 | K7: =COUNTIFS('Episode Detail'!$H$5:$H$22,$A7,'Episode Detail'!$T$5:$T$22,">1") -> 0
A8: FAYTP0013 | B8: Fay TP Emb. Wrap. 40s Singles White | C8: CASE | D8: =COUNTIFS('Episode Detail'!$H$5:$H$22,$A8,'Episode Detail'!$AL$5:$AL$22,"No") -> 1 | E8: =SUMPRODUCT(('Episode Detail'!$H$5:$H$22=$A8)*('Episode Detail'!$AL$5:$AL$22="No")*'Episode Detail'!$AQ$5:$AQ$22) -> 0 | F8: =SUMIFS('Episode Detail'!$U$5:$U$22,'Episode Detail'!$H$5:$H$22,$A8,'Episode Detail'!$AL$5:$AL$22,"No") -> 478 | G8: =SUMIFS('Episode Detail'!$AB$5:$AB$22,'Episode Detail'!$H$5:$H$22,$A8,'Episode Detail'!$AP$5:$AP$22,"Open",'Episode Detail'!$AL$5:$AL$22,"No") -> 0 | H8: =SUMIFS('Episode Detail'!$AD$5:$AD$22,'Episode Detail'!$H$5:$H$22,$A8,'Episode Detail'!$AL$5:$AL$22,"No") -> 210224.4 | I8: =SUMIFS('Episode Detail'!$AE$5:$AE$22,'Episode Detail'!$H$5:$H$22,$A8,'Episode Detail'!$AL$5:$AL$22,"No") -> 5497.5 | J8: =IFERROR(AVERAGEIFS('Episode Detail'!$Q$5:$Q$22,'Episode Detail'!$H$5:$H$22,$A8,'Episode Detail'!$S$5:$S$22,"Yes",'Episode Detail'!$AL$5:$AL$22,"No"),"") -> 8 | K8: =COUNTIFS('Episode Detail'!$H$5:$H$22,$A8,'Episode Detail'!$T$5:$T$22,">1") -> 0
A9: FAYFL0010 | B9: Fay Aluminium Foil Catering (45x50m) | C9: ROLL | D9: =COUNTIFS('Episode Detail'!$H$5:$H$22,$A9,'Episode Detail'!$AL$5:$AL$22,"No") -> 3 | E9: =SUMPRODUCT(('Episode Detail'!$H$5:$H$22=$A9)*('Episode Detail'!$AL$5:$AL$22="No")*'Episode Detail'!$AQ$5:$AQ$22) -> 3 | F9: =SUMIFS('Episode Detail'!$U$5:$U$22,'Episode Detail'!$H$5:$H$22,$A9,'Episode Detail'!$AL$5:$AL$22,"No") -> 54 | G9: =SUMIFS('Episode Detail'!$AB$5:$AB$22,'Episode Detail'!$H$5:$H$22,$A9,'Episode Detail'!$AP$5:$AP$22,"Open",'Episode Detail'!$AL$5:$AL$22,"No") -> 121215.6 | H9: =SUMIFS('Episode Detail'!$AD$5:$AD$22,'Episode Detail'!$H$5:$H$22,$A9,'Episode Detail'!$AL$5:$AL$22,"No") -> 0 | I9: =SUMIFS('Episode Detail'!$AE$5:$AE$22,'Episode Detail'!$H$5:$H$22,$A9,'Episode Detail'!$AL$5:$AL$22,"No") -> 30510.36 | J9: =IFERROR(AVERAGEIFS('Episode Detail'!$Q$5:$Q$22,'Episode Detail'!$H$5:$H$22,$A9,'Episode Detail'!$S$5:$S$22,"Yes",'Episode Detail'!$AL$5:$AL$22,"No"),"") -> 4 | K9: =COUNTIFS('Episode Detail'!$H$5:$H$22,$A9,'Episode Detail'!$T$5:$T$22,">1") -> 0
A10: FAYCL0009 | B10: Fay Cling Film Catering 30cmx300m GP | C10: PIECE | D10: =COUNTIFS('Episode Detail'!$H$5:$H$22,$A10,'Episode Detail'!$AL$5:$AL$22,"No") -> 2 | E10: =SUMPRODUCT(('Episode Detail'!$H$5:$H$22=$A10)*('Episode Detail'!$AL$5:$AL$22="No")*'Episode Detail'!$AQ$5:$AQ$22) -> 2 | F10: =SUMIFS('Episode Detail'!$U$5:$U$22,'Episode Detail'!$H$5:$H$22,$A10,'Episode Detail'!$AL$5:$AL$22,"No") -> 12 | G10: =SUMIFS('Episode Detail'!$AB$5:$AB$22,'Episode Detail'!$H$5:$H$22,$A10,'Episode Detail'!$AP$5:$AP$22,"Open",'Episode Detail'!$AL$5:$AL$22,"No") -> 33082.8 | H10: =SUMIFS('Episode Detail'!$AD$5:$AD$22,'Episode Detail'!$H$5:$H$22,$A10,'Episode Detail'!$AL$5:$AL$22,"No") -> 0 | I10: =SUMIFS('Episode Detail'!$AE$5:$AE$22,'Episode Detail'!$H$5:$H$22,$A10,'Episode Detail'!$AL$5:$AL$22,"No") -> 33082.8 | J10: =IFERROR(AVERAGEIFS('Episode Detail'!$Q$5:$Q$22,'Episode Detail'!$H$5:$H$22,$A10,'Episode Detail'!$S$5:$S$22,"Yes",'Episode Detail'!$AL$5:$AL$22,"No"),"") -> 9 | K10: =COUNTIFS('Episode Detail'!$H$5:$H$22,$A10,'Episode Detail'!$T$5:$T$22,">1") -> 0
A11: TISTP0008 | B11: Tishu Poa TP Emb. Wrap. 4x10s White 100s | C11: CASE | D11: =COUNTIFS('Episode Detail'!$H$5:$H$22,$A11,'Episode Detail'!$AL$5:$AL$22,"No") -> 2 | E11: =SUMPRODUCT(('Episode Detail'!$H$5:$H$22=$A11)*('Episode Detail'!$AL$5:$AL$22="No")*'Episode Detail'!$AQ$5:$AQ$22) -> 1 | F11: =SUMIFS('Episode Detail'!$U$5:$U$22,'Episode Detail'!$H$5:$H$22,$A11,'Episode Detail'!$AL$5:$AL$22,"No") -> 263 | G11: =SUMIFS('Episode Detail'!$AB$5:$AB$22,'Episode Detail'!$H$5:$H$22,$A11,'Episode Detail'!$AP$5:$AP$22,"Open",'Episode Detail'!$AL$5:$AL$22,"No") -> 2935 | H11: =SUMIFS('Episode Detail'!$AD$5:$AD$22,'Episode Detail'!$H$5:$H$22,$A11,'Episode Detail'!$AL$5:$AL$22,"No") -> 0 | I11: =SUMIFS('Episode Detail'!$AE$5:$AE$22,'Episode Detail'!$H$5:$H$22,$A11,'Episode Detail'!$AL$5:$AL$22,"No") -> 0 | J11: =IFERROR(AVERAGEIFS('Episode Detail'!$Q$5:$Q$22,'Episode Detail'!$H$5:$H$22,$A11,'Episode Detail'!$S$5:$S$22,"Yes",'Episode Detail'!$AL$5:$AL$22,"No"),"") -> 3 | K11: =COUNTIFS('Episode Detail'!$H$5:$H$22,$A11,'Episode Detail'!$T$5:$T$22,">1") -> 0
A12: COWGT0001 | B12: Cow & Gate First 400g | C12: CAN | D12: =COUNTIFS('Episode Detail'!$H$5:$H$22,$A12,'Episode Detail'!$AL$5:$AL$22,"No") -> 1 | E12: =SUMPRODUCT(('Episode Detail'!$H$5:$H$22=$A12)*('Episode Detail'!$AL$5:$AL$22="No")*'Episode Detail'!$AQ$5:$AQ$22) -> 1 | F12: =SUMIFS('Episode Detail'!$U$5:$U$22,'Episode Detail'!$H$5:$H$22,$A12,'Episode Detail'!$AL$5:$AL$22,"No") -> 36 | G12: =SUMIFS('Episode Detail'!$AB$5:$AB$22,'Episode Detail'!$H$5:$H$22,$A12,'Episode Detail'!$AP$5:$AP$22,"Open",'Episode Detail'!$AL$5:$AL$22,"No") -> 37260 | H12: =SUMIFS('Episode Detail'!$AD$5:$AD$22,'Episode Detail'!$H$5:$H$22,$A12,'Episode Detail'!$AL$5:$AL$22,"No") -> 0 | I12: =SUMIFS('Episode Detail'!$AE$5:$AE$22,'Episode Detail'!$H$5:$H$22,$A12,'Episode Detail'!$AL$5:$AL$22,"No") -> 0 | J12: =IFERROR(AVERAGEIFS('Episode Detail'!$Q$5:$Q$22,'Episode Detail'!$H$5:$H$22,$A12,'Episode Detail'!$S$5:$S$22,"Yes",'Episode Detail'!$AL$5:$AL$22,"No"),"") | K12: =COUNTIFS('Episode Detail'!$H$5:$H$22,$A12,'Episode Detail'!$T$5:$T$22,">1") -> 0
A13: COWGT0002 | B13: Cow & Gate Follow Up 400g | C13: CAN | D13: =COUNTIFS('Episode Detail'!$H$5:$H$22,$A13,'Episode Detail'!$AL$5:$AL$22,"No") -> 1 | E13: =SUMPRODUCT(('Episode Detail'!$H$5:$H$22=$A13)*('Episode Detail'!$AL$5:$AL$22="No")*'Episode Detail'!$AQ$5:$AQ$22) -> 1 | F13: =SUMIFS('Episode Detail'!$U$5:$U$22,'Episode Detail'!$H$5:$H$22,$A13,'Episode Detail'!$AL$5:$AL$22,"No") -> 1188 | G13: =SUMIFS('Episode Detail'!$AB$5:$AB$22,'Episode Detail'!$H$5:$H$22,$A13,'Episode Detail'!$AP$5:$AP$22,"Open",'Episode Detail'!$AL$5:$AL$22,"No") -> 1892531.5 | H13: =SUMIFS('Episode Detail'!$AD$5:$AD$22,'Episode Detail'!$H$5:$H$22,$A13,'Episode Detail'!$AL$5:$AL$22,"No") -> 0 | I13: =SUMIFS('Episode Detail'!$AE$5:$AE$22,'Episode Detail'!$H$5:$H$22,$A13,'Episode Detail'!$AL$5:$AL$22,"No") -> 0 | J13: =IFERROR(AVERAGEIFS('Episode Detail'!$Q$5:$Q$22,'Episode Detail'!$H$5:$H$22,$A13,'Episode Detail'!$S$5:$S$22,"Yes",'Episode Detail'!$AL$5:$AL$22,"No"),"") -> 2 | K13: =COUNTIFS('Episode Detail'!$H$5:$H$22,$A13,'Episode Detail'!$T$5:$T$22,">1") -> 0
A14: SIFTP0009 | B14: Sifa TP Emb. Unwrap. 4x10s White | C14: CASE | D14: =COUNTIFS('Episode Detail'!$H$5:$H$22,$A14,'Episode Detail'!$AL$5:$AL$22,"No") -> 0 | E14: =SUMPRODUCT(('Episode Detail'!$H$5:$H$22=$A14)*('Episode Detail'!$AL$5:$AL$22="No")*'Episode Detail'!$AQ$5:$AQ$22) -> 0 | F14: =SUMIFS('Episode Detail'!$U$5:$U$22,'Episode Detail'!$H$5:$H$22,$A14,'Episode Detail'!$AL$5:$AL$22,"No") -> 0 | G14: =SUMIFS('Episode Detail'!$AB$5:$AB$22,'Episode Detail'!$H$5:$H$22,$A14,'Episode Detail'!$AP$5:$AP$22,"Open",'Episode Detail'!$AL$5:$AL$22,"No") -> 0 | H14: =SUMIFS('Episode Detail'!$AD$5:$AD$22,'Episode Detail'!$H$5:$H$22,$A14,'Episode Detail'!$AL$5:$AL$22,"No") -> 0 | I14: =SUMIFS('Episode Detail'!$AE$5:$AE$22,'Episode Detail'!$H$5:$H$22,$A14,'Episode Detail'!$AL$5:$AL$22,"No") -> 0 | J14: =IFERROR(AVERAGEIFS('Episode Detail'!$Q$5:$Q$22,'Episode Detail'!$H$5:$H$22,$A14,'Episode Detail'!$S$5:$S$22,"Yes",'Episode Detail'!$AL$5:$AL$22,"No"),"") | K14: =COUNTIFS('Episode Detail'!$H$5:$H$22,$A14,'Episode Detail'!$T$5:$T$22,">1") -> 0
A15: FAYTP0008 | B15: Fay TP Emb. Unwrap. 4x10s White | C15: CASE | D15: =COUNTIFS('Episode Detail'!$H$5:$H$22,$A15,'Episode Detail'!$AL$5:$AL$22,"No") -> 2 | E15: =SUMPRODUCT(('Episode Detail'!$H$5:$H$22=$A15)*('Episode Detail'!$AL$5:$AL$22="No")*'Episode Detail'!$AQ$5:$AQ$22) -> 0 | F15: =SUMIFS('Episode Detail'!$U$5:$U$22,'Episode Detail'!$H$5:$H$22,$A15,'Episode Detail'!$AL$5:$AL$22,"No") -> 302 | G15: =SUMIFS('Episode Detail'!$AB$5:$AB$22,'Episode Detail'!$H$5:$H$22,$A15,'Episode Detail'!$AP$5:$AP$22,"Open",'Episode Detail'!$AL$5:$AL$22,"No") -> 0 | H15: =SUMIFS('Episode Detail'!$AD$5:$AD$22,'Episode Detail'!$H$5:$H$22,$A15,'Episode Detail'!$AL$5:$AL$22,"No") -> 59340.6 | I15: =SUMIFS('Episode Detail'!$AE$5:$AE$22,'Episode Detail'!$H$5:$H$22,$A15,'Episode Detail'!$AL$5:$AL$22,"No") -> 0 | J15: =IFERROR(AVERAGEIFS('Episode Detail'!$Q$5:$Q$22,'Episode Detail'!$H$5:$H$22,$A15,'Episode Detail'!$S$5:$S$22,"Yes",'Episode Detail'!$AL$5:$AL$22,"No"),"") -> 4 | K15: =COUNTIFS('Episode Detail'!$H$5:$H$22,$A15,'Episode Detail'!$T$5:$T$22,">1") -> 1
A16: COSTP0023 | B16: Cosy Poa TP Emb. Wrap. 4x10s White 150s | C16: CASE | D16: =COUNTIFS('Episode Detail'!$H$5:$H$22,$A16,'Episode Detail'!$AL$5:$AL$22,"No") -> 1 | E16: =SUMPRODUCT(('Episode Detail'!$H$5:$H$22=$A16)*('Episode Detail'!$AL$5:$AL$22="No")*'Episode Detail'!$AQ$5:$AQ$22) -> 1 | F16: =SUMIFS('Episode Detail'!$U$5:$U$22,'Episode Detail'!$H$5:$H$22,$A16,'Episode Detail'!$AL$5:$AL$22,"No") -> 260 | G16: =SUMIFS('Episode Detail'!$AB$5:$AB$22,'Episode Detail'!$H$5:$H$22,$A16,'Episode Detail'!$AP$5:$AP$22,"Open",'Episode Detail'!$AL$5:$AL$22,"No") -> 19500 | H16: =SUMIFS('Episode Detail'!$AD$5:$AD$22,'Episode Detail'!$H$5:$H$22,$A16,'Episode Detail'!$AL$5:$AL$22,"No") -> 0 | I16: =SUMIFS('Episode Detail'!$AE$5:$AE$22,'Episode Detail'!$H$5:$H$22,$A16,'Episode Detail'!$AL$5:$AL$22,"No") -> 19500 | J16: =IFERROR(AVERAGEIFS('Episode Detail'!$Q$5:$Q$22,'Episode Detail'!$H$5:$H$22,$A16,'Episode Detail'!$S$5:$S$22,"Yes",'Episode Detail'!$AL$5:$AL$22,"No"),"") | K16: =COUNTIFS('Episode Detail'!$H$5:$H$22,$A16,'Episode Detail'!$T$5:$T$22,">1") -> 0

Sheet By Account
A1: By account — main account rollup
A2: Parent / branch hierarchy comes from AcumaticaCustomer.parent_acumatica_id, matching the dashboard tree.
A4: Main Account | B4: Channel | C4: Episodes | D4: Branches affected | E4: Distinct orders | F4: Revenue at Risk | G4: Lost Revenue | H4: Revenue-Days Delayed | I4: Avg Days Delay | J4: Oldest open (days)
A5: Khetia Drapers Ltd | B5: Modern Trade T2 | C5: =COUNTIFS('Episode Detail'!$E$5:$E$22,$A5,'Episode Detail'!$AL$5:$AL$22,"No") -> 5 | D5: =SUMPRODUCT(('Episode Detail'!$E$5:$E$22=$A5)*('Episode Detail'!$AL$5:$AL$22="No")*'Episode Detail'!$AR$5:$AR$22) -> 2 | E5: =SUMPRODUCT(('Episode Detail'!$E$5:$E$22=$A5)*('Episode Detail'!$AL$5:$AL$22="No")*'Episode Detail'!$AQ$5:$AQ$22) -> 3 | F5: =SUMIFS('Episode Detail'!$AB$5:$AB$22,'Episode Detail'!$E$5:$E$22,$A5,'Episode Detail'!$AP$5:$AP$22,"Open",'Episode Detail'!$AL$5:$AL$22,"No") -> 168057.9 | G5: =SUMIFS('Episode Detail'!$AE$5:$AE$22,'Episode Detail'!$E$5:$E$22,$A5,'Episode Detail'!$AL$5:$AL$22,"No") -> 173555.4 | H5: =SUMIFS('Episode Detail'!$AD$5:$AD$22,'Episode Detail'!$E$5:$E$22,$A5,'Episode Detail'!$AL$5:$AL$22,"No") -> 475654 | I5: =IFERROR(AVERAGEIFS('Episode Detail'!$Q$5:$Q$22,'Episode Detail'!$E$5:$E$22,$A5,'Episode Detail'!$S$5:$S$22,"Yes",'Episode Detail'!$AL$5:$AL$22,"No"),"") -> 11.4 | J5: =IFERROR(_xlfn.MAXIFS('Episode Detail'!$Q$5:$Q$22,'Episode Detail'!$E$5:$E$22,$A5,'Episode Detail'!$AP$5:$AP$22,"Open",'Episode Detail'!$AL$5:$AL$22,"No"),"") -> 13
A6: Majid Al Futtaim Hypermarkets Ltd | B6: Modern Trade T1 | C6: =COUNTIFS('Episode Detail'!$E$5:$E$22,$A6,'Episode Detail'!$AL$5:$AL$22,"No") -> 2 | D6: =SUMPRODUCT(('Episode Detail'!$E$5:$E$22=$A6)*('Episode Detail'!$AL$5:$AL$22="No")*'Episode Detail'!$AR$5:$AR$22) -> 1 | E6: =SUMPRODUCT(('Episode Detail'!$E$5:$E$22=$A6)*('Episode Detail'!$AL$5:$AL$22="No")*'Episode Detail'!$AQ$5:$AQ$22) -> 2 | F6: =SUMIFS('Episode Detail'!$AB$5:$AB$22,'Episode Detail'!$E$5:$E$22,$A6,'Episode Detail'!$AP$5:$AP$22,"Open",'Episode Detail'!$AL$5:$AL$22,"No") -> 90705.24 | G6: =SUMIFS('Episode Detail'!$AE$5:$AE$22,'Episode Detail'!$E$5:$E$22,$A6,'Episode Detail'!$AL$5:$AL$22,"No") -> 0 | H6: =SUMIFS('Episode Detail'!$AD$5:$AD$22,'Episode Detail'!$E$5:$E$22,$A6,'Episode Detail'!$AL$5:$AL$22,"No") -> 0 | I6: =IFERROR(AVERAGEIFS('Episode Detail'!$Q$5:$Q$22,'Episode Detail'!$E$5:$E$22,$A6,'Episode Detail'!$S$5:$S$22,"Yes",'Episode Detail'!$AL$5:$AL$22,"No"),"") -> 2 | J6: =IFERROR(_xlfn.MAXIFS('Episode Detail'!$Q$5:$Q$22,'Episode Detail'!$E$5:$E$22,$A6,'Episode Detail'!$AP$5:$AP$22,"Open",'Episode Detail'!$AL$5:$AL$22,"No"),"") -> 2
A7: Quick Mart Ltd | B7: Modern Trade T1 | C7: =COUNTIFS('Episode Detail'!$E$5:$E$22,$A7,'Episode Detail'!$AL$5:$AL$22,"No") -> 3 | D7: =SUMPRODUCT(('Episode Detail'!$E$5:$E$22=$A7)*('Episode Detail'!$AL$5:$AL$22="No")*'Episode Detail'!$AR$5:$AR$22) -> 1 | E7: =SUMPRODUCT(('Episode Detail'!$E$5:$E$22=$A7)*('Episode Detail'!$AL$5:$AL$22="No")*'Episode Detail'!$AQ$5:$AQ$22) -> 3 | F7: =SUMIFS('Episode Detail'!$AB$5:$AB$22,'Episode Detail'!$E$5:$E$22,$A7,'Episode Detail'!$AP$5:$AP$22,"Open",'Episode Detail'!$AL$5:$AL$22,"No") -> 63593.16 | G7: =SUMIFS('Episode Detail'!$AE$5:$AE$22,'Episode Detail'!$E$5:$E$22,$A7,'Episode Detail'!$AL$5:$AL$22,"No") -> 63593.16 | H7: =SUMIFS('Episode Detail'!$AD$5:$AD$22,'Episode Detail'!$E$5:$E$22,$A7,'Episode Detail'!$AL$5:$AL$22,"No") -> 0 | I7: =IFERROR(AVERAGEIFS('Episode Detail'!$Q$5:$Q$22,'Episode Detail'!$E$5:$E$22,$A7,'Episode Detail'!$S$5:$S$22,"Yes",'Episode Detail'!$AL$5:$AL$22,"No"),"") -> 8.6666667 | J7: =IFERROR(_xlfn.MAXIFS('Episode Detail'!$Q$5:$Q$22,'Episode Detail'!$E$5:$E$22,$A7,'Episode Detail'!$AP$5:$AP$22,"Open",'Episode Detail'!$AL$5:$AL$22,"No"),"") -> 9
A8: Sam West Distributors LTD | B8: General Trade | C8: =COUNTIFS('Episode Detail'!$E$5:$E$22,$A8,'Episode Detail'!$AL$5:$AL$22,"No") -> 1 | D8: =SUMPRODUCT(('Episode Detail'!$E$5:$E$22=$A8)*('Episode Detail'!$AL$5:$AL$22="No")*'Episode Detail'!$AR$5:$AR$22) -> 0 | E8: =SUMPRODUCT(('Episode Detail'!$E$5:$E$22=$A8)*('Episode Detail'!$AL$5:$AL$22="No")*'Episode Detail'!$AQ$5:$AQ$22) -> 0 | F8: =SUMIFS('Episode Detail'!$AB$5:$AB$22,'Episode Detail'!$E$5:$E$22,$A8,'Episode Detail'!$AP$5:$AP$22,"Open",'Episode Detail'!$AL$5:$AL$22,"No") -> 0 | G8: =SUMIFS('Episode Detail'!$AE$5:$AE$22,'Episode Detail'!$E$5:$E$22,$A8,'Episode Detail'!$AL$5:$AL$22,"No") -> 0 | H8: =SUMIFS('Episode Detail'!$AD$5:$AD$22,'Episode Detail'!$E$5:$E$22,$A8,'Episode Detail'!$AL$5:$AL$22,"No") -> 0 | I8: =IFERROR(AVERAGEIFS('Episode Detail'!$Q$5:$Q$22,'Episode Detail'!$E$5:$E$22,$A8,'Episode Detail'!$S$5:$S$22,"Yes",'Episode Detail'!$AL$5:$AL$22,"No"),"") -> 2 | J8: =IFERROR(_xlfn.MAXIFS('Episode Detail'!$Q$5:$Q$22,'Episode Detail'!$E$5:$E$22,$A8,'Episode Detail'!$AP$5:$AP$22,"Open",'Episode Detail'!$AL$5:$AL$22,"No"),"") -> 0
A9: Stage Mattresses Ltd | B9: General Trade | C9: =COUNTIFS('Episode Detail'!$E$5:$E$22,$A9,'Episode Detail'!$AL$5:$AL$22,"No") -> 1 | D9: =SUMPRODUCT(('Episode Detail'!$E$5:$E$22=$A9)*('Episode Detail'!$AL$5:$AL$22="No")*'Episode Detail'!$AR$5:$AR$22) -> 1 | E9: =SUMPRODUCT(('Episode Detail'!$E$5:$E$22=$A9)*('Episode Detail'!$AL$5:$AL$22="No")*'Episode Detail'!$AQ$5:$AQ$22) -> 1 | F9: =SUMIFS('Episode Detail'!$AB$5:$AB$22,'Episode Detail'!$E$5:$E$22,$A9,'Episode Detail'!$AP$5:$AP$22,"Open",'Episode Detail'!$AL$5:$AL$22,"No") -> 37260 | G9: =SUMIFS('Episode Detail'!$AE$5:$AE$22,'Episode Detail'!$E$5:$E$22,$A9,'Episode Detail'!$AL$5:$AL$22,"No") -> 0 | H9: =SUMIFS('Episode Detail'!$AD$5:$AD$22,'Episode Detail'!$E$5:$E$22,$A9,'Episode Detail'!$AL$5:$AL$22,"No") -> 0 | I9: =IFERROR(AVERAGEIFS('Episode Detail'!$Q$5:$Q$22,'Episode Detail'!$E$5:$E$22,$A9,'Episode Detail'!$S$5:$S$22,"Yes",'Episode Detail'!$AL$5:$AL$22,"No"),"") | J9: =IFERROR(_xlfn.MAXIFS('Episode Detail'!$Q$5:$Q$22,'Episode Detail'!$E$5:$E$22,$A9,'Episode Detail'!$AP$5:$AP$22,"Open",'Episode Detail'!$AL$5:$AL$22,"No"),"") -> 2
A10: Goodlife Pharmacy Ltd | B10: Pharmacy | C10: =COUNTIFS('Episode Detail'!$E$5:$E$22,$A10,'Episode Detail'!$AL$5:$AL$22,"No") -> 1 | D10: =SUMPRODUCT(('Episode Detail'!$E$5:$E$22=$A10)*('Episode Detail'!$AL$5:$AL$22="No")*'Episode Detail'!$AR$5:$AR$22) -> 1 | E10: =SUMPRODUCT(('Episode Detail'!$E$5:$E$22=$A10)*('Episode Detail'!$AL$5:$AL$22="No")*'Episode Detail'!$AQ$5:$AQ$22) -> 1 | F10: =SUMIFS('Episode Detail'!$AB$5:$AB$22,'Episode Detail'!$E$5:$E$22,$A10,'Episode Detail'!$AP$5:$AP$22,"Open",'Episode Detail'!$AL$5:$AL$22,"No") -> 1892531.5 | G10: =SUMIFS('Episode Detail'!$AE$5:$AE$22,'Episode Detail'!$E$5:$E$22,$A10,'Episode Detail'!$AL$5:$AL$22,"No") -> 0 | H10: =SUMIFS('Episode Detail'!$AD$5:$AD$22,'Episode Detail'!$E$5:$E$22,$A10,'Episode Detail'!$AL$5:$AL$22,"No") -> 0 | I10: =IFERROR(AVERAGEIFS('Episode Detail'!$Q$5:$Q$22,'Episode Detail'!$E$5:$E$22,$A10,'Episode Detail'!$S$5:$S$22,"Yes",'Episode Detail'!$AL$5:$AL$22,"No"),"") -> 2 | J10: =IFERROR(_xlfn.MAXIFS('Episode Detail'!$Q$5:$Q$22,'Episode Detail'!$E$5:$E$22,$A10,'Episode Detail'!$AP$5:$AP$22,"Open",'Episode Detail'!$AL$5:$AL$22,"No"),"") -> 2
A11: Nairobi Java House Ltd | B11: Modern Trade T2 | C11: =COUNTIFS('Episode Detail'!$E$5:$E$22,$A11,'Episode Detail'!$AL$5:$AL$22,"No") -> 0 | D11: =SUMPRODUCT(('Episode Detail'!$E$5:$E$22=$A11)*('Episode Detail'!$AL$5:$AL$22="No")*'Episode Detail'!$AR$5:$AR$22) -> 0 | E11: =SUMPRODUCT(('Episode Detail'!$E$5:$E$22=$A11)*('Episode Detail'!$AL$5:$AL$22="No")*'Episode Detail'!$AQ$5:$AQ$22) -> 0 | F11: =SUMIFS('Episode Detail'!$AB$5:$AB$22,'Episode Detail'!$E$5:$E$22,$A11,'Episode Detail'!$AP$5:$AP$22,"Open",'Episode Detail'!$AL$5:$AL$22,"No") -> 0 | G11: =SUMIFS('Episode Detail'!$AE$5:$AE$22,'Episode Detail'!$E$5:$E$22,$A11,'Episode Detail'!$AL$5:$AL$22,"No") -> 0 | H11: =SUMIFS('Episode Detail'!$AD$5:$AD$22,'Episode Detail'!$E$5:$E$22,$A11,'Episode Detail'!$AL$5:$AL$22,"No") -> 0 | I11: =IFERROR(AVERAGEIFS('Episode Detail'!$Q$5:$Q$22,'Episode Detail'!$E$5:$E$22,$A11,'Episode Detail'!$S$5:$S$22,"Yes",'Episode Detail'!$AL$5:$AL$22,"No"),"") | J11: =IFERROR(_xlfn.MAXIFS('Episode Detail'!$Q$5:$Q$22,'Episode Detail'!$E$5:$E$22,$A11,'Episode Detail'!$AP$5:$AP$22,"Open",'Episode Detail'!$AL$5:$AL$22,"No"),"") -> 0
A12: Maguna's Super Stores (K) Ltd | B12: Modern Trade T2 | C12: =COUNTIFS('Episode Detail'!$E$5:$E$22,$A12,'Episode Detail'!$AL$5:$AL$22,"No") -> 2 | D12: =SUMPRODUCT(('Episode Detail'!$E$5:$E$22=$A12)*('Episode Detail'!$AL$5:$AL$22="No")*'Episode Detail'!$AR$5:$AR$22) -> 0 | E12: =SUMPRODUCT(('Episode Detail'!$E$5:$E$22=$A12)*('Episode Detail'!$AL$5:$AL$22="No")*'Episode Detail'!$AQ$5:$AQ$22) -> 0 | F12: =SUMIFS('Episode Detail'!$AB$5:$AB$22,'Episode Detail'!$E$5:$E$22,$A12,'Episode Detail'!$AP$5:$AP$22,"Open",'Episode Detail'!$AL$5:$AL$22,"No") -> 0 | G12: =SUMIFS('Episode Detail'!$AE$5:$AE$22,'Episode Detail'!$E$5:$E$22,$A12,'Episode Detail'!$AL$5:$AL$22,"No") -> 0 | H12: =SUMIFS('Episode Detail'!$AD$5:$AD$22,'Episode Detail'!$E$5:$E$22,$A12,'Episode Detail'!$AL$5:$AL$22,"No") -> 59340.6 | I12: =IFERROR(AVERAGEIFS('Episode Detail'!$Q$5:$Q$22,'Episode Detail'!$E$5:$E$22,$A12,'Episode Detail'!$S$5:$S$22,"Yes",'Episode Detail'!$AL$5:$AL$22,"No"),"") -> 4 | J12: =IFERROR(_xlfn.MAXIFS('Episode Detail'!$Q$5:$Q$22,'Episode Detail'!$E$5:$E$22,$A12,'Episode Detail'!$AP$5:$AP$22,"Open",'Episode Detail'!$AL$5:$AL$22,"No"),"") -> 0
A13: Sheal Limited | B13: (not classified) | C13: =COUNTIFS('Episode Detail'!$E$5:$E$22,$A13,'Episode Detail'!$AL$5:$AL$22,"No") -> 1 | D13: =SUMPRODUCT(('Episode Detail'!$E$5:$E$22=$A13)*('Episode Detail'!$AL$5:$AL$22="No")*'Episode Detail'!$AR$5:$AR$22) -> 1 | E13: =SUMPRODUCT(('Episode Detail'!$E$5:$E$22=$A13)*('Episode Detail'!$AL$5:$AL$22="No")*'Episode Detail'!$AQ$5:$AQ$22) -> 1 | F13: =SUMIFS('Episode Detail'!$AB$5:$AB$22,'Episode Detail'!$E$5:$E$22,$A13,'Episode Detail'!$AP$5:$AP$22,"Open",'Episode Detail'!$AL$5:$AL$22,"No") -> 2935 | G13: =SUMIFS('Episode Detail'!$AE$5:$AE$22,'Episode Detail'!$E$5:$E$22,$A13,'Episode Detail'!$AL$5:$AL$22,"No") -> 0 | H13: =SUMIFS('Episode Detail'!$AD$5:$AD$22,'Episode Detail'!$E$5:$E$22,$A13,'Episode Detail'!$AL$5:$AL$22,"No") -> 0 | I13: =IFERROR(AVERAGEIFS('Episode Detail'!$Q$5:$Q$22,'Episode Detail'!$E$5:$E$22,$A13,'Episode Detail'!$S$5:$S$22,"Yes",'Episode Detail'!$AL$5:$AL$22,"No"),"") -> 4 | J13: =IFERROR(_xlfn.MAXIFS('Episode Detail'!$Q$5:$Q$22,'Episode Detail'!$E$5:$E$22,$A13,'Episode Detail'!$AP$5:$AP$22,"Open",'Episode Detail'!$AL$5:$AL$22,"No"),"") -> 4
A14: Bluewave Multisupplies Ltd | B14: (not classified) | C14: =COUNTIFS('Episode Detail'!$E$5:$E$22,$A14,'Episode Detail'!$AL$5:$AL$22,"No") -> 1 | D14: =SUMPRODUCT(('Episode Detail'!$E$5:$E$22=$A14)*('Episode Detail'!$AL$5:$AL$22="No")*'Episode Detail'!$AR$5:$AR$22) -> 1 | E14: =SUMPRODUCT(('Episode Detail'!$E$5:$E$22=$A14)*('Episode Detail'!$AL$5:$AL$22="No")*'Episode Detail'!$AQ$5:$AQ$22) -> 1 | F14: =SUMIFS('Episode Detail'!$AB$5:$AB$22,'Episode Detail'!$E$5:$E$22,$A14,'Episode Detail'!$AP$5:$AP$22,"Open",'Episode Detail'!$AL$5:$AL$22,"No") -> 19500 | G14: =SUMIFS('Episode Detail'!$AE$5:$AE$22,'Episode Detail'!$E$5:$E$22,$A14,'Episode Detail'!$AL$5:$AL$22,"No") -> 19500 | H14: =SUMIFS('Episode Detail'!$AD$5:$AD$22,'Episode Detail'!$E$5:$E$22,$A14,'Episode Detail'!$AL$5:$AL$22,"No") -> 0 | I14: =IFERROR(AVERAGEIFS('Episode Detail'!$Q$5:$Q$22,'Episode Detail'!$E$5:$E$22,$A14,'Episode Detail'!$S$5:$S$22,"Yes",'Episode Detail'!$AL$5:$AL$22,"No"),"") | J14: =IFERROR(_xlfn.MAXIFS('Episode Detail'!$Q$5:$Q$22,'Episode Detail'!$E$5:$E$22,$A14,'Episode Detail'!$AP$5:$AP$22,"Open",'Episode Detail'!$AL$5:$AL$22,"No"),"") -> 15

Sheet Acumatica Bridge
A1: Reconciliation to the Acumatica Sales Orders screen
A2: Filter: Order Type = SO, Status = Back Order, Created On 01–23 Jul 2026, snapshot 23/07/2026 17:41 EAT. Gate: unexplained variance must be under 0.5%.
A4: STEP 1 — Acumatica raw export
A5: Line | B5: Orders | C5: Value (KES) | D5: Note
A6: Acumatica raw export rows | B6: 84 | C6: 8436411 | D6: Screen repeats an order once per shipment
A7: less duplicate rows (one per shipment) | B7: -10 | C7: 0 | D7: SO361051 x4, SO365985 x3, SO366417 x2 ...
A8: → Acumatica DISTINCT orders | B8: 74 | C8: 8436411 | D8: This is the number to quote
A9: Acumatica "Unbilled Order Total" | C9: 3861891 | D9: Finance view of open value
A11: STEP 2 — Bridge to dashboard Revenue at Risk
A12: Bridge line | B12: Value (KES) | C12: Why it differs
A13: Acumatica Unbilled Order Total | B13: 3861891 | C13: Starting point — the ERP figure
A14: less shipped, not yet invoiced | B14: -284500 | C14: Unbilled includes goods already despatched
A15: less zero-value / free promotional lines | B15: -12400 | C15: e.g. SO366417 read Unbilled 0 while still Back Order
A16: less non-SO order types (PP) | B16: -156300 | C16: Screen filter said SO but export leaked 12 PP rows
A17: less rejected / on-hold headers | B17: -98200 | C17: Credit blocks — never reached the warehouse
A18: plus short lines on "Shipping" headers | B18: 412800 | C18: Line is short although the header has moved on
A19: plus qty picked but not shipped (committed) | B19: 0 | C19: Held OPEN by design — customer still has nothing
A20: Sample-data adjustment ** TEMPLATE ONLY — DELETE IN PRODUCTION ** | B20: =Summary!$B$8-SUM(B13:B19) -> -1448708.2 | C20: Exists only so this template demonstrates a PASSING gate. Real bridge lines must be derived from the ledger.
A21: → Dashboard Revenue at Risk (expected) | B21: =SUM(B13:B20) -> 2274582.8
A22: Dashboard Revenue at Risk (actual, from Summary) | B22: =Summary!$B$8 -> 2274582.8
A23: Unexplained variance | B23: =B22-B21 -> 0 | C23: =IFERROR(ABS(B23)/B13,"") -> 0
A24: Reconciled? | B24: =IF(IFERROR(ABS(B23)/B13,1)<=0.005,"PASS","FAIL — raise AcumaticaReconciliationResult, severity high") -> PASS
A26: The bridge amounts above are ILLUSTRATIVE. ReconcileWithAcumaticaJob must compute each line from the ledger, not by hand.
