Workbook

Sheet Read Me
A1: Acumatica Back Order Report — how to read it
A2: Source: Sales_Orders_202607231.xlsx (Back Orders, created 01–23 Jul 2026) and Sales_Orders_202607232.xlsx (all orders created 23 Jul 2026). Snapshot taken 23/07/2026 17:41.
A4: Field / topic | B4: Explanation
A5: What "Back Order" means in Acumatica | B5: Status = Back Order means at least one line on the order still has Open Qty that could not be allocated from available stock. It is a LIVE status, not a history flag — the moment the last line ships, the order leaves this status and disappears from this report.
A6: Why you cannot see "resolved" here | B6: Because the status is live, every order in this file is STILL unresolved as at 23/07 17:41. Orders that went on back order earlier in July and have since been filled are already gone from the file — they are not marked "resolved", they are simply absent. To measure resolution you need either (a) a saved daily snapshot of this same report to diff day-on-day, or (b) the line-level Open Qty report (see Data Gaps below).
A7: Line Total | B7: Full value of the order as entered (KES, ex-VAT).
A8: Unbilled Order Total | B8: Order value not yet invoiced. Used here as the proxy for OPEN VALUE — what the customer ordered and has not yet been billed for. Caveat: it includes goods already shipped but not yet invoiced, so it slightly overstates true unshipped value.
A9: Fulfilled % (calculated) | B9: (Line Total - Unbilled) / Line Total. A VALUE measure, not a quantity measure. SO366417 (Elburgon Bidii) shows 100% yet is still Back Order — the residual open lines are zero-value / free items. Always confirm against line-level Open Qty before telling a customer an order is complete.
A10: Shipments | B10: Count of distinct shipment numbers raised against the order. 0 = nothing has left the warehouse at all. 2+ = the order is being filled in drips as stock trickles in.
A11: Age (days) | B11: Snapshot date (23/07) minus Order Date. Anything past 7 days on a Modern Trade order is a service failure — most MT customers cancel or penalise beyond that.
A12: Order Type PP vs SO | B12: The screenshot filter was Order Type = SO (72 records). The export also picked up 12 PP (Professional/Project) rows, so this file has 84 rows / 74 unique orders. Duplicate order numbers = one row per shipment, so ALWAYS de-duplicate on Order Nbr. before summing value or you will double-count.
A13: DATA GAPS — what to export next
A14: 1. Line-level open quantity | B14: Sales Orders > Open Sales Order Details (or the SO Line generic inquiry) filtered to Open Qty > 0. Gives Inventory ID, Ordered Qty, Qty on Shipments, Open Qty per SKU. Without this you cannot say WHICH items are short — only which customers are waiting.
A15: 2. Inventory availability | B15: Inventory > Inventory Allocation Details / IN Inventory Balance by warehouse (FGS, TPFGS). Gives On Hand, Available, Available for Shipping, Allocated per Inventory ID. Screenshot 2 shows the field you need — item SIFTP0015 reads On Hand 100 CASE but Available -87 CASE, i.e. oversold by 87 cases.
A16: 3. Inbound supply | B16: Purchase Orders / Production Orders with expected receipt dates per Inventory ID. This is the only place the real REASON for the shortage lives (late import, mill downtime, short shipment, MOQ timing).
A17: 4. Daily snapshot | B17: Save this same export every morning to a dated folder. Diffing yesterday vs today is what produces a true "resolved / still open / newly backordered" report.

Sheet Order Detail
A1: Open back orders — order level (74 orders)
A2: Snapshot date: | B2: 46226
A4: Order Nbr. | B4: Type | C4: Order Date | D4: Age (days) | E4: Customer Name | F4: Main Account | G4: Customer Group | H4: Category | I4: Ordered Qty | J4: Line Total (KES) | K4: Open / Unbilled (KES) | L4: Fulfilled % | M4: Shipments | N4: Fill stage | O4: Priority flag
A5: SO367174 | B5: SO | C5: 46226 | D5: =$B$2-C5 -> 0 | E5: Goodlife Pharmacy Ltd | F5: Goodlife Pharmacy Ltd | G5: Consumer sales | H5: Pharmacy | I5: 1188 | J5: 1892526.2 | K5: 1892526.2 | L5: =IFERROR((J5-K5)/J5,"") -> 0 | M5: 0 | N5: =IF(M5=0,"Not started",IF(L5>=0.9999,"Value complete","Partial")) -> Not started | O5: =IF(AND(D5>7,K5>25000),"ESCALATE",IF(K5>100000,"High value",IF(D5>7,"Aged","Monitor"))) -> High value
A6: SO363506 | B6: SO | C6: 46213 | D6: =$B$2-C6 -> 13 | E6: Khetia Drapers Ltd - Plus | F6: Khetia Drapers Ltd | G6: Consumer sales | H6: Modern Trade T2 | I6: 1356 | J6: 193337.3 | K6: 94472.29 | L6: =IFERROR((J6-K6)/J6,"") -> 0.51136025 | M6: 1 | N6: =IF(M6=0,"Not started",IF(L6>=0.9999,"Value complete","Partial")) -> Partial | O6: =IF(AND(D6>7,K6>25000),"ESCALATE",IF(K6>100000,"High value",IF(D6>7,"Aged","Monitor"))) -> ESCALATE
A7: SO365985 | B7: SO | C7: 46223 | D7: =$B$2-C7 -> 3 | E7: Sam West Distributors LTD | F7: Sam West Distributors LTD | G7: Consumer sales | H7: General Trade | I7: 980 | J7: 842970.73 | K7: 92770.72 | L7: =IFERROR((J7-K7)/J7,"") -> 0.88994788 | M7: 3 | N7: =IF(M7=0,"Not started",IF(L7>=0.9999,"Value complete","Partial")) -> Partial | O7: =IF(AND(D7>7,K7>25000),"ESCALATE",IF(K7>100000,"High value",IF(D7>7,"Aged","Monitor"))) -> Monitor
A8: SO363491 | B8: SO | C8: 46213 | D8: =$B$2-C8 -> 13 | E8: Khetia Drapers Ltd - Gigamart | F8: Khetia Drapers Ltd | G8: Consumer sales | H8: Modern Trade T2 | I8: 1086 | J8: 157062.68 | K8: 85936.8 | L8: =IFERROR((J8-K8)/J8,"") -> 0.45285029 | M8: 1 | N8: =IF(M8=0,"Not started",IF(L8>=0.9999,"Value complete","Partial")) -> Partial | O8: =IF(AND(D8>7,K8>25000),"ESCALATE",IF(K8>100000,"High value",IF(D8>7,"Aged","Monitor"))) -> ESCALATE
A9: SO367069 | B9: PP | C9: 46226 | D9: =$B$2-C9 -> 0 | E9: Cash Sale A/C - Professional Sales | F9: Cash Sale A/C - Professional Sales | G9: Kim-Fay Professional | H9: (not classified) | I9: 32 | J9: 85655.17 | K9: 85655.17 | L9: =IFERROR((J9-K9)/J9,"") -> 0 | M9: 0 | N9: =IF(M9=0,"Not started",IF(L9>=0.9999,"Value complete","Partial")) -> Not started | O9: =IF(AND(D9>7,K9>25000),"ESCALATE",IF(K9>100000,"High value",IF(D9>7,"Aged","Monitor"))) -> Monitor
A10: SO363495 | B10: SO | C10: 46213 | D10: =$B$2-C10 -> 13 | E10: Khetia Drapers Ltd - Eldoret CBD | F10: Khetia Drapers Ltd | G10: Consumer sales | H10: Modern Trade T2 | I10: 1128 | J10: 151791.69 | K10: 72864.28 | L10: =IFERROR((J10-K10)/J10,"") -> 0.51997188 | M10: 1 | N10: =IF(M10=0,"Not started",IF(L10>=0.9999,"Value complete","Partial")) -> Partial | O10: =IF(AND(D10>7,K10>25000),"ESCALATE",IF(K10>100000,"High value",IF(D10>7,"Aged","Monitor"))) -> ESCALATE
A11: SO363507 | B11: SO | C11: 46213 | D11: =$B$2-C11 -> 13 | E11: Khetia Drapers Ltd - Kakamega Poa | F11: Khetia Drapers Ltd | G11: Consumer sales | H11: Modern Trade T2 | I11: 876 | J11: 123528.38 | K11: 72472.52 | L11: =IFERROR((J11-K11)/J11,"") -> 0.4133128 | M11: 1 | N11: =IF(M11=0,"Not started",IF(L11>=0.9999,"Value complete","Partial")) -> Partial | O11: =IF(AND(D11>7,K11>25000),"ESCALATE",IF(K11>100000,"High value",IF(D11>7,"Aged","Monitor"))) -> ESCALATE
A12: SO363603 | B12: SO | C12: 46213 | D12: =$B$2-C12 -> 13 | E12: Khetia Drapers Ltd - Thika | F12: Khetia Drapers Ltd | G12: Consumer sales | H12: Modern Trade T2 | I12: 965 | J12: 148325.31 | K12: 70744.52 | L12: =IFERROR((J12-K12)/J12,"") -> 0.52304485 | M12: 1 | N12: =IF(M12=0,"Not started",IF(L12>=0.9999,"Value complete","Partial")) -> Partial | O12: =IF(AND(D12>7,K12>25000),"ESCALATE",IF(K12>100000,"High value",IF(D12>7,"Aged","Monitor"))) -> ESCALATE
A13: SO363504 | B13: SO | C13: 46213 | D13: =$B$2-C13 -> 13 | E13: Khetia Drapers Ltd - Cross Roads | F13: Khetia Drapers Ltd | G13: Consumer sales | H13: Modern Trade T2 | I13: 933 | J13: 142850.14 | K13: 69457.45 | L13: =IFERROR((J13-K13)/J13,"") -> 0.51377402 | M13: 1 | N13: =IF(M13=0,"Not started",IF(L13>=0.9999,"Value complete","Partial")) -> Partial | O13: =IF(AND(D13>7,K13>25000),"ESCALATE",IF(K13>100000,"High value",IF(D13>7,"Aged","Monitor"))) -> ESCALATE
A14: SO363621 | B14: SO | C14: 46213 | D14: =$B$2-C14 -> 13 | E14: Khetia Drapers Ltd - Mirema | F14: Khetia Drapers Ltd | G14: Consumer sales | H14: Modern Trade T2 | I14: 528 | J14: 104301.95 | K14: 68926.51 | L14: =IFERROR((J14-K14)/J14,"") -> 0.33916375 | M14: 1 | N14: =IF(M14=0,"Not started",IF(L14>=0.9999,"Value complete","Partial")) -> Partial | O14: =IF(AND(D14>7,K14>25000),"ESCALATE",IF(K14>100000,"High value",IF(D14>7,"Aged","Monitor"))) -> ESCALATE
A15: SO367051 | B15: SO | C15: 46226 | D15: =$B$2-C15 -> 0 | E15: Stage Mattresses Ltd | F15: Stage Mattresses Ltd | G15: Consumer sales | H15: General Trade | I15: 1793 | J15: 1444436.4 | K15: 62100 | L15: =IFERROR((J15-K15)/J15,"") -> 0.95700745 | M15: 2 | N15: =IF(M15=0,"Not started",IF(L15>=0.9999,"Value complete","Partial")) -> Partial | O15: =IF(AND(D15>7,K15>25000),"ESCALATE",IF(K15>100000,"High value",IF(D15>7,"Aged","Monitor"))) -> Monitor
A16: SO367035 | B16: SO | C16: 46226 | D16: =$B$2-C16 -> 0 | E16: Majid Al Futtaim Hypermarkets Ltd - Business Bay Square | F16: Majid Al Futtaim Hypermarkets Ltd | G16: Consumer sales | H16: Modern Trade T1 | I16: 24 | J16: 61020.62 | K16: 61020.62 | L16: =IFERROR((J16-K16)/J16,"") -> 0 | M16: 0 | N16: =IF(M16=0,"Not started",IF(L16>=0.9999,"Value complete","Partial")) -> Not started | O16: =IF(AND(D16>7,K16>25000),"ESCALATE",IF(K16>100000,"High value",IF(D16>7,"Aged","Monitor"))) -> Monitor
... A78: SO366417 | B78: SO | C78: 46224 | D78: =$B$2-C78 -> 2 | E78: Elburgon Bidii Store Ltd | F78: Elburgon Bidii Store Ltd | G78: Consumer sales | H78: General Trade | I78: 235 | J78: 186122.54 | K78: 0 | L78: =IFERROR((J78-K78)/J78,"") -> 1 | M78: 2 | N78: =IF(M78=0,"Not started",IF(L78>=0.9999,"Value complete","Partial")) -> Value complete | O78: =IF(AND(D78>7,K78>25000),"ESCALATE",IF(K78>100000,"High value",IF(D78>7,"Aged","Monitor"))) -> Monitor
A79: TOTAL | I79: =SUM(I5:I78) -> 20366 | J79: =SUM(J5:J78) -> 8436410.5 | K79: =SUM(K5:K78) -> 3861890.5 | L79: =IFERROR((J79-K79)/J79,"") -> 0.54223535

Sheet Summary
A1: Back order position — 01 to 23 July 2026
A2: All figures pull from Order Detail.
A5: Metric | B5: Value
A6: Open back orders (unique) | B6: =COUNTA('Order Detail'!$A$5:$A$78) -> 74
A7: Total order value on back order (KES) | B7: =SUM('Order Detail'!$J$5:$J$78) -> 8436410.5
A8: Open / unbilled value (KES) | B8: =SUM('Order Detail'!$K$5:$K$78) -> 3861890.5
A9: Value already fulfilled (KES) | B9: =B7-B8 -> 4574520
A10: Overall value fill rate | B10: =IFERROR(B9/B7,"") -> 0.54223535
A11: Orders with ZERO shipments raised | B11: =COUNTIF('Order Detail'!$M$5:$M$78,0) -> 15
A12: Open value on those orders (KES) | B12: =SUMIF('Order Detail'!$M$5:$M$78,0,'Order Detail'!$K$5:$K$78) -> 2267947.8
A13: Orders older than 7 days | B13: =COUNTIF('Order Detail'!$D$5:$D$78,">7") -> 41
A14: Open value older than 7 days (KES) | B14: =SUMIF('Order Detail'!$D$5:$D$78,">7",'Order Detail'!$K$5:$K$78) -> 1281680.7
A15: Flagged ESCALATE | B15: =COUNTIF('Order Detail'!$O$5:$O$78,"ESCALATE") -> 23
A18: By category
A19: Category | B19: Orders | C19: Order value (KES) | D19: Open value (KES) | E19: Fill rate
A20: Modern Trade T2 | B20: =COUNTIF('Order Detail'!$H$5:$H$78,$A20) -> 32 | C20: =SUMIF('Order Detail'!$H$5:$H$78,$A20,'Order Detail'!$J$5:$J$78) -> 2875397.1 | D20: =SUMIF('Order Detail'!$H$5:$H$78,$A20,'Order Detail'!$K$5:$K$78) -> 1196456.7 | E20: =IFERROR((C20-D20)/C20,"") -> 0.58389862
A21: (not classified) | B21: =COUNTIF('Order Detail'!$H$5:$H$78,$A21) -> 17 | C21: =SUMIF('Order Detail'!$H$5:$H$78,$A21,'Order Detail'!$J$5:$J$78) -> 756792.37 | D21: =SUMIF('Order Detail'!$H$5:$H$78,$A21,'Order Detail'!$K$5:$K$78) -> 244762.14 | E21: =IFERROR((C21-D21)/C21,"") -> 0.67657954
A22: Modern Trade T1 | B22: =COUNTIF('Order Detail'!$H$5:$H$78,$A22) -> 10 | C22: =SUMIF('Order Detail'!$H$5:$H$78,$A22,'Order Detail'!$J$5:$J$78) -> 286527.41 | D22: =SUMIF('Order Detail'!$H$5:$H$78,$A22,'Order Detail'!$K$5:$K$78) -> 273213.62 | E22: =IFERROR((C22-D22)/C22,"") -> 0.046466026
A23: Pharmacy | B23: =COUNTIF('Order Detail'!$H$5:$H$78,$A23) -> 6 | C23: =SUMIF('Order Detail'!$H$5:$H$78,$A23,'Order Detail'!$J$5:$J$78) -> 2033740.8 | D23: =SUMIF('Order Detail'!$H$5:$H$78,$A23,'Order Detail'!$K$5:$K$78) -> 1988880.5 | E23: =IFERROR((C23-D23)/C23,"") -> 0.022058052
A24: Direct To Consumer (Cash Sale) | B24: =COUNTIF('Order Detail'!$H$5:$H$78,$A24) -> 6 | C24: =SUMIF('Order Detail'!$H$5:$H$78,$A24,'Order Detail'!$J$5:$J$78) -> 10423.13 | D24: =SUMIF('Order Detail'!$H$5:$H$78,$A24,'Order Detail'!$K$5:$K$78) -> 3706.86 | E24: =IFERROR((C24-D24)/C24,"") -> 0.64436211
A25: General Trade | B25: =COUNTIF('Order Detail'!$H$5:$H$78,$A25) -> 3 | C25: =SUMIF('Order Detail'!$H$5:$H$78,$A25,'Order Detail'!$J$5:$J$78) -> 2473529.6 | D25: =SUMIF('Order Detail'!$H$5:$H$78,$A25,'Order Detail'!$K$5:$K$78) -> 154870.72 | E25: =IFERROR((C25-D25)/C25,"") -> 0.93738878
A26: Total | B26: =SUM(B20:B25) -> 74 | C26: =SUM(C20:C25) -> 8436410.5 | D26: =SUM(D20:D25) -> 3861890.5 | E26: =IFERROR((C26-D26)/C26,"") -> 0.54223535
A29: By age bucket
A30: Age bucket | B30: Lower | C30: Upper | D30: Orders | E30: Open value (KES)
A31: Same day | B31: 0 | C31: 0 | D31: =COUNTIFS('Order Detail'!$D$5:$D$78,">="&$B31,'Order Detail'!$D$5:$D$78,"<="&$C31) -> 10 | E31: =SUMIFS('Order Detail'!$K$5:$K$78,'Order Detail'!$D$5:$D$78,">="&$B31,'Order Detail'!$D$5:$D$78,"<="&$C31) -> 2208360
A32: 1-3 days | B32: 1 | C32: 3 | D32: =COUNTIFS('Order Detail'!$D$5:$D$78,">="&$B32,'Order Detail'!$D$5:$D$78,"<="&$C32) -> 14 | E32: =SUMIFS('Order Detail'!$K$5:$K$78,'Order Detail'!$D$5:$D$78,">="&$B32,'Order Detail'!$D$5:$D$78,"<="&$C32) -> 266825.29
A33: 4-7 days | B33: 4 | C33: 7 | D33: =COUNTIFS('Order Detail'!$D$5:$D$78,">="&$B33,'Order Detail'!$D$5:$D$78,"<="&$C33) -> 9 | E33: =SUMIFS('Order Detail'!$K$5:$K$78,'Order Detail'!$D$5:$D$78,">="&$B33,'Order Detail'!$D$5:$D$78,"<="&$C33) -> 105024.53
A34: 8-14 days | B34: 8 | C34: 14 | D34: =COUNTIFS('Order Detail'!$D$5:$D$78,">="&$B34,'Order Detail'!$D$5:$D$78,"<="&$C34) -> 35 | E34: =SUMIFS('Order Detail'!$K$5:$K$78,'Order Detail'!$D$5:$D$78,">="&$B34,'Order Detail'!$D$5:$D$78,"<="&$C34) -> 1230059.9
A35: 15+ days | B35: 15 | C35: 999 | D35: =COUNTIFS('Order Detail'!$D$5:$D$78,">="&$B35,'Order Detail'!$D$5:$D$78,"<="&$C35) -> 6 | E35: =SUMIFS('Order Detail'!$K$5:$K$78,'Order Detail'!$D$5:$D$78,">="&$B35,'Order Detail'!$D$5:$D$78,"<="&$C35) -> 51620.73
A36: Total | D36: =SUM(D31:D35) -> 74 | E36: =SUM(E31:E35) -> 3861890.5

Sheet By Account
A1: Where the back order sits — by trading account
A2: Concentration matters more than the total: a few accounts carry most of the exposure.
A4: Main account | B4: Orders | C4: Order value (KES) | D4: Open value (KES) | E4: Fill rate | F4: Oldest order (days) | G4: Orders not started
A5: Khetia Drapers Ltd | B5: =COUNTIF('Order Detail'!$F$5:$F$78,$A5) -> 21 | C5: =SUMIF('Order Detail'!$F$5:$F$78,$A5,'Order Detail'!$J$5:$J$78) -> 2110591.9 | D5: =SUMIF('Order Detail'!$F$5:$F$78,$A5,'Order Detail'!$K$5:$K$78) -> 1055252.1 | E5: =IFERROR((C5-D5)/C5,"") -> 0.50002075 | F5: =SUMPRODUCT(MAX(('Order Detail'!$F$5:$F$78=$A5)*'Order Detail'!$D$5:$D$78)) -> 13 | G5: =COUNTIFS('Order Detail'!$F$5:$F$78,$A5,'Order Detail'!$M$5:$M$78,0) -> 0
A6: Maguna's Super Stores (K) Ltd | B6: =COUNTIF('Order Detail'!$F$5:$F$78,$A6) -> 10 | C6: =SUMIF('Order Detail'!$F$5:$F$78,$A6,'Order Detail'!$J$5:$J$78) -> 590994.73 | D6: =SUMIF('Order Detail'!$F$5:$F$78,$A6,'Order Detail'!$K$5:$K$78) -> 124369.4 | E6: =IFERROR((C6-D6)/C6,"") -> 0.78955921 | F6: =SUMPRODUCT(MAX(('Order Detail'!$F$5:$F$78=$A6)*'Order Detail'!$D$5:$D$78)) -> 13 | G6: =COUNTIFS('Order Detail'!$F$5:$F$78,$A6,'Order Detail'!$M$5:$M$78,0) -> 0
A7: Cash Sale Staff | B7: =COUNTIF('Order Detail'!$F$5:$F$78,$A7) -> 6 | C7: =SUMIF('Order Detail'!$F$5:$F$78,$A7,'Order Detail'!$J$5:$J$78) -> 10423.13 | D7: =SUMIF('Order Detail'!$F$5:$F$78,$A7,'Order Detail'!$K$5:$K$78) -> 3706.86 | E7: =IFERROR((C7-D7)/C7,"") -> 0.64436211 | F7: =SUMPRODUCT(MAX(('Order Detail'!$F$5:$F$78=$A7)*'Order Detail'!$D$5:$D$78)) -> 15 | G7: =COUNTIFS('Order Detail'!$F$5:$F$78,$A7,'Order Detail'!$M$5:$M$78,0) -> 0
A8: Majid Al Futtaim Hypermarkets Ltd | B8: =COUNTIF('Order Detail'!$F$5:$F$78,$A8) -> 5 | C8: =SUMIF('Order Detail'!$F$5:$F$78,$A8,'Order Detail'!$J$5:$J$78) -> 151725.72 | D8: =SUMIF('Order Detail'!$F$5:$F$78,$A8,'Order Detail'!$K$5:$K$78) -> 151725.72 | E8: =IFERROR((C8-D8)/C8,"") -> 0 | F8: =SUMPRODUCT(MAX(('Order Detail'!$F$5:$F$78=$A8)*'Order Detail'!$D$5:$D$78)) -> 3 | G8: =COUNTIFS('Order Detail'!$F$5:$F$78,$A8,'Order Detail'!$M$5:$M$78,0) -> 5
A9: Quick Mart Ltd | B9: =COUNTIF('Order Detail'!$F$5:$F$78,$A9) -> 5 | C9: =SUMIF('Order Detail'!$F$5:$F$78,$A9,'Order Detail'!$J$5:$J$78) -> 134801.69 | D9: =SUMIF('Order Detail'!$F$5:$F$78,$A9,'Order Detail'!$K$5:$K$78) -> 121487.9 | E9: =IFERROR((C9-D9)/C9,"") -> 0.09876575 | F9: =SUMPRODUCT(MAX(('Order Detail'!$F$5:$F$78=$A9)*'Order Detail'!$D$5:$D$78)) -> 8 | G9: =COUNTIFS('Order Detail'!$F$5:$F$78,$A9,'Order Detail'!$M$5:$M$78,0) -> 4
A10: Cash Sale A/C - Aptamil | B10: =COUNTIF('Order Detail'!$F$5:$F$78,$A10) -> 2 | C10: =SUMIF('Order Detail'!$F$5:$F$78,$A10,'Order Detail'!$J$5:$J$78) -> 12762.25 | D10: =SUMIF('Order Detail'!$F$5:$F$78,$A10,'Order Detail'!$K$5:$K$78) -> 1037.76 | E10: =IFERROR((C10-D10)/C10,"") -> 0.91868518 | F10: =SUMPRODUCT(MAX(('Order Detail'!$F$5:$F$78=$A10)*'Order Detail'!$D$5:$D$78)) -> 17 | G10: =COUNTIFS('Order Detail'!$F$5:$F$78,$A10,'Order Detail'!$M$5:$M$78,0) -> 0
A11: Bluewave Multisupplies Ltd | B11: =COUNTIF('Order Detail'!$F$5:$F$78,$A11) -> 2 | C11: =SUMIF('Order Detail'!$F$5:$F$78,$A11,'Order Detail'!$J$5:$J$78) -> 102408.71 | D11: =SUMIF('Order Detail'!$F$5:$F$78,$A11,'Order Detail'!$K$5:$K$78) -> 44850 | E11: =IFERROR((C11-D11)/C11,"") -> 0.56204897 | F11: =SUMPRODUCT(MAX(('Order Detail'!$F$5:$F$78=$A11)*'Order Detail'!$D$5:$D$78)) -> 21 | G11: =COUNTIFS('Order Detail'!$F$5:$F$78,$A11,'Order Detail'!$M$5:$M$78,0) -> 0
A12: Wells Farmart Limited | B12: =COUNTIF('Order Detail'!$F$5:$F$78,$A12) -> 2 | C12: =SUMIF('Order Detail'!$F$5:$F$78,$A12,'Order Detail'!$J$5:$J$78) -> 138355.14 | D12: =SUMIF('Order Detail'!$F$5:$F$78,$A12,'Order Detail'!$K$5:$K$78) -> 9525 | E12: =IFERROR((C12-D12)/C12,"") -> 0.93115543 | F12: =SUMPRODUCT(MAX(('Order Detail'!$F$5:$F$78=$A12)*'Order Detail'!$D$5:$D$78)) -> 16 | G12: =COUNTIFS('Order Detail'!$F$5:$F$78,$A12,'Order Detail'!$M$5:$M$78,0) -> 0
A13: Eka Hotel Ltd-Eldoret | B13: =COUNTIF('Order Detail'!$F$5:$F$78,$A13) -> 1 | C13: =SUMIF('Order Detail'!$F$5:$F$78,$A13,'Order Detail'!$J$5:$J$78) -> 11120.8 | D13: =SUMIF('Order Detail'!$F$5:$F$78,$A13,'Order Detail'!$K$5:$K$78) -> 4655.28 | E13: =IFERROR((C13-D13)/C13,"") -> 0.58138983 | F13: =SUMPRODUCT(MAX(('Order Detail'!$F$5:$F$78=$A13)*'Order Detail'!$D$5:$D$78)) -> 6 | G13: =COUNTIFS('Order Detail'!$F$5:$F$78,$A13,'Order Detail'!$M$5:$M$78,0) -> 0
A14: Creative Consolidated Systems Ltd | B14: =COUNTIF('Order Detail'!$F$5:$F$78,$A14) -> 1 | C14: =SUMIF('Order Detail'!$F$5:$F$78,$A14,'Order Detail'!$J$5:$J$78) -> 63000 | D14: =SUMIF('Order Detail'!$F$5:$F$78,$A14,'Order Detail'!$K$5:$K$78) -> 10500 | E14: =IFERROR((C14-D14)/C14,"") -> 0.83333333 | F14: =SUMPRODUCT(MAX(('Order Detail'!$F$5:$F$78=$A14)*'Order Detail'!$D$5:$D$78)) -> 1 | G14: =COUNTIFS('Order Detail'!$F$5:$F$78,$A14,'Order Detail'!$M$5:$M$78,0) -> 0
A15: East African Chains Ltd | B15: =COUNTIF('Order Detail'!$F$5:$F$78,$A15) -> 1 | C15: =SUMIF('Order Detail'!$F$5:$F$78,$A15,'Order Detail'!$J$5:$J$78) -> 1826.77 | D15: =SUMIF('Order Detail'!$F$5:$F$78,$A15,'Order Detail'!$K$5:$K$78) -> 1826.77 | E15: =IFERROR((C15-D15)/C15,"") -> 0 | F15: =SUMPRODUCT(MAX(('Order Detail'!$F$5:$F$78=$A15)*'Order Detail'!$D$5:$D$78)) -> 0 | G15: =COUNTIFS('Order Detail'!$F$5:$F$78,$A15,'Order Detail'!$M$5:$M$78,0) -> 1
A16: Ava Apotheke Ltd | B16: =COUNTIF('Order Detail'!$F$5:$F$78,$A16) -> 1 | C16: =SUMIF('Order Detail'!$F$5:$F$78,$A16,'Order Detail'!$J$5:$J$78) -> 44871.21 | D16: =SUMIF('Order Detail'!$F$5:$F$78,$A16,'Order Detail'!$K$5:$K$78) -> 44871.21 | E16: =IFERROR((C16-D16)/C16,"") -> 0 | F16: =SUMPRODUCT(MAX(('Order Detail'!$F$5:$F$78=$A16)*'Order Detail'!$D$5:$D$78)) -> 0 | G16: =COUNTIFS('Order Detail'!$F$5:$F$78,$A16,'Order Detail'!$M$5:$M$78,0) -> 1
... A33: The Address Management Company Limited | B33: =COUNTIF('Order Detail'!$F$5:$F$78,$A33) -> 1 | C33: =SUMIF('Order Detail'!$F$5:$F$78,$A33,'Order Detail'!$J$5:$J$78) -> 2.6 | D33: =SUMIF('Order Detail'!$F$5:$F$78,$A33,'Order Detail'!$K$5:$K$78) -> 2.6 | E33: =IFERROR((C33-D33)/C33,"") -> 0 | F33: =SUMPRODUCT(MAX(('Order Detail'!$F$5:$F$78=$A33)*'Order Detail'!$D$5:$D$78)) -> 2 | G33: =COUNTIFS('Order Detail'!$F$5:$F$78,$A33,'Order Detail'!$M$5:$M$78,0) -> 1
A34: Total | B34: =SUM(B5:B33) -> 74 | C34: =SUM(C5:C33) -> 8436410.5 | D34: =SUM(D5:D33) -> 3861890.5 | E34: =IFERROR((C34-D34)/C34,"") -> 0.54223535 | G34: =SUM(G5:G33) -> 15

Sheet 23 Jul Snapshot
A1: All orders created 23 July 2026 — status mix
A2: Second file. Shows what proportion of one day's intake fell into back order, and what was blocked for credit rather than stock.
A4: Status | B4: Orders | C4: % of orders | D4: Value (KES) | E4: % of value
A5: Shipping | B5: 238 | C5: =IFERROR(B5/$B$12,"") -> 0.81786942 | D5: 30811443 | E5: =IFERROR(D5/$D$12,"") -> 0.6708953
A6: Completed | B6: 24 | C6: =IFERROR(B6/$B$12,"") -> 0.082474227 | D6: 9647807.6 | E6: =IFERROR(D6/$D$12,"") -> 0.21007353
A7: Back Order | B7: 8 | C7: =IFERROR(B7/$B$12,"") -> 0.027491409 | D7: 3504876 | E7: =IFERROR(D7/$D$12,"") -> 0.076315957
A8: Rejected | B8: 10 | C8: =IFERROR(B8/$B$12,"") -> 0.034364261 | D8: 1076504.9 | E8: =IFERROR(D8/$D$12,"") -> 0.02344006
A9: Pending Approval | B9: 7 | C9: =IFERROR(B9/$B$12,"") -> 0.024054983 | D9: 857334.25 | E9: =IFERROR(D9/$D$12,"") -> 0.018667789
A10: On Hold | B10: 3 | C10: =IFERROR(B10/$B$12,"") -> 0.010309278 | D10: 27893.75 | E10: =IFERROR(D10/$D$12,"") -> 0.00060736479
A11: Open | B11: 1 | C11: =IFERROR(B11/$B$12,"") -> 0.0034364261 | D11: 0 | E11: =IFERROR(D11/$D$12,"") -> 0
A12: Total | B12: =SUM(B5:B11) -> 291 | C12: 1 | D12: =SUM(D5:D11) -> 45925860 | E12: 1
A15: Orders rejected on 23 July — these are CREDIT blocks, not stock blocks
A16: Order Nbr. | B16: Customer | C16: Value (KES) | D16: Rejection reason
A17: SO366958 | B17: Golden Two Distributors | C17: 439448.28 | D17: Account is in arrears
A18: SO366962 | B18: DEFWES DOD: Water Works | C18: 239980.5 | D18: Account is in arrears
A19: SO366955 | B19: DEFWES DOD: Water Works | C19: 154411 | D19: Account is in arrears
A20: SO367196 | B20: ILRI | C20: 79914 | D20: Account is in arrears
A21: SO366973 | B21: DEFWES Langata Barracks | C21: 73340.01 | D21: Account is in arrears
A22: SO366974 | B22: DEFWES Langata Barracks | C22: 37128 | D22: Account is in arrears
A23: SO366977 | B23: DEFWES Langata Barracks | C23: 23329.38 | D23: Account is in arrears
A24: SO367077 | B24: Chester Hotel | C24: 20605.17 | D24: Account is in arrears
A25: SO367201 | B25: Kolobot Gardens Limited | C25: 5000 | D25: Client on Upfront - Share Payment
A26: SO366932 | B26: Bidii Supermarket - Matuu | C26: 3348.57 | D26: Account is in arrears

Sheet Shortage Diagnosis
A1: Reasons for shortage — what the data supports, and what it cannot
A2: The two files contain no SKU-level or inventory data. Everything below is either an observed pattern (evidence stated) or a hypothesis that needs the exports listed on Read Me.
A4: Pattern observed | B4: Evidence in the data | C4: Most likely cause | D4: Confidence | E4: How to confirm
A5: Single bulk MT drop on 10 July still ~59% filled after 13 days | B5: 32 orders dated 10/07 (Khetia Drapers 21 branches, Maguna's 10, Karen Provision 1). KES 2.88m ordered, KES 1.20m still open. Every one partially shipped — so stock existed, just not enough. | C5: A month-start branch-replenishment drop that exceeded available cover. Allocation spread thinly across branches rather than filling priority stores first. | D5: High — pattern is unambiguous | E5: Pull Open Qty by Inventory ID for these 32 orders; if the same 5-10 SKUs appear on all of them it is a supply shortage, if it is scattered it is an allocation-policy issue.
A6: Carrefour (Majid Al Futtaim) and Quick Mart orders at 0% — nothing shipped at all | B6: 10 orders across 5 MAF branches and 5 Quick Mart branches, KES 273k open, ZERO shipments raised. Small quantities (6-24 units). Repeating unit values (KES 2,756.90 and KES 2,542.53) across branches. | C6: One or two specific SKUs are at zero available. Because the branch orders are single-line, the whole order blocks. This is a hard out-of-stock, not a partial shortage. | D6: High — the repeating unit price points to a common SKU | E6: Open any one of these orders (e.g. SO367035) and read the Inventory ID on the open line, then check Available in the FGS warehouse.
A7: Goodlife Pharmacy SO367174 — KES 1.89m, nothing shipped | B7: Largest single exposure in the file. 1,188 units, 0 shipments, raised same day (23/07). | C7: Most likely still in normal same-day processing rather than a true shortage. Order was only hours old at snapshot. | D7: Low — needs a next-day re-check | E7: Re-run the report on 24/07. If it is still Back Order at 0%, escalate; if it has moved to Shipping it was just processing lag and should be excluded from shortage reporting.
A8: Overselling — negative Available on stock that is physically on hand | B8: Screenshot 2, item SIFTP0015 (Sifa TP Emb. Unwrap Twinpack 20x2s): On Hand 100 CASE but Available -87 CASE, Available for Shipping 0.00. | C8: Commitments (other open orders) exceed on-hand. Sales is taking orders against stock already promised elsewhere. Nothing is missing from the warehouse — it is a booking-discipline problem. | D8: High — read directly off the screen | E8: Run Inventory Allocation Details for the top short SKUs. If On Hand > 0 while Available < 0 across several items, the fix is an ATP (available-to-promise) check at order entry, not more stock.
A9: Orders being filled in multiple drips | B9: SO361051 (Java House) has 4 shipments over 22 days; SO365985 (Sam West) 3 shipments in 3 days; SO367051 (Stage Mattresses) 2 same-day shipments. | C9: Stock arriving in small tranches and being released immediately. Indicates hand-to-mouth supply on those lines rather than a single stockout event. | D9: Medium | E9: Compare shipment dates against goods-receipt dates on the relevant POs / production orders.
A10: Free / zero-value lines keeping orders open | B10: SO366417 (Elburgon Bidii) shows Unbilled = 0 yet status is still Back Order. Screenshot 2 shows several lines with Free Item ticked and value 0.00. | C10: Promotional free-goods lines have no value, so value-based fill rate reads 100% while quantity is still outstanding. These inflate the back order count without inflating exposure. | D10: High | E10: Filter the line-level report on Free Item = Yes and report those separately from commercial shortfall.
A11: NOT a stock problem — credit blocks | B11: On 23/07 alone, 10 orders worth KES 1.08m were Rejected. 8 of the 10 read "Account is in arrears". | C11: These never reach the warehouse and must be kept out of any fill-rate or shortage metric, or they will make supply look worse than it is. | D11: High | E11: Already confirmed by the Rejection Reason field.
A12: CANNOT BE ANSWERED FROM THESE FILES | B12: Neither file has an Inventory ID, Open Qty, or any stock balance column. There is also no historical snapshot. | C12: Which specific items are short, how short, whether stock has since come back, and why it went short (late import / mill downtime / short shipment / MOQ timing) all sit outside this export. | D12: — | E12: Export the four datasets listed on the Read Me tab. Item 1 (line-level Open Qty) and item 2 (inventory availability) together give you the "check inventory and compare" view you asked for.
