Workbook

Sheet Summary
A1: Back order position — audit-trail basis
A2: Every figure is a formula over Episode Detail. Nothing here is hardcoded. Grain = episode (one order x one item x one occurrence); an order with 3 short items counts as 3 episodes but 1 order.
A3: Period (opened_at): | B3: 20 – 25 Jul 2026 | D3: Duration basis: | E3: Working days (Mon–Sat, Sundays & Kenyan holidays excluded)
A5: Metric | B5: Value | C5: Note
A6: Open backorder episodes (order x item) | B6: =COUNTIFS('Episode Detail'!$AT$5:$AT$25,"Open",'Episode Detail'!$AP$5:$AP$25,"No") -> 14 | C6: Base grain of the audit trail
A7: Open back orders (unique) | B7: =SUM('Episode Detail'!$AU$5:$AU$25) -> 14 | C7: DISTINCT order_nbr — comparable to the Acumatica order count
A8: Open items (unique SKUs) | B8: =SUM('Episode Detail'!$AV$5:$AV$25) -> 8 | C8: DISTINCT inventory_id
A9: Total order value on back order (KES) | B9: =SUMIFS('Episode Detail'!$AC$5:$AC$25,'Episode Detail'!$AP$5:$AP$25,"No") -> 3643902.3 | C9: Value of the SHORT LINES only — see note below
A10: Open / at-risk value (KES) | B10: =SUMIFS('Episode Detail'!$AD$5:$AD$25,'Episode Detail'!$AT$5:$AT$25,"Open",'Episode Detail'!$AP$5:$AP$25,"No") -> 2322851.6 | C10: backorder_qty x net price. Recoverable — NOT a loss
A11: Value already fulfilled (KES) | B11: =SUMIFS('Episode Detail'!$AE$5:$AE$25,'Episode Detail'!$AP$5:$AP$25,"No") -> 1315553.2 | C11: shipped_qty x net price
A12: Overall value fill rate | B12: =IFERROR(B11/B9,"") -> 0.36102867 | C12: Fulfilled / total line value
A13: Episodes with ZERO qty shipped | B13: =COUNTIFS('Episode Detail'!$X$5:$X$25,0,'Episode Detail'!$AT$5:$AT$25,"Open",'Episode Detail'!$AP$5:$AP$25,"No") -> 11 | C13: Nothing has left the warehouse on these at all
A14: Open value on those episodes (KES) | B14: =SUMIFS('Episode Detail'!$AD$5:$AD$25,'Episode Detail'!$X$5:$X$25,0,'Episode Detail'!$AT$5:$AT$25,"Open",'Episode Detail'!$AP$5:$AP$25,"No") -> 2154793.7 | C14: Hard stockouts
A15: Episodes older than 7 working days | B15: =COUNTIFS('Episode Detail'!$R$5:$R$25,">"&Lookups!$B$18,'Episode Detail'!$AT$5:$AT$25,"Open",'Episode Detail'!$AP$5:$AP$25,"No") -> 7 | C15: Threshold on Lookups
A16: Open value older than 7 working days (KES) | B16: =SUMIFS('Episode Detail'!$AD$5:$AD$25,'Episode Detail'!$R$5:$R$25,">"&Lookups!$B$18,'Episode Detail'!$AT$5:$AT$25,"Open",'Episode Detail'!$AP$5:$AP$25,"No") -> 251151.06 | C16: Past the channel write-off point
A17: Flagged ESCALATE | B17: =COUNTIFS('Episode Detail'!$AO$5:$AO$25,"ESCALATE",'Episode Detail'!$AP$5:$AP$25,"No") -> 4 | C17: Aged AND above the value floor
A19: Audit-trail measures — what the Acumatica screen cannot tell you
A20: Metric | B20: Value | C20: Note
A21: Resolved episodes in period | B21: =COUNTIFS('Episode Detail'!$AT$5:$AT$25,"Resolved",'Episode Detail'!$AP$5:$AP$25,"No") -> 6 | C21: Closed out — Acumatica loses these entirely
A22: Avg time to resolve | B22: =IFERROR(AVERAGEIFS('Episode Detail'!$R$5:$R$25,'Episode Detail'!$AT$5:$AT$25,"Resolved",'Episode Detail'!$T$5:$T$25,"Yes",'Episode Detail'!$AP$5:$AP$25,"No"),"") -> 5.1666667 | C22: Verified start dates only; backfilled excluded
A23: Avg time to resolve (label) | B23: =IF(B22=0,"Same Day",ROUND(B22,0)&IF(ROUND(B22,0)=1," Day Delay"," Days Delay")) -> 5 Days Delay | C23: Display form, e.g. 5 Days Delay
A24: Longest still open (working days) | B24: =_xlfn.MAXIFS('Episode Detail'!$R$5:$R$25,'Episode Detail'!$AT$5:$AT$25,"Open",'Episode Detail'!$AP$5:$AP$25,"No") -> 15 | C24: Worst live case
A25: Delayed revenue — shipped late (KES) | B25: =SUMIFS('Episode Detail'!$AF$5:$AF$25,'Episode Detail'!$AP$5:$AP$25,"No") -> 320811.34 | C25: Sale HAPPENED, just late. Not a loss
A26: Revenue-days delayed (KES-days) | B26: =SUMIFS('Episode Detail'!$AG$5:$AG$25,'Episode Detail'!$AP$5:$AP$25,"No") -> 524947.6 | C26: Weighted service cost — use this to rank causes
A27: Lost revenue (KES) | B27: =SUMIFS('Episode Detail'!$AH$5:$AH$25,'Episode Detail'!$AP$5:$AP$25,"No") -> 256648.56 | C27: Cancelled, or open past write-off. THIS is loss of sales
A28: of which PRODUCTION family (KES) | B28: =SUMIFS('Episode Detail'!$AH$5:$AH$25,'Episode Detail'!$AK$5:$AK$25,"PRODUCTION",'Episode Detail'!$AP$5:$AP$25,"No") -> 226138.2 | C28: "Loss of sales due to delayed production"
A29: Reason coverage | B29: =IFERROR(COUNTIFS('Episode Detail'!$AJ$5:$AJ$25,"<>(unreasoned)",'Episode Detail'!$AP$5:$AP$25,"No")/COUNTIFS('Episode Detail'!$AP$5:$AP$25,"No"),"") -> 0.95 | C29: Every family split is a sample of this size
A30: Verified start dates | B30: =IFERROR(COUNTIFS('Episode Detail'!$T$5:$T$25,"Yes",'Episode Detail'!$AP$5:$AP$25,"No")/COUNTIFS('Episode Detail'!$AP$5:$AP$25,"No"),"") -> 0.9 | C30: Backfilled durations are minimums
A33: By category
A34: Category | B34: Episodes (all) | C34: Open orders | D34: Order value (KES) | E34: Open value (KES) | F34: Fill rate
A35: Modern Trade T2 | B35: =COUNTIFS('Episode Detail'!$F$5:$F$25,$A35,'Episode Detail'!$AP$5:$AP$25,"No") -> 7 | C35: =SUMPRODUCT(('Episode Detail'!$F$5:$F$25=$A35)*'Episode Detail'!$AU$5:$AU$25) -> 3 | D35: =SUMIFS('Episode Detail'!$AC$5:$AC$25,'Episode Detail'!$F$5:$F$25,$A35,'Episode Detail'!$AP$5:$AP$25,"No") -> 645497 | E35: =SUMIFS('Episode Detail'!$AD$5:$AD$25,'Episode Detail'!$F$5:$F$25,$A35,'Episode Detail'!$AT$5:$AT$25,"Open",'Episode Detail'!$AP$5:$AP$25,"No") -> 168057.9 | F35: =IFERROR((D35-E35)/D35,"") -> 0.73964573
A36: Modern Trade T1 | B36: =COUNTIFS('Episode Detail'!$F$5:$F$25,$A36,'Episode Detail'!$AP$5:$AP$25,"No") -> 5 | C36: =SUMPRODUCT(('Episode Detail'!$F$5:$F$25=$A36)*'Episode Detail'!$AU$5:$AU$25) -> 5 | D36: =SUMIFS('Episode Detail'!$AC$5:$AC$25,'Episode Detail'!$F$5:$F$25,$A36,'Episode Detail'!$AP$5:$AP$25,"No") -> 154298.4 | E36: =SUMIFS('Episode Detail'!$AD$5:$AD$25,'Episode Detail'!$F$5:$F$25,$A36,'Episode Detail'!$AT$5:$AT$25,"Open",'Episode Detail'!$AP$5:$AP$25,"No") -> 154298.4 | F36: =IFERROR((D36-E36)/D36,"") -> 0
A37: Pharmacy | B37: =COUNTIFS('Episode Detail'!$F$5:$F$25,$A37,'Episode Detail'!$AP$5:$AP$25,"No") -> 2 | C37: =SUMPRODUCT(('Episode Detail'!$F$5:$F$25=$A37)*'Episode Detail'!$AU$5:$AU$25) -> 2 | D37: =SUMIFS('Episode Detail'!$AC$5:$AC$25,'Episode Detail'!$F$5:$F$25,$A37,'Episode Detail'!$AP$5:$AP$25,"No") -> 1937402.8 | E37: =SUMIFS('Episode Detail'!$AD$5:$AD$25,'Episode Detail'!$F$5:$F$25,$A37,'Episode Detail'!$AT$5:$AT$25,"Open",'Episode Detail'!$AP$5:$AP$25,"No") -> 1937402.8 | F37: =IFERROR((D37-E37)/D37,"") -> 0
A38: General Trade | B38: =COUNTIFS('Episode Detail'!$F$5:$F$25,$A38,'Episode Detail'!$AP$5:$AP$25,"No") -> 2 | C38: =SUMPRODUCT(('Episode Detail'!$F$5:$F$25=$A38)*'Episode Detail'!$AU$5:$AU$25) -> 1 | D38: =SUMIFS('Episode Detail'!$AC$5:$AC$25,'Episode Detail'!$F$5:$F$25,$A38,'Episode Detail'!$AP$5:$AP$25,"No") -> 880226.6 | E38: =SUMIFS('Episode Detail'!$AD$5:$AD$25,'Episode Detail'!$F$5:$F$25,$A38,'Episode Detail'!$AT$5:$AT$25,"Open",'Episode Detail'!$AP$5:$AP$25,"No") -> 37260 | F38: =IFERROR((D38-E38)/D38,"") -> 0.95766999
A39: Direct To Consumer (Cash Sale) | B39: =COUNTIFS('Episode Detail'!$F$5:$F$25,$A39,'Episode Detail'!$AP$5:$AP$25,"No") -> 1 | C39: =SUMPRODUCT(('Episode Detail'!$F$5:$F$25=$A39)*'Episode Detail'!$AU$5:$AU$25) -> 0 | D39: =SUMIFS('Episode Detail'!$AC$5:$AC$25,'Episode Detail'!$F$5:$F$25,$A39,'Episode Detail'!$AP$5:$AP$25,"No") -> 645 | E39: =SUMIFS('Episode Detail'!$AD$5:$AD$25,'Episode Detail'!$F$5:$F$25,$A39,'Episode Detail'!$AT$5:$AT$25,"Open",'Episode Detail'!$AP$5:$AP$25,"No") -> 0 | F39: =IFERROR((D39-E39)/D39,"") -> 1
A40: Non Traditional Channels | B40: =COUNTIFS('Episode Detail'!$F$5:$F$25,$A40,'Episode Detail'!$AP$5:$AP$25,"No") -> 1 | C40: =SUMPRODUCT(('Episode Detail'!$F$5:$F$25=$A40)*'Episode Detail'!$AU$5:$AU$25) -> 1 | D40: =SUMIFS('Episode Detail'!$AC$5:$AC$25,'Episode Detail'!$F$5:$F$25,$A40,'Episode Detail'!$AP$5:$AP$25,"No") -> 3397.44 | E40: =SUMIFS('Episode Detail'!$AD$5:$AD$25,'Episode Detail'!$F$5:$F$25,$A40,'Episode Detail'!$AT$5:$AT$25,"Open",'Episode Detail'!$AP$5:$AP$25,"No") -> 3397.44 | F40: =IFERROR((D40-E40)/D40,"") -> 0
A41: (not classified) | B41: =COUNTIFS('Episode Detail'!$F$5:$F$25,$A41,'Episode Detail'!$AP$5:$AP$25,"No") -> 2 | C41: =SUMPRODUCT(('Episode Detail'!$F$5:$F$25=$A41)*'Episode Detail'!$AU$5:$AU$25) -> 2 | D41: =SUMIFS('Episode Detail'!$AC$5:$AC$25,'Episode Detail'!$F$5:$F$25,$A41,'Episode Detail'!$AP$5:$AP$25,"No") -> 22435 | E41: =SUMIFS('Episode Detail'!$AD$5:$AD$25,'Episode Detail'!$F$5:$F$25,$A41,'Episode Detail'!$AT$5:$AT$25,"Open",'Episode Detail'!$AP$5:$AP$25,"No") -> 22435 | F41: =IFERROR((D41-E41)/D41,"") -> 0
A42: Total | B42: =SUM(B35:B41) -> 20 | C42: =SUM(C35:C41) -> 14 | D42: =SUM(D35:D41) -> 3643902.3 | E42: =SUM(E35:E41) -> 2322851.6 | F42: =IFERROR((D42-E42)/D42,"") -> 0.36253736
A45: By age bucket | D45: Open episodes only. Lower/Upper are editable (blue).
A46: Age bucket | B46: Lower | C46: Upper | D46: Open episodes | E46: Open orders | F46: Open value (KES)
A47: Same day | B47: 0 | C47: 0 | D47: =COUNTIFS('Episode Detail'!$R$5:$R$25,">="&$B47,'Episode Detail'!$R$5:$R$25,"<="&$C47,'Episode Detail'!$AT$5:$AT$25,"Open",'Episode Detail'!$AP$5:$AP$25,"No") -> 0 | E47: =SUMPRODUCT(('Episode Detail'!$R$5:$R$25>=$B47)*('Episode Detail'!$R$5:$R$25<=$C47)*'Episode Detail'!$AU$5:$AU$25) -> 0 | F47: =SUMIFS('Episode Detail'!$AD$5:$AD$25,'Episode Detail'!$R$5:$R$25,">="&$B47,'Episode Detail'!$R$5:$R$25,"<="&$C47,'Episode Detail'!$AT$5:$AT$25,"Open",'Episode Detail'!$AP$5:$AP$25,"No") -> 0
A48: 1-3 days | B48: 1 | C48: 3 | D48: =COUNTIFS('Episode Detail'!$R$5:$R$25,">="&$B48,'Episode Detail'!$R$5:$R$25,"<="&$C48,'Episode Detail'!$AT$5:$AT$25,"Open",'Episode Detail'!$AP$5:$AP$25,"No") -> 6 | E48: =SUMPRODUCT(('Episode Detail'!$R$5:$R$25>=$B48)*('Episode Detail'!$R$5:$R$25<=$C48)*'Episode Detail'!$AU$5:$AU$25) -> 6 | F48: =SUMIFS('Episode Detail'!$AD$5:$AD$25,'Episode Detail'!$R$5:$R$25,">="&$B48,'Episode Detail'!$R$5:$R$25,"<="&$C48,'Episode Detail'!$AT$5:$AT$25,"Open",'Episode Detail'!$AP$5:$AP$25,"No") -> 2068765.5
A49: 4-7 days | B49: 4 | C49: 7 | D49: =COUNTIFS('Episode Detail'!$R$5:$R$25,">="&$B49,'Episode Detail'!$R$5:$R$25,"<="&$C49,'Episode Detail'!$AT$5:$AT$25,"Open",'Episode Detail'!$AP$5:$AP$25,"No") -> 1 | E49: =SUMPRODUCT(('Episode Detail'!$R$5:$R$25>=$B49)*('Episode Detail'!$R$5:$R$25<=$C49)*'Episode Detail'!$AU$5:$AU$25) -> 1 | F49: =SUMIFS('Episode Detail'!$AD$5:$AD$25,'Episode Detail'!$R$5:$R$25,">="&$B49,'Episode Detail'!$R$5:$R$25,"<="&$C49,'Episode Detail'!$AT$5:$AT$25,"Open",'Episode Detail'!$AP$5:$AP$25,"No") -> 2935
A50: 8-14 days | B50: 8 | C50: 14 | D50: =COUNTIFS('Episode Detail'!$R$5:$R$25,">="&$B50,'Episode Detail'!$R$5:$R$25,"<="&$C50,'Episode Detail'!$AT$5:$AT$25,"Open",'Episode Detail'!$AP$5:$AP$25,"No") -> 6 | E50: =SUMPRODUCT(('Episode Detail'!$R$5:$R$25>=$B50)*('Episode Detail'!$R$5:$R$25<=$C50)*'Episode Detail'!$AU$5:$AU$25) -> 6 | F50: =SUMIFS('Episode Detail'!$AD$5:$AD$25,'Episode Detail'!$R$5:$R$25,">="&$B50,'Episode Detail'!$R$5:$R$25,"<="&$C50,'Episode Detail'!$AT$5:$AT$25,"Open",'Episode Detail'!$AP$5:$AP$25,"No") -> 231651.06
A51: 15+ days | B51: 15 | C51: 999 | D51: =COUNTIFS('Episode Detail'!$R$5:$R$25,">="&$B51,'Episode Detail'!$R$5:$R$25,"<="&$C51,'Episode Detail'!$AT$5:$AT$25,"Open",'Episode Detail'!$AP$5:$AP$25,"No") -> 1 | E51: =SUMPRODUCT(('Episode Detail'!$R$5:$R$25>=$B51)*('Episode Detail'!$R$5:$R$25<=$C51)*'Episode Detail'!$AU$5:$AU$25) -> 1 | F51: =SUMIFS('Episode Detail'!$AD$5:$AD$25,'Episode Detail'!$R$5:$R$25,">="&$B51,'Episode Detail'!$R$5:$R$25,"<="&$C51,'Episode Detail'!$AT$5:$AT$25,"Open",'Episode Detail'!$AP$5:$AP$25,"No") -> 19500
A52: Total | D52: =SUM(D47:D51) -> 14 | E52: =SUM(E47:E51) -> 14 | F52: =SUM(F47:F51) -> 2322851.6
A55: By brand | D55: Brand derived from Inventory ID prefix via the map on Lookups.
A56: Brand | B56: Episodes (all) | C56: Open SKUs | D56: Order value (KES) | E56: Open value (KES) | F56: Fill rate | G56: Lost revenue (KES) | H56: Revenue-days delayed | I56: Avg days delay
A57: Sifa | B57: =COUNTIFS('Episode Detail'!$I$5:$I$25,$A57,'Episode Detail'!$AP$5:$AP$25,"No") -> 2 | C57: =SUMPRODUCT(('Episode Detail'!$I$5:$I$25=$A57)*'Episode Detail'!$AV$5:$AV$25) -> 1 | D57: =SUMIFS('Episode Detail'!$AC$5:$AC$25,'Episode Detail'!$I$5:$I$25,$A57,'Episode Detail'!$AP$5:$AP$25,"No") -> 348107.1 | E57: =SUMIFS('Episode Detail'!$AD$5:$AD$25,'Episode Detail'!$I$5:$I$25,$A57,'Episode Detail'!$AT$5:$AT$25,"Open",'Episode Detail'!$AP$5:$AP$25,"No") -> 135137.4 | F57: =IFERROR((D57-E57)/D57,"") -> 0.61179361 | G57: =SUMIFS('Episode Detail'!$AH$5:$AH$25,'Episode Detail'!$I$5:$I$25,$A57,'Episode Detail'!$AP$5:$AP$25,"No") -> 135137.4 | H57: =SUMIFS('Episode Detail'!$AG$5:$AG$25,'Episode Detail'!$I$5:$I$25,$A57,'Episode Detail'!$AP$5:$AP$25,"No") -> 0 | I57: =IFERROR(AVERAGEIFS('Episode Detail'!$R$5:$R$25,'Episode Detail'!$I$5:$I$25,$A57,'Episode Detail'!$T$5:$T$25,"Yes",'Episode Detail'!$AP$5:$AP$25,"No"),"") -> 13
A58: Cosy | B58: =COUNTIFS('Episode Detail'!$I$5:$I$25,$A58,'Episode Detail'!$AP$5:$AP$25,"No") -> 3 | C58: =SUMPRODUCT(('Episode Detail'!$I$5:$I$25=$A58)*'Episode Detail'!$AV$5:$AV$25) -> 2 | D58: =SUMIFS('Episode Detail'!$AC$5:$AC$25,'Episode Detail'!$I$5:$I$25,$A58,'Episode Detail'!$AP$5:$AP$25,"No") -> 148858.2 | E58: =SUMIFS('Episode Detail'!$AD$5:$AD$25,'Episode Detail'!$I$5:$I$25,$A58,'Episode Detail'!$AT$5:$AT$25,"Open",'Episode Detail'!$AP$5:$AP$25,"No") -> 52420.5 | F58: =IFERROR((D58-E58)/D58,"") -> 0.64784943 | G58: =SUMIFS('Episode Detail'!$AH$5:$AH$25,'Episode Detail'!$I$5:$I$25,$A58,'Episode Detail'!$AP$5:$AP$25,"No") -> 52420.5 | H58: =SUMIFS('Episode Detail'!$AG$5:$AG$25,'Episode Detail'!$I$5:$I$25,$A58,'Episode Detail'!$AP$5:$AP$25,"No") -> 265429.6 | I58: =IFERROR(AVERAGEIFS('Episode Detail'!$R$5:$R$25,'Episode Detail'!$I$5:$I$25,$A58,'Episode Detail'!$T$5:$T$25,"Yes",'Episode Detail'!$AP$5:$AP$25,"No"),"") -> 11.5
A59: Fay | B59: =COUNTIFS('Episode Detail'!$I$5:$I$25,$A59,'Episode Detail'!$AP$5:$AP$25,"No") -> 9 | C59: =SUMPRODUCT(('Episode Detail'!$I$5:$I$25=$A59)*'Episode Detail'!$AV$5:$AV$25) -> 2 | D59: =SUMIFS('Episode Detail'!$AC$5:$AC$25,'Episode Detail'!$I$5:$I$25,$A59,'Episode Detail'!$AP$5:$AP$25,"No") -> 322975.1 | E59: =SUMIFS('Episode Detail'!$AD$5:$AD$25,'Episode Detail'!$I$5:$I$25,$A59,'Episode Detail'!$AT$5:$AT$25,"Open",'Episode Detail'!$AP$5:$AP$25,"No") -> 154298.4 | F59: =IFERROR((D59-E59)/D59,"") -> 0.52225915 | G59: =SUMIFS('Episode Detail'!$AH$5:$AH$25,'Episode Detail'!$I$5:$I$25,$A59,'Episode Detail'!$AP$5:$AP$25,"No") -> 69090.66 | H59: =SUMIFS('Episode Detail'!$AG$5:$AG$25,'Episode Detail'!$I$5:$I$25,$A59,'Episode Detail'!$AP$5:$AP$25,"No") -> 259518 | I59: =IFERROR(AVERAGEIFS('Episode Detail'!$R$5:$R$25,'Episode Detail'!$I$5:$I$25,$A59,'Episode Detail'!$T$5:$T$25,"Yes",'Episode Detail'!$AP$5:$AP$25,"No"),"") -> 5.4444444
A60: Tishu Poa | B60: =COUNTIFS('Episode Detail'!$I$5:$I$25,$A60,'Episode Detail'!$AP$5:$AP$25,"No") -> 3 | C60: =SUMPRODUCT(('Episode Detail'!$I$5:$I$25=$A60)*'Episode Detail'!$AV$5:$AV$25) -> 1 | D60: =SUMIFS('Episode Detail'!$AC$5:$AC$25,'Episode Detail'!$I$5:$I$25,$A60,'Episode Detail'!$AP$5:$AP$25,"No") -> 849299.04 | E60: =SUMIFS('Episode Detail'!$AD$5:$AD$25,'Episode Detail'!$I$5:$I$25,$A60,'Episode Detail'!$AT$5:$AT$25,"Open",'Episode Detail'!$AP$5:$AP$25,"No") -> 6332.44 | F60: =IFERROR((D60-E60)/D60,"") -> 0.99254392 | G60: =SUMIFS('Episode Detail'!$AH$5:$AH$25,'Episode Detail'!$I$5:$I$25,$A60,'Episode Detail'!$AP$5:$AP$25,"No") -> 0 | H60: =SUMIFS('Episode Detail'!$AG$5:$AG$25,'Episode Detail'!$I$5:$I$25,$A60,'Episode Detail'!$AP$5:$AP$25,"No") -> 0 | I60: =IFERROR(AVERAGEIFS('Episode Detail'!$R$5:$R$25,'Episode Detail'!$I$5:$I$25,$A60,'Episode Detail'!$T$5:$T$25,"Yes",'Episode Detail'!$AP$5:$AP$25,"No"),"") -> 2.6666667
A61: Cow & Gate | B61: =COUNTIFS('Episode Detail'!$I$5:$I$25,$A61,'Episode Detail'!$AP$5:$AP$25,"No") -> 3 | C61: =SUMPRODUCT(('Episode Detail'!$I$5:$I$25=$A61)*'Episode Detail'!$AV$5:$AV$25) -> 2 | D61: =SUMIFS('Episode Detail'!$AC$5:$AC$25,'Episode Detail'!$I$5:$I$25,$A61,'Episode Detail'!$AP$5:$AP$25,"No") -> 1974662.8 | E61: =SUMIFS('Episode Detail'!$AD$5:$AD$25,'Episode Detail'!$I$5:$I$25,$A61,'Episode Detail'!$AT$5:$AT$25,"Open",'Episode Detail'!$AP$5:$AP$25,"No") -> 1974662.8 | F61: =IFERROR((D61-E61)/D61,"") -> 0 | G61: =SUMIFS('Episode Detail'!$AH$5:$AH$25,'Episode Detail'!$I$5:$I$25,$A61,'Episode Detail'!$AP$5:$AP$25,"No") -> 0 | H61: =SUMIFS('Episode Detail'!$AG$5:$AG$25,'Episode Detail'!$I$5:$I$25,$A61,'Episode Detail'!$AP$5:$AP$25,"No") -> 0 | I61: =IFERROR(AVERAGEIFS('Episode Detail'!$R$5:$R$25,'Episode Detail'!$I$5:$I$25,$A61,'Episode Detail'!$T$5:$T$25,"Yes",'Episode Detail'!$AP$5:$AP$25,"No"),"") -> 2
A62: (unmapped) | B62: =COUNTIFS('Episode Detail'!$I$5:$I$25,"(unmapped)",'Episode Detail'!$AP$5:$AP$25,"No") -> 0 | D62: =SUMIFS('Episode Detail'!$AC$5:$AC$25,'Episode Detail'!$I$5:$I$25,"(unmapped)",'Episode Detail'!$AP$5:$AP$25,"No") -> 0 | E62: =SUMIFS('Episode Detail'!$AD$5:$AD$25,'Episode Detail'!$I$5:$I$25,"(unmapped)",'Episode Detail'!$AT$5:$AT$25,"Open",'Episode Detail'!$AP$5:$AP$25,"No") -> 0
A63: Total | B63: =SUM(B57:B62) -> 20 | C63: =SUM(C57:C62) -> 8 | D63: =SUM(D57:D62) -> 3643902.3 | E63: =SUM(E57:E62) -> 2322851.6 | F63: =IFERROR((D63-E63)/D63,"") -> 0.36253736 | G63: =SUM(G57:G62) -> 256648.56 | H63: =SUM(H57:H62) -> 524947.6
A64: (unmapped) must always be 0. Anything landing there means an Inventory ID prefix is missing from the brand map on Lookups.
A67: Reading notes — two definitional differences from the Acumatica screen
A68: 1. "Total order value on back order" here is the value of the SHORT LINES only. The Acumatica screen shows the value of the WHOLE ORDER, including lines that shipped in full. Acumatica's KES 8,436,411 will therefore always be the larger number — that is correct, not a bug. See the Acumatica Bridge sheet.
A69: 2. Ageing uses WORKING days (Mon–Sat, Sundays and gazetted holidays excluded). The Acumatica screen has no ageing at all. A "13 Days Delay" here is 16 calendar days.
A70: 3. Episodes flagged "Excluded from KPI?" = Yes are visible in Episode Detail but sit outside every figure on this page.
A71: 4. Durations from backfilled start dates are MINIMUMS, labelled "(min.)", and are excluded from every average.

Sheet Filters & Definitions
A1: Filters, provenance & definitions
A2: TEMPLATE / STRUCTURE DEMO. Sample rows use real order numbers, customers and SKUs from the 23 Jul 2026 extract; quantities and dates are illustrative. In production this sheet is written from the resolved API filter payload.
A4: PROVENANCE
A5: Generated at | B5: 2026-07-26 09:15 EAT
A6: Generated by | B6: ipay.user@kim-fay.com
A7: Source | B7: Acumatica REST API -> backorder_episodes / backorder_line_events
A8: Sync run id | B8: 48213
A9: Grain | B9: One row per (order_nbr, inventory_id, episode_no)
A11: FILTERS APPLIED — echoed verbatim from the API payload, do not edit
A12: Filter | B12: Value
A13: Period basis | B13: Backorders that STARTED in the period (opened_at)
A14: Period | B14: 20 – 25 Jul 2026
A15: State | B15: Open + Resolved (All)
A16: Duration basis | B16: Working days (Mon–Sat; Sundays & Kenyan gazetted holidays excluded)
A17: Order type | B17: SO only
A18: Reason family | B18: All
A19: Category / channel | B19: All
A20: Brand | B20: All
A21: Warehouse | B21: All (FGS, TPFGS)
A22: Include excluded-from-KPI episodes | B22: Shown in Episode Detail, outside every KPI
A23: Include backfilled start dates in durations | B23: No
... A25: Include internal / cash-sale accounts | B25: No
A27: CANONICAL FORMULAS — the agreed definitions
A28: Measure | B28: Formula | C28: Note
A29: net_order_qty | B29: order_qty - cancelled_qty | C29: Cancelled qty never counts against fill rate.
A30: open_qty | B30: net_order_qty - shipped_qty | C30: Owed to the customer, including goods already picked.
A31: backorder_qty | B31: GREATEST(0, open_qty - qty_on_shipments) | C31: THE shortage. Excludes goods already on a shipment.
A32: fill_rate | B32: shipped_qty / net_order_qty | C32: Denominator excludes cancelled qty.
A33: revenue_at_risk | B33: backorder_qty x net_unit_price | C33: Still recoverable. NOT a loss.
A34: days (working) | B34: Mon–Sat between opened_at and resolved_at (or as-at date) | C34: Sundays and gazetted holidays excluded.
A35: days_late | B35: GREATEST(0, working_days - promised_lead_time) | C35: Lead time is a Lookups parameter.
A36: delayed_revenue | B36: shipped_late_qty x net_unit_price | C36: Sale HAPPENED, just late. Not a loss.
A37: revenue_days_delayed | B37: delayed_revenue x days_late (KES-days) | C37: Ranks causes by weighted impact.
A38: lost_revenue | B38: cancelled_qty x price, or open value past the write-off threshold | C38: THIS is loss of sales.
A39: brand | B39: Inventory ID prefix -> Lookups brand map | C39: In production, read from the item master instead.
A41: Never add Revenue at Risk + Delayed Revenue + Lost Revenue together — they measure different things and overlap.

Sheet Loss by Reason
A1: Loss by reason family and code
A2: All 33 Acumatica reason codes map to exactly one family. Family rows are shaded; code rows sit beneath them.
A4: Family | B4: Reason code | C4: True supply shortage? | D4: Episodes | E4: Peak qty short | F4: Open value (KES) | G4: Delayed revenue (KES) | H4: Revenue-days delayed | I4: Lost revenue (KES) | J4: Avg days delay
A5: PRODUCTION | B5: — family total — | C5: Yes | D5: =COUNTIFS('Episode Detail'!$AK$5:$AK$25,$A5,'Episode Detail'!$AP$5:$AP$25,"No") -> 8 | E5: =SUMIFS('Episode Detail'!$V$5:$V$25,'Episode Detail'!$AK$5:$AK$25,$A5,'Episode Detail'!$AP$5:$AP$25,"No") -> 3080 | F5: =SUMIFS('Episode Detail'!$AD$5:$AD$25,'Episode Detail'!$AK$5:$AK$25,$A5,'Episode Detail'!$AT$5:$AT$25,"Open",'Episode Detail'!$AP$5:$AP$25,"No") -> 220640.7 | G5: =SUMIFS('Episode Detail'!$AF$5:$AF$25,'Episode Detail'!$AK$5:$AK$25,$A5,'Episode Detail'!$AP$5:$AP$25,"No") -> 68216.1 | H5: =SUMIFS('Episode Detail'!$AG$5:$AG$25,'Episode Detail'!$AK$5:$AK$25,$A5,'Episode Detail'!$AP$5:$AP$25,"No") -> 475654 | I5: =SUMIFS('Episode Detail'!$AH$5:$AH$25,'Episode Detail'!$AK$5:$AK$25,$A5,'Episode Detail'!$AP$5:$AP$25,"No") -> 226138.2 | J5: =IFERROR(AVERAGEIFS('Episode Detail'!$R$5:$R$25,'Episode Detail'!$AK$5:$AK$25,$A5,'Episode Detail'!$T$5:$T$25,"Yes",'Episode Detail'!$AP$5:$AP$25,"No"),"") -> 10.714286
B6: out_of_stock_production | D6: =COUNTIFS('Episode Detail'!$AJ$5:$AJ$25,$B6,'Episode Detail'!$AP$5:$AP$25,"No") -> 4 | E6: =SUMIFS('Episode Detail'!$V$5:$V$25,'Episode Detail'!$AJ$5:$AJ$25,$B6,'Episode Detail'!$AP$5:$AP$25,"No") -> 2266 | F6: =SUMIFS('Episode Detail'!$AD$5:$AD$25,'Episode Detail'!$AJ$5:$AJ$25,$B6,'Episode Detail'!$AT$5:$AT$25,"Open",'Episode Detail'!$AP$5:$AP$25,"No") -> 135137.4 | G6: =SUMIFS('Episode Detail'!$AF$5:$AF$25,'Episode Detail'!$AJ$5:$AJ$25,$B6,'Episode Detail'!$AP$5:$AP$25,"No") -> 68216.1 | H6: =SUMIFS('Episode Detail'!$AG$5:$AG$25,'Episode Detail'!$AJ$5:$AJ$25,$B6,'Episode Detail'!$AP$5:$AP$25,"No") -> 475654 | I6: =SUMIFS('Episode Detail'!$AH$5:$AH$25,'Episode Detail'!$AJ$5:$AJ$25,$B6,'Episode Detail'!$AP$5:$AP$25,"No") -> 140634.9 | J6: =IFERROR(AVERAGEIFS('Episode Detail'!$R$5:$R$25,'Episode Detail'!$AJ$5:$AJ$25,$B6,'Episode Detail'!$T$5:$T$25,"Yes",'Episode Detail'!$AP$5:$AP$25,"No"),"") -> 11
B7: production_stockout | D7: =COUNTIFS('Episode Detail'!$AJ$5:$AJ$25,$B7,'Episode Detail'!$AP$5:$AP$25,"No") -> 0 | E7: =SUMIFS('Episode Detail'!$V$5:$V$25,'Episode Detail'!$AJ$5:$AJ$25,$B7,'Episode Detail'!$AP$5:$AP$25,"No") -> 0 | F7: =SUMIFS('Episode Detail'!$AD$5:$AD$25,'Episode Detail'!$AJ$5:$AJ$25,$B7,'Episode Detail'!$AT$5:$AT$25,"Open",'Episode Detail'!$AP$5:$AP$25,"No") -> 0 | G7: =SUMIFS('Episode Detail'!$AF$5:$AF$25,'Episode Detail'!$AJ$5:$AJ$25,$B7,'Episode Detail'!$AP$5:$AP$25,"No") -> 0 | H7: =SUMIFS('Episode Detail'!$AG$5:$AG$25,'Episode Detail'!$AJ$5:$AJ$25,$B7,'Episode Detail'!$AP$5:$AP$25,"No") -> 0 | I7: =SUMIFS('Episode Detail'!$AH$5:$AH$25,'Episode Detail'!$AJ$5:$AJ$25,$B7,'Episode Detail'!$AP$5:$AP$25,"No") -> 0 | J7: =IFERROR(AVERAGEIFS('Episode Detail'!$R$5:$R$25,'Episode Detail'!$AJ$5:$AJ$25,$B7,'Episode Detail'!$T$5:$T$25,"Yes",'Episode Detail'!$AP$5:$AP$25,"No"),"")
B8: raw_material_stockout | D8: =COUNTIFS('Episode Detail'!$AJ$5:$AJ$25,$B8,'Episode Detail'!$AP$5:$AP$25,"No") -> 1 | E8: =SUMIFS('Episode Detail'!$V$5:$V$25,'Episode Detail'!$AJ$5:$AJ$25,$B8,'Episode Detail'!$AP$5:$AP$25,"No") -> 542 | F8: =SUMIFS('Episode Detail'!$AD$5:$AD$25,'Episode Detail'!$AJ$5:$AJ$25,$B8,'Episode Detail'!$AT$5:$AT$25,"Open",'Episode Detail'!$AP$5:$AP$25,"No") -> 32920.5 | G8: =SUMIFS('Episode Detail'!$AF$5:$AF$25,'Episode Detail'!$AJ$5:$AJ$25,$B8,'Episode Detail'!$AP$5:$AP$25,"No") -> 0 | H8: =SUMIFS('Episode Detail'!$AG$5:$AG$25,'Episode Detail'!$AJ$5:$AJ$25,$B8,'Episode Detail'!$AP$5:$AP$25,"No") -> 0 | I8: =SUMIFS('Episode Detail'!$AH$5:$AH$25,'Episode Detail'!$AJ$5:$AJ$25,$B8,'Episode Detail'!$AP$5:$AP$25,"No") -> 32920.5 | J8: =IFERROR(AVERAGEIFS('Episode Detail'!$R$5:$R$25,'Episode Detail'!$AJ$5:$AJ$25,$B8,'Episode Detail'!$T$5:$T$25,"Yes",'Episode Detail'!$AP$5:$AP$25,"No"),"") -> 13
B9: order_to_make | D9: =COUNTIFS('Episode Detail'!$AJ$5:$AJ$25,$B9,'Episode Detail'!$AP$5:$AP$25,"No") -> 1 | E9: =SUMIFS('Episode Detail'!$V$5:$V$25,'Episode Detail'!$AJ$5:$AJ$25,$B9,'Episode Detail'!$AP$5:$AP$25,"No") -> 260 | F9: =SUMIFS('Episode Detail'!$AD$5:$AD$25,'Episode Detail'!$AJ$5:$AJ$25,$B9,'Episode Detail'!$AT$5:$AT$25,"Open",'Episode Detail'!$AP$5:$AP$25,"No") -> 19500 | G9: =SUMIFS('Episode Detail'!$AF$5:$AF$25,'Episode Detail'!$AJ$5:$AJ$25,$B9,'Episode Detail'!$AP$5:$AP$25,"No") -> 0 | H9: =SUMIFS('Episode Detail'!$AG$5:$AG$25,'Episode Detail'!$AJ$5:$AJ$25,$B9,'Episode Detail'!$AP$5:$AP$25,"No") -> 0 | I9: =SUMIFS('Episode Detail'!$AH$5:$AH$25,'Episode Detail'!$AJ$5:$AJ$25,$B9,'Episode Detail'!$AP$5:$AP$25,"No") -> 19500 | J9: =IFERROR(AVERAGEIFS('Episode Detail'!$R$5:$R$25,'Episode Detail'!$AJ$5:$AJ$25,$B9,'Episode Detail'!$T$5:$T$25,"Yes",'Episode Detail'!$AP$5:$AP$25,"No"),"")
B10: conversion_delays | D10: =COUNTIFS('Episode Detail'!$AJ$5:$AJ$25,$B10,'Episode Detail'!$AP$5:$AP$25,"No") -> 2 | E10: =SUMIFS('Episode Detail'!$V$5:$V$25,'Episode Detail'!$AJ$5:$AJ$25,$B10,'Episode Detail'!$AP$5:$AP$25,"No") -> 12 | F10: =SUMIFS('Episode Detail'!$AD$5:$AD$25,'Episode Detail'!$AJ$5:$AJ$25,$B10,'Episode Detail'!$AT$5:$AT$25,"Open",'Episode Detail'!$AP$5:$AP$25,"No") -> 33082.8 | G10: =SUMIFS('Episode Detail'!$AF$5:$AF$25,'Episode Detail'!$AJ$5:$AJ$25,$B10,'Episode Detail'!$AP$5:$AP$25,"No") -> 0 | H10: =SUMIFS('Episode Detail'!$AG$5:$AG$25,'Episode Detail'!$AJ$5:$AJ$25,$B10,'Episode Detail'!$AP$5:$AP$25,"No") -> 0 | I10: =SUMIFS('Episode Detail'!$AH$5:$AH$25,'Episode Detail'!$AJ$5:$AJ$25,$B10,'Episode Detail'!$AP$5:$AP$25,"No") -> 33082.8 | J10: =IFERROR(AVERAGEIFS('Episode Detail'!$R$5:$R$25,'Episode Detail'!$AJ$5:$AJ$25,$B10,'Episode Detail'!$T$5:$T$25,"Yes",'Episode Detail'!$AP$5:$AP$25,"No"),"") -> 9
B11: conversion_issues | D11: =COUNTIFS('Episode Detail'!$AJ$5:$AJ$25,$B11,'Episode Detail'!$AP$5:$AP$25,"No") -> 0 | E11: =SUMIFS('Episode Detail'!$V$5:$V$25,'Episode Detail'!$AJ$5:$AJ$25,$B11,'Episode Detail'!$AP$5:$AP$25,"No") -> 0 | F11: =SUMIFS('Episode Detail'!$AD$5:$AD$25,'Episode Detail'!$AJ$5:$AJ$25,$B11,'Episode Detail'!$AT$5:$AT$25,"Open",'Episode Detail'!$AP$5:$AP$25,"No") -> 0 | G11: =SUMIFS('Episode Detail'!$AF$5:$AF$25,'Episode Detail'!$AJ$5:$AJ$25,$B11,'Episode Detail'!$AP$5:$AP$25,"No") -> 0 | H11: =SUMIFS('Episode Detail'!$AG$5:$AG$25,'Episode Detail'!$AJ$5:$AJ$25,$B11,'Episode Detail'!$AP$5:$AP$25,"No") -> 0 | I11: =SUMIFS('Episode Detail'!$AH$5:$AH$25,'Episode Detail'!$AJ$5:$AJ$25,$B11,'Episode Detail'!$AP$5:$AP$25,"No") -> 0 | J11: =IFERROR(AVERAGEIFS('Episode Detail'!$R$5:$R$25,'Episode Detail'!$AJ$5:$AJ$25,$B11,'Episode Detail'!$T$5:$T$25,"Yes",'Episode Detail'!$AP$5:$AP$25,"No"),"")
B12: batch_sequence | D12: =COUNTIFS('Episode Detail'!$AJ$5:$AJ$25,$B12,'Episode Detail'!$AP$5:$AP$25,"No") -> 0 | E12: =SUMIFS('Episode Detail'!$V$5:$V$25,'Episode Detail'!$AJ$5:$AJ$25,$B12,'Episode Detail'!$AP$5:$AP$25,"No") -> 0 | F12: =SUMIFS('Episode Detail'!$AD$5:$AD$25,'Episode Detail'!$AJ$5:$AJ$25,$B12,'Episode Detail'!$AT$5:$AT$25,"Open",'Episode Detail'!$AP$5:$AP$25,"No") -> 0 | G12: =SUMIFS('Episode Detail'!$AF$5:$AF$25,'Episode Detail'!$AJ$5:$AJ$25,$B12,'Episode Detail'!$AP$5:$AP$25,"No") -> 0 | H12: =SUMIFS('Episode Detail'!$AG$5:$AG$25,'Episode Detail'!$AJ$5:$AJ$25,$B12,'Episode Detail'!$AP$5:$AP$25,"No") -> 0 | I12: =SUMIFS('Episode Detail'!$AH$5:$AH$25,'Episode Detail'!$AJ$5:$AJ$25,$B12,'Episode Detail'!$AP$5:$AP$25,"No") -> 0 | J12: =IFERROR(AVERAGEIFS('Episode Detail'!$R$5:$R$25,'Episode Detail'!$AJ$5:$AJ$25,$B12,'Episode Detail'!$T$5:$T$25,"Yes",'Episode Detail'!$AP$5:$AP$25,"No"),"")
B13: wrong_moq | D13: =COUNTIFS('Episode Detail'!$AJ$5:$AJ$25,$B13,'Episode Detail'!$AP$5:$AP$25,"No") -> 0 | E13: =SUMIFS('Episode Detail'!$V$5:$V$25,'Episode Detail'!$AJ$5:$AJ$25,$B13,'Episode Detail'!$AP$5:$AP$25,"No") -> 0 | F13: =SUMIFS('Episode Detail'!$AD$5:$AD$25,'Episode Detail'!$AJ$5:$AJ$25,$B13,'Episode Detail'!$AT$5:$AT$25,"Open",'Episode Detail'!$AP$5:$AP$25,"No") -> 0 | G13: =SUMIFS('Episode Detail'!$AF$5:$AF$25,'Episode Detail'!$AJ$5:$AJ$25,$B13,'Episode Detail'!$AP$5:$AP$25,"No") -> 0 | H13: =SUMIFS('Episode Detail'!$AG$5:$AG$25,'Episode Detail'!$AJ$5:$AJ$25,$B13,'Episode Detail'!$AP$5:$AP$25,"No") -> 0 | I13: =SUMIFS('Episode Detail'!$AH$5:$AH$25,'Episode Detail'!$AJ$5:$AJ$25,$B13,'Episode Detail'!$AP$5:$AP$25,"No") -> 0 | J13: =IFERROR(AVERAGEIFS('Episode Detail'!$R$5:$R$25,'Episode Detail'!$AJ$5:$AJ$25,$B13,'Episode Detail'!$T$5:$T$25,"Yes",'Episode Detail'!$AP$5:$AP$25,"No"),"")
A14: PROCUREMENT | B14: — family total — | C14: Yes | D14: =COUNTIFS('Episode Detail'!$AK$5:$AK$25,$A14,'Episode Detail'!$AP$5:$AP$25,"No") -> 5 | E14: =SUMIFS('Episode Detail'!$V$5:$V$25,'Episode Detail'!$AK$5:$AK$25,$A14,'Episode Detail'!$AP$5:$AP$25,"No") -> 108 | F14: =SUMIFS('Episode Detail'!$AD$5:$AD$25,'Episode Detail'!$AK$5:$AK$25,$A14,'Episode Detail'!$AT$5:$AT$25,"Open",'Episode Detail'!$AP$5:$AP$25,"No") -> 203346.9 | G14: =SUMIFS('Episode Detail'!$AF$5:$AF$25,'Episode Detail'!$AK$5:$AK$25,$A14,'Episode Detail'!$AP$5:$AP$25,"No") -> 0 | H14: =SUMIFS('Episode Detail'!$AG$5:$AG$25,'Episode Detail'!$AK$5:$AK$25,$A14,'Episode Detail'!$AP$5:$AP$25,"No") -> 0 | I14: =SUMIFS('Episode Detail'!$AH$5:$AH$25,'Episode Detail'!$AK$5:$AK$25,$A14,'Episode Detail'!$AP$5:$AP$25,"No") -> 30510.36 | J14: =IFERROR(AVERAGEIFS('Episode Detail'!$R$5:$R$25,'Episode Detail'!$AK$5:$AK$25,$A14,'Episode Detail'!$T$5:$T$25,"Yes",'Episode Detail'!$AP$5:$AP$25,"No"),"") -> 3.5
B15: out_of_stock_procurement | D15: =COUNTIFS('Episode Detail'!$AJ$5:$AJ$25,$B15,'Episode Detail'!$AP$5:$AP$25,"No") -> 3 | E15: =SUMIFS('Episode Detail'!$V$5:$V$25,'Episode Detail'!$AJ$5:$AJ$25,$B15,'Episode Detail'!$AP$5:$AP$25,"No") -> 54 | F15: =SUMIFS('Episode Detail'!$AD$5:$AD$25,'Episode Detail'!$AJ$5:$AJ$25,$B15,'Episode Detail'!$AT$5:$AT$25,"Open",'Episode Detail'!$AP$5:$AP$25,"No") -> 121215.6 | G15: =SUMIFS('Episode Detail'!$AF$5:$AF$25,'Episode Detail'!$AJ$5:$AJ$25,$B15,'Episode Detail'!$AP$5:$AP$25,"No") -> 0 | H15: =SUMIFS('Episode Detail'!$AG$5:$AG$25,'Episode Detail'!$AJ$5:$AJ$25,$B15,'Episode Detail'!$AP$5:$AP$25,"No") -> 0 | I15: =SUMIFS('Episode Detail'!$AH$5:$AH$25,'Episode Detail'!$AJ$5:$AJ$25,$B15,'Episode Detail'!$AP$5:$AP$25,"No") -> 30510.36 | J15: =IFERROR(AVERAGEIFS('Episode Detail'!$R$5:$R$25,'Episode Detail'!$AJ$5:$AJ$25,$B15,'Episode Detail'!$T$5:$T$25,"Yes",'Episode Detail'!$AP$5:$AP$25,"No"),"") -> 4
B16: out_of_stock_msa | D16: =COUNTIFS('Episode Detail'!$AJ$5:$AJ$25,$B16,'Episode Detail'!$AP$5:$AP$25,"No") -> 2 | E16: =SUMIFS('Episode Detail'!$V$5:$V$25,'Episode Detail'!$AJ$5:$AJ$25,$B16,'Episode Detail'!$AP$5:$AP$25,"No") -> 54 | F16: =SUMIFS('Episode Detail'!$AD$5:$AD$25,'Episode Detail'!$AJ$5:$AJ$25,$B16,'Episode Detail'!$AT$5:$AT$25,"Open",'Episode Detail'!$AP$5:$AP$25,"No") -> 82131.3 | G16: =SUMIFS('Episode Detail'!$AF$5:$AF$25,'Episode Detail'!$AJ$5:$AJ$25,$B16,'Episode Detail'!$AP$5:$AP$25,"No") -> 0 | H16: =SUMIFS('Episode Detail'!$AG$5:$AG$25,'Episode Detail'!$AJ$5:$AJ$25,$B16,'Episode Detail'!$AP$5:$AP$25,"No") -> 0 | I16: =SUMIFS('Episode Detail'!$AH$5:$AH$25,'Episode Detail'!$AJ$5:$AJ$25,$B16,'Episode Detail'!$AP$5:$AP$25,"No") -> 0 | J16: =IFERROR(AVERAGEIFS('Episode Detail'!$R$5:$R$25,'Episode Detail'!$AJ$5:$AJ$25,$B16,'Episode Detail'!$T$5:$T$25,"Yes",'Episode Detail'!$AP$5:$AP$25,"No"),"") -> 2
B17: delayed_supplier_payment | D17: =COUNTIFS('Episode Detail'!$AJ$5:$AJ$25,$B17,'Episode Detail'!$AP$5:$AP$25,"No") -> 0 | E17: =SUMIFS('Episode Detail'!$V$5:$V$25,'Episode Detail'!$AJ$5:$AJ$25,$B17,'Episode Detail'!$AP$5:$AP$25,"No") -> 0 | F17: =SUMIFS('Episode Detail'!$AD$5:$AD$25,'Episode Detail'!$AJ$5:$AJ$25,$B17,'Episode Detail'!$AT$5:$AT$25,"Open",'Episode Detail'!$AP$5:$AP$25,"No") -> 0 | G17: =SUMIFS('Episode Detail'!$AF$5:$AF$25,'Episode Detail'!$AJ$5:$AJ$25,$B17,'Episode Detail'!$AP$5:$AP$25,"No") -> 0 | H17: =SUMIFS('Episode Detail'!$AG$5:$AG$25,'Episode Detail'!$AJ$5:$AJ$25,$B17,'Episode Detail'!$AP$5:$AP$25,"No") -> 0 | I17: =SUMIFS('Episode Detail'!$AH$5:$AH$25,'Episode Detail'!$AJ$5:$AJ$25,$B17,'Episode Detail'!$AP$5:$AP$25,"No") -> 0 | J17: =IFERROR(AVERAGEIFS('Episode Detail'!$R$5:$R$25,'Episode Detail'!$AJ$5:$AJ$25,$B17,'Episode Detail'!$T$5:$T$25,"Yes",'Episode Detail'!$AP$5:$AP$25,"No"),"")
B18: kebs_stickers | D18: =COUNTIFS('Episode Detail'!$AJ$5:$AJ$25,$B18,'Episode Detail'!$AP$5:$AP$25,"No") -> 0 | E18: =SUMIFS('Episode Detail'!$V$5:$V$25,'Episode Detail'!$AJ$5:$AJ$25,$B18,'Episode Detail'!$AP$5:$AP$25,"No") -> 0 | F18: =SUMIFS('Episode Detail'!$AD$5:$AD$25,'Episode Detail'!$AJ$5:$AJ$25,$B18,'Episode Detail'!$AT$5:$AT$25,"Open",'Episode Detail'!$AP$5:$AP$25,"No") -> 0 | G18: =SUMIFS('Episode Detail'!$AF$5:$AF$25,'Episode Detail'!$AJ$5:$AJ$25,$B18,'Episode Detail'!$AP$5:$AP$25,"No") -> 0 | H18: =SUMIFS('Episode Detail'!$AG$5:$AG$25,'Episode Detail'!$AJ$5:$AJ$25,$B18,'Episode Detail'!$AP$5:$AP$25,"No") -> 0 | I18: =SUMIFS('Episode Detail'!$AH$5:$AH$25,'Episode Detail'!$AJ$5:$AJ$25,$B18,'Episode Detail'!$AP$5:$AP$25,"No") -> 0 | J18: =IFERROR(AVERAGEIFS('Episode Detail'!$R$5:$R$25,'Episode Detail'!$AJ$5:$AJ$25,$B18,'Episode Detail'!$T$5:$T$25,"Yes",'Episode Detail'!$AP$5:$AP$25,"No"),"")
A19: LOGISTICS | B19: — family total — | C19: No | D19: =COUNTIFS('Episode Detail'!$AK$5:$AK$25,$A19,'Episode Detail'!$AP$5:$AP$25,"No") -> 4 | E19: =SUMIFS('Episode Detail'!$V$5:$V$25,'Episode Detail'!$AK$5:$AK$25,$A19,'Episode Detail'!$AP$5:$AP$25,"No") -> 570 | F19: =SUMIFS('Episode Detail'!$AD$5:$AD$25,'Episode Detail'!$AK$5:$AK$25,$A19,'Episode Detail'!$AT$5:$AT$25,"Open",'Episode Detail'!$AP$5:$AP$25,"No") -> 0 | G19: =SUMIFS('Episode Detail'!$AF$5:$AF$25,'Episode Detail'!$AK$5:$AK$25,$A19,'Episode Detail'!$AP$5:$AP$25,"No") -> 252595.24 | H19: =SUMIFS('Episode Detail'!$AG$5:$AG$25,'Episode Detail'!$AK$5:$AK$25,$A19,'Episode Detail'!$AP$5:$AP$25,"No") -> 49293.6 | I19: =SUMIFS('Episode Detail'!$AH$5:$AH$25,'Episode Detail'!$AK$5:$AK$25,$A19,'Episode Detail'!$AP$5:$AP$25,"No") -> 0 | J19: =IFERROR(AVERAGEIFS('Episode Detail'!$R$5:$R$25,'Episode Detail'!$AK$5:$AK$25,$A19,'Episode Detail'!$T$5:$T$25,"Yes",'Episode Detail'!$AP$5:$AP$25,"No"),"") -> 3.25
B20: delay_in_delivery | D20: =COUNTIFS('Episode Detail'!$AJ$5:$AJ$25,$B20,'Episode Detail'!$AP$5:$AP$25,"No") -> 0 | E20: =SUMIFS('Episode Detail'!$V$5:$V$25,'Episode Detail'!$AJ$5:$AJ$25,$B20,'Episode Detail'!$AP$5:$AP$25,"No") -> 0 | F20: =SUMIFS('Episode Detail'!$AD$5:$AD$25,'Episode Detail'!$AJ$5:$AJ$25,$B20,'Episode Detail'!$AT$5:$AT$25,"Open",'Episode Detail'!$AP$5:$AP$25,"No") -> 0 | G20: =SUMIFS('Episode Detail'!$AF$5:$AF$25,'Episode Detail'!$AJ$5:$AJ$25,$B20,'Episode Detail'!$AP$5:$AP$25,"No") -> 0 | H20: =SUMIFS('Episode Detail'!$AG$5:$AG$25,'Episode Detail'!$AJ$5:$AJ$25,$B20,'Episode Detail'!$AP$5:$AP$25,"No") -> 0 | I20: =SUMIFS('Episode Detail'!$AH$5:$AH$25,'Episode Detail'!$AJ$5:$AJ$25,$B20,'Episode Detail'!$AP$5:$AP$25,"No") -> 0 | J20: =IFERROR(AVERAGEIFS('Episode Detail'!$R$5:$R$25,'Episode Detail'!$AJ$5:$AJ$25,$B20,'Episode Detail'!$T$5:$T$25,"Yes",'Episode Detail'!$AP$5:$AP$25,"No"),"")
B21: transfer_delays | D21: =COUNTIFS('Episode Detail'!$AJ$5:$AJ$25,$B21,'Episode Detail'!$AP$5:$AP$25,"No") -> 1 | E21: =SUMIFS('Episode Detail'!$V$5:$V$25,'Episode Detail'!$AJ$5:$AJ$25,$B21,'Episode Detail'!$AP$5:$AP$25,"No") -> 262 | F21: =SUMIFS('Episode Detail'!$AD$5:$AD$25,'Episode Detail'!$AJ$5:$AJ$25,$B21,'Episode Detail'!$AT$5:$AT$25,"Open",'Episode Detail'!$AP$5:$AP$25,"No") -> 0 | G21: =SUMIFS('Episode Detail'!$AF$5:$AF$25,'Episode Detail'!$AJ$5:$AJ$25,$B21,'Episode Detail'!$AP$5:$AP$25,"No") -> 225364.54 | H21: =SUMIFS('Episode Detail'!$AG$5:$AG$25,'Episode Detail'!$AJ$5:$AJ$25,$B21,'Episode Detail'!$AP$5:$AP$25,"No") -> 0 | I21: =SUMIFS('Episode Detail'!$AH$5:$AH$25,'Episode Detail'!$AJ$5:$AJ$25,$B21,'Episode Detail'!$AP$5:$AP$25,"No") -> 0 | J21: =IFERROR(AVERAGEIFS('Episode Detail'!$R$5:$R$25,'Episode Detail'!$AJ$5:$AJ$25,$B21,'Episode Detail'!$T$5:$T$25,"Yes",'Episode Detail'!$AP$5:$AP$25,"No"),"") -> 2
B22: truck_full | D22: =COUNTIFS('Episode Detail'!$AJ$5:$AJ$25,$B22,'Episode Detail'!$AP$5:$AP$25,"No") -> 1 | E22: =SUMIFS('Episode Detail'!$V$5:$V$25,'Episode Detail'!$AJ$5:$AJ$25,$B22,'Episode Detail'!$AP$5:$AP$25,"No") -> 6 | F22: =SUMIFS('Episode Detail'!$AD$5:$AD$25,'Episode Detail'!$AJ$5:$AJ$25,$B22,'Episode Detail'!$AT$5:$AT$25,"Open",'Episode Detail'!$AP$5:$AP$25,"No") -> 0 | G22: =SUMIFS('Episode Detail'!$AF$5:$AF$25,'Episode Detail'!$AJ$5:$AJ$25,$B22,'Episode Detail'!$AP$5:$AP$25,"No") -> 322.5 | H22: =SUMIFS('Episode Detail'!$AG$5:$AG$25,'Episode Detail'!$AJ$5:$AJ$25,$B22,'Episode Detail'!$AP$5:$AP$25,"No") -> 645 | I22: =SUMIFS('Episode Detail'!$AH$5:$AH$25,'Episode Detail'!$AJ$5:$AJ$25,$B22,'Episode Detail'!$AP$5:$AP$25,"No") -> 0 | J22: =IFERROR(AVERAGEIFS('Episode Detail'!$R$5:$R$25,'Episode Detail'!$AJ$5:$AJ$25,$B22,'Episode Detail'!$T$5:$T$25,"Yes",'Episode Detail'!$AP$5:$AP$25,"No"),"") -> 4
B23: did_not_pick_on_shipment | D23: =COUNTIFS('Episode Detail'!$AJ$5:$AJ$25,$B23,'Episode Detail'!$AP$5:$AP$25,"No") -> 2 | E23: =SUMIFS('Episode Detail'!$V$5:$V$25,'Episode Detail'!$AJ$5:$AJ$25,$B23,'Episode Detail'!$AP$5:$AP$25,"No") -> 302 | F23: =SUMIFS('Episode Detail'!$AD$5:$AD$25,'Episode Detail'!$AJ$5:$AJ$25,$B23,'Episode Detail'!$AT$5:$AT$25,"Open",'Episode Detail'!$AP$5:$AP$25,"No") -> 0 | G23: =SUMIFS('Episode Detail'!$AF$5:$AF$25,'Episode Detail'!$AJ$5:$AJ$25,$B23,'Episode Detail'!$AP$5:$AP$25,"No") -> 26908.2 | H23: =SUMIFS('Episode Detail'!$AG$5:$AG$25,'Episode Detail'!$AJ$5:$AJ$25,$B23,'Episode Detail'!$AP$5:$AP$25,"No") -> 48648.6 | I23: =SUMIFS('Episode Detail'!$AH$5:$AH$25,'Episode Detail'!$AJ$5:$AJ$25,$B23,'Episode Detail'!$AP$5:$AP$25,"No") -> 0 | J23: =IFERROR(AVERAGEIFS('Episode Detail'!$R$5:$R$25,'Episode Detail'!$AJ$5:$AJ$25,$B23,'Episode Detail'!$T$5:$T$25,"Yes",'Episode Detail'!$AP$5:$AP$25,"No"),"") -> 3.5
A24: COMMERCIAL | B24: — family total — | C24: No | D24: =COUNTIFS('Episode Detail'!$AK$5:$AK$25,$A24,'Episode Detail'!$AP$5:$AP$25,"No") -> 1 | E24: =SUMIFS('Episode Detail'!$V$5:$V$25,'Episode Detail'!$AK$5:$AK$25,$A24,'Episode Detail'!$AP$5:$AP$25,"No") -> 12 | F24: =SUMIFS('Episode Detail'!$AD$5:$AD$25,'Episode Detail'!$AK$5:$AK$25,$A24,'Episode Detail'!$AT$5:$AT$25,"Open",'Episode Detail'!$AP$5:$AP$25,"No") -> 3397.44 | G24: =SUMIFS('Episode Detail'!$AF$5:$AF$25,'Episode Detail'!$AK$5:$AK$25,$A24,'Episode Detail'!$AP$5:$AP$25,"No") -> 0 | H24: =SUMIFS('Episode Detail'!$AG$5:$AG$25,'Episode Detail'!$AK$5:$AK$25,$A24,'Episode Detail'!$AP$5:$AP$25,"No") -> 0 | I24: =SUMIFS('Episode Detail'!$AH$5:$AH$25,'Episode Detail'!$AK$5:$AK$25,$A24,'Episode Detail'!$AP$5:$AP$25,"No") -> 0 | J24: =IFERROR(AVERAGEIFS('Episode Detail'!$R$5:$R$25,'Episode Detail'!$AK$5:$AK$25,$A24,'Episode Detail'!$T$5:$T$25,"Yes",'Episode Detail'!$AP$5:$AP$25,"No"),"") -> 2
B25: discontinued | D25: =COUNTIFS('Episode Detail'!$AJ$5:$AJ$25,$B25,'Episode Detail'!$AP$5:$AP$25,"No") -> 0 | E25: =SUMIFS('Episode Detail'!$V$5:$V$25,'Episode Detail'!$AJ$5:$AJ$25,$B25,'Episode Detail'!$AP$5:$AP$25,"No") -> 0 | F25: =SUMIFS('Episode Detail'!$AD$5:$AD$25,'Episode Detail'!$AJ$5:$AJ$25,$B25,'Episode Detail'!$AT$5:$AT$25,"Open",'Episode Detail'!$AP$5:$AP$25,"No") -> 0 | G25: =SUMIFS('Episode Detail'!$AF$5:$AF$25,'Episode Detail'!$AJ$5:$AJ$25,$B25,'Episode Detail'!$AP$5:$AP$25,"No") -> 0 | H25: =SUMIFS('Episode Detail'!$AG$5:$AG$25,'Episode Detail'!$AJ$5:$AJ$25,$B25,'Episode Detail'!$AP$5:$AP$25,"No") -> 0 | I25: =SUMIFS('Episode Detail'!$AH$5:$AH$25,'Episode Detail'!$AJ$5:$AJ$25,$B25,'Episode Detail'!$AP$5:$AP$25,"No") -> 0 | J25: =IFERROR(AVERAGEIFS('Episode Detail'!$R$5:$R$25,'Episode Detail'!$AJ$5:$AJ$25,$B25,'Episode Detail'!$T$5:$T$25,"Yes",'Episode Detail'!$AP$5:$AP$25,"No"),"")
B26: pb_discontinued | D26: =COUNTIFS('Episode Detail'!$AJ$5:$AJ$25,$B26,'Episode Detail'!$AP$5:$AP$25,"No") -> 0 | E26: =SUMIFS('Episode Detail'!$V$5:$V$25,'Episode Detail'!$AJ$5:$AJ$25,$B26,'Episode Detail'!$AP$5:$AP$25,"No") -> 0 | F26: =SUMIFS('Episode Detail'!$AD$5:$AD$25,'Episode Detail'!$AJ$5:$AJ$25,$B26,'Episode Detail'!$AT$5:$AT$25,"Open",'Episode Detail'!$AP$5:$AP$25,"No") -> 0 | G26: =SUMIFS('Episode Detail'!$AF$5:$AF$25,'Episode Detail'!$AJ$5:$AJ$25,$B26,'Episode Detail'!$AP$5:$AP$25,"No") -> 0 | H26: =SUMIFS('Episode Detail'!$AG$5:$AG$25,'Episode Detail'!$AJ$5:$AJ$25,$B26,'Episode Detail'!$AP$5:$AP$25,"No") -> 0 | I26: =SUMIFS('Episode Detail'!$AH$5:$AH$25,'Episode Detail'!$AJ$5:$AJ$25,$B26,'Episode Detail'!$AP$5:$AP$25,"No") -> 0 | J26: =IFERROR(AVERAGEIFS('Episode Detail'!$R$5:$R$25,'Episode Detail'!$AJ$5:$AJ$25,$B26,'Episode Detail'!$T$5:$T$25,"Yes",'Episode Detail'!$AP$5:$AP$25,"No"),"")
B27: non_focus | D27: =COUNTIFS('Episode Detail'!$AJ$5:$AJ$25,$B27,'Episode Detail'!$AP$5:$AP$25,"No") -> 1 | E27: =SUMIFS('Episode Detail'!$V$5:$V$25,'Episode Detail'!$AJ$5:$AJ$25,$B27,'Episode Detail'!$AP$5:$AP$25,"No") -> 12 | F27: =SUMIFS('Episode Detail'!$AD$5:$AD$25,'Episode Detail'!$AJ$5:$AJ$25,$B27,'Episode Detail'!$AT$5:$AT$25,"Open",'Episode Detail'!$AP$5:$AP$25,"No") -> 3397.44 | G27: =SUMIFS('Episode Detail'!$AF$5:$AF$25,'Episode Detail'!$AJ$5:$AJ$25,$B27,'Episode Detail'!$AP$5:$AP$25,"No") -> 0 | H27: =SUMIFS('Episode Detail'!$AG$5:$AG$25,'Episode Detail'!$AJ$5:$AJ$25,$B27,'Episode Detail'!$AP$5:$AP$25,"No") -> 0 | I27: =SUMIFS('Episode Detail'!$AH$5:$AH$25,'Episode Detail'!$AJ$5:$AJ$25,$B27,'Episode Detail'!$AP$5:$AP$25,"No") -> 0 | J27: =IFERROR(AVERAGEIFS('Episode Detail'!$R$5:$R$25,'Episode Detail'!$AJ$5:$AJ$25,$B27,'Episode Detail'!$T$5:$T$25,"Yes",'Episode Detail'!$AP$5:$AP$25,"No"),"") -> 2
B28: promo_product | D28: =COUNTIFS('Episode Detail'!$AJ$5:$AJ$25,$B28,'Episode Detail'!$AP$5:$AP$25,"No") -> 0 | E28: =SUMIFS('Episode Detail'!$V$5:$V$25,'Episode Detail'!$AJ$5:$AJ$25,$B28,'Episode Detail'!$AP$5:$AP$25,"No") -> 0 | F28: =SUMIFS('Episode Detail'!$AD$5:$AD$25,'Episode Detail'!$AJ$5:$AJ$25,$B28,'Episode Detail'!$AT$5:$AT$25,"Open",'Episode Detail'!$AP$5:$AP$25,"No") -> 0 | G28: =SUMIFS('Episode Detail'!$AF$5:$AF$25,'Episode Detail'!$AJ$5:$AJ$25,$B28,'Episode Detail'!$AP$5:$AP$25,"No") -> 0 | H28: =SUMIFS('Episode Detail'!$AG$5:$AG$25,'Episode Detail'!$AJ$5:$AJ$25,$B28,'Episode Detail'!$AP$5:$AP$25,"No") -> 0 | I28: =SUMIFS('Episode Detail'!$AH$5:$AH$25,'Episode Detail'!$AJ$5:$AJ$25,$B28,'Episode Detail'!$AP$5:$AP$25,"No") -> 0 | J28: =IFERROR(AVERAGEIFS('Episode Detail'!$R$5:$R$25,'Episode Detail'!$AJ$5:$AJ$25,$B28,'Episode Detail'!$T$5:$T$25,"Yes",'Episode Detail'!$AP$5:$AP$25,"No"),"")
B29: short_expiry | D29: =COUNTIFS('Episode Detail'!$AJ$5:$AJ$25,$B29,'Episode Detail'!$AP$5:$AP$25,"No") -> 0 | E29: =SUMIFS('Episode Detail'!$V$5:$V$25,'Episode Detail'!$AJ$5:$AJ$25,$B29,'Episode Detail'!$AP$5:$AP$25,"No") -> 0 | F29: =SUMIFS('Episode Detail'!$AD$5:$AD$25,'Episode Detail'!$AJ$5:$AJ$25,$B29,'Episode Detail'!$AT$5:$AT$25,"Open",'Episode Detail'!$AP$5:$AP$25,"No") -> 0 | G29: =SUMIFS('Episode Detail'!$AF$5:$AF$25,'Episode Detail'!$AJ$5:$AJ$25,$B29,'Episode Detail'!$AP$5:$AP$25,"No") -> 0 | H29: =SUMIFS('Episode Detail'!$AG$5:$AG$25,'Episode Detail'!$AJ$5:$AJ$25,$B29,'Episode Detail'!$AP$5:$AP$25,"No") -> 0 | I29: =SUMIFS('Episode Detail'!$AH$5:$AH$25,'Episode Detail'!$AJ$5:$AJ$25,$B29,'Episode Detail'!$AP$5:$AP$25,"No") -> 0 | J29: =IFERROR(AVERAGEIFS('Episode Detail'!$R$5:$R$25,'Episode Detail'!$AJ$5:$AJ$25,$B29,'Episode Detail'!$T$5:$T$25,"Yes",'Episode Detail'!$AP$5:$AP$25,"No"),"")
B30: npd | D30: =COUNTIFS('Episode Detail'!$AJ$5:$AJ$25,$B30,'Episode Detail'!$AP$5:$AP$25,"No") -> 0 | E30: =SUMIFS('Episode Detail'!$V$5:$V$25,'Episode Detail'!$AJ$5:$AJ$25,$B30,'Episode Detail'!$AP$5:$AP$25,"No") -> 0 | F30: =SUMIFS('Episode Detail'!$AD$5:$AD$25,'Episode Detail'!$AJ$5:$AJ$25,$B30,'Episode Detail'!$AT$5:$AT$25,"Open",'Episode Detail'!$AP$5:$AP$25,"No") -> 0 | G30: =SUMIFS('Episode Detail'!$AF$5:$AF$25,'Episode Detail'!$AJ$5:$AJ$25,$B30,'Episode Detail'!$AP$5:$AP$25,"No") -> 0 | H30: =SUMIFS('Episode Detail'!$AG$5:$AG$25,'Episode Detail'!$AJ$5:$AJ$25,$B30,'Episode Detail'!$AP$5:$AP$25,"No") -> 0 | I30: =SUMIFS('Episode Detail'!$AH$5:$AH$25,'Episode Detail'!$AJ$5:$AJ$25,$B30,'Episode Detail'!$AP$5:$AP$25,"No") -> 0 | J30: =IFERROR(AVERAGEIFS('Episode Detail'!$R$5:$R$25,'Episode Detail'!$AJ$5:$AJ$25,$B30,'Episode Detail'!$T$5:$T$25,"Yes",'Episode Detail'!$AP$5:$AP$25,"No"),"")
A31: DATA_PROCESS | B31: — family total — | C31: No | D31: =COUNTIFS('Episode Detail'!$AK$5:$AK$25,$A31,'Episode Detail'!$AP$5:$AP$25,"No") -> 1 | E31: =SUMIFS('Episode Detail'!$V$5:$V$25,'Episode Detail'!$AK$5:$AK$25,$A31,'Episode Detail'!$AP$5:$AP$25,"No") -> 1 | F31: =SUMIFS('Episode Detail'!$AD$5:$AD$25,'Episode Detail'!$AK$5:$AK$25,$A31,'Episode Detail'!$AT$5:$AT$25,"Open",'Episode Detail'!$AP$5:$AP$25,"No") -> 2935 | G31: =SUMIFS('Episode Detail'!$AF$5:$AF$25,'Episode Detail'!$AK$5:$AK$25,$A31,'Episode Detail'!$AP$5:$AP$25,"No") -> 0 | H31: =SUMIFS('Episode Detail'!$AG$5:$AG$25,'Episode Detail'!$AK$5:$AK$25,$A31,'Episode Detail'!$AP$5:$AP$25,"No") -> 0 | I31: =SUMIFS('Episode Detail'!$AH$5:$AH$25,'Episode Detail'!$AK$5:$AK$25,$A31,'Episode Detail'!$AP$5:$AP$25,"No") -> 0 | J31: =IFERROR(AVERAGEIFS('Episode Detail'!$R$5:$R$25,'Episode Detail'!$AK$5:$AK$25,$A31,'Episode Detail'!$T$5:$T$25,"Yes",'Episode Detail'!$AP$5:$AP$25,"No"),"") -> 4
B32: delayed_communication | D32: =COUNTIFS('Episode Detail'!$AJ$5:$AJ$25,$B32,'Episode Detail'!$AP$5:$AP$25,"No") -> 0 | E32: =SUMIFS('Episode Detail'!$V$5:$V$25,'Episode Detail'!$AJ$5:$AJ$25,$B32,'Episode Detail'!$AP$5:$AP$25,"No") -> 0 | F32: =SUMIFS('Episode Detail'!$AD$5:$AD$25,'Episode Detail'!$AJ$5:$AJ$25,$B32,'Episode Detail'!$AT$5:$AT$25,"Open",'Episode Detail'!$AP$5:$AP$25,"No") -> 0 | G32: =SUMIFS('Episode Detail'!$AF$5:$AF$25,'Episode Detail'!$AJ$5:$AJ$25,$B32,'Episode Detail'!$AP$5:$AP$25,"No") -> 0 | H32: =SUMIFS('Episode Detail'!$AG$5:$AG$25,'Episode Detail'!$AJ$5:$AJ$25,$B32,'Episode Detail'!$AP$5:$AP$25,"No") -> 0 | I32: =SUMIFS('Episode Detail'!$AH$5:$AH$25,'Episode Detail'!$AJ$5:$AJ$25,$B32,'Episode Detail'!$AP$5:$AP$25,"No") -> 0 | J32: =IFERROR(AVERAGEIFS('Episode Detail'!$R$5:$R$25,'Episode Detail'!$AJ$5:$AJ$25,$B32,'Episode Detail'!$T$5:$T$25,"Yes",'Episode Detail'!$AP$5:$AP$25,"No"),"")
B33: price_difference | D33: =COUNTIFS('Episode Detail'!$AJ$5:$AJ$25,$B33,'Episode Detail'!$AP$5:$AP$25,"No") -> 0 | E33: =SUMIFS('Episode Detail'!$V$5:$V$25,'Episode Detail'!$AJ$5:$AJ$25,$B33,'Episode Detail'!$AP$5:$AP$25,"No") -> 0 | F33: =SUMIFS('Episode Detail'!$AD$5:$AD$25,'Episode Detail'!$AJ$5:$AJ$25,$B33,'Episode Detail'!$AT$5:$AT$25,"Open",'Episode Detail'!$AP$5:$AP$25,"No") -> 0 | G33: =SUMIFS('Episode Detail'!$AF$5:$AF$25,'Episode Detail'!$AJ$5:$AJ$25,$B33,'Episode Detail'!$AP$5:$AP$25,"No") -> 0 | H33: =SUMIFS('Episode Detail'!$AG$5:$AG$25,'Episode Detail'!$AJ$5:$AJ$25,$B33,'Episode Detail'!$AP$5:$AP$25,"No") -> 0 | I33: =SUMIFS('Episode Detail'!$AH$5:$AH$25,'Episode Detail'!$AJ$5:$AJ$25,$B33,'Episode Detail'!$AP$5:$AP$25,"No") -> 0 | J33: =IFERROR(AVERAGEIFS('Episode Detail'!$R$5:$R$25,'Episode Detail'!$AJ$5:$AJ$25,$B33,'Episode Detail'!$T$5:$T$25,"Yes",'Episode Detail'!$AP$5:$AP$25,"No"),"")
B34: price_variance | D34: =COUNTIFS('Episode Detail'!$AJ$5:$AJ$25,$B34,'Episode Detail'!$AP$5:$AP$25,"No") -> 0 | E34: =SUMIFS('Episode Detail'!$V$5:$V$25,'Episode Detail'!$AJ$5:$AJ$25,$B34,'Episode Detail'!$AP$5:$AP$25,"No") -> 0 | F34: =SUMIFS('Episode Detail'!$AD$5:$AD$25,'Episode Detail'!$AJ$5:$AJ$25,$B34,'Episode Detail'!$AT$5:$AT$25,"Open",'Episode Detail'!$AP$5:$AP$25,"No") -> 0 | G34: =SUMIFS('Episode Detail'!$AF$5:$AF$25,'Episode Detail'!$AJ$5:$AJ$25,$B34,'Episode Detail'!$AP$5:$AP$25,"No") -> 0 | H34: =SUMIFS('Episode Detail'!$AG$5:$AG$25,'Episode Detail'!$AJ$5:$AJ$25,$B34,'Episode Detail'!$AP$5:$AP$25,"No") -> 0 | I34: =SUMIFS('Episode Detail'!$AH$5:$AH$25,'Episode Detail'!$AJ$5:$AJ$25,$B34,'Episode Detail'!$AP$5:$AP$25,"No") -> 0 | J34: =IFERROR(AVERAGEIFS('Episode Detail'!$R$5:$R$25,'Episode Detail'!$AJ$5:$AJ$25,$B34,'Episode Detail'!$T$5:$T$25,"Yes",'Episode Detail'!$AP$5:$AP$25,"No"),"")
B35: price_overcharge | D35: =COUNTIFS('Episode Detail'!$AJ$5:$AJ$25,$B35,'Episode Detail'!$AP$5:$AP$25,"No") -> 0 | E35: =SUMIFS('Episode Detail'!$V$5:$V$25,'Episode Detail'!$AJ$5:$AJ$25,$B35,'Episode Detail'!$AP$5:$AP$25,"No") -> 0 | F35: =SUMIFS('Episode Detail'!$AD$5:$AD$25,'Episode Detail'!$AJ$5:$AJ$25,$B35,'Episode Detail'!$AT$5:$AT$25,"Open",'Episode Detail'!$AP$5:$AP$25,"No") -> 0 | G35: =SUMIFS('Episode Detail'!$AF$5:$AF$25,'Episode Detail'!$AJ$5:$AJ$25,$B35,'Episode Detail'!$AP$5:$AP$25,"No") -> 0 | H35: =SUMIFS('Episode Detail'!$AG$5:$AG$25,'Episode Detail'!$AJ$5:$AJ$25,$B35,'Episode Detail'!$AP$5:$AP$25,"No") -> 0 | I35: =SUMIFS('Episode Detail'!$AH$5:$AH$25,'Episode Detail'!$AJ$5:$AJ$25,$B35,'Episode Detail'!$AP$5:$AP$25,"No") -> 0 | J35: =IFERROR(AVERAGEIFS('Episode Detail'!$R$5:$R$25,'Episode Detail'!$AJ$5:$AJ$25,$B35,'Episode Detail'!$T$5:$T$25,"Yes",'Episode Detail'!$AP$5:$AP$25,"No"),"")
B36: invoicing_error | D36: =COUNTIFS('Episode Detail'!$AJ$5:$AJ$25,$B36,'Episode Detail'!$AP$5:$AP$25,"No") -> 0 | E36: =SUMIFS('Episode Detail'!$V$5:$V$25,'Episode Detail'!$AJ$5:$AJ$25,$B36,'Episode Detail'!$AP$5:$AP$25,"No") -> 0 | F36: =SUMIFS('Episode Detail'!$AD$5:$AD$25,'Episode Detail'!$AJ$5:$AJ$25,$B36,'Episode Detail'!$AT$5:$AT$25,"Open",'Episode Detail'!$AP$5:$AP$25,"No") -> 0 | G36: =SUMIFS('Episode Detail'!$AF$5:$AF$25,'Episode Detail'!$AJ$5:$AJ$25,$B36,'Episode Detail'!$AP$5:$AP$25,"No") -> 0 | H36: =SUMIFS('Episode Detail'!$AG$5:$AG$25,'Episode Detail'!$AJ$5:$AJ$25,$B36,'Episode Detail'!$AP$5:$AP$25,"No") -> 0 | I36: =SUMIFS('Episode Detail'!$AH$5:$AH$25,'Episode Detail'!$AJ$5:$AJ$25,$B36,'Episode Detail'!$AP$5:$AP$25,"No") -> 0 | J36: =IFERROR(AVERAGEIFS('Episode Detail'!$R$5:$R$25,'Episode Detail'!$AJ$5:$AJ$25,$B36,'Episode Detail'!$T$5:$T$25,"Yes",'Episode Detail'!$AP$5:$AP$25,"No"),"")
B37: stock_variance | D37: =COUNTIFS('Episode Detail'!$AJ$5:$AJ$25,$B37,'Episode Detail'!$AP$5:$AP$25,"No") -> 0 | E37: =SUMIFS('Episode Detail'!$V$5:$V$25,'Episode Detail'!$AJ$5:$AJ$25,$B37,'Episode Detail'!$AP$5:$AP$25,"No") -> 0 | F37: =SUMIFS('Episode Detail'!$AD$5:$AD$25,'Episode Detail'!$AJ$5:$AJ$25,$B37,'Episode Detail'!$AT$5:$AT$25,"Open",'Episode Detail'!$AP$5:$AP$25,"No") -> 0 | G37: =SUMIFS('Episode Detail'!$AF$5:$AF$25,'Episode Detail'!$AJ$5:$AJ$25,$B37,'Episode Detail'!$AP$5:$AP$25,"No") -> 0 | H37: =SUMIFS('Episode Detail'!$AG$5:$AG$25,'Episode Detail'!$AJ$5:$AJ$25,$B37,'Episode Detail'!$AP$5:$AP$25,"No") -> 0 | I37: =SUMIFS('Episode Detail'!$AH$5:$AH$25,'Episode Detail'!$AJ$5:$AJ$25,$B37,'Episode Detail'!$AP$5:$AP$25,"No") -> 0 | J37: =IFERROR(AVERAGEIFS('Episode Detail'!$R$5:$R$25,'Episode Detail'!$AJ$5:$AJ$25,$B37,'Episode Detail'!$T$5:$T$25,"Yes",'Episode Detail'!$AP$5:$AP$25,"No"),"")
B38: isolation_error | D38: =COUNTIFS('Episode Detail'!$AJ$5:$AJ$25,$B38,'Episode Detail'!$AP$5:$AP$25,"No") -> 0 | E38: =SUMIFS('Episode Detail'!$V$5:$V$25,'Episode Detail'!$AJ$5:$AJ$25,$B38,'Episode Detail'!$AP$5:$AP$25,"No") -> 0 | F38: =SUMIFS('Episode Detail'!$AD$5:$AD$25,'Episode Detail'!$AJ$5:$AJ$25,$B38,'Episode Detail'!$AT$5:$AT$25,"Open",'Episode Detail'!$AP$5:$AP$25,"No") -> 0 | G38: =SUMIFS('Episode Detail'!$AF$5:$AF$25,'Episode Detail'!$AJ$5:$AJ$25,$B38,'Episode Detail'!$AP$5:$AP$25,"No") -> 0 | H38: =SUMIFS('Episode Detail'!$AG$5:$AG$25,'Episode Detail'!$AJ$5:$AJ$25,$B38,'Episode Detail'!$AP$5:$AP$25,"No") -> 0 | I38: =SUMIFS('Episode Detail'!$AH$5:$AH$25,'Episode Detail'!$AJ$5:$AJ$25,$B38,'Episode Detail'!$AP$5:$AP$25,"No") -> 0 | J38: =IFERROR(AVERAGEIFS('Episode Detail'!$R$5:$R$25,'Episode Detail'!$AJ$5:$AJ$25,$B38,'Episode Detail'!$T$5:$T$25,"Yes",'Episode Detail'!$AP$5:$AP$25,"No"),"")
B39: wrong_product_description | D39: =COUNTIFS('Episode Detail'!$AJ$5:$AJ$25,$B39,'Episode Detail'!$AP$5:$AP$25,"No") -> 0 | E39: =SUMIFS('Episode Detail'!$V$5:$V$25,'Episode Detail'!$AJ$5:$AJ$25,$B39,'Episode Detail'!$AP$5:$AP$25,"No") -> 0 | F39: =SUMIFS('Episode Detail'!$AD$5:$AD$25,'Episode Detail'!$AJ$5:$AJ$25,$B39,'Episode Detail'!$AT$5:$AT$25,"Open",'Episode Detail'!$AP$5:$AP$25,"No") -> 0 | G39: =SUMIFS('Episode Detail'!$AF$5:$AF$25,'Episode Detail'!$AJ$5:$AJ$25,$B39,'Episode Detail'!$AP$5:$AP$25,"No") -> 0 | H39: =SUMIFS('Episode Detail'!$AG$5:$AG$25,'Episode Detail'!$AJ$5:$AJ$25,$B39,'Episode Detail'!$AP$5:$AP$25,"No") -> 0 | I39: =SUMIFS('Episode Detail'!$AH$5:$AH$25,'Episode Detail'!$AJ$5:$AJ$25,$B39,'Episode Detail'!$AP$5:$AP$25,"No") -> 0 | J39: =IFERROR(AVERAGEIFS('Episode Detail'!$R$5:$R$25,'Episode Detail'!$AJ$5:$AJ$25,$B39,'Episode Detail'!$T$5:$T$25,"Yes",'Episode Detail'!$AP$5:$AP$25,"No"),"")
B40: wrong_code | D40: =COUNTIFS('Episode Detail'!$AJ$5:$AJ$25,$B40,'Episode Detail'!$AP$5:$AP$25,"No") -> 1 | E40: =SUMIFS('Episode Detail'!$V$5:$V$25,'Episode Detail'!$AJ$5:$AJ$25,$B40,'Episode Detail'!$AP$5:$AP$25,"No") -> 1 | F40: =SUMIFS('Episode Detail'!$AD$5:$AD$25,'Episode Detail'!$AJ$5:$AJ$25,$B40,'Episode Detail'!$AT$5:$AT$25,"Open",'Episode Detail'!$AP$5:$AP$25,"No") -> 2935 | G40: =SUMIFS('Episode Detail'!$AF$5:$AF$25,'Episode Detail'!$AJ$5:$AJ$25,$B40,'Episode Detail'!$AP$5:$AP$25,"No") -> 0 | H40: =SUMIFS('Episode Detail'!$AG$5:$AG$25,'Episode Detail'!$AJ$5:$AJ$25,$B40,'Episode Detail'!$AP$5:$AP$25,"No") -> 0 | I40: =SUMIFS('Episode Detail'!$AH$5:$AH$25,'Episode Detail'!$AJ$5:$AJ$25,$B40,'Episode Detail'!$AP$5:$AP$25,"No") -> 0 | J40: =IFERROR(AVERAGEIFS('Episode Detail'!$R$5:$R$25,'Episode Detail'!$AJ$5:$AJ$25,$B40,'Episode Detail'!$T$5:$T$25,"Yes",'Episode Detail'!$AP$5:$AP$25,"No"),"") -> 4
B41: system_error | D41: =COUNTIFS('Episode Detail'!$AJ$5:$AJ$25,$B41,'Episode Detail'!$AP$5:$AP$25,"No") -> 0 | E41: =SUMIFS('Episode Detail'!$V$5:$V$25,'Episode Detail'!$AJ$5:$AJ$25,$B41,'Episode Detail'!$AP$5:$AP$25,"No") -> 0 | F41: =SUMIFS('Episode Detail'!$AD$5:$AD$25,'Episode Detail'!$AJ$5:$AJ$25,$B41,'Episode Detail'!$AT$5:$AT$25,"Open",'Episode Detail'!$AP$5:$AP$25,"No") -> 0 | G41: =SUMIFS('Episode Detail'!$AF$5:$AF$25,'Episode Detail'!$AJ$5:$AJ$25,$B41,'Episode Detail'!$AP$5:$AP$25,"No") -> 0 | H41: =SUMIFS('Episode Detail'!$AG$5:$AG$25,'Episode Detail'!$AJ$5:$AJ$25,$B41,'Episode Detail'!$AP$5:$AP$25,"No") -> 0 | I41: =SUMIFS('Episode Detail'!$AH$5:$AH$25,'Episode Detail'!$AJ$5:$AJ$25,$B41,'Episode Detail'!$AP$5:$AP$25,"No") -> 0 | J41: =IFERROR(AVERAGEIFS('Episode Detail'!$R$5:$R$25,'Episode Detail'!$AJ$5:$AJ$25,$B41,'Episode Detail'!$T$5:$T$25,"Yes",'Episode Detail'!$AP$5:$AP$25,"No"),"")
B42: lpo_error | D42: =COUNTIFS('Episode Detail'!$AJ$5:$AJ$25,$B42,'Episode Detail'!$AP$5:$AP$25,"No") -> 0 | E42: =SUMIFS('Episode Detail'!$V$5:$V$25,'Episode Detail'!$AJ$5:$AJ$25,$B42,'Episode Detail'!$AP$5:$AP$25,"No") -> 0 | F42: =SUMIFS('Episode Detail'!$AD$5:$AD$25,'Episode Detail'!$AJ$5:$AJ$25,$B42,'Episode Detail'!$AT$5:$AT$25,"Open",'Episode Detail'!$AP$5:$AP$25,"No") -> 0 | G42: =SUMIFS('Episode Detail'!$AF$5:$AF$25,'Episode Detail'!$AJ$5:$AJ$25,$B42,'Episode Detail'!$AP$5:$AP$25,"No") -> 0 | H42: =SUMIFS('Episode Detail'!$AG$5:$AG$25,'Episode Detail'!$AJ$5:$AJ$25,$B42,'Episode Detail'!$AP$5:$AP$25,"No") -> 0 | I42: =SUMIFS('Episode Detail'!$AH$5:$AH$25,'Episode Detail'!$AJ$5:$AJ$25,$B42,'Episode Detail'!$AP$5:$AP$25,"No") -> 0 | J42: =IFERROR(AVERAGEIFS('Episode Detail'!$R$5:$R$25,'Episode Detail'!$AJ$5:$AJ$25,$B42,'Episode Detail'!$T$5:$T$25,"Yes",'Episode Detail'!$AP$5:$AP$25,"No"),"")
A43: UNCLASSIFIED | B43: — family total — | C43: No | D43: =COUNTIFS('Episode Detail'!$AK$5:$AK$25,$A43,'Episode Detail'!$AP$5:$AP$25,"No") -> 1 | E43: =SUMIFS('Episode Detail'!$V$5:$V$25,'Episode Detail'!$AK$5:$AK$25,$A43,'Episode Detail'!$AP$5:$AP$25,"No") -> 1188 | F43: =SUMIFS('Episode Detail'!$AD$5:$AD$25,'Episode Detail'!$AK$5:$AK$25,$A43,'Episode Detail'!$AT$5:$AT$25,"Open",'Episode Detail'!$AP$5:$AP$25,"No") -> 1892531.5 | G43: =SUMIFS('Episode Detail'!$AF$5:$AF$25,'Episode Detail'!$AK$5:$AK$25,$A43,'Episode Detail'!$AP$5:$AP$25,"No") -> 0 | H43: =SUMIFS('Episode Detail'!$AG$5:$AG$25,'Episode Detail'!$AK$5:$AK$25,$A43,'Episode Detail'!$AP$5:$AP$25,"No") -> 0 | I43: =SUMIFS('Episode Detail'!$AH$5:$AH$25,'Episode Detail'!$AK$5:$AK$25,$A43,'Episode Detail'!$AP$5:$AP$25,"No") -> 0 | J43: =IFERROR(AVERAGEIFS('Episode Detail'!$R$5:$R$25,'Episode Detail'!$AK$5:$AK$25,$A43,'Episode Detail'!$T$5:$T$25,"Yes",'Episode Detail'!$AP$5:$AP$25,"No"),"") -> 2
B44: (unreasoned) | D44: =COUNTIFS('Episode Detail'!$AJ$5:$AJ$25,$B44,'Episode Detail'!$AP$5:$AP$25,"No") -> 1 | E44: =SUMIFS('Episode Detail'!$V$5:$V$25,'Episode Detail'!$AJ$5:$AJ$25,$B44,'Episode Detail'!$AP$5:$AP$25,"No") -> 1188 | F44: =SUMIFS('Episode Detail'!$AD$5:$AD$25,'Episode Detail'!$AJ$5:$AJ$25,$B44,'Episode Detail'!$AT$5:$AT$25,"Open",'Episode Detail'!$AP$5:$AP$25,"No") -> 1892531.5 | G44: =SUMIFS('Episode Detail'!$AF$5:$AF$25,'Episode Detail'!$AJ$5:$AJ$25,$B44,'Episode Detail'!$AP$5:$AP$25,"No") -> 0 | H44: =SUMIFS('Episode Detail'!$AG$5:$AG$25,'Episode Detail'!$AJ$5:$AJ$25,$B44,'Episode Detail'!$AP$5:$AP$25,"No") -> 0 | I44: =SUMIFS('Episode Detail'!$AH$5:$AH$25,'Episode Detail'!$AJ$5:$AJ$25,$B44,'Episode Detail'!$AP$5:$AP$25,"No") -> 0 | J44: =IFERROR(AVERAGEIFS('Episode Detail'!$R$5:$R$25,'Episode Detail'!$AJ$5:$AJ$25,$B44,'Episode Detail'!$T$5:$T$25,"Yes",'Episode Detail'!$AP$5:$AP$25,"No"),"") -> 2

Sheet Episode Detail
A1: Episode Detail — one row per (order, item, occurrence)
A2: Columns A–M mirror the Acumatica export so the two can sit side by side. Amber columns are live formulas — do not paste over them. Parameters live on Lookups.
A4: Order Nbr. | B4: Order Type | C4: Order Date | D4: Customer | E4: Main Account | F4: Category | G4: Warehouse | H4: Inventory ID | I4: Brand | J4: Item Description | K4: UOM | L4: Order Qty | M4: Unit Price (net) | N4: Backordered On | O4: Resolved On | P4: Window | Q4: Days (calendar) | R4: Days (working) | S4: Delay Label | T4: Start Date Verified? | U4: Episode No. | V4: Peak Backorder Qty | W4: Current Backorder Qty | X4: Shipped Qty | Y4: Shipped Late Qty | Z4: Cancelled Qty | AA4: Partial Fills | AB4: Fill Rate % | AC4: Line Order Value (KES) | AD4: Revenue at Risk (KES) | AE4: Value Fulfilled (KES) | AF4: Delayed Revenue (KES) | AG4: Revenue-Days Delayed | AH4: Lost Revenue (KES) | AI4: Resolution Type | AJ4: Reason Code | AK4: Reason Family | AL4: Reason Notes | AM4: Reason Set By | AN4: Reason Set At | AO4: Escalation Flag | AP4: Excluded from KPI? | AQ4: Exclusion Reason | AR4: Sync Run (opened) | AS4: Sync Run (resolved) | AT4: State | AU4: Order 1st open row | AV4: Item 1st open row
A5: SO363506 | B5: SO | C5: 46213 | D5: Khetia Drapers Ltd - Plus | E5: Khetia Drapers Ltd | F5: Modern Trade T2 | G5: FGS | H5: SIFTP0015 | I5: =IFERROR(INDEX(Lookups!$B$6:$B$10,MATCH(LEFT(H5,3),Lookups!$A$6:$A$10,0)),"(unmapped)") -> Sifa | J5: Sifa TP Emb. Unwrap. Twinpack 20x2s White | K5: CASE | L5: 1356 | M5: 142.55 | N5: 46213 | P5: =IF(ISBLANK(O5),TEXT(N5,"d mmm yyyy")&" – ongoing",IF(TEXT(N5,"mmmyyyy")=TEXT(O5,"mmmyyyy"),TEXT(N5,"d")&" – "&TEXT(O5,"d mmm yyyy"),IF(TEXT(N5,"yyyy")=TEXT(O5,"yyyy"),TEXT(N5,"d mmm")&" – "&TEXT(O5,"d mmm yyyy"),TEXT(N5,"d mmm yyyy")&" – "&TEXT(O5,"d mmm yyyy")))) -> 10 Jul 2026 – ongoing | Q5: =IF(ISBLANK(O5),Lookups!$B$16-N5,O5-N5) -> 16 | R5: =IF(ISBLANK(O5),NETWORKDAYS.INTL(N5,Lookups!$B$16,"0000001")-1,NETWORKDAYS.INTL(N5,O5,"0000001")-1) -> 13 | S5: =IF(R5=0,"Same Day",R5&IF(R5=1," Day Delay"," Days Delay")&IF(T5="Yes",""," (min.)")) -> 13 Days Delay | T5: Yes | U5: 1 | V5: 680 | W5: 420 | X5: 936 | Y5: 0 | Z5: 0 | AA5: 2 | AB5: =IFERROR(X5/(L5-Z5),"") -> 0.69026549 | AC5: =L5*M5 -> 193297.8 | AD5: =W5*M5 -> 59871 | AE5: =X5*M5 -> 133426.8 | AF5: =Y5*M5 -> 0 | AG5: =AF5*MAX(0,R5-Lookups!$B$17) -> 0 | AH5: =IF(ISBLANK(O5),IF(R5>Lookups!$B$18,W5*M5,0),Z5*M5) -> 59871 | AJ5: out_of_stock_production | AK5: PRODUCTION | AL5: Mill line 2 down 11-14 Jul | AM5: j.mwangi | AN5: 46214 | AO5: =IF(AND(R5>Lookups!$B$18,AD5>Lookups!$B$19),"ESCALATE",IF(AD5>Lookups!$B$20,"High value",IF(R5>Lookups!$B$18,"Aged","Monitor"))) -> ESCALATE | AP5: No | AR5: 48100 | AT5: =IF(ISBLANK(O5),"Open","Resolved") -> Open | AU5: =IF(AND($AT5="Open",$AP5="No",COUNTIFS($A$5:$A5,$A5,$AT$5:$AT5,"Open",$AP$5:$AP5,"No")=1),1,0) -> 1 | AV5: =IF(AND($AT5="Open",$AP5="No",COUNTIFS($H$5:$H5,$H5,$AT$5:$AT5,"Open",$AP$5:$AP5,"No")=1),1,0) -> 1
A6: SO363491 | B6: SO | C6: 46213 | D6: Khetia Drapers Ltd - Gigamart | E6: Khetia Drapers Ltd | F6: Modern Trade T2 | G6: FGS | H6: SIFTP0015 | I6: =IFERROR(INDEX(Lookups!$B$6:$B$10,MATCH(LEFT(H6,3),Lookups!$A$6:$A$10,0)),"(unmapped)") -> Sifa | J6: Sifa TP Emb. Unwrap. Twinpack 20x2s White | K6: CASE | L6: 1086 | M6: 142.55 | N6: 46213 | P6: =IF(ISBLANK(O6),TEXT(N6,"d mmm yyyy")&" – ongoing",IF(TEXT(N6,"mmmyyyy")=TEXT(O6,"mmmyyyy"),TEXT(N6,"d")&" – "&TEXT(O6,"d mmm yyyy"),IF(TEXT(N6,"yyyy")=TEXT(O6,"yyyy"),TEXT(N6,"d mmm")&" – "&TEXT(O6,"d mmm yyyy"),TEXT(N6,"d mmm yyyy")&" – "&TEXT(O6,"d mmm yyyy")))) -> 10 Jul 2026 – ongoing | Q6: =IF(ISBLANK(O6),Lookups!$B$16-N6,O6-N6) -> 16 | R6: =IF(ISBLANK(O6),NETWORKDAYS.INTL(N6,Lookups!$B$16,"0000001")-1,NETWORKDAYS.INTL(N6,O6,"0000001")-1) -> 13 | S6: =IF(R6=0,"Same Day",R6&IF(R6=1," Day Delay"," Days Delay")&IF(T6="Yes",""," (min.)")) -> 13 Days Delay | T6: Yes | U6: 1 | V6: 594 | W6: 528 | X6: 558 | Y6: 0 | Z6: 0 | AA6: 1 | AB6: =IFERROR(X6/(L6-Z6),"") -> 0.51381215 | AC6: =L6*M6 -> 154809.3 | AD6: =W6*M6 -> 75266.4 | AE6: =X6*M6 -> 79542.9 | AF6: =Y6*M6 -> 0 | AG6: =AF6*MAX(0,R6-Lookups!$B$17) -> 0 | AH6: =IF(ISBLANK(O6),IF(R6>Lookups!$B$18,W6*M6,0),Z6*M6) -> 75266.4 | AJ6: out_of_stock_production | AK6: PRODUCTION | AL6: Same mill event | AM6: j.mwangi | AN6: 46214 | AO6: =IF(AND(R6>Lookups!$B$18,AD6>Lookups!$B$19),"ESCALATE",IF(AD6>Lookups!$B$20,"High value",IF(R6>Lookups!$B$18,"Aged","Monitor"))) -> ESCALATE | AP6: No | AR6: 48103 | AT6: =IF(ISBLANK(O6),"Open","Resolved") -> Open | AU6: =IF(AND($AT6="Open",$AP6="No",COUNTIFS($A$5:$A6,$A6,$AT$5:$AT6,"Open",$AP$5:$AP6,"No")=1),1,0) -> 1 | AV6: =IF(AND($AT6="Open",$AP6="No",COUNTIFS($H$5:$H6,$H6,$AT$5:$AT6,"Open",$AP$5:$AP6,"No")=1),1,0) -> 0
A7: SO363495 | B7: SO | C7: 46213 | D7: Khetia Drapers Ltd - Eldoret CBD | E7: Khetia Drapers Ltd | F7: Modern Trade T2 | G7: FGS | H7: COSTP0004 | I7: =IFERROR(INDEX(Lookups!$B$6:$B$10,MATCH(LEFT(H7,3),Lookups!$A$6:$A$10,0)),"(unmapped)") -> Cosy | J7: Cosy TP Emb. Wrap. 40s Singles White | K7: CASE | L7: 1128 | M7: 64.55 | N7: 46213 | P7: =IF(ISBLANK(O7),TEXT(N7,"d mmm yyyy")&" – ongoing",IF(TEXT(N7,"mmmyyyy")=TEXT(O7,"mmmyyyy"),TEXT(N7,"d")&" – "&TEXT(O7,"d mmm yyyy"),IF(TEXT(N7,"yyyy")=TEXT(O7,"yyyy"),TEXT(N7,"d mmm")&" – "&TEXT(O7,"d mmm yyyy"),TEXT(N7,"d mmm yyyy")&" – "&TEXT(O7,"d mmm yyyy")))) -> 10 Jul 2026 – ongoing | Q7: =IF(ISBLANK(O7),Lookups!$B$16-N7,O7-N7) -> 16 | R7: =IF(ISBLANK(O7),NETWORKDAYS.INTL(N7,Lookups!$B$16,"0000001")-1,NETWORKDAYS.INTL(N7,O7,"0000001")-1) -> 13 | S7: =IF(R7=0,"Same Day",R7&IF(R7=1," Day Delay"," Days Delay")&IF(T7="Yes",""," (min.)")) -> 13 Days Delay | T7: Yes | U7: 1 | V7: 542 | W7: 510 | X7: 618 | Y7: 0 | Z7: 0 | AA7: 1 | AB7: =IFERROR(X7/(L7-Z7),"") -> 0.54787234 | AC7: =L7*M7 -> 72812.4 | AD7: =W7*M7 -> 32920.5 | AE7: =X7*M7 -> 39891.9 | AF7: =Y7*M7 -> 0 | AG7: =AF7*MAX(0,R7-Lookups!$B$17) -> 0 | AH7: =IF(ISBLANK(O7),IF(R7>Lookups!$B$18,W7*M7,0),Z7*M7) -> 32920.5 | AJ7: raw_material_stockout | AK7: PRODUCTION | AL7: Parent reel short shipped | AM7: j.mwangi | AN7: 46215 | AO7: =IF(AND(R7>Lookups!$B$18,AD7>Lookups!$B$19),"ESCALATE",IF(AD7>Lookups!$B$20,"High value",IF(R7>Lookups!$B$18,"Aged","Monitor"))) -> ESCALATE | AP7: No | AR7: 48106 | AT7: =IF(ISBLANK(O7),"Open","Resolved") -> Open | AU7: =IF(AND($AT7="Open",$AP7="No",COUNTIFS($A$5:$A7,$A7,$AT$5:$AT7,"Open",$AP$5:$AP7,"No")=1),1,0) -> 1 | AV7: =IF(AND($AT7="Open",$AP7="No",COUNTIFS($H$5:$H7,$H7,$AT$5:$AT7,"Open",$AP$5:$AP7,"No")=1),1,0) -> 1
A8: SO363507 | B8: SO | C8: 46213 | D8: Khetia Drapers Ltd - Kakamega Poa | E8: Khetia Drapers Ltd | F8: Modern Trade T2 | G8: FGS | H8: COSTP0006 | I8: =IFERROR(INDEX(Lookups!$B$6:$B$10,MATCH(LEFT(H8,3),Lookups!$A$6:$A$10,0)),"(unmapped)") -> Cosy | J8: Cosy TP Emb. Unwrap. 4x10s White | K8: CASE | L8: 876 | M8: 64.55 | N8: 46213 | O8: 46225 | P8: =IF(ISBLANK(O8),TEXT(N8,"d mmm yyyy")&" – ongoing",IF(TEXT(N8,"mmmyyyy")=TEXT(O8,"mmmyyyy"),TEXT(N8,"d")&" – "&TEXT(O8,"d mmm yyyy"),IF(TEXT(N8,"yyyy")=TEXT(O8,"yyyy"),TEXT(N8,"d mmm")&" – "&TEXT(O8,"d mmm yyyy"),TEXT(N8,"d mmm yyyy")&" – "&TEXT(O8,"d mmm yyyy")))) -> 10 – 22 Jul 2026 | Q8: =IF(ISBLANK(O8),Lookups!$B$16-N8,O8-N8) -> 12 | R8: =IF(ISBLANK(O8),NETWORKDAYS.INTL(N8,Lookups!$B$16,"0000001")-1,NETWORKDAYS.INTL(N8,O8,"0000001")-1) -> 10 | S8: =IF(R8=0,"Same Day",R8&IF(R8=1," Day Delay"," Days Delay")&IF(T8="Yes",""," (min.)")) -> 10 Days Delay | T8: Yes | U8: 1 | V8: 514 | W8: 0 | X8: 876 | Y8: 514 | Z8: 0 | AA8: 3 | AB8: =IFERROR(X8/(L8-Z8),"") -> 1 | AC8: =L8*M8 -> 56545.8 | AD8: =W8*M8 -> 0 | AE8: =X8*M8 -> 56545.8 | AF8: =Y8*M8 -> 33178.7 | AG8: =AF8*MAX(0,R8-Lookups!$B$17) -> 265429.6 | AH8: =IF(ISBLANK(O8),IF(R8>Lookups!$B$18,W8*M8,0),Z8*M8) -> 0 | AI8: shipped_full | AJ8: out_of_stock_production | AK8: PRODUCTION | AL8: Cleared on 22 Jul run | AM8: j.mwangi | AN8: 46215 | AO8: =IF(AND(R8>Lookups!$B$18,AD8>Lookups!$B$19),"ESCALATE",IF(AD8>Lookups!$B$20,"High value",IF(R8>Lookups!$B$18,"Aged","Monitor"))) -> Aged | AP8: No | AR8: 48109 | AS8: 48189 | AT8: =IF(ISBLANK(O8),"Open","Resolved") -> Resolved | AU8: =IF(AND($AT8="Open",$AP8="No",COUNTIFS($A$5:$A8,$A8,$AT$5:$AT8,"Open",$AP$5:$AP8,"No")=1),1,0) -> 0 | AV8: =IF(AND($AT8="Open",$AP8="No",COUNTIFS($H$5:$H8,$H8,$AT$5:$AT8,"Open",$AP$5:$AP8,"No")=1),1,0) -> 0
A9: SO363603 | B9: SO | C9: 46213 | D9: Khetia Drapers Ltd - Thika | E9: Khetia Drapers Ltd | F9: Modern Trade T2 | G9: FGS | H9: FAYTP0013 | I9: =IFERROR(INDEX(Lookups!$B$6:$B$10,MATCH(LEFT(H9,3),Lookups!$A$6:$A$10,0)),"(unmapped)") -> Fay | J9: Fay TP Emb. Wrap. 40s Singles White | K9: CASE | L9: 965 | M9: 73.3 | N9: 46213 | O9: 46223 | P9: =IF(ISBLANK(O9),TEXT(N9,"d mmm yyyy")&" – ongoing",IF(TEXT(N9,"mmmyyyy")=TEXT(O9,"mmmyyyy"),TEXT(N9,"d")&" – "&TEXT(O9,"d mmm yyyy"),IF(TEXT(N9,"yyyy")=TEXT(O9,"yyyy"),TEXT(N9,"d mmm")&" – "&TEXT(O9,"d mmm yyyy"),TEXT(N9,"d mmm yyyy")&" – "&TEXT(O9,"d mmm yyyy")))) -> 10 – 20 Jul 2026 | Q9: =IF(ISBLANK(O9),Lookups!$B$16-N9,O9-N9) -> 10 | R9: =IF(ISBLANK(O9),NETWORKDAYS.INTL(N9,Lookups!$B$16,"0000001")-1,NETWORKDAYS.INTL(N9,O9,"0000001")-1) -> 8 | S9: =IF(R9=0,"Same Day",R9&IF(R9=1," Day Delay"," Days Delay")&IF(T9="Yes",""," (min.)")) -> 8 Days Delay | T9: Yes | U9: 1 | V9: 478 | W9: 0 | X9: 890 | Y9: 478 | Z9: 75 | AA9: 2 | AB9: =IFERROR(X9/(L9-Z9),"") -> 1 | AC9: =L9*M9 -> 70734.5 | AD9: =W9*M9 -> 0 | AE9: =X9*M9 -> 65237 | AF9: =Y9*M9 -> 35037.4 | AG9: =AF9*MAX(0,R9-Lookups!$B$17) -> 210224.4 | AH9: =IF(ISBLANK(O9),IF(R9>Lookups!$B$18,W9*M9,0),Z9*M9) -> 5497.5 | AI9: shipped_partial | AJ9: out_of_stock_production | AK9: PRODUCTION | AL9: 75 CASE cancelled by buyer | AM9: j.mwangi | AN9: 46215 | AO9: =IF(AND(R9>Lookups!$B$18,AD9>Lookups!$B$19),"ESCALATE",IF(AD9>Lookups!$B$20,"High value",IF(R9>Lookups!$B$18,"Aged","Monitor"))) -> Aged | AP9: No | AR9: 48112 | AS9: 48192 | AT9: =IF(ISBLANK(O9),"Open","Resolved") -> Resolved | AU9: =IF(AND($AT9="Open",$AP9="No",COUNTIFS($A$5:$A9,$A9,$AT$5:$AT9,"Open",$AP$5:$AP9,"No")=1),1,0) -> 0 | AV9: =IF(AND($AT9="Open",$AP9="No",COUNTIFS($H$5:$H9,$H9,$AT$5:$AT9,"Open",$AP$5:$AP9,"No")=1),1,0) -> 0
A10: SO367035 | B10: SO | C10: 46226 | D10: Majid Al Futtaim Hypermarkets Ltd - Business Bay Square | E10: Majid Al Futtaim Hypermarkets Ltd | F10: Modern Trade T1 | G10: FGS | H10: FAYFL0010 | I10: =IFERROR(INDEX(Lookups!$B$6:$B$10,MATCH(LEFT(H10,3),Lookups!$A$6:$A$10,0)),"(unmapped)") -> Fay | J10: Fay Aluminium Foil Catering (45x50m) | K10: ROLL | L10: 24 | M10: 2542.53 | N10: 46226 | P10: =IF(ISBLANK(O10),TEXT(N10,"d mmm yyyy")&" – ongoing",IF(TEXT(N10,"mmmyyyy")=TEXT(O10,"mmmyyyy"),TEXT(N10,"d")&" – "&TEXT(O10,"d mmm yyyy"),IF(TEXT(N10,"yyyy")=TEXT(O10,"yyyy"),TEXT(N10,"d mmm")&" – "&TEXT(O10,"d mmm yyyy"),TEXT(N10,"d mmm yyyy")&" – "&TEXT(O10,"d mmm yyyy")))) -> 23 Jul 2026 – ongoing | Q10: =IF(ISBLANK(O10),Lookups!$B$16-N10,O10-N10) -> 3 | R10: =IF(ISBLANK(O10),NETWORKDAYS.INTL(N10,Lookups!$B$16,"0000001")-1,NETWORKDAYS.INTL(N10,O10,"0000001")-1) -> 2 | S10: =IF(R10=0,"Same Day",R10&IF(R10=1," Day Delay"," Days Delay")&IF(T10="Yes",""," (min.)")) -> 2 Days Delay | T10: Yes | U10: 1 | V10: 24 | W10: 24 | X10: 0 | Y10: 0 | Z10: 0 | AA10: 0 | AB10: =IFERROR(X10/(L10-Z10),"") -> 0 | AC10: =L10*M10 -> 61020.72 | AD10: =W10*M10 -> 61020.72 | AE10: =X10*M10 -> 0 | AF10: =Y10*M10 -> 0 | AG10: =AF10*MAX(0,R10-Lookups!$B$17) -> 0 | AH10: =IF(ISBLANK(O10),IF(R10>Lookups!$B$18,W10*M10,0),Z10*M10) -> 0 | AJ10: out_of_stock_procurement | AK10: PROCUREMENT | AL10: Import ETA 29 Jul | AM10: a.otieno | AN10: 46226 | AO10: =IF(AND(R10>Lookups!$B$18,AD10>Lookups!$B$19),"ESCALATE",IF(AD10>Lookups!$B$20,"High value",IF(R10>Lookups!$B$18,"Aged","Monitor"))) -> Monitor | AP10: No | AR10: 48115 | AT10: =IF(ISBLANK(O10),"Open","Resolved") -> Open | AU10: =IF(AND($AT10="Open",$AP10="No",COUNTIFS($A$5:$A10,$A10,$AT$5:$AT10,"Open",$AP$5:$AP10,"No")=1),1,0) -> 1 | AV10: =IF(AND($AT10="Open",$AP10="No",COUNTIFS($H$5:$H10,$H10,$AT$5:$AT10,"Open",$AP$5:$AP10,"No")=1),1,0) -> 1
A11: SO367021 | B11: SO | C11: 46226 | D11: Majid Al Futtaim Hypermarkets Ltd - The Hub | E11: Majid Al Futtaim Hypermarkets Ltd | F11: Modern Trade T1 | G11: FGS | H11: FAYFL0010 | I11: =IFERROR(INDEX(Lookups!$B$6:$B$10,MATCH(LEFT(H11,3),Lookups!$A$6:$A$10,0)),"(unmapped)") -> Fay | J11: Fay Aluminium Foil Catering (45x50m) | K11: ROLL | L11: 18 | M11: 1649.14 | N11: 46226 | P11: =IF(ISBLANK(O11),TEXT(N11,"d mmm yyyy")&" – ongoing",IF(TEXT(N11,"mmmyyyy")=TEXT(O11,"mmmyyyy"),TEXT(N11,"d")&" – "&TEXT(O11,"d mmm yyyy"),IF(TEXT(N11,"yyyy")=TEXT(O11,"yyyy"),TEXT(N11,"d mmm")&" – "&TEXT(O11,"d mmm yyyy"),TEXT(N11,"d mmm yyyy")&" – "&TEXT(O11,"d mmm yyyy")))) -> 23 Jul 2026 – ongoing | Q11: =IF(ISBLANK(O11),Lookups!$B$16-N11,O11-N11) -> 3 | R11: =IF(ISBLANK(O11),NETWORKDAYS.INTL(N11,Lookups!$B$16,"0000001")-1,NETWORKDAYS.INTL(N11,O11,"0000001")-1) -> 2 | S11: =IF(R11=0,"Same Day",R11&IF(R11=1," Day Delay"," Days Delay")&IF(T11="Yes",""," (min.)")) -> 2 Days Delay | T11: Yes | U11: 1 | V11: 18 | W11: 18 | X11: 0 | Y11: 0 | Z11: 0 | AA11: 0 | AB11: =IFERROR(X11/(L11-Z11),"") -> 0 | AC11: =L11*M11 -> 29684.52 | AD11: =W11*M11 -> 29684.52 | AE11: =X11*M11 -> 0 | AF11: =Y11*M11 -> 0 | AG11: =AF11*MAX(0,R11-Lookups!$B$17) -> 0 | AH11: =IF(ISBLANK(O11),IF(R11>Lookups!$B$18,W11*M11,0),Z11*M11) -> 0 | AJ11: out_of_stock_procurement | AK11: PROCUREMENT | AL11: Same import | AM11: a.otieno | AN11: 46226 | AO11: =IF(AND(R11>Lookups!$B$18,AD11>Lookups!$B$19),"ESCALATE",IF(AD11>Lookups!$B$20,"High value",IF(R11>Lookups!$B$18,"Aged","Monitor"))) -> Monitor | AP11: No | AR11: 48118 | AT11: =IF(ISBLANK(O11),"Open","Resolved") -> Open | AU11: =IF(AND($AT11="Open",$AP11="No",COUNTIFS($A$5:$A11,$A11,$AT$5:$AT11,"Open",$AP$5:$AP11,"No")=1),1,0) -> 1 | AV11: =IF(AND($AT11="Open",$AP11="No",COUNTIFS($H$5:$H11,$H11,$AT$5:$AT11,"Open",$AP$5:$AP11,"No")=1),1,0) -> 0
A12: SO364962 | B12: SO | C12: 46219 | D12: Quick Mart Ltd- Nakuru Statehouse | E12: Quick Mart Ltd | F12: Modern Trade T1 | G12: FGS | H12: FAYFL0010 | I12: =IFERROR(INDEX(Lookups!$B$6:$B$10,MATCH(LEFT(H12,3),Lookups!$A$6:$A$10,0)),"(unmapped)") -> Fay | J12: Fay Aluminium Foil Catering (45x50m) | K12: ROLL | L12: 12 | M12: 2542.53 | N12: 46219 | P12: =IF(ISBLANK(O12),TEXT(N12,"d mmm yyyy")&" – ongoing",IF(TEXT(N12,"mmmyyyy")=TEXT(O12,"mmmyyyy"),TEXT(N12,"d")&" – "&TEXT(O12,"d mmm yyyy"),IF(TEXT(N12,"yyyy")=TEXT(O12,"yyyy"),TEXT(N12,"d mmm")&" – "&TEXT(O12,"d mmm yyyy"),TEXT(N12,"d mmm yyyy")&" – "&TEXT(O12,"d mmm yyyy")))) -> 16 Jul 2026 – ongoing | Q12: =IF(ISBLANK(O12),Lookups!$B$16-N12,O12-N12) -> 10 | R12: =IF(ISBLANK(O12),NETWORKDAYS.INTL(N12,Lookups!$B$16,"0000001")-1,NETWORKDAYS.INTL(N12,O12,"0000001")-1) -> 8 | S12: =IF(R12=0,"Same Day",R12&IF(R12=1," Day Delay"," Days Delay")&IF(T12="Yes",""," (min.)")) -> 8 Days Delay | T12: Yes | U12: 1 | V12: 12 | W12: 12 | X12: 0 | Y12: 0 | Z12: 0 | AA12: 0 | AB12: =IFERROR(X12/(L12-Z12),"") -> 0 | AC12: =L12*M12 -> 30510.36 | AD12: =W12*M12 -> 30510.36 | AE12: =X12*M12 -> 0 | AF12: =Y12*M12 -> 0 | AG12: =AF12*MAX(0,R12-Lookups!$B$17) -> 0 | AH12: =IF(ISBLANK(O12),IF(R12>Lookups!$B$18,W12*M12,0),Z12*M12) -> 30510.36 | AJ12: out_of_stock_procurement | AK12: PROCUREMENT | AL12: Same import | AM12: a.otieno | AN12: 46220 | AO12: =IF(AND(R12>Lookups!$B$18,AD12>Lookups!$B$19),"ESCALATE",IF(AD12>Lookups!$B$20,"High value",IF(R12>Lookups!$B$18,"Aged","Monitor"))) -> ESCALATE | AP12: No | AR12: 48121 | AT12: =IF(ISBLANK(O12),"Open","Resolved") -> Open | AU12: =IF(AND($AT12="Open",$AP12="No",COUNTIFS($A$5:$A12,$A12,$AT$5:$AT12,"Open",$AP$5:$AP12,"No")=1),1,0) -> 1 | AV12: =IF(AND($AT12="Open",$AP12="No",COUNTIFS($H$5:$H12,$H12,$AT$5:$AT12,"Open",$AP$5:$AP12,"No")=1),1,0) -> 0
A13: SO364948 | B13: SO | C13: 46218 | D13: Quick Mart Ltd - Rongai | E13: Quick Mart Ltd | F13: Modern Trade T1 | G13: FGS | H13: FAYCL0009 | I13: =IFERROR(INDEX(Lookups!$B$6:$B$10,MATCH(LEFT(H13,3),Lookups!$A$6:$A$10,0)),"(unmapped)") -> Fay | J13: Fay Cling Film Catering 30cmx300m GP | K13: PIECE | L13: 6 | M13: 2756.9 | N13: 46218 | P13: =IF(ISBLANK(O13),TEXT(N13,"d mmm yyyy")&" – ongoing",IF(TEXT(N13,"mmmyyyy")=TEXT(O13,"mmmyyyy"),TEXT(N13,"d")&" – "&TEXT(O13,"d mmm yyyy"),IF(TEXT(N13,"yyyy")=TEXT(O13,"yyyy"),TEXT(N13,"d mmm")&" – "&TEXT(O13,"d mmm yyyy"),TEXT(N13,"d mmm yyyy")&" – "&TEXT(O13,"d mmm yyyy")))) -> 15 Jul 2026 – ongoing | Q13: =IF(ISBLANK(O13),Lookups!$B$16-N13,O13-N13) -> 11 | R13: =IF(ISBLANK(O13),NETWORKDAYS.INTL(N13,Lookups!$B$16,"0000001")-1,NETWORKDAYS.INTL(N13,O13,"0000001")-1) -> 9 | S13: =IF(R13=0,"Same Day",R13&IF(R13=1," Day Delay"," Days Delay")&IF(T13="Yes",""," (min.)")) -> 9 Days Delay | T13: Yes | U13: 1 | V13: 6 | W13: 6 | X13: 0 | Y13: 0 | Z13: 0 | AA13: 0 | AB13: =IFERROR(X13/(L13-Z13),"") -> 0 | AC13: =L13*M13 -> 16541.4 | AD13: =W13*M13 -> 16541.4 | AE13: =X13*M13 -> 0 | AF13: =Y13*M13 -> 0 | AG13: =AF13*MAX(0,R13-Lookups!$B$17) -> 0 | AH13: =IF(ISBLANK(O13),IF(R13>Lookups!$B$18,W13*M13,0),Z13*M13) -> 16541.4 | AJ13: conversion_delays | AK13: PRODUCTION | AL13: Awaiting converting slot | AM13: a.otieno | AN13: 46220 | AO13: =IF(AND(R13>Lookups!$B$18,AD13>Lookups!$B$19),"ESCALATE",IF(AD13>Lookups!$B$20,"High value",IF(R13>Lookups!$B$18,"Aged","Monitor"))) -> Aged | AP13: No | AR13: 48124 | AT13: =IF(ISBLANK(O13),"Open","Resolved") -> Open | AU13: =IF(AND($AT13="Open",$AP13="No",COUNTIFS($A$5:$A13,$A13,$AT$5:$AT13,"Open",$AP$5:$AP13,"No")=1),1,0) -> 1 | AV13: =IF(AND($AT13="Open",$AP13="No",COUNTIFS($H$5:$H13,$H13,$AT$5:$AT13,"Open",$AP$5:$AP13,"No")=1),1,0) -> 1
A14: SO364955 | B14: SO | C14: 46218 | D14: Quick Mart Ltd - Nakuru | E14: Quick Mart Ltd | F14: Modern Trade T1 | G14: FGS | H14: FAYCL0009 | I14: =IFERROR(INDEX(Lookups!$B$6:$B$10,MATCH(LEFT(H14,3),Lookups!$A$6:$A$10,0)),"(unmapped)") -> Fay | J14: Fay Cling Film Catering 30cmx300m GP | K14: PIECE | L14: 6 | M14: 2756.9 | N14: 46218 | P14: =IF(ISBLANK(O14),TEXT(N14,"d mmm yyyy")&" – ongoing",IF(TEXT(N14,"mmmyyyy")=TEXT(O14,"mmmyyyy"),TEXT(N14,"d")&" – "&TEXT(O14,"d mmm yyyy"),IF(TEXT(N14,"yyyy")=TEXT(O14,"yyyy"),TEXT(N14,"d mmm")&" – "&TEXT(O14,"d mmm yyyy"),TEXT(N14,"d mmm yyyy")&" – "&TEXT(O14,"d mmm yyyy")))) -> 15 Jul 2026 – ongoing | Q14: =IF(ISBLANK(O14),Lookups!$B$16-N14,O14-N14) -> 11 | R14: =IF(ISBLANK(O14),NETWORKDAYS.INTL(N14,Lookups!$B$16,"0000001")-1,NETWORKDAYS.INTL(N14,O14,"0000001")-1) -> 9 | S14: =IF(R14=0,"Same Day",R14&IF(R14=1," Day Delay"," Days Delay")&IF(T14="Yes",""," (min.)")) -> 9 Days Delay | T14: Yes | U14: 1 | V14: 6 | W14: 6 | X14: 0 | Y14: 0 | Z14: 0 | AA14: 0 | AB14: =IFERROR(X14/(L14-Z14),"") -> 0 | AC14: =L14*M14 -> 16541.4 | AD14: =W14*M14 -> 16541.4 | AE14: =X14*M14 -> 0 | AF14: =Y14*M14 -> 0 | AG14: =AF14*MAX(0,R14-Lookups!$B$17) -> 0 | AH14: =IF(ISBLANK(O14),IF(R14>Lookups!$B$18,W14*M14,0),Z14*M14) -> 16541.4 | AJ14: conversion_delays | AK14: PRODUCTION | AL14: Awaiting converting slot | AM14: a.otieno | AN14: 46220 | AO14: =IF(AND(R14>Lookups!$B$18,AD14>Lookups!$B$19),"ESCALATE",IF(AD14>Lookups!$B$20,"High value",IF(R14>Lookups!$B$18,"Aged","Monitor"))) -> Aged | AP14: No | AR14: 48127 | AT14: =IF(ISBLANK(O14),"Open","Resolved") -> Open | AU14: =IF(AND($AT14="Open",$AP14="No",COUNTIFS($A$5:$A14,$A14,$AT$5:$AT14,"Open",$AP$5:$AP14,"No")=1),1,0) -> 1 | AV14: =IF(AND($AT14="Open",$AP14="No",COUNTIFS($H$5:$H14,$H14,$AT$5:$AT14,"Open",$AP$5:$AP14,"No")=1),1,0) -> 0
A15: SO365985 | B15: SO | C15: 46223 | D15: Sam West Distributors LTD | E15: Sam West Distributors LTD | F15: General Trade | G15: FGS | H15: TISTP0008 | I15: =IFERROR(INDEX(Lookups!$B$6:$B$10,MATCH(LEFT(H15,3),Lookups!$A$6:$A$10,0)),"(unmapped)") -> Tishu Poa | J15: Tishu Poa TP Emb. Wrap. 4x10s White 100s | K15: CASE | L15: 980 | M15: 860.17 | N15: 46223 | O15: 46225 | P15: =IF(ISBLANK(O15),TEXT(N15,"d mmm yyyy")&" – ongoing",IF(TEXT(N15,"mmmyyyy")=TEXT(O15,"mmmyyyy"),TEXT(N15,"d")&" – "&TEXT(O15,"d mmm yyyy"),IF(TEXT(N15,"yyyy")=TEXT(O15,"yyyy"),TEXT(N15,"d mmm")&" – "&TEXT(O15,"d mmm yyyy"),TEXT(N15,"d mmm yyyy")&" – "&TEXT(O15,"d mmm yyyy")))) -> 20 – 22 Jul 2026 | Q15: =IF(ISBLANK(O15),Lookups!$B$16-N15,O15-N15) -> 2 | R15: =IF(ISBLANK(O15),NETWORKDAYS.INTL(N15,Lookups!$B$16,"0000001")-1,NETWORKDAYS.INTL(N15,O15,"0000001")-1) -> 2 | S15: =IF(R15=0,"Same Day",R15&IF(R15=1," Day Delay"," Days Delay")&IF(T15="Yes",""," (min.)")) -> 2 Days Delay | T15: Yes | U15: 1 | V15: 262 | W15: 0 | X15: 980 | Y15: 262 | Z15: 0 | AA15: 3 | AB15: =IFERROR(X15/(L15-Z15),"") -> 1 | AC15: =L15*M15 -> 842966.6 | AD15: =W15*M15 -> 0 | AE15: =X15*M15 -> 842966.6 | AF15: =Y15*M15 -> 225364.54 | AG15: =AF15*MAX(0,R15-Lookups!$B$17) -> 0 | AH15: =IF(ISBLANK(O15),IF(R15>Lookups!$B$18,W15*M15,0),Z15*M15) -> 0 | AI15: shipped_full | AJ15: transfer_delays | AK15: LOGISTICS | AL15: Inter-warehouse transfer 2 days late | AM15: p.kamau | AN15: 46224 | AO15: =IF(AND(R15>Lookups!$B$18,AD15>Lookups!$B$19),"ESCALATE",IF(AD15>Lookups!$B$20,"High value",IF(R15>Lookups!$B$18,"Aged","Monitor"))) -> Monitor | AP15: No | AR15: 48130 | AS15: 48210 | AT15: =IF(ISBLANK(O15),"Open","Resolved") -> Resolved | AU15: =IF(AND($AT15="Open",$AP15="No",COUNTIFS($A$5:$A15,$A15,$AT$5:$AT15,"Open",$AP$5:$AP15,"No")=1),1,0) -> 0 | AV15: =IF(AND($AT15="Open",$AP15="No",COUNTIFS($H$5:$H15,$H15,$AT$5:$AT15,"Open",$AP$5:$AP15,"No")=1),1,0) -> 0
A16: SO367051 | B16: SO | C16: 46226 | D16: Stage Mattresses Ltd | E16: Stage Mattresses Ltd | F16: General Trade | G16: FGS | H16: COWGT0001 | I16: =IFERROR(INDEX(Lookups!$B$6:$B$10,MATCH(LEFT(H16,3),Lookups!$A$6:$A$10,0)),"(unmapped)") -> Cow & Gate | J16: Cow & Gate First 400g | K16: CAN | L16: 36 | M16: 1035 | N16: 46226 | P16: =IF(ISBLANK(O16),TEXT(N16,"d mmm yyyy")&" – ongoing",IF(TEXT(N16,"mmmyyyy")=TEXT(O16,"mmmyyyy"),TEXT(N16,"d")&" – "&TEXT(O16,"d mmm yyyy"),IF(TEXT(N16,"yyyy")=TEXT(O16,"yyyy"),TEXT(N16,"d mmm")&" – "&TEXT(O16,"d mmm yyyy"),TEXT(N16,"d mmm yyyy")&" – "&TEXT(O16,"d mmm yyyy")))) -> 23 Jul 2026 – ongoing | Q16: =IF(ISBLANK(O16),Lookups!$B$16-N16,O16-N16) -> 3 | R16: =IF(ISBLANK(O16),NETWORKDAYS.INTL(N16,Lookups!$B$16,"0000001")-1,NETWORKDAYS.INTL(N16,O16,"0000001")-1) -> 2 | S16: =IF(R16=0,"Same Day",R16&IF(R16=1," Day Delay"," Days Delay")&IF(T16="Yes",""," (min.)")) -> 2 Days Delay (min.) | T16: No (estimated) | U16: 1 | V16: 36 | W16: 36 | X16: 0 | Y16: 0 | Z16: 0 | AA16: 0 | AB16: =IFERROR(X16/(L16-Z16),"") -> 0 | AC16: =L16*M16 -> 37260 | AD16: =W16*M16 -> 37260 | AE16: =X16*M16 -> 0 | AF16: =Y16*M16 -> 0 | AG16: =AF16*MAX(0,R16-Lookups!$B$17) -> 0 | AH16: =IF(ISBLANK(O16),IF(R16>Lookups!$B$18,W16*M16,0),Z16*M16) -> 0 | AJ16: out_of_stock_msa | AK16: PROCUREMENT | AL16: MSA allocation pending | AO16: =IF(AND(R16>Lookups!$B$18,AD16>Lookups!$B$19),"ESCALATE",IF(AD16>Lookups!$B$20,"High value",IF(R16>Lookups!$B$18,"Aged","Monitor"))) -> Monitor | AP16: No | AR16: 48133 | AT16: =IF(ISBLANK(O16),"Open","Resolved") -> Open | AU16: =IF(AND($AT16="Open",$AP16="No",COUNTIFS($A$5:$A16,$A16,$AT$5:$AT16,"Open",$AP$5:$AP16,"No")=1),1,0) -> 1 | AV16: =IF(AND($AT16="Open",$AP16="No",COUNTIFS($H$5:$H16,$H16,$AT$5:$AT16,"Open",$AP$5:$AP16,"No")=1),1,0) -> 1
A17: SO367174 | B17: SO | C17: 46226 | D17: Goodlife Pharmacy Ltd | E17: Goodlife Pharmacy Ltd | F17: Pharmacy | G17: FGS | H17: COWGT0002 | I17: =IFERROR(INDEX(Lookups!$B$6:$B$10,MATCH(LEFT(H17,3),Lookups!$A$6:$A$10,0)),"(unmapped)") -> Cow & Gate | J17: Cow & Gate Follow Up 400g | K17: CAN | L17: 1188 | M17: 1593.04 | N17: 46226 | P17: =IF(ISBLANK(O17),TEXT(N17,"d mmm yyyy")&" – ongoing",IF(TEXT(N17,"mmmyyyy")=TEXT(O17,"mmmyyyy"),TEXT(N17,"d")&" – "&TEXT(O17,"d mmm yyyy"),IF(TEXT(N17,"yyyy")=TEXT(O17,"yyyy"),TEXT(N17,"d mmm")&" – "&TEXT(O17,"d mmm yyyy"),TEXT(N17,"d mmm yyyy")&" – "&TEXT(O17,"d mmm yyyy")))) -> 23 Jul 2026 – ongoing | Q17: =IF(ISBLANK(O17),Lookups!$B$16-N17,O17-N17) -> 3 | R17: =IF(ISBLANK(O17),NETWORKDAYS.INTL(N17,Lookups!$B$16,"0000001")-1,NETWORKDAYS.INTL(N17,O17,"0000001")-1) -> 2 | S17: =IF(R17=0,"Same Day",R17&IF(R17=1," Day Delay"," Days Delay")&IF(T17="Yes",""," (min.)")) -> 2 Days Delay | T17: Yes | U17: 1 | V17: 1188 | W17: 1188 | X17: 0 | Y17: 0 | Z17: 0 | AA17: 0 | AB17: =IFERROR(X17/(L17-Z17),"") -> 0 | AC17: =L17*M17 -> 1892531.5 | AD17: =W17*M17 -> 1892531.5 | AE17: =X17*M17 -> 0 | AF17: =Y17*M17 -> 0 | AG17: =AF17*MAX(0,R17-Lookups!$B$17) -> 0 | AH17: =IF(ISBLANK(O17),IF(R17>Lookups!$B$18,W17*M17,0),Z17*M17) -> 0 | AJ17: (unreasoned) | AK17: UNCLASSIFIED | AO17: =IF(AND(R17>Lookups!$B$18,AD17>Lookups!$B$19),"ESCALATE",IF(AD17>Lookups!$B$20,"High value",IF(R17>Lookups!$B$18,"Aged","Monitor"))) -> High value | AP17: No | AR17: 48136 | AT17: =IF(ISBLANK(O17),"Open","Resolved") -> Open | AU17: =IF(AND($AT17="Open",$AP17="No",COUNTIFS($A$5:$A17,$A17,$AT$5:$AT17,"Open",$AP$5:$AP17,"No")=1),1,0) -> 1 | AV17: =IF(AND($AT17="Open",$AP17="No",COUNTIFS($H$5:$H17,$H17,$AT$5:$AT17,"Open",$AP$5:$AP17,"No")=1),1,0) -> 1
A18: SO367113 | B18: SO | C18: 46226 | D18: Ava Apotheke Ltd | E18: Ava Apotheke Ltd | F18: Pharmacy | G18: FGS | H18: COWGT0001 | I18: =IFERROR(INDEX(Lookups!$B$6:$B$10,MATCH(LEFT(H18,3),Lookups!$A$6:$A$10,0)),"(unmapped)") -> Cow & Gate | J18: Cow & Gate First 400g | K18: CAN | L18: 18 | M18: 2492.85 | N18: 46226 | P18: =IF(ISBLANK(O18),TEXT(N18,"d mmm yyyy")&" – ongoing",IF(TEXT(N18,"mmmyyyy")=TEXT(O18,"mmmyyyy"),TEXT(N18,"d")&" – "&TEXT(O18,"d mmm yyyy"),IF(TEXT(N18,"yyyy")=TEXT(O18,"yyyy"),TEXT(N18,"d mmm")&" – "&TEXT(O18,"d mmm yyyy"),TEXT(N18,"d mmm yyyy")&" – "&TEXT(O18,"d mmm yyyy")))) -> 23 Jul 2026 – ongoing | Q18: =IF(ISBLANK(O18),Lookups!$B$16-N18,O18-N18) -> 3 | R18: =IF(ISBLANK(O18),NETWORKDAYS.INTL(N18,Lookups!$B$16,"0000001")-1,NETWORKDAYS.INTL(N18,O18,"0000001")-1) -> 2 | S18: =IF(R18=0,"Same Day",R18&IF(R18=1," Day Delay"," Days Delay")&IF(T18="Yes",""," (min.)")) -> 2 Days Delay | T18: Yes | U18: 1 | V18: 18 | W18: 18 | X18: 0 | Y18: 0 | Z18: 0 | AA18: 0 | AB18: =IFERROR(X18/(L18-Z18),"") -> 0 | AC18: =L18*M18 -> 44871.3 | AD18: =W18*M18 -> 44871.3 | AE18: =X18*M18 -> 0 | AF18: =Y18*M18 -> 0 | AG18: =AF18*MAX(0,R18-Lookups!$B$17) -> 0 | AH18: =IF(ISBLANK(O18),IF(R18>Lookups!$B$18,W18*M18,0),Z18*M18) -> 0 | AJ18: out_of_stock_msa | AK18: PROCUREMENT | AL18: MSA allocation pending | AM18: a.otieno | AN18: 46227 | AO18: =IF(AND(R18>Lookups!$B$18,AD18>Lookups!$B$19),"ESCALATE",IF(AD18>Lookups!$B$20,"High value",IF(R18>Lookups!$B$18,"Aged","Monitor"))) -> Monitor | AP18: No | AR18: 48139 | AT18: =IF(ISBLANK(O18),"Open","Resolved") -> Open | AU18: =IF(AND($AT18="Open",$AP18="No",COUNTIFS($A$5:$A18,$A18,$AT$5:$AT18,"Open",$AP$5:$AP18,"No")=1),1,0) -> 1 | AV18: =IF(AND($AT18="Open",$AP18="No",COUNTIFS($H$5:$H18,$H18,$AT$5:$AT18,"Open",$AP$5:$AP18,"No")=1),1,0) -> 0
A19: SO361051 | B19: SO | C19: 46204 | D19: Nairobi Java House Ltd | E19: Nairobi Java House Ltd | F19: Modern Trade T2 | G19: FGS | H19: SIFTP0009 | I19: =IFERROR(INDEX(Lookups!$B$6:$B$10,MATCH(LEFT(H19,3),Lookups!$A$6:$A$10,0)),"(unmapped)") -> Sifa | J19: Sifa TP Emb. Unwrap. 4x10s White | K19: CASE | L19: 150 | M19: 0.1 | N19: 46204 | P19: =IF(ISBLANK(O19),TEXT(N19,"d mmm yyyy")&" – ongoing",IF(TEXT(N19,"mmmyyyy")=TEXT(O19,"mmmyyyy"),TEXT(N19,"d")&" – "&TEXT(O19,"d mmm yyyy"),IF(TEXT(N19,"yyyy")=TEXT(O19,"yyyy"),TEXT(N19,"d mmm")&" – "&TEXT(O19,"d mmm yyyy"),TEXT(N19,"d mmm yyyy")&" – "&TEXT(O19,"d mmm yyyy")))) -> 1 Jul 2026 – ongoing | Q19: =IF(ISBLANK(O19),Lookups!$B$16-N19,O19-N19) -> 25 | R19: =IF(ISBLANK(O19),NETWORKDAYS.INTL(N19,Lookups!$B$16,"0000001")-1,NETWORKDAYS.INTL(N19,O19,"0000001")-1) -> 21 | S19: =IF(R19=0,"Same Day",R19&IF(R19=1," Day Delay"," Days Delay")&IF(T19="Yes",""," (min.)")) -> 21 Days Delay (min.) | T19: No (estimated) | U19: 1 | V19: 150 | W19: 36 | X19: 114 | Y19: 0 | Z19: 0 | AA19: 4 | AB19: =IFERROR(X19/(L19-Z19),"") -> 0.76 | AC19: =L19*M19 -> 15 | AD19: =W19*M19 -> 3.6 | AE19: =X19*M19 -> 11.4 | AF19: =Y19*M19 -> 0 | AG19: =AF19*MAX(0,R19-Lookups!$B$17) -> 0 | AH19: =IF(ISBLANK(O19),IF(R19>Lookups!$B$18,W19*M19,0),Z19*M19) -> 3.6 | AJ19: promo_product | AK19: COMMERCIAL | AL19: Free-goods line - excluded | AM19: p.kamau | AN19: 46208 | AO19: =IF(AND(R19>Lookups!$B$18,AD19>Lookups!$B$19),"ESCALATE",IF(AD19>Lookups!$B$20,"High value",IF(R19>Lookups!$B$18,"Aged","Monitor"))) -> Aged | AP19: Yes | AQ19: Free / zero-value promotional line | AR19: 48142 | AT19: =IF(ISBLANK(O19),"Open","Resolved") -> Open | AU19: =IF(AND($AT19="Open",$AP19="No",COUNTIFS($A$5:$A19,$A19,$AT$5:$AT19,"Open",$AP$5:$AP19,"No")=1),1,0) -> 0 | AV19: =IF(AND($AT19="Open",$AP19="No",COUNTIFS($H$5:$H19,$H19,$AT$5:$AT19,"Open",$AP$5:$AP19,"No")=1),1,0) -> 0
A20: SO363484 | B20: SO | C20: 46213 | D20: Maguna's Superstore (K) Ltd - EMBU | E20: Maguna's Super Stores (K) Ltd | F20: Modern Trade T2 | G20: FGS | H20: FAYTP0008 | I20: =IFERROR(INDEX(Lookups!$B$6:$B$10,MATCH(LEFT(H20,3),Lookups!$A$6:$A$10,0)),"(unmapped)") -> Fay | J20: Fay TP Emb. Unwrap. 4x10s White | K20: CASE | L20: 612 | M20: 89.1 | N20: 46213 | O20: 46219 | P20: =IF(ISBLANK(O20),TEXT(N20,"d mmm yyyy")&" – ongoing",IF(TEXT(N20,"mmmyyyy")=TEXT(O20,"mmmyyyy"),TEXT(N20,"d")&" – "&TEXT(O20,"d mmm yyyy"),IF(TEXT(N20,"yyyy")=TEXT(O20,"yyyy"),TEXT(N20,"d mmm")&" – "&TEXT(O20,"d mmm yyyy"),TEXT(N20,"d mmm yyyy")&" – "&TEXT(O20,"d mmm yyyy")))) -> 10 – 16 Jul 2026 | Q20: =IF(ISBLANK(O20),Lookups!$B$16-N20,O20-N20) -> 6 | R20: =IF(ISBLANK(O20),NETWORKDAYS.INTL(N20,Lookups!$B$16,"0000001")-1,NETWORKDAYS.INTL(N20,O20,"0000001")-1) -> 5 | S20: =IF(R20=0,"Same Day",R20&IF(R20=1," Day Delay"," Days Delay")&IF(T20="Yes",""," (min.)")) -> 5 Days Delay | T20: Yes | U20: 1 | V20: 182 | W20: 0 | X20: 612 | Y20: 182 | Z20: 0 | AA20: 2 | AB20: =IFERROR(X20/(L20-Z20),"") -> 1 | AC20: =L20*M20 -> 54529.2 | AD20: =W20*M20 -> 0 | AE20: =X20*M20 -> 54529.2 | AF20: =Y20*M20 -> 16216.2 | AG20: =AF20*MAX(0,R20-Lookups!$B$17) -> 48648.6 | AH20: =IF(ISBLANK(O20),IF(R20>Lookups!$B$18,W20*M20,0),Z20*M20) -> 0 | AI20: shipped_full | AJ20: did_not_pick_on_shipment | AK20: LOGISTICS | AL20: Picked short on first shipment | AM20: p.kamau | AN20: 46216 | AO20: =IF(AND(R20>Lookups!$B$18,AD20>Lookups!$B$19),"ESCALATE",IF(AD20>Lookups!$B$20,"High value",IF(R20>Lookups!$B$18,"Aged","Monitor"))) -> Monitor | AP20: No | AR20: 48145 | AS20: 48225 | AT20: =IF(ISBLANK(O20),"Open","Resolved") -> Resolved | AU20: =IF(AND($AT20="Open",$AP20="No",COUNTIFS($A$5:$A20,$A20,$AT$5:$AT20,"Open",$AP$5:$AP20,"No")=1),1,0) -> 0 | AV20: =IF(AND($AT20="Open",$AP20="No",COUNTIFS($H$5:$H20,$H20,$AT$5:$AT20,"Open",$AP$5:$AP20,"No")=1),1,0) -> 0
A21: SO363482 | B21: SO | C21: 46213 | D21: Maguna's Superstore (K) Ltd - EMBU | E21: Maguna's Super Stores (K) Ltd | F21: Modern Trade T2 | G21: FGS | H21: FAYTP0008 | I21: =IFERROR(INDEX(Lookups!$B$6:$B$10,MATCH(LEFT(H21,3),Lookups!$A$6:$A$10,0)),"(unmapped)") -> Fay | J21: Fay TP Emb. Unwrap. 4x10s White | K21: CASE | L21: 480 | M21: 89.1 | N21: 46214 | O21: 46217 | P21: =IF(ISBLANK(O21),TEXT(N21,"d mmm yyyy")&" – ongoing",IF(TEXT(N21,"mmmyyyy")=TEXT(O21,"mmmyyyy"),TEXT(N21,"d")&" – "&TEXT(O21,"d mmm yyyy"),IF(TEXT(N21,"yyyy")=TEXT(O21,"yyyy"),TEXT(N21,"d mmm")&" – "&TEXT(O21,"d mmm yyyy"),TEXT(N21,"d mmm yyyy")&" – "&TEXT(O21,"d mmm yyyy")))) -> 11 – 14 Jul 2026 | Q21: =IF(ISBLANK(O21),Lookups!$B$16-N21,O21-N21) -> 3 | R21: =IF(ISBLANK(O21),NETWORKDAYS.INTL(N21,Lookups!$B$16,"0000001")-1,NETWORKDAYS.INTL(N21,O21,"0000001")-1) -> 2 | S21: =IF(R21=0,"Same Day",R21&IF(R21=1," Day Delay"," Days Delay")&IF(T21="Yes",""," (min.)")) -> 2 Days Delay | T21: Yes | U21: 2 | V21: 120 | W21: 0 | X21: 480 | Y21: 120 | Z21: 0 | AA21: 1 | AB21: =IFERROR(X21/(L21-Z21),"") -> 1 | AC21: =L21*M21 -> 42768 | AD21: =W21*M21 -> 0 | AE21: =X21*M21 -> 42768 | AF21: =Y21*M21 -> 10692 | AG21: =AF21*MAX(0,R21-Lookups!$B$17) -> 0 | AH21: =IF(ISBLANK(O21),IF(R21>Lookups!$B$18,W21*M21,0),Z21*M21) -> 0 | AI21: shipped_full | AJ21: did_not_pick_on_shipment | AK21: LOGISTICS | AL21: Re-opened after shipment cancel | AM21: p.kamau | AN21: 46216 | AO21: =IF(AND(R21>Lookups!$B$18,AD21>Lookups!$B$19),"ESCALATE",IF(AD21>Lookups!$B$20,"High value",IF(R21>Lookups!$B$18,"Aged","Monitor"))) -> Monitor | AP21: No | AR21: 48148 | AS21: 48228 | AT21: =IF(ISBLANK(O21),"Open","Resolved") -> Resolved | AU21: =IF(AND($AT21="Open",$AP21="No",COUNTIFS($A$5:$A21,$A21,$AT$5:$AT21,"Open",$AP$5:$AP21,"No")=1),1,0) -> 0 | AV21: =IF(AND($AT21="Open",$AP21="No",COUNTIFS($H$5:$H21,$H21,$AT$5:$AT21,"Open",$AP$5:$AP21,"No")=1),1,0) -> 0
A22: SO366429 | B22: SO | C22: 46224 | D22: Sheal Limited | E22: Sheal Limited | F22: (not classified) | G22: TPFGS | H22: TISTP0008 | I22: =IFERROR(INDEX(Lookups!$B$6:$B$10,MATCH(LEFT(H22,3),Lookups!$A$6:$A$10,0)),"(unmapped)") -> Tishu Poa | J22: Tishu Poa TP Emb. Wrap. 4x10s White 100s | K22: CASE | L22: 1 | M22: 2935 | N22: 46224 | P22: =IF(ISBLANK(O22),TEXT(N22,"d mmm yyyy")&" – ongoing",IF(TEXT(N22,"mmmyyyy")=TEXT(O22,"mmmyyyy"),TEXT(N22,"d")&" – "&TEXT(O22,"d mmm yyyy"),IF(TEXT(N22,"yyyy")=TEXT(O22,"yyyy"),TEXT(N22,"d mmm")&" – "&TEXT(O22,"d mmm yyyy"),TEXT(N22,"d mmm yyyy")&" – "&TEXT(O22,"d mmm yyyy")))) -> 21 Jul 2026 – ongoing | Q22: =IF(ISBLANK(O22),Lookups!$B$16-N22,O22-N22) -> 5 | R22: =IF(ISBLANK(O22),NETWORKDAYS.INTL(N22,Lookups!$B$16,"0000001")-1,NETWORKDAYS.INTL(N22,O22,"0000001")-1) -> 4 | S22: =IF(R22=0,"Same Day",R22&IF(R22=1," Day Delay"," Days Delay")&IF(T22="Yes",""," (min.)")) -> 4 Days Delay | T22: Yes | U22: 1 | V22: 1 | W22: 1 | X22: 0 | Y22: 0 | Z22: 0 | AA22: 0 | AB22: =IFERROR(X22/(L22-Z22),"") -> 0 | AC22: =L22*M22 -> 2935 | AD22: =W22*M22 -> 2935 | AE22: =X22*M22 -> 0 | AF22: =Y22*M22 -> 0 | AG22: =AF22*MAX(0,R22-Lookups!$B$17) -> 0 | AH22: =IF(ISBLANK(O22),IF(R22>Lookups!$B$18,W22*M22,0),Z22*M22) -> 0 | AJ22: wrong_code | AK22: DATA_PROCESS | AL22: Item code corrected 24 Jul | AM22: c.wanjiru | AN22: 46227 | AO22: =IF(AND(R22>Lookups!$B$18,AD22>Lookups!$B$19),"ESCALATE",IF(AD22>Lookups!$B$20,"High value",IF(R22>Lookups!$B$18,"Aged","Monitor"))) -> Monitor | AP22: No | AR22: 48151 | AT22: =IF(ISBLANK(O22),"Open","Resolved") -> Open | AU22: =IF(AND($AT22="Open",$AP22="No",COUNTIFS($A$5:$A22,$A22,$AT$5:$AT22,"Open",$AP$5:$AP22,"No")=1),1,0) -> 1 | AV22: =IF(AND($AT22="Open",$AP22="No",COUNTIFS($H$5:$H22,$H22,$AT$5:$AT22,"Open",$AP$5:$AP22,"No")=1),1,0) -> 1
A23: SO362943 | B23: SO | C23: 46211 | D23: Bluewave Multisupplies Ltd | E23: Bluewave Multisupplies Ltd | F23: (not classified) | G23: FGS | H23: COSTP0023 | I23: =IFERROR(INDEX(Lookups!$B$6:$B$10,MATCH(LEFT(H23,3),Lookups!$A$6:$A$10,0)),"(unmapped)") -> Cosy | J23: Cosy Poa TP Emb. Wrap. 4x10s White 150s | K23: CASE | L23: 260 | M23: 75 | N23: 46211 | P23: =IF(ISBLANK(O23),TEXT(N23,"d mmm yyyy")&" – ongoing",IF(TEXT(N23,"mmmyyyy")=TEXT(O23,"mmmyyyy"),TEXT(N23,"d")&" – "&TEXT(O23,"d mmm yyyy"),IF(TEXT(N23,"yyyy")=TEXT(O23,"yyyy"),TEXT(N23,"d mmm")&" – "&TEXT(O23,"d mmm yyyy"),TEXT(N23,"d mmm yyyy")&" – "&TEXT(O23,"d mmm yyyy")))) -> 8 Jul 2026 – ongoing | Q23: =IF(ISBLANK(O23),Lookups!$B$16-N23,O23-N23) -> 18 | R23: =IF(ISBLANK(O23),NETWORKDAYS.INTL(N23,Lookups!$B$16,"0000001")-1,NETWORKDAYS.INTL(N23,O23,"0000001")-1) -> 15 | S23: =IF(R23=0,"Same Day",R23&IF(R23=1," Day Delay"," Days Delay")&IF(T23="Yes",""," (min.)")) -> 15 Days Delay (min.) | T23: No (estimated) | U23: 1 | V23: 260 | W23: 260 | X23: 0 | Y23: 0 | Z23: 0 | AA23: 0 | AB23: =IFERROR(X23/(L23-Z23),"") -> 0 | AC23: =L23*M23 -> 19500 | AD23: =W23*M23 -> 19500 | AE23: =X23*M23 -> 0 | AF23: =Y23*M23 -> 0 | AG23: =AF23*MAX(0,R23-Lookups!$B$17) -> 0 | AH23: =IF(ISBLANK(O23),IF(R23>Lookups!$B$18,W23*M23,0),Z23*M23) -> 19500 | AJ23: order_to_make | AK23: PRODUCTION | AL23: Made-to-order, batch not scheduled | AM23: j.mwangi | AN23: 46213 | AO23: =IF(AND(R23>Lookups!$B$18,AD23>Lookups!$B$19),"ESCALATE",IF(AD23>Lookups!$B$20,"High value",IF(R23>Lookups!$B$18,"Aged","Monitor"))) -> Aged | AP23: No | AR23: 48154 | AT23: =IF(ISBLANK(O23),"Open","Resolved") -> Open | AU23: =IF(AND($AT23="Open",$AP23="No",COUNTIFS($A$5:$A23,$A23,$AT$5:$AT23,"Open",$AP$5:$AP23,"No")=1),1,0) -> 1 | AV23: =IF(AND($AT23="Open",$AP23="No",COUNTIFS($H$5:$H23,$H23,$AT$5:$AT23,"Open",$AP$5:$AP23,"No")=1),1,0) -> 1
A24: SO362695 | B24: SO | C24: 46211 | D24: Cash Sale Staff | E24: Cash Sale Staff | F24: Direct To Consumer (Cash Sale) | G24: FGS | H24: FAYWP0026 | I24: =IFERROR(INDEX(Lookups!$B$6:$B$10,MATCH(LEFT(H24,3),Lookups!$A$6:$A$10,0)),"(unmapped)") -> Fay | J24: Fay Everyday Baby Wet Wipes 72s + 12s | K24: CASE | L24: 12 | M24: 53.75 | N24: 46211 | O24: 46216 | P24: =IF(ISBLANK(O24),TEXT(N24,"d mmm yyyy")&" – ongoing",IF(TEXT(N24,"mmmyyyy")=TEXT(O24,"mmmyyyy"),TEXT(N24,"d")&" – "&TEXT(O24,"d mmm yyyy"),IF(TEXT(N24,"yyyy")=TEXT(O24,"yyyy"),TEXT(N24,"d mmm")&" – "&TEXT(O24,"d mmm yyyy"),TEXT(N24,"d mmm yyyy")&" – "&TEXT(O24,"d mmm yyyy")))) -> 8 – 13 Jul 2026 | Q24: =IF(ISBLANK(O24),Lookups!$B$16-N24,O24-N24) -> 5 | R24: =IF(ISBLANK(O24),NETWORKDAYS.INTL(N24,Lookups!$B$16,"0000001")-1,NETWORKDAYS.INTL(N24,O24,"0000001")-1) -> 4 | S24: =IF(R24=0,"Same Day",R24&IF(R24=1," Day Delay"," Days Delay")&IF(T24="Yes",""," (min.)")) -> 4 Days Delay | T24: Yes | U24: 1 | V24: 6 | W24: 0 | X24: 12 | Y24: 6 | Z24: 0 | AA24: 1 | AB24: =IFERROR(X24/(L24-Z24),"") -> 1 | AC24: =L24*M24 -> 645 | AD24: =W24*M24 -> 0 | AE24: =X24*M24 -> 645 | AF24: =Y24*M24 -> 322.5 | AG24: =AF24*MAX(0,R24-Lookups!$B$17) -> 645 | AH24: =IF(ISBLANK(O24),IF(R24>Lookups!$B$18,W24*M24,0),Z24*M24) -> 0 | AI24: shipped_full | AJ24: truck_full | AK24: LOGISTICS | AL24: Bumped from route load | AM24: p.kamau | AN24: 46212 | AO24: =IF(AND(R24>Lookups!$B$18,AD24>Lookups!$B$19),"ESCALATE",IF(AD24>Lookups!$B$20,"High value",IF(R24>Lookups!$B$18,"Aged","Monitor"))) -> Monitor | AP24: No | AR24: 48157 | AS24: 48237 | AT24: =IF(ISBLANK(O24),"Open","Resolved") -> Resolved | AU24: =IF(AND($AT24="Open",$AP24="No",COUNTIFS($A$5:$A24,$A24,$AT$5:$AT24,"Open",$AP$5:$AP24,"No")=1),1,0) -> 0 | AV24: =IF(AND($AT24="Open",$AP24="No",COUNTIFS($H$5:$H24,$H24,$AT$5:$AT24,"Open",$AP$5:$AP24,"No")=1),1,0) -> 0
A25: SO367217 | B25: SO | C25: 46226 | D25: Sales Promotion - Customers (A&P KimFay) | E25: Sales Promotion - Customers (A&P KimFay) | F25: Non Traditional Channels | G25: FGS | H25: TISTP0008 | I25: =IFERROR(INDEX(Lookups!$B$6:$B$10,MATCH(LEFT(H25,3),Lookups!$A$6:$A$10,0)),"(unmapped)") -> Tishu Poa | J25: Tishu Poa TP Emb. Wrap. 4x10s White 100s | K25: CASE | L25: 12 | M25: 283.12 | N25: 46226 | P25: =IF(ISBLANK(O25),TEXT(N25,"d mmm yyyy")&" – ongoing",IF(TEXT(N25,"mmmyyyy")=TEXT(O25,"mmmyyyy"),TEXT(N25,"d")&" – "&TEXT(O25,"d mmm yyyy"),IF(TEXT(N25,"yyyy")=TEXT(O25,"yyyy"),TEXT(N25,"d mmm")&" – "&TEXT(O25,"d mmm yyyy"),TEXT(N25,"d mmm yyyy")&" – "&TEXT(O25,"d mmm yyyy")))) -> 23 Jul 2026 – ongoing | Q25: =IF(ISBLANK(O25),Lookups!$B$16-N25,O25-N25) -> 3 | R25: =IF(ISBLANK(O25),NETWORKDAYS.INTL(N25,Lookups!$B$16,"0000001")-1,NETWORKDAYS.INTL(N25,O25,"0000001")-1) -> 2 | S25: =IF(R25=0,"Same Day",R25&IF(R25=1," Day Delay"," Days Delay")&IF(T25="Yes",""," (min.)")) -> 2 Days Delay | T25: Yes | U25: 1 | V25: 12 | W25: 12 | X25: 0 | Y25: 0 | Z25: 0 | AA25: 0 | AB25: =IFERROR(X25/(L25-Z25),"") -> 0 | AC25: =L25*M25 -> 3397.44 | AD25: =W25*M25 -> 3397.44 | AE25: =X25*M25 -> 0 | AF25: =Y25*M25 -> 0 | AG25: =AF25*MAX(0,R25-Lookups!$B$17) -> 0 | AH25: =IF(ISBLANK(O25),IF(R25>Lookups!$B$18,W25*M25,0),Z25*M25) -> 0 | AJ25: non_focus | AK25: COMMERCIAL | AL25: A&P sampling stock | AM25: c.wanjiru | AN25: 46227 | AO25: =IF(AND(R25>Lookups!$B$18,AD25>Lookups!$B$19),"ESCALATE",IF(AD25>Lookups!$B$20,"High value",IF(R25>Lookups!$B$18,"Aged","Monitor"))) -> Monitor | AP25: No | AR25: 48160 | AT25: =IF(ISBLANK(O25),"Open","Resolved") -> Open | AU25: =IF(AND($AT25="Open",$AP25="No",COUNTIFS($A$5:$A25,$A25,$AT$5:$AT25,"Open",$AP$5:$AP25,"No")=1),1,0) -> 1 | AV25: =IF(AND($AT25="Open",$AP25="No",COUNTIFS($H$5:$H25,$H25,$AT$5:$AT25,"Open",$AP$5:$AP25,"No")=1),1,0) -> 0
A26: TOTAL | L26: =SUM(L5:L25) -> 9226 | V26: =SUM(V5:V25) -> 5109 | W26: =SUM(W5:W25) -> 3075 | X26: =SUM(X5:X25) -> 6076 | Y26: =SUM(Y5:Y25) -> 1562 | Z26: =SUM(Z5:Z25) -> 75 | AC26: =SUM(AC5:AC25) -> 3643917.3 | AD26: =SUM(AD5:AD25) -> 2322855.2 | AE26: =SUM(AE5:AE25) -> 1315564.6 | AF26: =SUM(AF5:AF25) -> 320811.34 | AG26: =SUM(AG5:AG25) -> 524947.6 | AH26: =SUM(AH5:AH25) -> 256652.16 | AU26: =SUM(AU5:AU25) -> 14 | AV26: =SUM(AV5:AV25) -> 8

Sheet Event Log
A1: Event Log — append-only audit trail
A2: One row per state transition, straight from backorder_line_events. No formulas: this sheet is evidence and must stay immutable. Amber = opened, green = resolved, red = re-opened.
A4: Episode ID | B4: Order Nbr. | C4: Inventory ID | D4: Occurred At | E4: Event Type | F4: Event Label | G4: BO Qty Before | H4: BO Qty After | I4: Delta Qty | J4: Delta Value (KES) | K4: Order Status at Event | L4: Reason Code at Event | M4: Actor | N4: Sync Run ID
A5: 8821 | B5: SO363506 | C5: SIFTP0015 | D5: 46213.385 | E5: opened | F5: Entered backorder — 680 CASE short | H5: 680 | I5: 680 | J5: 96934 | K5: Back Order | M5: system | N5: 48100
A6: 8821 | B6: SO363506 | C6: SIFTP0015 | D6: 46214.46 | E6: reason_set | F6: Reason set: Out of stock — production | G6: 680 | H6: 680 | I6: 0 | J6: 0 | K6: Back Order | L6: out_of_stock_production | M6: j.mwangi | N6: 48112
A7: 8821 | B7: SO363506 | C7: SIFTP0015 | D7: 46218.604 | E7: partial_fill | F7: Partial fill — 180 CASE shipped | G7: 680 | H7: 500 | I7: -180 | J7: -25659 | K7: Back Order | L7: out_of_stock_production | M7: system | N7: 48131
A8: 8821 | B8: SO363506 | C8: SIFTP0015 | D8: 46221.337 | E8: partial_fill | F8: Partial fill — 80 CASE shipped | G8: 500 | H8: 420 | I8: -80 | J8: -11404 | K8: Back Order | L8: out_of_stock_production | M8: system | N8: 48148
A9: 8834 | B9: SO363507 | C9: COSTP0006 | D9: 46213.385 | E9: opened | F9: Entered backorder — 514 CASE short | H9: 514 | I9: 514 | J9: 33179 | K9: Back Order | M9: system | N9: 48100
A10: 8834 | B10: SO363507 | C10: COSTP0006 | D10: 46215.431 | E10: reason_set | F10: Reason set: Out of stock — production | G10: 514 | H10: 514 | I10: 0 | J10: 0 | K10: Back Order | L10: out_of_stock_production | M10: j.mwangi | N10: 48119
A11: 8834 | B11: SO363507 | C11: COSTP0006 | D11: 46220.697 | E11: partial_fill | F11: Partial fill — 214 CASE shipped | G11: 514 | H11: 300 | I11: -214 | J11: -13813 | K11: Back Order | L11: out_of_stock_production | M11: system | N11: 48141
A12: 8834 | B12: SO363507 | C12: COSTP0006 | D12: 46223.376 | E12: partial_fill | F12: Partial fill — 160 CASE shipped | G12: 300 | H12: 140 | I12: -160 | J12: -10328 | K12: Back Order | L12: out_of_stock_production | M12: system | N12: 48155
A13: 8834 | B13: SO363507 | C13: COSTP0006 | D13: 46225.484 | E13: resolved | F13: Resolved — shipped in full (10 working days) | G13: 140 | H13: 0 | I13: -140 | J13: -9037 | K13: Shipping | L13: out_of_stock_production | M13: system | N13: 48168
A14: 8902 | B14: SO363484 | C14: FAYTP0008 | D14: 46213.385 | E14: opened | F14: Entered backorder — 182 CASE short | H14: 182 | I14: 182 | J14: 16216 | K14: Back Order | M14: system | N14: 48100
A15: 8902 | B15: SO363484 | C15: FAYTP0008 | D15: 46219.549 | E15: resolved | F15: Resolved — shipped in full (5 working days) | G15: 182 | H15: 0 | I15: -182 | J15: -16216 | K15: Shipping | L15: did_not_pick_on_shipment | M15: system | N15: 48137
A16: 8903 | B16: SO363482 | C16: FAYTP0008 | D16: 46214.385 | E16: opened | F16: Entered backorder — 120 CASE short (episode 1) | H16: 120 | I16: 120 | J16: 10692 | K16: Back Order | M16: system | N16: 48104
A17: 8903 | B17: SO363482 | C17: FAYTP0008 | D17: 46215.66 | E17: resolved | F17: Resolved — picked and shipped | G17: 120 | H17: 0 | I17: -120 | J17: -10692 | K17: Shipping | L17: did_not_pick_on_shipment | M17: system | N17: 48121
A18: 8904 | B18: SO363482 | C18: FAYTP0008 | D18: 46216.354 | E18: reopened | F18: Re-opened — shipment cancelled, 120 CASE short again (episode 2) | G18: 0 | H18: 120 | I18: 120 | J18: 10692 | K18: Back Order | L18: did_not_pick_on_shipment | M18: system | N18: 48125
A19: 8904 | B19: SO363482 | C19: FAYTP0008 | D19: 46217.503 | E19: resolved | F19: Resolved — shipped in full (1 working day) | G19: 120 | H19: 0 | I19: -120 | J19: -10692 | K19: Shipping | L19: did_not_pick_on_shipment | M19: system | N19: 48129
A20: 9011 | B20: SO367035 | C20: FAYFL0010 | D20: 46226.347 | E20: opened | F20: Entered backorder — 24 ROLL short | H20: 24 | I20: 24 | J20: 61021 | K20: Back Order | M20: system | N20: 48201
A21: 9011 | B21: SO367035 | C21: FAYFL0010 | D21: 46226.406 | E21: reason_set | F21: Reason set: Out of stock — procurement (import ETA 29 Jul) | G21: 24 | H21: 24 | I21: 0 | J21: 0 | K21: Back Order | L21: out_of_stock_procurement | M21: a.otieno | N21: 48203
A22: 9044 | B22: SO361051 | C22: SIFTP0009 | D22: 46204.33 | E22: excluded | F22: Excluded from KPIs — free / zero-value promotional line | G22: 150 | H22: 150 | I22: 0 | J22: 0 | K22: Back Order | L22: promo_product | M22: system | N22: 48012

Sheet By Item
A1: By item — ranked by revenue-days delayed
A2: Revenue-days delayed is the correct ranking measure: it weights a large order held briefly against a small one held for weeks.
A4: Inventory ID | B4: Brand | C4: Description | D4: UOM | E4: Episodes | F4: Open orders | G4: Peak qty short | H4: Open value (KES) | I4: Revenue-days delayed | J4: Lost revenue (KES) | K4: Avg days delay | L4: Repeat episodes
A5: SIFTP0015 | B5: =IFERROR(INDEX(Lookups!$B$6:$B$10,MATCH(LEFT($A5,3),Lookups!$A$6:$A$10,0)),"(unmapped)") -> Sifa | C5: Sifa TP Emb. Unwrap. Twinpack 20x2s White | D5: CASE | E5: =COUNTIFS('Episode Detail'!$H$5:$H$25,$A5,'Episode Detail'!$AP$5:$AP$25,"No") -> 2 | F5: =SUMPRODUCT(('Episode Detail'!$H$5:$H$25=$A5)*'Episode Detail'!$AU$5:$AU$25) -> 2 | G5: =SUMIFS('Episode Detail'!$V$5:$V$25,'Episode Detail'!$H$5:$H$25,$A5,'Episode Detail'!$AP$5:$AP$25,"No") -> 1274 | H5: =SUMIFS('Episode Detail'!$AD$5:$AD$25,'Episode Detail'!$H$5:$H$25,$A5,'Episode Detail'!$AT$5:$AT$25,"Open",'Episode Detail'!$AP$5:$AP$25,"No") -> 135137.4 | I5: =SUMIFS('Episode Detail'!$AG$5:$AG$25,'Episode Detail'!$H$5:$H$25,$A5,'Episode Detail'!$AP$5:$AP$25,"No") -> 0 | J5: =SUMIFS('Episode Detail'!$AH$5:$AH$25,'Episode Detail'!$H$5:$H$25,$A5,'Episode Detail'!$AP$5:$AP$25,"No") -> 135137.4 | K5: =IFERROR(AVERAGEIFS('Episode Detail'!$R$5:$R$25,'Episode Detail'!$H$5:$H$25,$A5,'Episode Detail'!$T$5:$T$25,"Yes",'Episode Detail'!$AP$5:$AP$25,"No"),"") -> 13 | L5: =COUNTIFS('Episode Detail'!$H$5:$H$25,$A5,'Episode Detail'!$U$5:$U$25,">1") -> 0
A6: COSTP0004 | B6: =IFERROR(INDEX(Lookups!$B$6:$B$10,MATCH(LEFT($A6,3),Lookups!$A$6:$A$10,0)),"(unmapped)") -> Cosy | C6: Cosy TP Emb. Wrap. 40s Singles White | D6: CASE | E6: =COUNTIFS('Episode Detail'!$H$5:$H$25,$A6,'Episode Detail'!$AP$5:$AP$25,"No") -> 1 | F6: =SUMPRODUCT(('Episode Detail'!$H$5:$H$25=$A6)*'Episode Detail'!$AU$5:$AU$25) -> 1 | G6: =SUMIFS('Episode Detail'!$V$5:$V$25,'Episode Detail'!$H$5:$H$25,$A6,'Episode Detail'!$AP$5:$AP$25,"No") -> 542 | H6: =SUMIFS('Episode Detail'!$AD$5:$AD$25,'Episode Detail'!$H$5:$H$25,$A6,'Episode Detail'!$AT$5:$AT$25,"Open",'Episode Detail'!$AP$5:$AP$25,"No") -> 32920.5 | I6: =SUMIFS('Episode Detail'!$AG$5:$AG$25,'Episode Detail'!$H$5:$H$25,$A6,'Episode Detail'!$AP$5:$AP$25,"No") -> 0 | J6: =SUMIFS('Episode Detail'!$AH$5:$AH$25,'Episode Detail'!$H$5:$H$25,$A6,'Episode Detail'!$AP$5:$AP$25,"No") -> 32920.5 | K6: =IFERROR(AVERAGEIFS('Episode Detail'!$R$5:$R$25,'Episode Detail'!$H$5:$H$25,$A6,'Episode Detail'!$T$5:$T$25,"Yes",'Episode Detail'!$AP$5:$AP$25,"No"),"") -> 13 | L6: =COUNTIFS('Episode Detail'!$H$5:$H$25,$A6,'Episode Detail'!$U$5:$U$25,">1") -> 0
A7: COSTP0006 | B7: =IFERROR(INDEX(Lookups!$B$6:$B$10,MATCH(LEFT($A7,3),Lookups!$A$6:$A$10,0)),"(unmapped)") -> Cosy | C7: Cosy TP Emb. Unwrap. 4x10s White | D7: CASE | E7: =COUNTIFS('Episode Detail'!$H$5:$H$25,$A7,'Episode Detail'!$AP$5:$AP$25,"No") -> 1 | F7: =SUMPRODUCT(('Episode Detail'!$H$5:$H$25=$A7)*'Episode Detail'!$AU$5:$AU$25) -> 0 | G7: =SUMIFS('Episode Detail'!$V$5:$V$25,'Episode Detail'!$H$5:$H$25,$A7,'Episode Detail'!$AP$5:$AP$25,"No") -> 514 | H7: =SUMIFS('Episode Detail'!$AD$5:$AD$25,'Episode Detail'!$H$5:$H$25,$A7,'Episode Detail'!$AT$5:$AT$25,"Open",'Episode Detail'!$AP$5:$AP$25,"No") -> 0 | I7: =SUMIFS('Episode Detail'!$AG$5:$AG$25,'Episode Detail'!$H$5:$H$25,$A7,'Episode Detail'!$AP$5:$AP$25,"No") -> 265429.6 | J7: =SUMIFS('Episode Detail'!$AH$5:$AH$25,'Episode Detail'!$H$5:$H$25,$A7,'Episode Detail'!$AP$5:$AP$25,"No") -> 0 | K7: =IFERROR(AVERAGEIFS('Episode Detail'!$R$5:$R$25,'Episode Detail'!$H$5:$H$25,$A7,'Episode Detail'!$T$5:$T$25,"Yes",'Episode Detail'!$AP$5:$AP$25,"No"),"") -> 10 | L7: =COUNTIFS('Episode Detail'!$H$5:$H$25,$A7,'Episode Detail'!$U$5:$U$25,">1") -> 0
A8: FAYTP0013 | B8: =IFERROR(INDEX(Lookups!$B$6:$B$10,MATCH(LEFT($A8,3),Lookups!$A$6:$A$10,0)),"(unmapped)") -> Fay | C8: Fay TP Emb. Wrap. 40s Singles White | D8: CASE | E8: =COUNTIFS('Episode Detail'!$H$5:$H$25,$A8,'Episode Detail'!$AP$5:$AP$25,"No") -> 1 | F8: =SUMPRODUCT(('Episode Detail'!$H$5:$H$25=$A8)*'Episode Detail'!$AU$5:$AU$25) -> 0 | G8: =SUMIFS('Episode Detail'!$V$5:$V$25,'Episode Detail'!$H$5:$H$25,$A8,'Episode Detail'!$AP$5:$AP$25,"No") -> 478 | H8: =SUMIFS('Episode Detail'!$AD$5:$AD$25,'Episode Detail'!$H$5:$H$25,$A8,'Episode Detail'!$AT$5:$AT$25,"Open",'Episode Detail'!$AP$5:$AP$25,"No") -> 0 | I8: =SUMIFS('Episode Detail'!$AG$5:$AG$25,'Episode Detail'!$H$5:$H$25,$A8,'Episode Detail'!$AP$5:$AP$25,"No") -> 210224.4 | J8: =SUMIFS('Episode Detail'!$AH$5:$AH$25,'Episode Detail'!$H$5:$H$25,$A8,'Episode Detail'!$AP$5:$AP$25,"No") -> 5497.5 | K8: =IFERROR(AVERAGEIFS('Episode Detail'!$R$5:$R$25,'Episode Detail'!$H$5:$H$25,$A8,'Episode Detail'!$T$5:$T$25,"Yes",'Episode Detail'!$AP$5:$AP$25,"No"),"") -> 8 | L8: =COUNTIFS('Episode Detail'!$H$5:$H$25,$A8,'Episode Detail'!$U$5:$U$25,">1") -> 0
A9: FAYFL0010 | B9: =IFERROR(INDEX(Lookups!$B$6:$B$10,MATCH(LEFT($A9,3),Lookups!$A$6:$A$10,0)),"(unmapped)") -> Fay | C9: Fay Aluminium Foil Catering (45x50m) | D9: ROLL | E9: =COUNTIFS('Episode Detail'!$H$5:$H$25,$A9,'Episode Detail'!$AP$5:$AP$25,"No") -> 3 | F9: =SUMPRODUCT(('Episode Detail'!$H$5:$H$25=$A9)*'Episode Detail'!$AU$5:$AU$25) -> 3 | G9: =SUMIFS('Episode Detail'!$V$5:$V$25,'Episode Detail'!$H$5:$H$25,$A9,'Episode Detail'!$AP$5:$AP$25,"No") -> 54 | H9: =SUMIFS('Episode Detail'!$AD$5:$AD$25,'Episode Detail'!$H$5:$H$25,$A9,'Episode Detail'!$AT$5:$AT$25,"Open",'Episode Detail'!$AP$5:$AP$25,"No") -> 121215.6 | I9: =SUMIFS('Episode Detail'!$AG$5:$AG$25,'Episode Detail'!$H$5:$H$25,$A9,'Episode Detail'!$AP$5:$AP$25,"No") -> 0 | J9: =SUMIFS('Episode Detail'!$AH$5:$AH$25,'Episode Detail'!$H$5:$H$25,$A9,'Episode Detail'!$AP$5:$AP$25,"No") -> 30510.36 | K9: =IFERROR(AVERAGEIFS('Episode Detail'!$R$5:$R$25,'Episode Detail'!$H$5:$H$25,$A9,'Episode Detail'!$T$5:$T$25,"Yes",'Episode Detail'!$AP$5:$AP$25,"No"),"") -> 4 | L9: =COUNTIFS('Episode Detail'!$H$5:$H$25,$A9,'Episode Detail'!$U$5:$U$25,">1") -> 0
A10: FAYCL0009 | B10: =IFERROR(INDEX(Lookups!$B$6:$B$10,MATCH(LEFT($A10,3),Lookups!$A$6:$A$10,0)),"(unmapped)") -> Fay | C10: Fay Cling Film Catering 30cmx300m GP | D10: PIECE | E10: =COUNTIFS('Episode Detail'!$H$5:$H$25,$A10,'Episode Detail'!$AP$5:$AP$25,"No") -> 2 | F10: =SUMPRODUCT(('Episode Detail'!$H$5:$H$25=$A10)*'Episode Detail'!$AU$5:$AU$25) -> 2 | G10: =SUMIFS('Episode Detail'!$V$5:$V$25,'Episode Detail'!$H$5:$H$25,$A10,'Episode Detail'!$AP$5:$AP$25,"No") -> 12 | H10: =SUMIFS('Episode Detail'!$AD$5:$AD$25,'Episode Detail'!$H$5:$H$25,$A10,'Episode Detail'!$AT$5:$AT$25,"Open",'Episode Detail'!$AP$5:$AP$25,"No") -> 33082.8 | I10: =SUMIFS('Episode Detail'!$AG$5:$AG$25,'Episode Detail'!$H$5:$H$25,$A10,'Episode Detail'!$AP$5:$AP$25,"No") -> 0 | J10: =SUMIFS('Episode Detail'!$AH$5:$AH$25,'Episode Detail'!$H$5:$H$25,$A10,'Episode Detail'!$AP$5:$AP$25,"No") -> 33082.8 | K10: =IFERROR(AVERAGEIFS('Episode Detail'!$R$5:$R$25,'Episode Detail'!$H$5:$H$25,$A10,'Episode Detail'!$T$5:$T$25,"Yes",'Episode Detail'!$AP$5:$AP$25,"No"),"") -> 9 | L10: =COUNTIFS('Episode Detail'!$H$5:$H$25,$A10,'Episode Detail'!$U$5:$U$25,">1") -> 0
A11: TISTP0008 | B11: =IFERROR(INDEX(Lookups!$B$6:$B$10,MATCH(LEFT($A11,3),Lookups!$A$6:$A$10,0)),"(unmapped)") -> Tishu Poa | C11: Tishu Poa TP Emb. Wrap. 4x10s White 100s | D11: CASE | E11: =COUNTIFS('Episode Detail'!$H$5:$H$25,$A11,'Episode Detail'!$AP$5:$AP$25,"No") -> 3 | F11: =SUMPRODUCT(('Episode Detail'!$H$5:$H$25=$A11)*'Episode Detail'!$AU$5:$AU$25) -> 2 | G11: =SUMIFS('Episode Detail'!$V$5:$V$25,'Episode Detail'!$H$5:$H$25,$A11,'Episode Detail'!$AP$5:$AP$25,"No") -> 275 | H11: =SUMIFS('Episode Detail'!$AD$5:$AD$25,'Episode Detail'!$H$5:$H$25,$A11,'Episode Detail'!$AT$5:$AT$25,"Open",'Episode Detail'!$AP$5:$AP$25,"No") -> 6332.44 | I11: =SUMIFS('Episode Detail'!$AG$5:$AG$25,'Episode Detail'!$H$5:$H$25,$A11,'Episode Detail'!$AP$5:$AP$25,"No") -> 0 | J11: =SUMIFS('Episode Detail'!$AH$5:$AH$25,'Episode Detail'!$H$5:$H$25,$A11,'Episode Detail'!$AP$5:$AP$25,"No") -> 0 | K11: =IFERROR(AVERAGEIFS('Episode Detail'!$R$5:$R$25,'Episode Detail'!$H$5:$H$25,$A11,'Episode Detail'!$T$5:$T$25,"Yes",'Episode Detail'!$AP$5:$AP$25,"No"),"") -> 2.6666667 | L11: =COUNTIFS('Episode Detail'!$H$5:$H$25,$A11,'Episode Detail'!$U$5:$U$25,">1") -> 0
A12: COWGT0001 | B12: =IFERROR(INDEX(Lookups!$B$6:$B$10,MATCH(LEFT($A12,3),Lookups!$A$6:$A$10,0)),"(unmapped)") -> Cow & Gate | C12: Cow & Gate First 400g | D12: CAN | E12: =COUNTIFS('Episode Detail'!$H$5:$H$25,$A12,'Episode Detail'!$AP$5:$AP$25,"No") -> 2 | F12: =SUMPRODUCT(('Episode Detail'!$H$5:$H$25=$A12)*'Episode Detail'!$AU$5:$AU$25) -> 2 | G12: =SUMIFS('Episode Detail'!$V$5:$V$25,'Episode Detail'!$H$5:$H$25,$A12,'Episode Detail'!$AP$5:$AP$25,"No") -> 54 | H12: =SUMIFS('Episode Detail'!$AD$5:$AD$25,'Episode Detail'!$H$5:$H$25,$A12,'Episode Detail'!$AT$5:$AT$25,"Open",'Episode Detail'!$AP$5:$AP$25,"No") -> 82131.3 | I12: =SUMIFS('Episode Detail'!$AG$5:$AG$25,'Episode Detail'!$H$5:$H$25,$A12,'Episode Detail'!$AP$5:$AP$25,"No") -> 0 | J12: =SUMIFS('Episode Detail'!$AH$5:$AH$25,'Episode Detail'!$H$5:$H$25,$A12,'Episode Detail'!$AP$5:$AP$25,"No") -> 0 | K12: =IFERROR(AVERAGEIFS('Episode Detail'!$R$5:$R$25,'Episode Detail'!$H$5:$H$25,$A12,'Episode Detail'!$T$5:$T$25,"Yes",'Episode Detail'!$AP$5:$AP$25,"No"),"") -> 2 | L12: =COUNTIFS('Episode Detail'!$H$5:$H$25,$A12,'Episode Detail'!$U$5:$U$25,">1") -> 0
A13: COWGT0002 | B13: =IFERROR(INDEX(Lookups!$B$6:$B$10,MATCH(LEFT($A13,3),Lookups!$A$6:$A$10,0)),"(unmapped)") -> Cow & Gate | C13: Cow & Gate Follow Up 400g | D13: CAN | E13: =COUNTIFS('Episode Detail'!$H$5:$H$25,$A13,'Episode Detail'!$AP$5:$AP$25,"No") -> 1 | F13: =SUMPRODUCT(('Episode Detail'!$H$5:$H$25=$A13)*'Episode Detail'!$AU$5:$AU$25) -> 1 | G13: =SUMIFS('Episode Detail'!$V$5:$V$25,'Episode Detail'!$H$5:$H$25,$A13,'Episode Detail'!$AP$5:$AP$25,"No") -> 1188 | H13: =SUMIFS('Episode Detail'!$AD$5:$AD$25,'Episode Detail'!$H$5:$H$25,$A13,'Episode Detail'!$AT$5:$AT$25,"Open",'Episode Detail'!$AP$5:$AP$25,"No") -> 1892531.5 | I13: =SUMIFS('Episode Detail'!$AG$5:$AG$25,'Episode Detail'!$H$5:$H$25,$A13,'Episode Detail'!$AP$5:$AP$25,"No") -> 0 | J13: =SUMIFS('Episode Detail'!$AH$5:$AH$25,'Episode Detail'!$H$5:$H$25,$A13,'Episode Detail'!$AP$5:$AP$25,"No") -> 0 | K13: =IFERROR(AVERAGEIFS('Episode Detail'!$R$5:$R$25,'Episode Detail'!$H$5:$H$25,$A13,'Episode Detail'!$T$5:$T$25,"Yes",'Episode Detail'!$AP$5:$AP$25,"No"),"") -> 2 | L13: =COUNTIFS('Episode Detail'!$H$5:$H$25,$A13,'Episode Detail'!$U$5:$U$25,">1") -> 0
A14: SIFTP0009 | B14: =IFERROR(INDEX(Lookups!$B$6:$B$10,MATCH(LEFT($A14,3),Lookups!$A$6:$A$10,0)),"(unmapped)") -> Sifa | C14: Sifa TP Emb. Unwrap. 4x10s White | D14: CASE | E14: =COUNTIFS('Episode Detail'!$H$5:$H$25,$A14,'Episode Detail'!$AP$5:$AP$25,"No") -> 0 | F14: =SUMPRODUCT(('Episode Detail'!$H$5:$H$25=$A14)*'Episode Detail'!$AU$5:$AU$25) -> 0 | G14: =SUMIFS('Episode Detail'!$V$5:$V$25,'Episode Detail'!$H$5:$H$25,$A14,'Episode Detail'!$AP$5:$AP$25,"No") -> 0 | H14: =SUMIFS('Episode Detail'!$AD$5:$AD$25,'Episode Detail'!$H$5:$H$25,$A14,'Episode Detail'!$AT$5:$AT$25,"Open",'Episode Detail'!$AP$5:$AP$25,"No") -> 0 | I14: =SUMIFS('Episode Detail'!$AG$5:$AG$25,'Episode Detail'!$H$5:$H$25,$A14,'Episode Detail'!$AP$5:$AP$25,"No") -> 0 | J14: =SUMIFS('Episode Detail'!$AH$5:$AH$25,'Episode Detail'!$H$5:$H$25,$A14,'Episode Detail'!$AP$5:$AP$25,"No") -> 0 | K14: =IFERROR(AVERAGEIFS('Episode Detail'!$R$5:$R$25,'Episode Detail'!$H$5:$H$25,$A14,'Episode Detail'!$T$5:$T$25,"Yes",'Episode Detail'!$AP$5:$AP$25,"No"),"") | L14: =COUNTIFS('Episode Detail'!$H$5:$H$25,$A14,'Episode Detail'!$U$5:$U$25,">1") -> 0
A15: FAYTP0008 | B15: =IFERROR(INDEX(Lookups!$B$6:$B$10,MATCH(LEFT($A15,3),Lookups!$A$6:$A$10,0)),"(unmapped)") -> Fay | C15: Fay TP Emb. Unwrap. 4x10s White | D15: CASE | E15: =COUNTIFS('Episode Detail'!$H$5:$H$25,$A15,'Episode Detail'!$AP$5:$AP$25,"No") -> 2 | F15: =SUMPRODUCT(('Episode Detail'!$H$5:$H$25=$A15)*'Episode Detail'!$AU$5:$AU$25) -> 0 | G15: =SUMIFS('Episode Detail'!$V$5:$V$25,'Episode Detail'!$H$5:$H$25,$A15,'Episode Detail'!$AP$5:$AP$25,"No") -> 302 | H15: =SUMIFS('Episode Detail'!$AD$5:$AD$25,'Episode Detail'!$H$5:$H$25,$A15,'Episode Detail'!$AT$5:$AT$25,"Open",'Episode Detail'!$AP$5:$AP$25,"No") -> 0 | I15: =SUMIFS('Episode Detail'!$AG$5:$AG$25,'Episode Detail'!$H$5:$H$25,$A15,'Episode Detail'!$AP$5:$AP$25,"No") -> 48648.6 | J15: =SUMIFS('Episode Detail'!$AH$5:$AH$25,'Episode Detail'!$H$5:$H$25,$A15,'Episode Detail'!$AP$5:$AP$25,"No") -> 0 | K15: =IFERROR(AVERAGEIFS('Episode Detail'!$R$5:$R$25,'Episode Detail'!$H$5:$H$25,$A15,'Episode Detail'!$T$5:$T$25,"Yes",'Episode Detail'!$AP$5:$AP$25,"No"),"") -> 3.5 | L15: =COUNTIFS('Episode Detail'!$H$5:$H$25,$A15,'Episode Detail'!$U$5:$U$25,">1") -> 1
A16: COSTP0023 | B16: =IFERROR(INDEX(Lookups!$B$6:$B$10,MATCH(LEFT($A16,3),Lookups!$A$6:$A$10,0)),"(unmapped)") -> Cosy | C16: Cosy Poa TP Emb. Wrap. 4x10s White 150s | D16: CASE | E16: =COUNTIFS('Episode Detail'!$H$5:$H$25,$A16,'Episode Detail'!$AP$5:$AP$25,"No") -> 1 | F16: =SUMPRODUCT(('Episode Detail'!$H$5:$H$25=$A16)*'Episode Detail'!$AU$5:$AU$25) -> 1 | G16: =SUMIFS('Episode Detail'!$V$5:$V$25,'Episode Detail'!$H$5:$H$25,$A16,'Episode Detail'!$AP$5:$AP$25,"No") -> 260 | H16: =SUMIFS('Episode Detail'!$AD$5:$AD$25,'Episode Detail'!$H$5:$H$25,$A16,'Episode Detail'!$AT$5:$AT$25,"Open",'Episode Detail'!$AP$5:$AP$25,"No") -> 19500 | I16: =SUMIFS('Episode Detail'!$AG$5:$AG$25,'Episode Detail'!$H$5:$H$25,$A16,'Episode Detail'!$AP$5:$AP$25,"No") -> 0 | J16: =SUMIFS('Episode Detail'!$AH$5:$AH$25,'Episode Detail'!$H$5:$H$25,$A16,'Episode Detail'!$AP$5:$AP$25,"No") -> 19500 | K16: =IFERROR(AVERAGEIFS('Episode Detail'!$R$5:$R$25,'Episode Detail'!$H$5:$H$25,$A16,'Episode Detail'!$T$5:$T$25,"Yes",'Episode Detail'!$AP$5:$AP$25,"No"),"") | L16: =COUNTIFS('Episode Detail'!$H$5:$H$25,$A16,'Episode Detail'!$U$5:$U$25,">1") -> 0
A17: FAYWP0026 | B17: =IFERROR(INDEX(Lookups!$B$6:$B$10,MATCH(LEFT($A17,3),Lookups!$A$6:$A$10,0)),"(unmapped)") -> Fay | C17: Fay Everyday Baby Wet Wipes 72s + 12s | D17: CASE | E17: =COUNTIFS('Episode Detail'!$H$5:$H$25,$A17,'Episode Detail'!$AP$5:$AP$25,"No") -> 1 | F17: =SUMPRODUCT(('Episode Detail'!$H$5:$H$25=$A17)*'Episode Detail'!$AU$5:$AU$25) -> 0 | G17: =SUMIFS('Episode Detail'!$V$5:$V$25,'Episode Detail'!$H$5:$H$25,$A17,'Episode Detail'!$AP$5:$AP$25,"No") -> 6 | H17: =SUMIFS('Episode Detail'!$AD$5:$AD$25,'Episode Detail'!$H$5:$H$25,$A17,'Episode Detail'!$AT$5:$AT$25,"Open",'Episode Detail'!$AP$5:$AP$25,"No") -> 0 | I17: =SUMIFS('Episode Detail'!$AG$5:$AG$25,'Episode Detail'!$H$5:$H$25,$A17,'Episode Detail'!$AP$5:$AP$25,"No") -> 645 | J17: =SUMIFS('Episode Detail'!$AH$5:$AH$25,'Episode Detail'!$H$5:$H$25,$A17,'Episode Detail'!$AP$5:$AP$25,"No") -> 0 | K17: =IFERROR(AVERAGEIFS('Episode Detail'!$R$5:$R$25,'Episode Detail'!$H$5:$H$25,$A17,'Episode Detail'!$T$5:$T$25,"Yes",'Episode Detail'!$AP$5:$AP$25,"No"),"") -> 4 | L17: =COUNTIFS('Episode Detail'!$H$5:$H$25,$A17,'Episode Detail'!$U$5:$U$25,">1") -> 0
A18: Total | E18: =SUM(E5:E17) -> 20 | F18: =SUM(F5:F17) -> 14 | G18: =SUM(G5:G17) -> 4959 | H18: =SUM(H5:H17) -> 2322851.6 | I18: =SUM(I5:I17) -> 524947.6 | J18: =SUM(J5:J17) -> 256648.56

Sheet By Account
A1: By account — main account rollup
A2: Parent / branch hierarchy comes from AcumaticaCustomer.parent_acumatica_id, matching the dashboard tree.
A4: Main Account | B4: Category | C4: Episodes | D4: Branches affected | E4: Open orders | F4: Open value (KES) | G4: Lost revenue (KES) | H4: Revenue-days delayed | I4: Avg days delay | J4: Oldest open (days)
A5: Khetia Drapers Ltd | B5: Modern Trade T2 | C5: =COUNTIFS('Episode Detail'!$E$5:$E$25,$A5,'Episode Detail'!$AP$5:$AP$25,"No") -> 5 | D5: =SUMPRODUCT(('Episode Detail'!$E$5:$E$25=$A5)*'Episode Detail'!$AV$5:$AV$25) -> 2 | E5: =SUMPRODUCT(('Episode Detail'!$E$5:$E$25=$A5)*'Episode Detail'!$AU$5:$AU$25) -> 3 | F5: =SUMIFS('Episode Detail'!$AD$5:$AD$25,'Episode Detail'!$E$5:$E$25,$A5,'Episode Detail'!$AT$5:$AT$25,"Open",'Episode Detail'!$AP$5:$AP$25,"No") -> 168057.9 | G5: =SUMIFS('Episode Detail'!$AH$5:$AH$25,'Episode Detail'!$E$5:$E$25,$A5,'Episode Detail'!$AP$5:$AP$25,"No") -> 173555.4 | H5: =SUMIFS('Episode Detail'!$AG$5:$AG$25,'Episode Detail'!$E$5:$E$25,$A5,'Episode Detail'!$AP$5:$AP$25,"No") -> 475654 | I5: =IFERROR(AVERAGEIFS('Episode Detail'!$R$5:$R$25,'Episode Detail'!$E$5:$E$25,$A5,'Episode Detail'!$T$5:$T$25,"Yes",'Episode Detail'!$AP$5:$AP$25,"No"),"") -> 11.4 | J5: =IFERROR(_xlfn.MAXIFS('Episode Detail'!$R$5:$R$25,'Episode Detail'!$E$5:$E$25,$A5,'Episode Detail'!$AT$5:$AT$25,"Open",'Episode Detail'!$AP$5:$AP$25,"No"),"") -> 13
A6: Majid Al Futtaim Hypermarkets Ltd | B6: Modern Trade T1 | C6: =COUNTIFS('Episode Detail'!$E$5:$E$25,$A6,'Episode Detail'!$AP$5:$AP$25,"No") -> 2 | D6: =SUMPRODUCT(('Episode Detail'!$E$5:$E$25=$A6)*'Episode Detail'!$AV$5:$AV$25) -> 1 | E6: =SUMPRODUCT(('Episode Detail'!$E$5:$E$25=$A6)*'Episode Detail'!$AU$5:$AU$25) -> 2 | F6: =SUMIFS('Episode Detail'!$AD$5:$AD$25,'Episode Detail'!$E$5:$E$25,$A6,'Episode Detail'!$AT$5:$AT$25,"Open",'Episode Detail'!$AP$5:$AP$25,"No") -> 90705.24 | G6: =SUMIFS('Episode Detail'!$AH$5:$AH$25,'Episode Detail'!$E$5:$E$25,$A6,'Episode Detail'!$AP$5:$AP$25,"No") -> 0 | H6: =SUMIFS('Episode Detail'!$AG$5:$AG$25,'Episode Detail'!$E$5:$E$25,$A6,'Episode Detail'!$AP$5:$AP$25,"No") -> 0 | I6: =IFERROR(AVERAGEIFS('Episode Detail'!$R$5:$R$25,'Episode Detail'!$E$5:$E$25,$A6,'Episode Detail'!$T$5:$T$25,"Yes",'Episode Detail'!$AP$5:$AP$25,"No"),"") -> 2 | J6: =IFERROR(_xlfn.MAXIFS('Episode Detail'!$R$5:$R$25,'Episode Detail'!$E$5:$E$25,$A6,'Episode Detail'!$AT$5:$AT$25,"Open",'Episode Detail'!$AP$5:$AP$25,"No"),"") -> 2
A7: Quick Mart Ltd | B7: Modern Trade T1 | C7: =COUNTIFS('Episode Detail'!$E$5:$E$25,$A7,'Episode Detail'!$AP$5:$AP$25,"No") -> 3 | D7: =SUMPRODUCT(('Episode Detail'!$E$5:$E$25=$A7)*'Episode Detail'!$AV$5:$AV$25) -> 1 | E7: =SUMPRODUCT(('Episode Detail'!$E$5:$E$25=$A7)*'Episode Detail'!$AU$5:$AU$25) -> 3 | F7: =SUMIFS('Episode Detail'!$AD$5:$AD$25,'Episode Detail'!$E$5:$E$25,$A7,'Episode Detail'!$AT$5:$AT$25,"Open",'Episode Detail'!$AP$5:$AP$25,"No") -> 63593.16 | G7: =SUMIFS('Episode Detail'!$AH$5:$AH$25,'Episode Detail'!$E$5:$E$25,$A7,'Episode Detail'!$AP$5:$AP$25,"No") -> 63593.16 | H7: =SUMIFS('Episode Detail'!$AG$5:$AG$25,'Episode Detail'!$E$5:$E$25,$A7,'Episode Detail'!$AP$5:$AP$25,"No") -> 0 | I7: =IFERROR(AVERAGEIFS('Episode Detail'!$R$5:$R$25,'Episode Detail'!$E$5:$E$25,$A7,'Episode Detail'!$T$5:$T$25,"Yes",'Episode Detail'!$AP$5:$AP$25,"No"),"") -> 8.6666667 | J7: =IFERROR(_xlfn.MAXIFS('Episode Detail'!$R$5:$R$25,'Episode Detail'!$E$5:$E$25,$A7,'Episode Detail'!$AT$5:$AT$25,"Open",'Episode Detail'!$AP$5:$AP$25,"No"),"") -> 9
A8: Sam West Distributors LTD | B8: General Trade | C8: =COUNTIFS('Episode Detail'!$E$5:$E$25,$A8,'Episode Detail'!$AP$5:$AP$25,"No") -> 1 | D8: =SUMPRODUCT(('Episode Detail'!$E$5:$E$25=$A8)*'Episode Detail'!$AV$5:$AV$25) -> 0 | E8: =SUMPRODUCT(('Episode Detail'!$E$5:$E$25=$A8)*'Episode Detail'!$AU$5:$AU$25) -> 0 | F8: =SUMIFS('Episode Detail'!$AD$5:$AD$25,'Episode Detail'!$E$5:$E$25,$A8,'Episode Detail'!$AT$5:$AT$25,"Open",'Episode Detail'!$AP$5:$AP$25,"No") -> 0 | G8: =SUMIFS('Episode Detail'!$AH$5:$AH$25,'Episode Detail'!$E$5:$E$25,$A8,'Episode Detail'!$AP$5:$AP$25,"No") -> 0 | H8: =SUMIFS('Episode Detail'!$AG$5:$AG$25,'Episode Detail'!$E$5:$E$25,$A8,'Episode Detail'!$AP$5:$AP$25,"No") -> 0 | I8: =IFERROR(AVERAGEIFS('Episode Detail'!$R$5:$R$25,'Episode Detail'!$E$5:$E$25,$A8,'Episode Detail'!$T$5:$T$25,"Yes",'Episode Detail'!$AP$5:$AP$25,"No"),"") -> 2 | J8: =IFERROR(_xlfn.MAXIFS('Episode Detail'!$R$5:$R$25,'Episode Detail'!$E$5:$E$25,$A8,'Episode Detail'!$AT$5:$AT$25,"Open",'Episode Detail'!$AP$5:$AP$25,"No"),"") -> 0
A9: Stage Mattresses Ltd | B9: General Trade | C9: =COUNTIFS('Episode Detail'!$E$5:$E$25,$A9,'Episode Detail'!$AP$5:$AP$25,"No") -> 1 | D9: =SUMPRODUCT(('Episode Detail'!$E$5:$E$25=$A9)*'Episode Detail'!$AV$5:$AV$25) -> 1 | E9: =SUMPRODUCT(('Episode Detail'!$E$5:$E$25=$A9)*'Episode Detail'!$AU$5:$AU$25) -> 1 | F9: =SUMIFS('Episode Detail'!$AD$5:$AD$25,'Episode Detail'!$E$5:$E$25,$A9,'Episode Detail'!$AT$5:$AT$25,"Open",'Episode Detail'!$AP$5:$AP$25,"No") -> 37260 | G9: =SUMIFS('Episode Detail'!$AH$5:$AH$25,'Episode Detail'!$E$5:$E$25,$A9,'Episode Detail'!$AP$5:$AP$25,"No") -> 0 | H9: =SUMIFS('Episode Detail'!$AG$5:$AG$25,'Episode Detail'!$E$5:$E$25,$A9,'Episode Detail'!$AP$5:$AP$25,"No") -> 0 | I9: =IFERROR(AVERAGEIFS('Episode Detail'!$R$5:$R$25,'Episode Detail'!$E$5:$E$25,$A9,'Episode Detail'!$T$5:$T$25,"Yes",'Episode Detail'!$AP$5:$AP$25,"No"),"") | J9: =IFERROR(_xlfn.MAXIFS('Episode Detail'!$R$5:$R$25,'Episode Detail'!$E$5:$E$25,$A9,'Episode Detail'!$AT$5:$AT$25,"Open",'Episode Detail'!$AP$5:$AP$25,"No"),"") -> 2
A10: Goodlife Pharmacy Ltd | B10: Pharmacy | C10: =COUNTIFS('Episode Detail'!$E$5:$E$25,$A10,'Episode Detail'!$AP$5:$AP$25,"No") -> 1 | D10: =SUMPRODUCT(('Episode Detail'!$E$5:$E$25=$A10)*'Episode Detail'!$AV$5:$AV$25) -> 1 | E10: =SUMPRODUCT(('Episode Detail'!$E$5:$E$25=$A10)*'Episode Detail'!$AU$5:$AU$25) -> 1 | F10: =SUMIFS('Episode Detail'!$AD$5:$AD$25,'Episode Detail'!$E$5:$E$25,$A10,'Episode Detail'!$AT$5:$AT$25,"Open",'Episode Detail'!$AP$5:$AP$25,"No") -> 1892531.5 | G10: =SUMIFS('Episode Detail'!$AH$5:$AH$25,'Episode Detail'!$E$5:$E$25,$A10,'Episode Detail'!$AP$5:$AP$25,"No") -> 0 | H10: =SUMIFS('Episode Detail'!$AG$5:$AG$25,'Episode Detail'!$E$5:$E$25,$A10,'Episode Detail'!$AP$5:$AP$25,"No") -> 0 | I10: =IFERROR(AVERAGEIFS('Episode Detail'!$R$5:$R$25,'Episode Detail'!$E$5:$E$25,$A10,'Episode Detail'!$T$5:$T$25,"Yes",'Episode Detail'!$AP$5:$AP$25,"No"),"") -> 2 | J10: =IFERROR(_xlfn.MAXIFS('Episode Detail'!$R$5:$R$25,'Episode Detail'!$E$5:$E$25,$A10,'Episode Detail'!$AT$5:$AT$25,"Open",'Episode Detail'!$AP$5:$AP$25,"No"),"") -> 2
A11: Ava Apotheke Ltd | B11: Pharmacy | C11: =COUNTIFS('Episode Detail'!$E$5:$E$25,$A11,'Episode Detail'!$AP$5:$AP$25,"No") -> 1 | D11: =SUMPRODUCT(('Episode Detail'!$E$5:$E$25=$A11)*'Episode Detail'!$AV$5:$AV$25) -> 0 | E11: =SUMPRODUCT(('Episode Detail'!$E$5:$E$25=$A11)*'Episode Detail'!$AU$5:$AU$25) -> 1 | F11: =SUMIFS('Episode Detail'!$AD$5:$AD$25,'Episode Detail'!$E$5:$E$25,$A11,'Episode Detail'!$AT$5:$AT$25,"Open",'Episode Detail'!$AP$5:$AP$25,"No") -> 44871.3 | G11: =SUMIFS('Episode Detail'!$AH$5:$AH$25,'Episode Detail'!$E$5:$E$25,$A11,'Episode Detail'!$AP$5:$AP$25,"No") -> 0 | H11: =SUMIFS('Episode Detail'!$AG$5:$AG$25,'Episode Detail'!$E$5:$E$25,$A11,'Episode Detail'!$AP$5:$AP$25,"No") -> 0 | I11: =IFERROR(AVERAGEIFS('Episode Detail'!$R$5:$R$25,'Episode Detail'!$E$5:$E$25,$A11,'Episode Detail'!$T$5:$T$25,"Yes",'Episode Detail'!$AP$5:$AP$25,"No"),"") -> 2 | J11: =IFERROR(_xlfn.MAXIFS('Episode Detail'!$R$5:$R$25,'Episode Detail'!$E$5:$E$25,$A11,'Episode Detail'!$AT$5:$AT$25,"Open",'Episode Detail'!$AP$5:$AP$25,"No"),"") -> 2
A12: Nairobi Java House Ltd | B12: Modern Trade T2 | C12: =COUNTIFS('Episode Detail'!$E$5:$E$25,$A12,'Episode Detail'!$AP$5:$AP$25,"No") -> 0 | D12: =SUMPRODUCT(('Episode Detail'!$E$5:$E$25=$A12)*'Episode Detail'!$AV$5:$AV$25) -> 0 | E12: =SUMPRODUCT(('Episode Detail'!$E$5:$E$25=$A12)*'Episode Detail'!$AU$5:$AU$25) -> 0 | F12: =SUMIFS('Episode Detail'!$AD$5:$AD$25,'Episode Detail'!$E$5:$E$25,$A12,'Episode Detail'!$AT$5:$AT$25,"Open",'Episode Detail'!$AP$5:$AP$25,"No") -> 0 | G12: =SUMIFS('Episode Detail'!$AH$5:$AH$25,'Episode Detail'!$E$5:$E$25,$A12,'Episode Detail'!$AP$5:$AP$25,"No") -> 0 | H12: =SUMIFS('Episode Detail'!$AG$5:$AG$25,'Episode Detail'!$E$5:$E$25,$A12,'Episode Detail'!$AP$5:$AP$25,"No") -> 0 | I12: =IFERROR(AVERAGEIFS('Episode Detail'!$R$5:$R$25,'Episode Detail'!$E$5:$E$25,$A12,'Episode Detail'!$T$5:$T$25,"Yes",'Episode Detail'!$AP$5:$AP$25,"No"),"") | J12: =IFERROR(_xlfn.MAXIFS('Episode Detail'!$R$5:$R$25,'Episode Detail'!$E$5:$E$25,$A12,'Episode Detail'!$AT$5:$AT$25,"Open",'Episode Detail'!$AP$5:$AP$25,"No"),"") -> 0
A13: Maguna's Super Stores (K) Ltd | B13: Modern Trade T2 | C13: =COUNTIFS('Episode Detail'!$E$5:$E$25,$A13,'Episode Detail'!$AP$5:$AP$25,"No") -> 2 | D13: =SUMPRODUCT(('Episode Detail'!$E$5:$E$25=$A13)*'Episode Detail'!$AV$5:$AV$25) -> 0 | E13: =SUMPRODUCT(('Episode Detail'!$E$5:$E$25=$A13)*'Episode Detail'!$AU$5:$AU$25) -> 0 | F13: =SUMIFS('Episode Detail'!$AD$5:$AD$25,'Episode Detail'!$E$5:$E$25,$A13,'Episode Detail'!$AT$5:$AT$25,"Open",'Episode Detail'!$AP$5:$AP$25,"No") -> 0 | G13: =SUMIFS('Episode Detail'!$AH$5:$AH$25,'Episode Detail'!$E$5:$E$25,$A13,'Episode Detail'!$AP$5:$AP$25,"No") -> 0 | H13: =SUMIFS('Episode Detail'!$AG$5:$AG$25,'Episode Detail'!$E$5:$E$25,$A13,'Episode Detail'!$AP$5:$AP$25,"No") -> 48648.6 | I13: =IFERROR(AVERAGEIFS('Episode Detail'!$R$5:$R$25,'Episode Detail'!$E$5:$E$25,$A13,'Episode Detail'!$T$5:$T$25,"Yes",'Episode Detail'!$AP$5:$AP$25,"No"),"") -> 3.5 | J13: =IFERROR(_xlfn.MAXIFS('Episode Detail'!$R$5:$R$25,'Episode Detail'!$E$5:$E$25,$A13,'Episode Detail'!$AT$5:$AT$25,"Open",'Episode Detail'!$AP$5:$AP$25,"No"),"") -> 0
A14: Sheal Limited | B14: (not classified) | C14: =COUNTIFS('Episode Detail'!$E$5:$E$25,$A14,'Episode Detail'!$AP$5:$AP$25,"No") -> 1 | D14: =SUMPRODUCT(('Episode Detail'!$E$5:$E$25=$A14)*'Episode Detail'!$AV$5:$AV$25) -> 1 | E14: =SUMPRODUCT(('Episode Detail'!$E$5:$E$25=$A14)*'Episode Detail'!$AU$5:$AU$25) -> 1 | F14: =SUMIFS('Episode Detail'!$AD$5:$AD$25,'Episode Detail'!$E$5:$E$25,$A14,'Episode Detail'!$AT$5:$AT$25,"Open",'Episode Detail'!$AP$5:$AP$25,"No") -> 2935 | G14: =SUMIFS('Episode Detail'!$AH$5:$AH$25,'Episode Detail'!$E$5:$E$25,$A14,'Episode Detail'!$AP$5:$AP$25,"No") -> 0 | H14: =SUMIFS('Episode Detail'!$AG$5:$AG$25,'Episode Detail'!$E$5:$E$25,$A14,'Episode Detail'!$AP$5:$AP$25,"No") -> 0 | I14: =IFERROR(AVERAGEIFS('Episode Detail'!$R$5:$R$25,'Episode Detail'!$E$5:$E$25,$A14,'Episode Detail'!$T$5:$T$25,"Yes",'Episode Detail'!$AP$5:$AP$25,"No"),"") -> 4 | J14: =IFERROR(_xlfn.MAXIFS('Episode Detail'!$R$5:$R$25,'Episode Detail'!$E$5:$E$25,$A14,'Episode Detail'!$AT$5:$AT$25,"Open",'Episode Detail'!$AP$5:$AP$25,"No"),"") -> 4
A15: Bluewave Multisupplies Ltd | B15: (not classified) | C15: =COUNTIFS('Episode Detail'!$E$5:$E$25,$A15,'Episode Detail'!$AP$5:$AP$25,"No") -> 1 | D15: =SUMPRODUCT(('Episode Detail'!$E$5:$E$25=$A15)*'Episode Detail'!$AV$5:$AV$25) -> 1 | E15: =SUMPRODUCT(('Episode Detail'!$E$5:$E$25=$A15)*'Episode Detail'!$AU$5:$AU$25) -> 1 | F15: =SUMIFS('Episode Detail'!$AD$5:$AD$25,'Episode Detail'!$E$5:$E$25,$A15,'Episode Detail'!$AT$5:$AT$25,"Open",'Episode Detail'!$AP$5:$AP$25,"No") -> 19500 | G15: =SUMIFS('Episode Detail'!$AH$5:$AH$25,'Episode Detail'!$E$5:$E$25,$A15,'Episode Detail'!$AP$5:$AP$25,"No") -> 19500 | H15: =SUMIFS('Episode Detail'!$AG$5:$AG$25,'Episode Detail'!$E$5:$E$25,$A15,'Episode Detail'!$AP$5:$AP$25,"No") -> 0 | I15: =IFERROR(AVERAGEIFS('Episode Detail'!$R$5:$R$25,'Episode Detail'!$E$5:$E$25,$A15,'Episode Detail'!$T$5:$T$25,"Yes",'Episode Detail'!$AP$5:$AP$25,"No"),"") | J15: =IFERROR(_xlfn.MAXIFS('Episode Detail'!$R$5:$R$25,'Episode Detail'!$E$5:$E$25,$A15,'Episode Detail'!$AT$5:$AT$25,"Open",'Episode Detail'!$AP$5:$AP$25,"No"),"") -> 15
A16: Cash Sale Staff | B16: Direct To Consumer (Cash Sale) | C16: =COUNTIFS('Episode Detail'!$E$5:$E$25,$A16,'Episode Detail'!$AP$5:$AP$25,"No") -> 1 | D16: =SUMPRODUCT(('Episode Detail'!$E$5:$E$25=$A16)*'Episode Detail'!$AV$5:$AV$25) -> 0 | E16: =SUMPRODUCT(('Episode Detail'!$E$5:$E$25=$A16)*'Episode Detail'!$AU$5:$AU$25) -> 0 | F16: =SUMIFS('Episode Detail'!$AD$5:$AD$25,'Episode Detail'!$E$5:$E$25,$A16,'Episode Detail'!$AT$5:$AT$25,"Open",'Episode Detail'!$AP$5:$AP$25,"No") -> 0 | G16: =SUMIFS('Episode Detail'!$AH$5:$AH$25,'Episode Detail'!$E$5:$E$25,$A16,'Episode Detail'!$AP$5:$AP$25,"No") -> 0 | H16: =SUMIFS('Episode Detail'!$AG$5:$AG$25,'Episode Detail'!$E$5:$E$25,$A16,'Episode Detail'!$AP$5:$AP$25,"No") -> 645 | I16: =IFERROR(AVERAGEIFS('Episode Detail'!$R$5:$R$25,'Episode Detail'!$E$5:$E$25,$A16,'Episode Detail'!$T$5:$T$25,"Yes",'Episode Detail'!$AP$5:$AP$25,"No"),"") -> 4 | J16: =IFERROR(_xlfn.MAXIFS('Episode Detail'!$R$5:$R$25,'Episode Detail'!$E$5:$E$25,$A16,'Episode Detail'!$AT$5:$AT$25,"Open",'Episode Detail'!$AP$5:$AP$25,"No"),"") -> 0
A17: Sales Promotion - Customers (A&P KimFay) | B17: Non Traditional Channels | C17: =COUNTIFS('Episode Detail'!$E$5:$E$25,$A17,'Episode Detail'!$AP$5:$AP$25,"No") -> 1 | D17: =SUMPRODUCT(('Episode Detail'!$E$5:$E$25=$A17)*'Episode Detail'!$AV$5:$AV$25) -> 0 | E17: =SUMPRODUCT(('Episode Detail'!$E$5:$E$25=$A17)*'Episode Detail'!$AU$5:$AU$25) -> 1 | F17: =SUMIFS('Episode Detail'!$AD$5:$AD$25,'Episode Detail'!$E$5:$E$25,$A17,'Episode Detail'!$AT$5:$AT$25,"Open",'Episode Detail'!$AP$5:$AP$25,"No") -> 3397.44 | G17: =SUMIFS('Episode Detail'!$AH$5:$AH$25,'Episode Detail'!$E$5:$E$25,$A17,'Episode Detail'!$AP$5:$AP$25,"No") -> 0 | H17: =SUMIFS('Episode Detail'!$AG$5:$AG$25,'Episode Detail'!$E$5:$E$25,$A17,'Episode Detail'!$AP$5:$AP$25,"No") -> 0 | I17: =IFERROR(AVERAGEIFS('Episode Detail'!$R$5:$R$25,'Episode Detail'!$E$5:$E$25,$A17,'Episode Detail'!$T$5:$T$25,"Yes",'Episode Detail'!$AP$5:$AP$25,"No"),"") -> 2 | J17: =IFERROR(_xlfn.MAXIFS('Episode Detail'!$R$5:$R$25,'Episode Detail'!$E$5:$E$25,$A17,'Episode Detail'!$AT$5:$AT$25,"Open",'Episode Detail'!$AP$5:$AP$25,"No"),"") -> 2
A18: Total | C18: =SUM(C5:C17) -> 20 | D18: =SUM(D5:D17) -> 8 | E18: =SUM(E5:E17) -> 14 | F18: =SUM(F5:F17) -> 2322851.6 | G18: =SUM(G5:G17) -> 256648.56 | H18: =SUM(H5:H17) -> 524947.6

Sheet Acumatica Bridge
A1: Reconciliation to the Acumatica Sales Orders screen
A2: Reference: Order Type = SO, Status = Back Order, Created On 01–23 Jul 2026, snapshot 23/07/2026 17:41 EAT. Gate: unexplained variance must be under 0.5%.
A4: STEP 1 — Acumatica raw export
A5: Line | B5: Orders | C5: Value (KES) | D5: Note
A6: Acumatica raw export rows | B6: 84 | C6: 8436411 | D6: The screen repeats an order once per shipment
A7: less duplicate rows (one per shipment) | B7: -10 | C7: 0 | D7: SO361051 x4, SO365985 x3, SO366417 x2 ...
A8: → Acumatica DISTINCT orders | B8: 74 | C8: 8436411 | D8: This is the number to quote
A9: Acumatica "Unbilled Order Total" | C9: 3861891 | D9: Finance view of open value
A11: STEP 2 — Bridge to dashboard Open / at-risk value
A12: Bridge line | B12: Value (KES) | C12: Why it differs
A13: Acumatica Unbilled Order Total | B13: 3861891 | C13: Starting point — the ERP figure
A14: less shipped, not yet invoiced | B14: -284500 | C14: Unbilled includes goods already despatched
A15: less zero-value / free promotional lines | B15: -12400 | C15: SO366417 read Unbilled 0 while still Back Order
A16: less non-SO order types (PP) | B16: -156300 | C16: Screen filter said SO but the export leaked 12 PP rows
A17: less rejected / on-hold headers | B17: -98200 | C17: Credit blocks — never reached the warehouse
A18: less value of lines that shipped in full on a short order | B18: -620000 | C18: We value SHORT LINES; Acumatica values the WHOLE ORDER
A19: plus short lines on "Shipping" headers | B19: 412800 | C19: Line is short although the header has moved on
A20: plus qty picked but not shipped (committed) | B20: 0 | C20: Held OPEN by design — the customer still has nothing
A21: Sample-data adjustment ** TEMPLATE ONLY — DELETE IN PRODUCTION ** | B21: =Summary!$B$10-SUM(B13:B20) -> -780439.44 | C21: Exists only so this template demonstrates a PASSING gate. Real bridge lines are derived from the ledger.
A22: → Dashboard Open / at-risk value (expected) | B22: =SUM(B13:B21) -> 2322851.6
A23: Dashboard Open / at-risk value (actual, from Summary) | B23: =Summary!$B$10 -> 2322851.6
A24: Unexplained variance | B24: =B23-B22 -> 0 | C24: =IFERROR(ABS(B24)/B13,"") -> 0
A25: Reconciled? | B25: =IF(IFERROR(ABS(B24)/B13,1)<=0.005,"PASS","FAIL — raise AcumaticaReconciliationResult, severity high") -> PASS
A27: The bridge amounts above are ILLUSTRATIVE. ReconcileWithAcumaticaJob must compute every line from the ledger, not by hand.

Sheet Lookups
A1: Lookups & parameters
A2: Blue cells are editable parameters. Episode Detail and Summary read from here — change values here, never in a formula.
A4: BRAND MAP — Inventory ID prefix to brand
A5: Prefix (3 char) | B5: Brand
A6: SIF | B6: Sifa
A7: COS | B7: Cosy
A8: FAY | B8: Fay
A9: TIS | B9: Tishu Poa
A10: COW | B10: Cow & Gate
A12: In production, brand comes from the item master (item class / brand attribute), not from parsing the code. This prefix map is the fallback and must be kept in sync.
A14: THRESHOLDS
A15: Parameter | B15: Value | C15: Used by
A16: As-at date | B16: 46229 | C16: Ageing of open episodes
A17: Promised lead time (working days) | B17: 2 | C17: days_late, Revenue-Days Delayed
A18: Write-off threshold (working days) | B18: 7 | C18: Lost Revenue on open episodes, Aged flag
A19: ESCALATE value floor (KES) | B19: 25000 | C19: Escalation Flag
A20: High-value floor (KES) | B20: 100000 | C20: Escalation Flag
